{
  "type": "Feature",
  "properties": {
    "gn:admin1_code":"21.0",
    "gn:admin2_code":"917.0",
    "gn:admin3_code":"3991.0",
    "gn:asciiname":"Petruse",
    "gn:country_code":"EE",
    "gn:dem":155,
    "gn:feature_class":"P",
    "gn:feature_code":"PPL",
    "gn:name":"Petruse",
    "gn:population":0,
    "gn:timezone":"Europe/Tallinn",
    "iso:country":"EE",
    "name:und_x_variant":[
        "Petruze",
        "Petruse"
    ],
    "wof:name":"Petruse",
    "wof:placetype":"locality"
},
  "geometry": {"coordinates":[27.17917000000001,57.715],"type":"Point"}
}