{
  "type": "Feature",
  "properties": {
    "gn:admin1_code":"5.0",
    "gn:admin2_code":"618.0",
    "gn:admin3_code":"1652.0",
    "gn:asciiname":"Kuningamaee",
    "gn:country_code":"EE",
    "gn:dem":59,
    "gn:feature_class":"P",
    "gn:feature_code":"PPL",
    "gn:name":"Kuningam\u00e4e",
    "gn:population":0,
    "gn:timezone":"Europe/Tallinn",
    "iso:country":"EE",
    "name:und_x_variant":[
        "Kuningamyaye",
        "Kuningam\u00e4e"
    ],
    "wof:name":"Kuningamaee",
    "wof:placetype":"locality"
},
  "geometry": {"coordinates":[25.90083,58.65361],"type":"Point"}
}