{
  "type": "Feature",
  "properties": {
    "gn:admin1_code":"5.0",
    "gn:admin2_code":"618.0",
    "gn:admin3_code":"1652.0",
    "gn:asciiname":"Kuningamaee",
    "gn:country_code":"EE",
    "gn:dem":59,
    "gn:feature_class":"P",
    "gn:feature_code":"PPL",
    "gn:name":"Kuningam\u00e4e",
    "gn:population":0,
    "gn:timezone":"Europe/Tallinn",
    "iso:country":"EE",
    "name:est_x_preferred":[
        "Kuningam\u00e4e"
    ],
    "name:hye_x_preferred":[
        "\u053f\u0578\u0582\u0576\u056b\u0576\u0563\u0561\u0574\u0575\u0561\u0565"
    ],
    "name:pol_x_preferred":[
        "Kuningam\u00e4e"
    ],
    "name:spa_x_preferred":[
        "Kuningam\u00e4e"
    ],
    "name:und_x_variant":[
        "Kuningamyaye"
    ],
    "name:vol_x_preferred":[
        "Kuningam\u00e4e"
    ],
    "wof:coterminous":[
        1713312077
    ],
    "wof:lang_x_official":[
        "est"
    ],
    "wof:lang_x_spoken":[
        "est"
    ],
    "wof:name":"Kuningamaee",
    "wof:placetype":"locality"
},
  "geometry": {"coordinates":[25.90083,58.65361],"type":"Point"}
}