{
  "type": "Feature",
  "properties": {
    "gn:admin1_code":"8.0",
    "gn:admin2_code":"661.0",
    "gn:admin3_code":"2744.0",
    "gn:asciiname":"Arupealse",
    "gn:country_code":"EE",
    "gn:dem":86,
    "gn:feature_class":"P",
    "gn:feature_code":"PPL",
    "gn:name":"Arupealse",
    "gn:population":0,
    "gn:timezone":"Europe/Tallinn",
    "iso:country":"EE",
    "name:und_x_variant":[
        "Aru"
    ],
    "wof:name":"Arupealse",
    "wof:placetype":"locality"
},
  "geometry": {"coordinates":[26.27667000000001,59.35639000000001],"type":"Point"}
}