{
  "type": "Feature",
  "properties": {
    "gn:admin1_code":"13.0",
    "gn:admin2_code":"317.0",
    "gn:admin3_code":"5854.0",
    "gn:asciiname":"Visja",
    "gn:country_code":"EE",
    "gn:dem":70,
    "gn:feature_class":"P",
    "gn:feature_code":"PPL",
    "gn:name":"Visja",
    "gn:population":0,
    "gn:timezone":"Europe/Tallinn",
    "iso:country":"EE",
    "name:und_x_variant":[
        "Vis\u2019ya",
        "Visja"
    ],
    "wof:name":"Visja",
    "wof:placetype":"locality"
},
  "geometry": {"coordinates":[24.88889,59.20278],"type":"Point"}
}