{
  "type": "Feature",
  "properties": {
    "gn:admin1_code":"8.0",
    "gn:admin2_code":"903.0",
    "gn:admin3_code":"7530.0",
    "gn:asciiname":"Selja",
    "gn:cc2":"EE",
    "gn:country_code":"EE",
    "gn:dem":61,
    "gn:feature_class":"P",
    "gn:feature_code":"PPL",
    "gn:name":"Selja",
    "gn:population":0,
    "gn:timezone":"Europe/Tallinn",
    "iso:country":"EE",
    "name:eng_x_preferred":[
        "Selja"
    ],
    "name:est_x_preferred":[
        "Selja"
    ],
    "name:hye_x_preferred":[
        "\u054d\u0565\u056c\u0575\u0561"
    ],
    "name:pol_x_preferred":[
        "Selja"
    ],
    "name:rus_x_preferred":[
        "\u0421\u0435\u043b\u044c\u044f"
    ],
    "name:und_x_variant":[
        "Myza Sel\u2019ya",
        "Selja Asundus",
        "Selja"
    ],
    "name:vol_x_preferred":[
        "Selja"
    ],
    "wof:name":"Selja",
    "wof:placetype":"locality"
},
  "geometry": {"coordinates":[26.41111,59.48972],"type":"Point"}
}