{
  "type": "Feature",
  "properties": {
    "gn:admin1_code":"4.0",
    "gn:admin2_code":"255.0",
    "gn:admin3_code":"8616.0",
    "gn:asciiname":"Udeva",
    "gn:country_code":"EE",
    "gn:dem":90,
    "gn:feature_class":"P",
    "gn:feature_code":"PPL",
    "gn:name":"Udeva",
    "gn:population":0,
    "gn:timezone":"Europe/Tallinn",
    "iso:country":"EE",
    "name:eng_x_preferred":[
        "Udeva"
    ],
    "name:est_x_preferred":[
        "Udeva"
    ],
    "name:hye_x_preferred":[
        "\u0548\u0582\u0564\u0587\u0561"
    ],
    "name:pol_x_preferred":[
        "Udeva"
    ],
    "name:rus_x_preferred":[
        "\u0423\u0434\u0435\u0432\u0430"
    ],
    "name:spa_x_preferred":[
        "Udeva"
    ],
    "name:ukr_x_preferred":[
        "\u0423\u0434\u0435\u0432\u0430"
    ],
    "name:vol_x_preferred":[
        "Udeva"
    ],
    "wof:coterminous":[
        1713306823
    ],
    "wof:lang_x_official":[
        "est"
    ],
    "wof:lang_x_spoken":[
        "est"
    ],
    "wof:name":"Udeva",
    "wof:placetype":"locality"
},
  "geometry": {"coordinates":[26.0225,58.93583],"type":"Point"}
}