{
  "type": "Feature",
  "properties": {
    "gn:admin1_code":"12.0",
    "gn:admin2_code":"622.0",
    "gn:admin3_code":"2831.0",
    "gn:asciiname":"Kastmekoja",
    "gn:country_code":"EE",
    "gn:dem":51,
    "gn:feature_class":"P",
    "gn:feature_code":"PPL",
    "gn:name":"Kastmekoja",
    "gn:population":0,
    "gn:timezone":"Europe/Tallinn",
    "iso:country":"EE",
    "wof:name":"Kastmekoja",
    "wof:placetype":"locality"
},
  "geometry": {"coordinates":[27.20889,58.24472],"type":"Point"}
}