{
  "type": "Feature",
  "properties": {
    "gn:admin1_code":"12.0",
    "gn:admin2_code":"622.0",
    "gn:admin3_code":"2831.0",
    "gn:asciiname":"Kastmekoja",
    "gn:country_code":"EE",
    "gn:dem":51,
    "gn:feature_class":"P",
    "gn:feature_code":"PPL",
    "gn:name":"Kastmekoja",
    "gn:population":0,
    "gn:timezone":"Europe/Tallinn",
    "iso:country":"EE",
    "name:deu_x_preferred":[
        "Kastmekoja"
    ],
    "name:est_x_preferred":[
        "Kastmekoja"
    ],
    "name:hye_x_preferred":[
        "\u053f\u0561\u057d\u057f\u0574\u0565\u056f\u0578\u0575\u0561"
    ],
    "name:pol_x_preferred":[
        "Kastmekoja"
    ],
    "name:spa_x_preferred":[
        "Kastmekoja"
    ],
    "name:ukr_x_preferred":[
        "\u041a\u0430\u0441\u0442\u043c\u0435\u043a\u043e\u044f"
    ],
    "name:vol_x_preferred":[
        "Kastmekoja"
    ],
    "wof:name":"Kastmekoja",
    "wof:placetype":"locality"
},
  "geometry": {"coordinates":[27.20889,58.24472],"type":"Point"}
}