{
  "type": "Feature",
  "properties": {
    "gn:admin1_code":"12.0",
    "gn:admin2_code":"622.0",
    "gn:admin3_code":"7964.0",
    "gn:asciiname":"Saeaessaare",
    "gn:country_code":"EE",
    "gn:dem":40,
    "gn:feature_class":"P",
    "gn:feature_code":"PPL",
    "gn:name":"S\u00e4\u00e4ssaare",
    "gn:population":0,
    "gn:timezone":"Europe/Tallinn",
    "iso:country":"EE",
    "name:und_x_variant":[
        "S\u00e4\u00e4ssaare"
    ],
    "wof:name":"Saeaessaare",
    "wof:placetype":"locality"
},
  "geometry": {"coordinates":[27.16444000000001,58.15389],"type":"Point"}
}