{
  "type": "Feature",
  "properties": {
    "gn:admin1_code":"3.0",
    "gn:admin2_code":"514.0",
    "gn:admin3_code":"7674.0",
    "gn:asciiname":"Sundja",
    "gn:country_code":"EE",
    "gn:dem":33,
    "gn:feature_class":"P",
    "gn:feature_code":"PPL",
    "gn:name":"Sundja",
    "gn:population":0,
    "gn:timezone":"Europe/Tallinn",
    "iso:country":"EE",
    "wof:lang_x_official":[
        "est"
    ],
    "wof:lang_x_spoken":[
        "est"
    ],
    "wof:name":"Sundja",
    "wof:placetype":"locality"
},
  "geometry": {"coordinates":[28.10548,59.37441],"type":"Point"}
}