{
  "type": "Feature",
  "properties": {
    "gn:gn_country":"EE",
    "gn:gn_fcode":"PPL",
    "gn:gn_pop":255,
    "gn:population":255,
    "iso:country":"EE",
    "name:bul_x_preferred":[
        "\u041c\u0435\u0445\u0438\u043a\u043e\u0440\u043c\u0430"
    ],
    "name:eng_x_preferred":[
        "Mehikoorma"
    ],
    "name:est_x_preferred":[
        "Mehikoorma"
    ],
    "name:fra_x_preferred":[
        "Mehikoorma"
    ],
    "name:hye_x_preferred":[
        "\u0544\u0565\u0570\u056b\u056f\u0578\u0578\u057c\u0574\u0561"
    ],
    "name:rus_x_preferred":[
        "\u041c\u0435\u0445\u0438\u043a\u043e\u043e\u0440\u043c\u0430"
    ],
    "name:swe_x_preferred":[
        "Mehikoorma"
    ],
    "name:unk_x_variant":[
        "Ismenka"
    ],
    "name:vol_x_preferred":[
        "Mehikoorma"
    ],
    "qs_pg:aaroncc":"EE",
    "qs_pg:gn_country":"EE",
    "qs_pg:gn_fcode":"PPL",
    "qs_pg:gn_pop":255,
    "qs_pg:name":"Mehikoorma",
    "qs_pg:name_adm0":"Eesti",
    "qs_pg:name_adm1":"Tartumaa",
    "qs_pg:photos_9k":1,
    "qs_pg:photos_9r":1,
    "qs_pg:photos_all":1,
    "qs_pg:photos_sr":0,
    "qs_pg:pop_sr":2,
    "qs_pg:qs_pg_placetype":"locality",
    "qs_pg:qs_pg_placetype_gp":"Town",
    "qs_pg:woe_adm0":23424805,
    "woe:adm0_id":23424805,
    "woe:name_adm0":"Eesti",
    "woe:name_adm1":"Tartumaa",
    "woe:placetype":"Town",
    "wof:name":"Mehikoorma",
    "wof:placetype":"locality",
    "wof:population":255
},
  "geometry": {"coordinates":[27.4725,58.23278],"type":"Point"}
}