{
  "type": "Feature",
  "properties": {
    "gn:admin1_code":"20.0",
    "gn:admin2_code":"480.0",
    "gn:admin3_code":"1061.0",
    "gn:asciiname":"Abjaku",
    "gn:cc2":"EE",
    "gn:country_code":"EE",
    "gn:dem":77,
    "gn:feature_class":"P",
    "gn:feature_code":"PPL",
    "gn:name":"Abjaku",
    "gn:population":0,
    "gn:timezone":"Europe/Tallinn",
    "iso:country":"EE",
    "name:und_x_variant":[
        "Myza Abiya",
        "Abja",
        "Abja Asundus",
        "Abjaku"
    ],
    "wof:name":"Abjaku",
    "wof:placetype":"locality"
},
  "geometry": {"coordinates":[25.36194,58.10972],"type":"Point"}
}