{
  "type": "Feature",
  "properties": {
    "gn:admin1_code":"4.0",
    "gn:admin2_code":"255.0",
    "gn:admin3_code":"3723.0",
    "gn:asciiname":"Kuusna",
    "gn:country_code":"EE",
    "gn:dem":101,
    "gn:feature_class":"P",
    "gn:feature_code":"PPL",
    "gn:name":"Kuusna",
    "gn:population":0,
    "gn:timezone":"Europe/Tallinn",
    "iso:country":"EE",
    "name:est_x_preferred":[
        "Kuusna"
    ],
    "name:hye_x_preferred":[
        "\u053f\u0578\u0582\u0578\u0582\u057d\u0576\u0561"
    ],
    "name:pol_x_preferred":[
        "Kuusna"
    ],
    "name:spa_x_preferred":[
        "Kuusna"
    ],
    "name:ukr_x_preferred":[
        "\u041a\u0443\u0443\u0441\u043d\u0430"
    ],
    "name:vol_x_preferred":[
        "Kuusna"
    ],
    "wof:name":"Kuusna",
    "wof:placetype":"locality"
},
  "geometry": {"coordinates":[25.92222000000001,59.00028],"type":"Point"}
}