{
  "type": "Feature",
  "properties": {
    "gn:admin1_code":"14.0",
    "gn:admin2_code":"714.0",
    "gn:admin3_code":"1300.0",
    "gn:asciiname":"Tolli",
    "gn:country_code":"EE",
    "gn:dem":9,
    "gn:feature_class":"P",
    "gn:feature_code":"PPL",
    "gn:name":"T\u00f5lli",
    "gn:population":0,
    "gn:timezone":"Europe/Tallinn",
    "iso:country":"EE",
    "name:deu_x_preferred":[
        "T\u00f5lli"
    ],
    "name:est_x_preferred":[
        "T\u00f5lli"
    ],
    "name:fas_x_preferred":[
        "\u062a\u0648\u0644\u06cc"
    ],
    "name:fra_x_preferred":[
        "T\u00f5lli"
    ],
    "name:hye_x_preferred":[
        "\u054f\u056b\u056c\u056c\u056b"
    ],
    "name:nld_x_preferred":[
        "T\u00f5lli"
    ],
    "name:pol_x_preferred":[
        "T\u00f5lli"
    ],
    "name:spa_x_preferred":[
        "T\u00f5lli"
    ],
    "name:ukr_x_preferred":[
        "\u0422\u0438\u043b\u043b\u0456"
    ],
    "name:und_x_variant":[
        "Tylli"
    ],
    "name:vol_x_preferred":[
        "T\u00f5lli"
    ],
    "wof:coterminous":[
        1713308631
    ],
    "wof:lang_x_official":[
        "est"
    ],
    "wof:lang_x_spoken":[
        "est"
    ],
    "wof:name":"Tolli",
    "wof:placetype":"locality"
},
  "geometry": {"coordinates":[22.38056,58.29861],"type":"Point"}
}