{
  "type": "Feature",
  "properties": {
    "gn:admin1_code":"11.0",
    "gn:admin2_code":"809.0",
    "gn:admin3_code":"4774.0",
    "gn:asciiname":"Mannare",
    "gn:country_code":"EE",
    "gn:dem":29,
    "gn:feature_class":"P",
    "gn:feature_code":"PPL",
    "gn:name":"Mannare",
    "gn:population":0,
    "gn:timezone":"Europe/Tallinn",
    "iso:country":"EE",
    "wof:name":"Mannare",
    "wof:placetype":"locality"
},
  "geometry": {"coordinates":[24.87139,58.55639],"type":"Point"}
}