{
  "type": "Feature",
  "properties": {
    "gn:admin1_code":"7.0",
    "gn:admin2_code":"184.0",
    "gn:admin3_code":"7283.0",
    "gn:asciiname":"Saardu",
    "gn:country_code":"EE",
    "gn:dem":8,
    "gn:feature_class":"P",
    "gn:feature_code":"PPL",
    "gn:name":"Saardu",
    "gn:population":0,
    "gn:timezone":"Europe/Tallinn",
    "iso:country":"EE",
    "name:deu_x_preferred":[
        "Saardu"
    ],
    "name:est_x_preferred":[
        "Saardu"
    ],
    "name:hye_x_preferred":[
        "\u054d\u0561\u0561\u057c\u0564\u0578\u0582"
    ],
    "name:pol_x_preferred":[
        "Saardu"
    ],
    "name:ukr_x_preferred":[
        "\u0421\u0430\u0430\u0440\u0434\u0443"
    ],
    "name:und_x_variant":[
        "Saardo",
        "Sardo",
        "Saardu"
    ],
    "name:urd_x_preferred":[
        "\u0633\u0627\u0631\u062f\u0648"
    ],
    "name:vol_x_preferred":[
        "Saardu"
    ],
    "wof:name":"Saardu",
    "wof:placetype":"locality"
},
  "geometry": {"coordinates":[23.61278,58.79944],"type":"Point"}
}