{
  "type": "Feature",
  "properties": {
    "gn:admin1_code":"3.0",
    "gn:admin2_code":"130.0",
    "gn:admin3_code":"3621.0",
    "gn:asciiname":"Gorodenka",
    "gn:country_code":"EE",
    "gn:dem":31,
    "gn:feature_class":"P",
    "gn:feature_code":"PPL",
    "gn:name":"Gorodenka",
    "gn:population":0,
    "gn:timezone":"Europe/Tallinn",
    "iso:country":"EE",
    "name:und_x_variant":[
        "Gorodenko"
    ],
    "wof:name":"Gorodenka",
    "wof:placetype":"locality"
},
  "geometry": {"coordinates":[27.81722,59.14056],"type":"Point"}
}