{
  "type": "Feature",
  "properties": {
    "gn:admin1_code":"21.0",
    "gn:admin2_code":"917.0",
    "gn:admin3_code":"3818.0",
    "gn:asciiname":"Tellaste",
    "gn:country_code":"EE",
    "gn:dem":120,
    "gn:feature_class":"P",
    "gn:feature_code":"PPL",
    "gn:name":"Tellaste",
    "gn:population":0,
    "gn:timezone":"Europe/Tallinn",
    "iso:country":"EE",
    "wof:name":"Tellaste",
    "wof:placetype":"locality"
},
  "geometry": {"coordinates":[27.34722,57.77778000000001],"type":"Point"}
}