{
  "type": "Feature",
  "properties": {
    "gn:admin1_code":"21.0",
    "gn:admin2_code":"917.0",
    "gn:admin3_code":"3818.0",
    "gn:asciiname":"Tellaste",
    "gn:country_code":"EE",
    "gn:dem":120,
    "gn:feature_class":"P",
    "gn:feature_code":"PPL",
    "gn:name":"Tellaste",
    "gn:population":0,
    "gn:timezone":"Europe/Tallinn",
    "iso:country":"EE",
    "name:est_x_preferred":[
        "Tellaste"
    ],
    "name:hye_x_preferred":[
        "\u054f\u0565\u056c\u056c\u0561\u057d\u057f\u0565"
    ],
    "name:pol_x_preferred":[
        "Tellaste"
    ],
    "name:spa_x_preferred":[
        "Tellaste"
    ],
    "name:ukr_x_preferred":[
        "\u0422\u0435\u043b\u043b\u0430\u0441\u0442\u0435"
    ],
    "name:vol_x_preferred":[
        "Tellaste"
    ],
    "wof:lang_x_official":[
        "est"
    ],
    "wof:lang_x_spoken":[
        "est"
    ],
    "wof:name":"Tellaste",
    "wof:placetype":"locality"
},
  "geometry": {"coordinates":[27.34722,57.77778],"type":"Point"}
}