{
  "type": "Feature",
  "properties": {
    "gn:admin1_code":"11.0",
    "gn:admin2_code":"624.0",
    "gn:admin3_code":"1394.0",
    "gn:asciiname":"Aruvaelja",
    "gn:country_code":"EE",
    "gn:dem":31,
    "gn:feature_class":"P",
    "gn:feature_code":"PPL",
    "gn:name":"Aruv\u00e4lja",
    "gn:population":0,
    "gn:timezone":"Europe/Tallinn",
    "iso:country":"EE",
    "name:ces_x_preferred":[
        "Aruv\u00e4lja"
    ],
    "name:est_x_preferred":[
        "Aruv\u00e4lja"
    ],
    "name:hye_x_preferred":[
        "\u0531\u057c\u0578\u0582\u057e\u0565\u056c\u0575\u0561"
    ],
    "name:pol_x_preferred":[
        "Aruv\u00e4lja"
    ],
    "name:vol_x_preferred":[
        "Aruv\u00e4lja"
    ],
    "wof:name":"Aruvaelja",
    "wof:placetype":"locality"
},
  "geometry": {"coordinates":[24.18667,58.45556],"type":"Point"}
}