{
  "type": "Feature",
  "properties": {
    "gn:admin1_code":"20.0",
    "gn:admin2_code":"615.0",
    "gn:admin3_code":"1386.0",
    "gn:asciiname":"Uduallika",
    "gn:country_code":"EE",
    "gn:dem":59,
    "gn:feature_class":"P",
    "gn:feature_code":"PPL",
    "gn:name":"Uduallika",
    "gn:population":0,
    "gn:timezone":"Europe/Tallinn",
    "iso:country":"EE",
    "wof:name":"Uduallika",
    "wof:placetype":"locality"
},
  "geometry": {"coordinates":[25.67306,58.665],"type":"Point"}
}