{
  "type": "Feature",
  "properties": {
    "gn:gn_country":"EE",
    "gn:gn_fcode":"PPL",
    "gn:gn_pop":115,
    "gn:population":115,
    "iso:country":"EE",
    "name:bul_x_preferred":[
        "\u0410\u0438\u0434\u0443"
    ],
    "name:ceb_x_preferred":[
        "Aidu"
    ],
    "name:deu_x_preferred":[
        "Aidu"
    ],
    "name:eng_x_preferred":[
        "Aidu"
    ],
    "name:est_x_preferred":[
        "Aidu"
    ],
    "name:fas_x_preferred":[
        "\u0627\u06cc\u062f\u0648\u060c \u0628\u062e\u0634 \u0648\u06cc\u0644\u062c\u0627\u0646\u062f\u06cc"
    ],
    "name:fas_x_variant":[
        "\u0627\u06cc\u062f\u0648"
    ],
    "name:fra_x_preferred":[
        "Aidu"
    ],
    "name:hye_x_preferred":[
        "\u0531\u056b\u0564\u0578\u0582"
    ],
    "name:nld_x_preferred":[
        "Aidu"
    ],
    "name:pol_x_preferred":[
        "Aidu"
    ],
    "name:spa_x_preferred":[
        "Aidu"
    ],
    "name:swe_x_preferred":[
        "Aidu"
    ],
    "name:ukr_x_preferred":[
        "\u0410\u0439\u0434\u0443"
    ],
    "name:unk_x_variant":[
        "Myza Aydu"
    ],
    "name:vol_x_preferred":[
        "Aidu"
    ],
    "qs_pg:aaroncc":"EE",
    "qs_pg:gn_country":"EE",
    "qs_pg:gn_fcode":"PPL",
    "qs_pg:gn_pop":115,
    "qs_pg:name":"Aidu",
    "qs_pg:name_adm0":"Eesti",
    "qs_pg:name_adm1":"Viljandimaa",
    "qs_pg:photos_9r":0,
    "qs_pg:photos_sr":0,
    "qs_pg:pop_sr":1,
    "qs_pg:qs_pg_placetype":"locality",
    "qs_pg:qs_pg_placetype_gp":"Town",
    "qs_pg:woe_adm0":23424805,
    "woe:adm0_id":23424805,
    "woe:name_adm0":"Eesti",
    "woe:name_adm1":"Viljandimaa",
    "woe:placetype":"Town",
    "wof:name":"Aidu",
    "wof:placetype":"locality",
    "wof:population":115
},
  "geometry": {"coordinates":[25.61194,58.24972],"type":"Point"}
}