{
  "type": "Feature",
  "properties": {
    "gn:admin1_code":"2.0",
    "gn:admin2_code":"205.0",
    "gn:admin3_code":"1713.0",
    "gn:asciiname":"Hagaste",
    "gn:country_code":"EE",
    "gn:dem":11,
    "gn:feature_class":"P",
    "gn:feature_code":"PPL",
    "gn:name":"Hagaste",
    "gn:population":0,
    "gn:timezone":"Europe/Tallinn",
    "iso:country":"EE",
    "name:und_x_variant":[
        "Khagaste",
        "Hagaste"
    ],
    "wof:name":"Hagaste",
    "wof:placetype":"locality"
},
  "geometry": {"coordinates":[22.95865,58.91969],"type":"Point"}
}