{
  "type": "Feature",
  "properties": {
    "gn:admin1_code":"4.0",
    "gn:admin2_code":"834.0",
    "gn:admin3_code":"7293.0",
    "gn:asciiname":"Saareotsa",
    "gn:country_code":"EE",
    "gn:dem":67,
    "gn:feature_class":"P",
    "gn:feature_code":"PPL",
    "gn:name":"Saareotsa",
    "gn:population":0,
    "gn:timezone":"Europe/Tallinn",
    "iso:country":"EE",
    "wof:name":"Saareotsa",
    "wof:placetype":"locality"
},
  "geometry": {"coordinates":[25.54528,58.73944],"type":"Point"}
}