{
  "type": "Feature",
  "properties": {
    "gn:admin1_code":"4.0",
    "gn:admin2_code":"834.0",
    "gn:admin3_code":"7293.0",
    "gn:asciiname":"Saareotsa",
    "gn:country_code":"EE",
    "gn:dem":67,
    "gn:feature_class":"P",
    "gn:feature_code":"PPL",
    "gn:name":"Saareotsa",
    "gn:population":0,
    "gn:timezone":"Europe/Tallinn",
    "iso:country":"EE",
    "name:est_x_preferred":[
        "Saareotsa"
    ],
    "name:fra_x_preferred":[
        "Saareotsa"
    ],
    "name:hye_x_preferred":[
        "\u054d\u0561\u0561\u057c\u0565\u0578\u0581\u0561"
    ],
    "name:pol_x_preferred":[
        "Saareotsa"
    ],
    "name:spa_x_preferred":[
        "Saareotsa"
    ],
    "name:ukr_x_preferred":[
        "\u0421\u0430\u0430\u0440\u0435\u043e\u0442\u0441\u0430"
    ],
    "name:urd_x_preferred":[
        "\u0633\u0627\u0631\u06d2\u0648\u062a\u0633\u0627"
    ],
    "name:vol_x_preferred":[
        "Saareotsa"
    ],
    "wof:name":"Saareotsa",
    "wof:placetype":"locality"
},
  "geometry": {"coordinates":[25.54528,58.73944],"type":"Point"}
}