{
  "type": "Feature",
  "properties": {
    "gn:admin1_code":"12.0",
    "gn:admin2_code":"284.0",
    "gn:admin3_code":"4156.0",
    "gn:asciiname":"Lauri",
    "gn:country_code":"EE",
    "gn:dem":116,
    "gn:feature_class":"P",
    "gn:feature_code":"PPL",
    "gn:name":"Lauri",
    "gn:population":0,
    "gn:timezone":"Europe/Tallinn",
    "iso:country":"EE",
    "wof:name":"Lauri",
    "wof:placetype":"locality"
},
  "geometry": {"coordinates":[26.85694,57.98444],"type":"Point"}
}