{
  "type": "Feature",
  "properties": {
    "gn:admin1_code":"14.0",
    "gn:admin2_code":"714.0",
    "gn:admin3_code":"3843.0",
    "gn:asciiname":"Pidula",
    "gn:cc2":"EE",
    "gn:country_code":"EE",
    "gn:dem":27,
    "gn:feature_class":"P",
    "gn:feature_code":"PPL",
    "gn:name":"Pidula",
    "gn:population":0,
    "gn:timezone":"Europe/Tallinn",
    "iso:country":"EE",
    "name:und_x_variant":[
        "Myza Pidula",
        "Pidula Asundus",
        "Pidula"
    ],
    "wof:name":"Pidula",
    "wof:placetype":"locality"
},
  "geometry": {"coordinates":[22.17167,58.41306],"type":"Point"}
}