{
  "type": "Feature",
  "properties": {
    "gn:admin1_code":"11.0",
    "gn:admin2_code":"638.0",
    "gn:admin3_code":"2545.0",
    "gn:asciiname":"Nomme",
    "gn:country_code":"EE",
    "gn:dem":51,
    "gn:feature_class":"P",
    "gn:feature_code":"PPL",
    "gn:name":"N\u00f5mme",
    "gn:population":0,
    "gn:timezone":"Europe/Tallinn",
    "iso:country":"EE",
    "name:und_x_variant":[
        "Nymme",
        "N\u00f5mmek\u00fcla",
        "N\u00f5mme"
    ],
    "wof:name":"Nomme",
    "wof:placetype":"locality"
},
  "geometry": {"coordinates":[24.76306,58.70139],"type":"Point"}
}