{
  "type": "Feature",
  "properties": {
    "gn:admin1_code":"7.0",
    "gn:admin2_code":"184.0",
    "gn:admin3_code":"9343.0",
    "gn:asciiname":"Vilkla",
    "gn:country_code":"EE",
    "gn:dem":7,
    "gn:feature_class":"P",
    "gn:feature_code":"PPL",
    "gn:name":"Vilkla",
    "gn:population":0,
    "gn:timezone":"Europe/Tallinn",
    "iso:country":"EE",
    "name:deu_x_preferred":[
        "Vilkla"
    ],
    "name:est_x_preferred":[
        "Vilkla"
    ],
    "name:hye_x_preferred":[
        "\u054e\u056b\u056c\u056f\u056c\u0561"
    ],
    "name:pol_x_preferred":[
        "Vilkla"
    ],
    "name:ukr_x_preferred":[
        "\u0412\u0456\u043b\u043a\u043b\u0430"
    ],
    "name:und_x_variant":[
        "Vil\u2019kil\u2019bi"
    ],
    "name:vol_x_preferred":[
        "Vilkla"
    ],
    "wof:lang_x_official":[
        "est"
    ],
    "wof:lang_x_spoken":[
        "est"
    ],
    "wof:name":"Vilkla",
    "wof:placetype":"locality"
},
  "geometry": {"coordinates":[23.61444,58.88833],"type":"Point"}
}