{
  "type": "Feature",
  "properties": {
    "gn:admin1_code":"7.0",
    "gn:admin2_code":"184.0",
    "gn:admin3_code":"9343.0",
    "gn:asciiname":"Vilkla",
    "gn:country_code":"EE",
    "gn:dem":7,
    "gn:feature_class":"P",
    "gn:feature_code":"PPL",
    "gn:name":"Vilkla",
    "gn:population":0,
    "gn:timezone":"Europe/Tallinn",
    "iso:country":"EE",
    "name:und_x_variant":[
        "Vil\u2019kil\u2019bi",
        "Vilkla"
    ],
    "wof:name":"Vilkla",
    "wof:placetype":"locality"
},
  "geometry": {"coordinates":[23.61444,58.88833],"type":"Point"}
}