{
  "type": "Feature",
  "properties": {
    "gn:gn_country":"EE",
    "gn:gn_fcode":"PPL",
    "gn:gn_pop":250,
    "gn:population":250,
    "iso:country":"EE",
    "name:bul_x_preferred":[
        "\u041a\u0438\u0440\u0431\u043b\u0430"
    ],
    "name:ceb_x_preferred":[
        "Kirbla"
    ],
    "name:deu_x_preferred":[
        "Kirbla"
    ],
    "name:eng_x_preferred":[
        "Kirbla"
    ],
    "name:est_x_preferred":[
        "Kirbla"
    ],
    "name:fin_x_preferred":[
        "Kirbla"
    ],
    "name:fra_x_preferred":[
        "Kirbla"
    ],
    "name:hye_x_preferred":[
        "\u053f\u056b\u057c\u0562\u056c\u0561"
    ],
    "name:nld_x_preferred":[
        "Kirbla"
    ],
    "name:pol_x_preferred":[
        "Kirbla"
    ],
    "name:rus_x_preferred":[
        "\u041a\u0438\u0440\u0431\u043b\u0430"
    ],
    "name:spa_x_preferred":[
        "Kirbla"
    ],
    "name:swe_x_preferred":[
        "Kirbla"
    ],
    "name:vol_x_preferred":[
        "Kirbla"
    ],
    "qs_pg:aaroncc":"EE",
    "qs_pg:gn_country":"EE",
    "qs_pg:gn_fcode":"PPL",
    "qs_pg:gn_pop":250,
    "qs_pg:name":"Kirbla",
    "qs_pg:name_adm0":"Eesti",
    "qs_pg:name_adm1":"L\u00e4\u00e4nemaa",
    "qs_pg:photos_9k":1,
    "qs_pg:photos_9r":1,
    "qs_pg:photos_all":3,
    "qs_pg:photos_sr":0,
    "qs_pg:pop_sr":2,
    "qs_pg:qs_pg_placetype":"locality",
    "qs_pg:qs_pg_placetype_gp":"Town",
    "qs_pg:woe_adm0":23424805,
    "woe:adm0_id":23424805,
    "woe:name_adm0":"Eesti",
    "woe:name_adm1":"L\u00e4\u00e4nemaa",
    "woe:placetype":"Town",
    "wof:name":"Kirbla",
    "wof:placetype":"locality",
    "wof:population":250
},
  "geometry": {"coordinates":[23.95417,58.73444],"type":"Point"}
}