{
  "type": "Feature",
  "properties": {
    "gn:admin1_code":"4.0",
    "gn:admin2_code":"255.0",
    "gn:admin3_code":"1441.0",
    "gn:asciiname":"Ataste",
    "gn:country_code":"EE",
    "gn:dem":85,
    "gn:feature_class":"P",
    "gn:feature_code":"PPL",
    "gn:name":"Ataste",
    "gn:population":0,
    "gn:timezone":"Europe/Tallinn",
    "iso:country":"EE",
    "name:und_x_variant":[
        "Alaste",
        "Ataste"
    ],
    "wof:name":"Ataste",
    "wof:placetype":"locality"
},
  "geometry": {"coordinates":[25.86333,58.94056],"type":"Point"}
}