{
  "type": "Feature",
  "properties": {
    "gn:admin1_code":"4.0",
    "gn:admin2_code":"255.0",
    "gn:admin3_code":"1441.0",
    "gn:asciiname":"Ataste",
    "gn:country_code":"EE",
    "gn:dem":85,
    "gn:feature_class":"P",
    "gn:feature_code":"PPL",
    "gn:name":"Ataste",
    "gn:population":0,
    "gn:timezone":"Europe/Tallinn",
    "iso:country":"EE",
    "name:est_x_preferred":[
        "Ataste"
    ],
    "name:hye_x_preferred":[
        "\u0531\u057f\u0561\u057d\u057f\u0565"
    ],
    "name:pol_x_preferred":[
        "Ataste"
    ],
    "name:spa_x_preferred":[
        "Ataste"
    ],
    "name:ukr_x_preferred":[
        "\u0410\u0442\u0430\u0441\u0442\u0435"
    ],
    "name:und_x_variant":[
        "Alaste",
        "Ataste"
    ],
    "name:vol_x_preferred":[
        "Ataste"
    ],
    "wof:name":"Ataste",
    "wof:placetype":"locality"
},
  "geometry": {"coordinates":[25.86333,58.94056],"type":"Point"}
}