{
  "type": "Feature",
  "properties": {
    "gn:admin1_code":"4.0",
    "gn:admin2_code":"834.0",
    "gn:admin3_code":"9336.0",
    "gn:asciiname":"Illassaare",
    "gn:country_code":"EE",
    "gn:dem":60,
    "gn:feature_class":"P",
    "gn:feature_code":"PPL",
    "gn:name":"Illassaare",
    "gn:population":0,
    "gn:timezone":"Europe/Tallinn",
    "iso:country":"EE",
    "name:und_x_variant":[
        "Illasaare"
    ],
    "wof:name":"Illassaare",
    "wof:placetype":"locality"
},
  "geometry": {"coordinates":[25.41444,58.7475],"type":"Point"}
}