{
  "type": "Feature",
  "properties": {
    "gn:admin1_code":"8.0",
    "gn:admin2_code":"792.0",
    "gn:admin3_code":"4403.0",
    "gn:asciiname":"Poriki",
    "gn:country_code":"EE",
    "gn:dem":97,
    "gn:feature_class":"P",
    "gn:feature_code":"PPL",
    "gn:name":"P\u00f5riki",
    "gn:population":0,
    "gn:timezone":"Europe/Tallinn",
    "iso:country":"EE",
    "name:und_x_variant":[
        "P\u00f5rika",
        "Pyriki",
        "P\u00f5riki Asundus",
        "P\u00f5riki"
    ],
    "wof:name":"Poriki",
    "wof:placetype":"locality"
},
  "geometry": {"coordinates":[25.83639,59.21778000000001],"type":"Point"}
}