{
  "type": "Feature",
  "properties": {
    "gn:admin1_code":"1.0",
    "gn:admin2_code":"431.0",
    "gn:admin3_code":"1782.0",
    "gn:asciiname":"Soo-otsa",
    "gn:country_code":"EE",
    "gn:dem":16,
    "gn:feature_class":"P",
    "gn:feature_code":"PPL",
    "gn:name":"Soo-otsa",
    "gn:population":0,
    "gn:timezone":"Europe/Tallinn",
    "iso:country":"EE",
    "name:deu_x_preferred":[
        "Soo-otsa"
    ],
    "name:est_x_preferred":[
        "Soo-otsa"
    ],
    "name:hye_x_preferred":[
        "\u054d\u0578\u0578-\u0548\u0581\u0561"
    ],
    "name:pol_x_preferred":[
        "Soo-otsa"
    ],
    "name:spa_x_preferred":[
        "Soo-otsa"
    ],
    "name:ukr_x_preferred":[
        "\u0421\u043e\u043e-\u043e\u0442\u0441\u0430"
    ],
    "name:und_x_variant":[
        "Sooltse",
        "Sootse",
        "Sol\u2019tsa"
    ],
    "name:vol_x_preferred":[
        "Soo-otsa"
    ],
    "wof:name":"Soo-otsa",
    "wof:placetype":"locality"
},
  "geometry": {"coordinates":[23.90528,59.18694],"type":"Point"}
}