{
  "type": "Feature",
  "properties": {
    "gn:admin1_code":"1.0",
    "gn:admin2_code":"141.0",
    "gn:admin3_code":"3716.0",
    "gn:asciiname":"Kuusemaee",
    "gn:country_code":"EE",
    "gn:dem":48,
    "gn:feature_class":"P",
    "gn:feature_code":"PPL",
    "gn:name":"Kuusem\u00e4e",
    "gn:population":0,
    "gn:timezone":"Europe/Tallinn",
    "iso:country":"EE",
    "name:est_x_preferred":[
        "Kuusem\u00e4e"
    ],
    "name:fra_x_preferred":[
        "Kuusem\u00e4e"
    ],
    "name:hye_x_preferred":[
        "\u053f\u0578\u0582\u0578\u0582\u057d\u0565\u0574\u0575\u0561\u0565"
    ],
    "name:nld_x_preferred":[
        "Kuusem\u00e4e"
    ],
    "name:pol_x_preferred":[
        "Kuusem\u00e4e"
    ],
    "name:sco_x_preferred":[
        "Kuusem\u00e4e"
    ],
    "name:slk_x_preferred":[
        "Kuusem\u00e4e"
    ],
    "name:spa_x_preferred":[
        "Kuusem\u00e4e"
    ],
    "name:vol_x_preferred":[
        "Kuusem\u00e4e"
    ],
    "wof:name":"Kuusemaee",
    "wof:placetype":"locality"
},
  "geometry": {"coordinates":[25.32278,59.36972],"type":"Point"}
}