{
  "type": "Feature",
  "properties": {
    "gn:admin1_code":"1.0",
    "gn:admin2_code":"141.0",
    "gn:admin3_code":"3716.0",
    "gn:asciiname":"Kuusemaee",
    "gn:country_code":"EE",
    "gn:dem":48,
    "gn:feature_class":"P",
    "gn:feature_code":"PPL",
    "gn:name":"Kuusem\u00e4e",
    "gn:population":0,
    "gn:timezone":"Europe/Tallinn",
    "iso:country":"EE",
    "name:und_x_variant":[
        "Kuusem\u00e4e"
    ],
    "wof:name":"Kuusemaee",
    "wof:placetype":"locality"
},
  "geometry": {"coordinates":[25.32278,59.36972],"type":"Point"}
}