{
  "type": "Feature",
  "properties": {
    "gn:admin1_code":"18.0",
    "gn:admin2_code":"283.0",
    "gn:admin3_code":"8165.0",
    "gn:asciiname":"Tatra",
    "gn:country_code":"EE",
    "gn:dem":63,
    "gn:feature_class":"P",
    "gn:feature_code":"PPL",
    "gn:name":"Tatra",
    "gn:population":0,
    "gn:timezone":"Europe/Tallinn",
    "iso:country":"EE",
    "wof:name":"Tatra",
    "wof:placetype":"locality"
},
  "geometry": {"coordinates":[26.68056,58.24722],"type":"Point"}
}