{
  "type": "Feature",
  "properties": {
    "gn:admin1_code":"18.0",
    "gn:admin2_code":"283.0",
    "gn:admin3_code":"8165.0",
    "gn:asciiname":"Tatra",
    "gn:country_code":"EE",
    "gn:dem":63,
    "gn:feature_class":"P",
    "gn:feature_code":"PPL",
    "gn:name":"Tatra",
    "gn:population":0,
    "gn:timezone":"Europe/Tallinn",
    "iso:country":"EE",
    "name:est_x_preferred":[
        "Tatra"
    ],
    "name:fra_x_preferred":[
        "Tatra"
    ],
    "name:hye_x_preferred":[
        "\u054f\u0561\u057f\u057c\u0561"
    ],
    "name:pol_x_preferred":[
        "Tatra"
    ],
    "name:spa_x_preferred":[
        "Tatra"
    ],
    "name:ukr_x_preferred":[
        "\u0422\u0430\u0442\u0440\u0430"
    ],
    "name:vol_x_preferred":[
        "Tatra"
    ],
    "wof:coterminous":[
        1713308863
    ],
    "wof:lang_x_official":[
        "est"
    ],
    "wof:lang_x_spoken":[
        "est"
    ],
    "wof:name":"Tatra",
    "wof:placetype":"locality"
},
  "geometry": {"coordinates":[26.68056,58.24722],"type":"Point"}
}