{
  "type": "Feature",
  "properties": {
    "gn:admin1_code":"11.0",
    "gn:admin2_code":"638.0",
    "gn:admin3_code":"5191.0",
    "gn:asciiname":"Linnamaee",
    "gn:country_code":"EE",
    "gn:dem":27,
    "gn:feature_class":"P",
    "gn:feature_code":"PPL",
    "gn:name":"Linnam\u00e4e",
    "gn:population":0,
    "gn:timezone":"Europe/Tallinn",
    "iso:country":"EE",
    "name:und_x_variant":[
        "Linnamaa",
        "Linnama",
        "Linnam\u00e4e"
    ],
    "wof:name":"Linnamaee",
    "wof:placetype":"locality"
},
  "geometry": {"coordinates":[24.41306,58.60471999999999],"type":"Point"}
}