{
  "type": "Feature",
  "properties": {
    "gn:admin1_code":"8.0",
    "gn:admin2_code":"792.0",
    "gn:admin3_code":"5551.0",
    "gn:asciiname":"Niidu",
    "gn:country_code":"EE",
    "gn:dem":104,
    "gn:feature_class":"P",
    "gn:feature_code":"PPL",
    "gn:name":"Niidu",
    "gn:population":0,
    "gn:timezone":"Europe/Tallinn",
    "iso:country":"EE",
    "name:ceb_x_preferred":[
        "Niidu"
    ],
    "name:est_x_preferred":[
        "Niidu"
    ],
    "name:hye_x_preferred":[
        "\u0546\u056b\u056b\u0564\u0578\u0582"
    ],
    "name:pol_x_preferred":[
        "Niidu"
    ],
    "name:spa_x_preferred":[
        "Niidu"
    ],
    "name:swe_x_preferred":[
        "Niidu"
    ],
    "name:vol_x_preferred":[
        "Niidu"
    ],
    "wof:name":"Niidu",
    "wof:placetype":"locality"
},
  "geometry": {"coordinates":[25.97917,59.24333000000001],"type":"Point"}
}