{
  "type": "Feature",
  "properties": {
    "gn:admin1_code":"1.0",
    "gn:admin2_code":"653.0",
    "gn:admin3_code":"7868.0",
    "gn:asciiname":"Seli",
    "gn:country_code":"EE",
    "gn:dem":54,
    "gn:feature_class":"P",
    "gn:feature_code":"PPL",
    "gn:name":"Seli",
    "gn:population":0,
    "gn:timezone":"Europe/Tallinn",
    "iso:country":"EE",
    "name:und_x_variant":[
        "Selik\u00fcla"
    ],
    "wof:name":"Seli",
    "wof:placetype":"locality"
},
  "geometry": {"coordinates":[25.09472,59.29139],"type":"Point"}
}