{
  "type": "Feature",
  "properties": {
    "gn:admin1_code":"19.0",
    "gn:admin2_code":"855.0",
    "gn:admin3_code":"9618.0",
    "gn:asciiname":"Vaeheru",
    "gn:country_code":"EE",
    "gn:dem":46,
    "gn:feature_class":"P",
    "gn:feature_code":"PPL",
    "gn:name":"V\u00e4heru",
    "gn:population":0,
    "gn:timezone":"Europe/Tallinn",
    "iso:country":"EE",
    "name:est_x_preferred":[
        "V\u00e4heru"
    ],
    "name:hye_x_preferred":[
        "\u054e\u0565\u0570\u0565\u057c\u0578\u0582"
    ],
    "name:pol_x_preferred":[
        "V\u00e4heru"
    ],
    "name:spa_x_preferred":[
        "V\u00e4heru"
    ],
    "name:ukr_x_preferred":[
        "\u0412\u044f\u0433\u0435\u0440\u0443"
    ],
    "name:vol_x_preferred":[
        "V\u00e4heru"
    ],
    "wof:coterminous":[
        1713310719
    ],
    "wof:lang_x_official":[
        "est"
    ],
    "wof:lang_x_spoken":[
        "est"
    ],
    "wof:name":"Vaeheru",
    "wof:placetype":"locality"
},
  "geometry": {"coordinates":[26.31472,57.79667],"type":"Point"}
}