{
  "type": "Feature",
  "properties": {
    "gn:admin1_code":"21.0",
    "gn:admin2_code":"917.0",
    "gn:admin3_code":"5188.0",
    "gn:asciiname":"Maee-Jaervere",
    "gn:country_code":"EE",
    "gn:dem":105,
    "gn:feature_class":"P",
    "gn:feature_code":"PPL",
    "gn:name":"M\u00e4e-J\u00e4rvere",
    "gn:population":0,
    "gn:timezone":"Europe/Tallinn",
    "iso:country":"EE",
    "wof:name":"Maee-Jaervere",
    "wof:placetype":"locality"
},
  "geometry": {"coordinates":[26.87694,57.89611],"type":"Point"}
}