{
  "type": "Feature",
  "properties": {
    "gn:country":"EE",
    "gn:fcode":"PPL",
    "gn:population":376,
    "iso:country":"EE",
    "name:ceb_x_preferred":[
        "Viru-Jaagupi"
    ],
    "name:ces_x_preferred":[
        "Viru-Jaagupi"
    ],
    "name:deu_x_preferred":[
        "Viru-Jaagupi"
    ],
    "name:eng_x_preferred":[
        "Viru-Jaagupi"
    ],
    "name:est_x_preferred":[
        "Viru-Jaagupi"
    ],
    "name:fra_x_preferred":[
        "Viru-Jaagupi"
    ],
    "name:hye_x_preferred":[
        "\u054e\u056b\u057c\u0578\u0582-\u0545\u0561\u0561\u0563\u0578\u0582\u057a\u056b"
    ],
    "name:kat_x_preferred":[
        "\u10d5\u10d8\u10e0\u10e3-\u10d8\u10d0\u10d0\u10d2\u10e3\u10de\u10d8"
    ],
    "name:nld_x_preferred":[
        "Viru-Jaagupi"
    ],
    "name:rus_x_preferred":[
        "\u0412\u0438\u0440\u0443-\u042f\u0430\u0433\u0443\u043f\u0438"
    ],
    "name:swe_x_preferred":[
        "Viru-Jaagupi"
    ],
    "name:und_x_variant":[
        "Sankt-Jakobi"
    ],
    "name:vol_x_preferred":[
        "Viru-Jaagupi"
    ],
    "qs_pg:aaroncc":"EE",
    "qs_pg:gn_country":"EE",
    "qs_pg:gn_fcode":"PPL",
    "qs_pg:gn_pop":376,
    "qs_pg:name":"Viru-Jaagupi",
    "qs_pg:name_adm0":"Eesti",
    "qs_pg:name_adm1":"L\u00e4\u00e4ne-Virumaa",
    "qs_pg:photos_9k":1,
    "qs_pg:photos_9r":2,
    "qs_pg:photos_all":47,
    "qs_pg:photos_sr":0,
    "qs_pg:pop_sr":2,
    "qs_pg:qs_pg_placetype":"locality",
    "qs_pg:qs_pg_placetype_gp":"Town",
    "qs_pg:woe_adm0":23424805,
    "woe:adm0_id":23424805,
    "woe:name_adm0":"Eesti",
    "woe:name_adm1":"L\u00e4\u00e4ne-Virumaa",
    "woe:placetype":"Town",
    "wof:name":"Viru-Jaagupi",
    "wof:placetype":"locality",
    "wof:population":376
},
  "geometry": {"coordinates":[26.47583,59.2425],"type":"Point"}
}