{
  "type": "Feature",
  "properties": {
    "gn:admin1_code":"7.0",
    "gn:admin2_code":"441.0",
    "gn:admin3_code":"6191.0",
    "gn:asciiname":"Annamoisa",
    "gn:country_code":"EE",
    "gn:dem":42,
    "gn:feature_class":"P",
    "gn:feature_code":"PPL",
    "gn:name":"Annam\u00f5isa",
    "gn:population":0,
    "gn:timezone":"Europe/Tallinn",
    "iso:country":"EE",
    "name:und_x_variant":[
        "Ankhamyiza",
        "Annam\u00f5isa"
    ],
    "wof:name":"Annamoisa",
    "wof:placetype":"locality"
},
  "geometry": {"coordinates":[24.09139,59.06556],"type":"Point"}
}