{
  "type": "Feature",
  "properties": {
    "gn:country":"EE",
    "gn:fcode":"PPL",
    "gn:population":854,
    "iso:country":"EE",
    "name:ceb_x_preferred":[
        "K\u00e4ina"
    ],
    "name:ces_x_preferred":[
        "K\u00e4ina"
    ],
    "name:deu_x_preferred":[
        "K\u00e4ina"
    ],
    "name:eng_x_preferred":[
        "K\u00e4ina"
    ],
    "name:est_x_preferred":[
        "K\u00e4ina"
    ],
    "name:fra_x_preferred":[
        "K\u00e4ina"
    ],
    "name:hye_x_preferred":[
        "\u053f\u0565\u056b\u0576\u0561"
    ],
    "name:lit_x_preferred":[
        "Keina"
    ],
    "name:pol_x_preferred":[
        "K\u00e4ina"
    ],
    "name:ron_x_preferred":[
        "K\u00e4ina"
    ],
    "name:srp_x_preferred":[
        "\u041a\u0430\u0458\u043d\u0430"
    ],
    "name:swe_x_preferred":[
        "K\u00e4ina"
    ],
    "name:und_x_variant":[
        "Kyayna"
    ],
    "name:vol_x_preferred":[
        "K\u00e4ina"
    ],
    "name:zho_x_preferred":[
        "\u51f1\u4f0a\u7d0d"
    ],
    "qs_pg:aaroncc":"EE",
    "qs_pg:gn_country":"EE",
    "qs_pg:gn_fcode":"PPL",
    "qs_pg:gn_pop":854,
    "qs_pg:name":"K\u00e4ina",
    "qs_pg:name_adm0":"Eesti",
    "qs_pg:name_adm1":"Hiiumaa",
    "qs_pg:photos_9k":1,
    "qs_pg:photos_9r":1,
    "qs_pg:photos_all":7,
    "qs_pg:photos_sr":0,
    "qs_pg:pop_sr":2,
    "qs_pg:qs_pg_placetype":"locality",
    "qs_pg:qs_pg_placetype_gp":"Town",
    "qs_pg:woe_adm0":23424805,
    "woe:adm0_id":23424805,
    "woe:name_adm0":"Eesti",
    "woe:name_adm1":"Hiiumaa",
    "woe:placetype":"Town",
    "wof:name":"K\u00e4ina",
    "wof:placetype":"locality",
    "wof:population":854
},
  "geometry": {"coordinates":[22.78972,58.82556],"type":"Point"}
}