{
  "type": "Feature",
  "properties": {
    "gn:admin1_code":"14.0",
    "gn:admin2_code":"714.0",
    "gn:admin3_code":"4604.0",
    "gn:asciiname":"Toomalouka",
    "gn:cc2":"EE",
    "gn:country_code":"EE",
    "gn:dem":5,
    "gn:feature_class":"P",
    "gn:feature_code":"PPL",
    "gn:name":"Toomal\u00f5uka",
    "gn:population":0,
    "gn:timezone":"Europe/Tallinn",
    "iso:country":"EE",
    "name:deu_x_preferred":[
        "Toomal\u00f5uka"
    ],
    "name:est_x_preferred":[
        "Toomal\u00f5uka"
    ],
    "name:fin_x_preferred":[
        "Toomal\u00f5uka"
    ],
    "name:hye_x_preferred":[
        "\u054f\u0578\u0578\u0574\u0561\u056c\u056b\u0578\u0582\u056f\u0561"
    ],
    "name:nld_x_preferred":[
        "Toomal\u00f5uka"
    ],
    "name:pol_x_preferred":[
        "Toomal\u00f5uka"
    ],
    "name:spa_x_preferred":[
        "Toomal\u00f5uka"
    ],
    "name:ukr_x_preferred":[
        "\u0422\u043e\u043e\u043c\u0430\u043b\u0438\u0443\u043a\u0430"
    ],
    "name:und_x_variant":[
        "Tooma-L\u00f5uka",
        "Tomalyuka",
        "Toomalauka"
    ],
    "name:vol_x_preferred":[
        "Toomal\u00f5uka"
    ],
    "wof:lang_x_official":[
        "est"
    ],
    "wof:lang_x_spoken":[
        "est"
    ],
    "wof:name":"Toomalouka",
    "wof:placetype":"locality"
},
  "geometry": {"coordinates":[22.11889,58.17889],"type":"Point"}
}