{
  "type": "Feature",
  "properties": {
    "gn:admin1_code":"14.0",
    "gn:admin2_code":"714.0",
    "gn:admin3_code":"4604.0",
    "gn:asciiname":"Toomalouka",
    "gn:cc2":"EE",
    "gn:country_code":"EE",
    "gn:dem":5,
    "gn:feature_class":"P",
    "gn:feature_code":"PPL",
    "gn:name":"Toomal\u00f5uka",
    "gn:population":0,
    "gn:timezone":"Europe/Tallinn",
    "iso:country":"EE",
    "name:und_x_variant":[
        "Tooma-L\u00f5uka",
        "Tomalyuka",
        "Toomalauka",
        "Toomal\u00f5uka"
    ],
    "wof:name":"Toomalouka",
    "wof:placetype":"locality"
},
  "geometry": {"coordinates":[22.11889,58.17889],"type":"Point"}
}