{
  "type": "Feature",
  "properties": {
    "gn:admin1_code":"21.0",
    "gn:admin2_code":"917.0",
    "gn:admin3_code":"9218.0",
    "gn:asciiname":"Meeldemaee",
    "gn:country_code":"EE",
    "gn:dem":124,
    "gn:feature_class":"P",
    "gn:feature_code":"PPL",
    "gn:name":"Meeldem\u00e4e",
    "gn:population":0,
    "gn:timezone":"Europe/Tallinn",
    "iso:country":"EE",
    "name:und_x_variant":[
        "Meeldem\u00e4e",
        "Meldem\u00e4e"
    ],
    "wof:name":"Meeldemaee",
    "wof:placetype":"locality"
},
  "geometry": {"coordinates":[27.08333,57.80444],"type":"Point"}
}