{
  "type": "Feature",
  "properties": {
    "gn:admin1_code":"20.0",
    "gn:admin2_code":"899.0",
    "gn:admin3_code":"4814.0",
    "gn:asciiname":"Matapera",
    "gn:country_code":"EE",
    "gn:dem":71,
    "gn:feature_class":"P",
    "gn:feature_code":"PPL",
    "gn:name":"Matapera",
    "gn:population":0,
    "gn:timezone":"Europe/Tallinn",
    "iso:country":"EE",
    "wof:name":"Matapera",
    "wof:placetype":"locality"
},
  "geometry": {"coordinates":[25.55806,58.33306],"type":"Point"}
}