{
  "type": "Feature",
  "properties": {
    "gn:admin1_code":"1.0",
    "gn:admin2_code":"431.0",
    "gn:admin3_code":"5424.0",
    "gn:asciiname":"Niitvaelja",
    "gn:country_code":"EE",
    "gn:dem":32,
    "gn:feature_class":"P",
    "gn:feature_code":"PPL",
    "gn:name":"Niitv\u00e4lja",
    "gn:population":0,
    "gn:timezone":"Europe/Tallinn",
    "iso:country":"EE",
    "name:und_x_variant":[
        "Niitv\u00e4lja"
    ],
    "wof:name":"Niitvaelja",
    "wof:placetype":"locality"
},
  "geometry": {"coordinates":[24.32361,59.30722],"type":"Point"}
}