{
  "type": "Feature",
  "properties": {
    "gn:admin1_code":"1.0",
    "gn:admin2_code":"431.0",
    "gn:admin3_code":"5424.0",
    "gn:asciiname":"Niitvaelja",
    "gn:country_code":"EE",
    "gn:dem":32,
    "gn:feature_class":"P",
    "gn:feature_code":"PPL",
    "gn:name":"Niitv\u00e4lja",
    "gn:population":0,
    "gn:timezone":"Europe/Tallinn",
    "iso:country":"EE",
    "name:est_x_preferred":[
        "Niitv\u00e4lja"
    ],
    "name:fra_x_preferred":[
        "Niitv\u00e4lja"
    ],
    "name:hye_x_preferred":[
        "\u0546\u056b\u056b\u057f\u057e\u0565\u056c\u0575\u0561"
    ],
    "name:pol_x_preferred":[
        "Niitv\u00e4lja"
    ],
    "name:spa_x_preferred":[
        "Niitv\u00e4lja"
    ],
    "name:swe_x_preferred":[
        "Niitv\u00e4lja"
    ],
    "name:ukr_x_preferred":[
        "\u041d\u0456\u0439\u0442\u0432\u044f\u043b\u044c\u044f"
    ],
    "name:vol_x_preferred":[
        "Niitv\u00e4lja"
    ],
    "wof:lang_x_official":[
        "est"
    ],
    "wof:lang_x_spoken":[
        "est"
    ],
    "wof:name":"Niitvaelja",
    "wof:placetype":"locality"
},
  "geometry": {"coordinates":[24.32361,59.30722],"type":"Point"}
}