{
  "type": "Feature",
  "properties": {
    "gn:gn_country":"EE",
    "gn:gn_fcode":"PPL",
    "gn:gn_pop":144,
    "gn:population":144,
    "iso:country":"EE",
    "name:bul_x_preferred":[
        "\u041a\u0443\u0434\u0438\u043d\u0430"
    ],
    "name:eng_x_preferred":[
        "Kudina"
    ],
    "name:est_x_preferred":[
        "Kudina"
    ],
    "name:hye_x_preferred":[
        "\u053f\u0578\u0582\u0564\u056b\u0576\u0561"
    ],
    "name:nld_x_preferred":[
        "Kudina"
    ],
    "name:pol_x_preferred":[
        "Kudina"
    ],
    "name:swe_x_preferred":[
        "Kudina"
    ],
    "name:unk_x_variant":[
        "Myza Kudina"
    ],
    "name:vol_x_preferred":[
        "Kudina"
    ],
    "qs_pg:aaroncc":"EE",
    "qs_pg:gn_country":"EE",
    "qs_pg:gn_fcode":"PPL",
    "qs_pg:gn_pop":144,
    "qs_pg:name":"Kudina",
    "qs_pg:name_adm0":"Eesti",
    "qs_pg:name_adm1":"J\u00f5gevamaa",
    "qs_pg:photos_9k":1,
    "qs_pg:photos_9r":1,
    "qs_pg:photos_all":1,
    "qs_pg:photos_sr":0,
    "qs_pg:pop_sr":1,
    "qs_pg:qs_pg_placetype":"locality",
    "qs_pg:qs_pg_placetype_gp":"Town",
    "qs_pg:woe_adm0":23424805,
    "woe:adm0_id":23424805,
    "woe:name_adm0":"Eesti",
    "woe:name_adm1":"J\u00f5gevamaa",
    "woe:placetype":"Town",
    "wof:name":"Kudina",
    "wof:placetype":"locality",
    "wof:population":144
},
  "geometry": {"coordinates":[26.69028,58.66889],"type":"Point"}
}