{
  "type": "Feature",
  "properties": {
    "gn:admin1_code":"13.0",
    "gn:admin2_code":"317.0",
    "gn:admin3_code":"5250.0",
    "gn:asciiname":"Maelivere",
    "gn:country_code":"EE",
    "gn:dem":65,
    "gn:feature_class":"P",
    "gn:feature_code":"PPL",
    "gn:name":"M\u00e4livere",
    "gn:population":0,
    "gn:timezone":"Europe/Tallinn",
    "iso:country":"EE",
    "name:est_x_preferred":[
        "M\u00e4livere"
    ],
    "name:hye_x_preferred":[
        "\u0544\u0565\u056c\u056b\u057e\u0565\u057c\u0565"
    ],
    "name:pol_x_preferred":[
        "M\u00e4livere"
    ],
    "name:rus_x_preferred":[
        "\u041c\u044f\u043b\u0438\u0432\u0435\u0440\u0435"
    ],
    "name:sco_x_preferred":[
        "M\u00e4livere"
    ],
    "name:spa_x_preferred":[
        "M\u00e4livere"
    ],
    "name:und_x_variant":[
        "Myalivere"
    ],
    "name:vol_x_preferred":[
        "M\u00e4livere"
    ],
    "wof:coterminous":[
        1713313313
    ],
    "wof:lang_x_official":[
        "est"
    ],
    "wof:lang_x_spoken":[
        "est"
    ],
    "wof:name":"Maelivere",
    "wof:placetype":"locality"
},
  "geometry": {"coordinates":[24.79972,59.11111],"type":"Point"}
}