{
  "type": "Feature",
  "properties": {
    "gn:admin1_code":"13.0",
    "gn:admin2_code":"317.0",
    "gn:admin3_code":"5250.0",
    "gn:asciiname":"Maelivere",
    "gn:country_code":"EE",
    "gn:dem":65,
    "gn:feature_class":"P",
    "gn:feature_code":"PPL",
    "gn:name":"M\u00e4livere",
    "gn:population":0,
    "gn:timezone":"Europe/Tallinn",
    "iso:country":"EE",
    "name:und_x_variant":[
        "Myalivere",
        "M\u00e4livere"
    ],
    "wof:name":"Maelivere",
    "wof:placetype":"locality"
},
  "geometry": {"coordinates":[24.79972,59.11111],"type":"Point"}
}