{
  "type": "Feature",
  "properties": {
    "gn:country":"EE",
    "gn:fcode":"PPL",
    "gn:population":117,
    "iso:country":"EE",
    "name:ceb_x_preferred":[
        "Saadj\u00e4rve"
    ],
    "name:eng_x_preferred":[
        "Saadj\u00e4rve"
    ],
    "name:est_x_preferred":[
        "Saadj\u00e4rve"
    ],
    "name:fra_x_preferred":[
        "Saadj\u00e4rve"
    ],
    "name:hye_x_preferred":[
        "\u054d\u0561\u0561\u0564\u0575\u0565\u057c\u057e\u0565"
    ],
    "name:nld_x_preferred":[
        "Saadj\u00e4rve"
    ],
    "name:pol_x_preferred":[
        "Saadj\u00e4rve"
    ],
    "name:spa_x_preferred":[
        "Saadj\u00e4rve"
    ],
    "name:swe_x_preferred":[
        "Saadj\u00e4rve"
    ],
    "name:ukr_x_preferred":[
        "\u0421\u0430\u0430\u0434\u044c\u044f\u0440\u0432\u0435"
    ],
    "name:urd_x_preferred":[
        "\u0633\u0627\u062f\u062c\u0631\u0648\u06d2"
    ],
    "name:vol_x_preferred":[
        "Saadj\u00e4rve"
    ],
    "qs_pg:aaroncc":"EE",
    "qs_pg:gn_country":"EE",
    "qs_pg:gn_fcode":"PPL",
    "qs_pg:gn_pop":117,
    "qs_pg:name":"Saadj\u00e4rve",
    "qs_pg:name_adm0":"Eesti",
    "qs_pg:name_adm1":"Tartumaa",
    "qs_pg:photos_9k":1,
    "qs_pg:photos_9r":1,
    "qs_pg:photos_all":11,
    "qs_pg:photos_sr":0,
    "qs_pg:pop_sr":1,
    "qs_pg:qs_pg_placetype":"locality",
    "qs_pg:qs_pg_placetype_gp":"Town",
    "qs_pg:woe_adm0":23424805,
    "woe:adm0_id":23424805,
    "woe:name_adm0":"Eesti",
    "woe:name_adm1":"Tartumaa",
    "woe:placetype":"Town",
    "wof:lang_x_official":[
        "est"
    ],
    "wof:lang_x_spoken":[
        "est"
    ],
    "wof:name":"Saadj\u00e4rve",
    "wof:placetype":"locality",
    "wof:population":117
},
  "geometry": {"coordinates":[26.67306,58.54472],"type":"Point"}
}