{
  "type": "Feature",
  "properties": {
    "gn:admin1_code":"14.0",
    "gn:admin2_code":"714.0",
    "gn:admin3_code":"7834.0",
    "gn:asciiname":"Vaetta",
    "gn:country_code":"EE",
    "gn:dem":4,
    "gn:feature_class":"P",
    "gn:feature_code":"PPL",
    "gn:name":"V\u00e4tta",
    "gn:population":0,
    "gn:timezone":"Europe/Tallinn",
    "iso:country":"EE",
    "wof:name":"Vaetta",
    "wof:placetype":"locality"
},
  "geometry": {"coordinates":[22.74194,58.22778],"type":"Point"}
}