{
  "type": "Feature",
  "properties": {
    "gn:admin1_code":"11.0",
    "gn:admin2_code":"430.0",
    "gn:admin3_code":"9544.0",
    "gn:asciiname":"Voitra",
    "gn:cc2":"EE",
    "gn:country_code":"EE",
    "gn:dem":25,
    "gn:feature_class":"P",
    "gn:feature_code":"PPL",
    "gn:name":"V\u00f5itra",
    "gn:population":0,
    "gn:timezone":"Europe/Tallinn",
    "iso:country":"EE",
    "name:est_x_preferred":[
        "V\u00f5itra"
    ],
    "name:hye_x_preferred":[
        "\u054e\u056b\u056b\u057f\u057c\u0561"
    ],
    "name:pol_x_preferred":[
        "V\u00f5itra"
    ],
    "name:spa_x_preferred":[
        "V\u00f5itra"
    ],
    "name:und_x_variant":[
        "Vyitra"
    ],
    "name:vol_x_preferred":[
        "V\u00f5itra"
    ],
    "wof:lang_x_official":[
        "est"
    ],
    "wof:lang_x_spoken":[
        "est"
    ],
    "wof:name":"Voitra",
    "wof:placetype":"locality"
},
  "geometry": {"coordinates":[24.10556,58.56722],"type":"Point"}
}