{
  "type": "Feature",
  "properties": {
    "gn:admin1_code":"11.0",
    "gn:admin2_code":"430.0",
    "gn:admin3_code":"9544.0",
    "gn:asciiname":"Voitra",
    "gn:cc2":"EE",
    "gn:country_code":"EE",
    "gn:dem":25,
    "gn:feature_class":"P",
    "gn:feature_code":"PPL",
    "gn:name":"V\u00f5itra",
    "gn:population":0,
    "gn:timezone":"Europe/Tallinn",
    "iso:country":"EE",
    "name:und_x_variant":[
        "Vyitra",
        "V\u00f5itra"
    ],
    "wof:name":"Voitra",
    "wof:placetype":"locality"
},
  "geometry": {"coordinates":[24.10556,58.56721999999999],"type":"Point"}
}