{
  "type": "Feature",
  "properties": {
    "gn:admin1_code":"12.0",
    "gn:admin2_code":"708.0",
    "gn:admin3_code":"2241.0",
    "gn:asciiname":"Joepera",
    "gn:cc2":"EE",
    "gn:country_code":"EE",
    "gn:dem":34,
    "gn:feature_class":"P",
    "gn:feature_code":"PPL",
    "gn:name":"J\u00f5epera",
    "gn:population":0,
    "gn:timezone":"Europe/Tallinn",
    "iso:country":"EE",
    "name:eng_x_preferred":[
        "J\u00f5epera"
    ],
    "name:est_x_preferred":[
        "J\u00f5epera"
    ],
    "name:fra_x_preferred":[
        "J\u00f5epera"
    ],
    "name:hye_x_preferred":[
        "\u0545\u056b\u0565\u057a\u0565\u057c\u0561"
    ],
    "name:nld_x_preferred":[
        "J\u00f5epera"
    ],
    "name:pol_x_preferred":[
        "J\u00f5epera"
    ],
    "name:rus_x_preferred":[
        "\u0419\u044b\u044d\u043d\u0435\u0440\u0430"
    ],
    "name:spa_x_preferred":[
        "J\u00f5epera"
    ],
    "name:ukr_x_preferred":[
        "\u0419\u0438\u0435\u043f\u0435\u0440\u0430"
    ],
    "name:und_x_variant":[
        "Yyyepera"
    ],
    "name:vol_x_preferred":[
        "J\u00f5epera"
    ],
    "wof:lang_x_official":[
        "est"
    ],
    "wof:lang_x_spoken":[
        "est"
    ],
    "wof:name":"Joepera",
    "wof:placetype":"locality"
},
  "geometry": {"coordinates":[27.43583,58.26333],"type":"Point"}
}