{
  "type": "Feature",
  "properties": {
    "gn:admin1_code":"11.0",
    "gn:admin2_code":"712.0",
    "gn:admin3_code":"7280.0",
    "gn:asciiname":"Saarde",
    "gn:cc2":"EE",
    "gn:country_code":"EE",
    "gn:dem":68,
    "gn:feature_class":"P",
    "gn:feature_code":"PPL",
    "gn:name":"Saarde",
    "gn:population":0,
    "gn:timezone":"Europe/Tallinn",
    "iso:country":"EE",
    "name:est_x_preferred":[
        "Saarde"
    ],
    "name:fra_x_preferred":[
        "Saarde"
    ],
    "name:hye_x_preferred":[
        "\u054d\u0561\u0561\u057c\u0564\u0565"
    ],
    "name:spa_x_preferred":[
        "Saarde"
    ],
    "name:und_x_variant":[
        "Saara"
    ],
    "name:urd_x_preferred":[
        "\u0633\u0627\u0631\u062f\u06d2"
    ],
    "name:vol_x_preferred":[
        "Saarde"
    ],
    "wof:lang_x_official":[
        "est"
    ],
    "wof:lang_x_spoken":[
        "est"
    ],
    "wof:name":"Saarde",
    "wof:placetype":"locality"
},
  "geometry": {"coordinates":[24.97444,58.13944],"type":"Point"}
}