{
  "type": "Feature",
  "properties": {
    "gn:admin1_code":"14.0",
    "gn:admin2_code":"714.0",
    "gn:admin3_code":"6842.0",
    "gn:asciiname":"Ratla",
    "gn:country_code":"EE",
    "gn:dem":18,
    "gn:feature_class":"P",
    "gn:feature_code":"PPL",
    "gn:name":"Ratla",
    "gn:population":0,
    "gn:timezone":"Europe/Tallinn",
    "iso:country":"EE",
    "wof:name":"Ratla",
    "wof:placetype":"locality"
},
  "geometry": {"coordinates":[22.83056,58.47556],"type":"Point"}
}