{
  "type": "Feature",
  "properties": {
    "gn:admin1_code":"4.0",
    "gn:admin2_code":"255.0",
    "gn:admin3_code":"1920.0",
    "gn:asciiname":"Huuksi",
    "gn:cc2":"EE",
    "gn:country_code":"EE",
    "gn:dem":74,
    "gn:feature_class":"P",
    "gn:feature_code":"PPL",
    "gn:name":"Huuksi",
    "gn:population":0,
    "gn:timezone":"Europe/Tallinn",
    "iso:country":"EE",
    "name:est_x_preferred":[
        "Huuksi"
    ],
    "name:hye_x_preferred":[
        "\u0540\u0578\u0582\u0578\u0582\u056f\u057d\u056b"
    ],
    "name:nld_x_preferred":[
        "Huuksi"
    ],
    "name:pol_x_preferred":[
        "Huuksi"
    ],
    "name:spa_x_preferred":[
        "Huuksi"
    ],
    "name:ukr_x_preferred":[
        "\u0413\u0443\u0443\u043a\u0441\u0456"
    ],
    "name:und_x_variant":[
        "Myza Khuksi",
        "Huuksi"
    ],
    "name:vol_x_preferred":[
        "Huuksi"
    ],
    "wof:name":"Huuksi",
    "wof:placetype":"locality"
},
  "geometry": {"coordinates":[25.81056,58.84028000000001],"type":"Point"}
}