{
  "type": "Feature",
  "properties": {
    "gn:admin1_code":"21.0",
    "gn:admin2_code":"732.0",
    "gn:admin3_code":"7243.0",
    "gn:asciiname":"Raeaeptsova",
    "gn:country_code":"EE",
    "gn:dem":59,
    "gn:feature_class":"P",
    "gn:feature_code":"PPL",
    "gn:name":"R\u00e4\u00e4ptsova",
    "gn:population":0,
    "gn:timezone":"Europe/Tallinn",
    "iso:country":"EE",
    "name:und_x_variant":[
        "R\u00e4btsev",
        "Suur R\u00e4\u00e4ptsova",
        "R\u00e4\u00e4ptsova",
        "R\u00e4\u00e4pts\u00fcv\u00e4"
    ],
    "wof:name":"Raeaeptsova",
    "wof:placetype":"locality"
},
  "geometry": {"coordinates":[27.715,57.85917],"type":"Point"}
}