{
  "type": "Feature",
  "properties": {
    "gn:admin1_code":"21.0",
    "gn:admin2_code":"732.0",
    "gn:admin3_code":"7243.0",
    "gn:asciiname":"Raeaeptsova",
    "gn:country_code":"EE",
    "gn:dem":59,
    "gn:feature_class":"P",
    "gn:feature_code":"PPL",
    "gn:name":"R\u00e4\u00e4ptsova",
    "gn:population":0,
    "gn:timezone":"Europe/Tallinn",
    "iso:country":"EE",
    "name:est_x_preferred":[
        "R\u00e4\u00e4ptsova"
    ],
    "name:hye_x_preferred":[
        "\u054c\u0565\u0565\u057a\u0581\u0578\u057e\u0561"
    ],
    "name:pol_x_preferred":[
        "R\u00e4\u00e4ptsova"
    ],
    "name:sco_x_preferred":[
        "R\u00e4\u00e4ptsova"
    ],
    "name:spa_x_preferred":[
        "R\u00e4\u00e4ptsova"
    ],
    "name:ukr_x_preferred":[
        "\u0420\u044f\u044f\u043f\u0442\u0441\u043e\u0432\u0430"
    ],
    "name:und_x_variant":[
        "R\u00e4btsev",
        "Suur R\u00e4\u00e4ptsova",
        "R\u00e4\u00e4pts\u00fcv\u00e4"
    ],
    "name:vol_x_preferred":[
        "R\u00e4\u00e4ptsova"
    ],
    "wof:coterminous":[
        1713316003
    ],
    "wof:lang_x_official":[
        "est"
    ],
    "wof:lang_x_spoken":[
        "est"
    ],
    "wof:name":"Raeaeptsova",
    "wof:placetype":"locality"
},
  "geometry": {"coordinates":[27.715,57.85917],"type":"Point"}
}