{
  "type": "Feature",
  "properties": {
    "gn:admin1_code":"18.0",
    "gn:admin2_code":"796.0",
    "gn:admin3_code":"3970.0",
    "gn:asciiname":"Korbi",
    "gn:country_code":"EE",
    "gn:dem":56,
    "gn:feature_class":"P",
    "gn:feature_code":"PPL",
    "gn:name":"Korbi",
    "gn:population":0,
    "gn:timezone":"Europe/Tallinn",
    "iso:country":"EE",
    "name:und_x_variant":[
        "Karbi"
    ],
    "wof:name":"Korbi",
    "wof:placetype":"locality"
},
  "geometry": {"coordinates":[26.92167,58.42194],"type":"Point"}
}