{
  "type": "Feature",
  "properties": {
    "gn:admin1_code":"1.0",
    "gn:admin2_code":"726.0",
    "gn:admin3_code":"6603.0",
    "gn:asciiname":"Paerinurme",
    "gn:country_code":"EE",
    "gn:dem":61,
    "gn:feature_class":"P",
    "gn:feature_code":"PPL",
    "gn:name":"P\u00e4rinurme",
    "gn:population":0,
    "gn:timezone":"Europe/Tallinn",
    "iso:country":"EE",
    "name:est_x_preferred":[
        "P\u00e4rinurme"
    ],
    "name:fra_x_preferred":[
        "P\u00e4rinurme"
    ],
    "name:hye_x_preferred":[
        "\u054a\u0565\u057c\u056b\u0576\u0578\u0582\u057c\u0574\u0565"
    ],
    "name:rus_x_preferred":[
        "\u041f\u044f\u0440\u0438\u043d\u0443\u0440\u043c\u0435"
    ],
    "name:spa_x_preferred":[
        "P\u00e4rinurme"
    ],
    "name:ukr_x_preferred":[
        "\u041f\u044f\u0440\u0456\u043d\u0443\u0440\u043c\u0435"
    ],
    "name:und_x_variant":[
        "Pyarinurme"
    ],
    "name:vol_x_preferred":[
        "P\u00e4rinurme"
    ],
    "wof:name":"Paerinurme",
    "wof:placetype":"locality"
},
  "geometry": {"coordinates":[24.58583,59.20083],"type":"Point"}
}