{
  "type": "Feature",
  "properties": {
    "gn:admin1_code":"7.0",
    "gn:admin2_code":"184.0",
    "gn:admin3_code":"7029.0",
    "gn:asciiname":"Rohense",
    "gn:country_code":"EE",
    "gn:dem":8,
    "gn:feature_class":"P",
    "gn:feature_code":"PPL",
    "gn:name":"Rohense",
    "gn:population":0,
    "gn:timezone":"Europe/Tallinn",
    "iso:country":"EE",
    "name:und_x_variant":[
        "Rokhense",
        "Rohense"
    ],
    "wof:name":"Rohense",
    "wof:placetype":"locality"
},
  "geometry": {"coordinates":[23.62167,58.92167],"type":"Point"}
}