{
  "type": "Feature",
  "properties": {
    "gn:admin1_code":"7.0",
    "gn:admin2_code":"184.0",
    "gn:admin3_code":"7029.0",
    "gn:asciiname":"Rohense",
    "gn:country_code":"EE",
    "gn:dem":8,
    "gn:feature_class":"P",
    "gn:feature_code":"PPL",
    "gn:name":"Rohense",
    "gn:population":0,
    "gn:timezone":"Europe/Tallinn",
    "iso:country":"EE",
    "name:deu_x_preferred":[
        "Rohense"
    ],
    "name:est_x_preferred":[
        "Rohense"
    ],
    "name:hye_x_preferred":[
        "\u054c\u0578\u0570\u0565\u0576\u057d\u0565"
    ],
    "name:pol_x_preferred":[
        "Rohense"
    ],
    "name:ukr_x_preferred":[
        "\u0420\u043e\u0433\u0435\u043d\u0441\u0435"
    ],
    "name:und_x_variant":[
        "Rokhense",
        "Rohense"
    ],
    "name:vol_x_preferred":[
        "Rohense"
    ],
    "wof:name":"Rohense",
    "wof:placetype":"locality"
},
  "geometry": {"coordinates":[23.62167,58.92167],"type":"Point"}
}