{
  "type": "Feature",
  "properties": {
    "gn:gn_country":"EE",
    "gn:gn_fcode":"PPL",
    "gn:gn_pop":93,
    "gn:population":93,
    "iso:country":"EE",
    "name:eng_x_preferred":[
        "P\u00f5hara"
    ],
    "name:est_x_preferred":[
        "P\u00f5hara"
    ],
    "name:hye_x_preferred":[
        "\u054a\u056b\u0570\u0561\u057c\u0561"
    ],
    "name:nld_x_preferred":[
        "P\u00f5hara"
    ],
    "name:pol_x_preferred":[
        "P\u00f5hara"
    ],
    "name:rus_x_preferred":[
        "\u041f\u044b\u0445\u0430\u0440\u0430"
    ],
    "name:unk_x_variant":[
        "Pykhara"
    ],
    "name:vol_x_preferred":[
        "P\u00f5hara"
    ],
    "qs_pg:aaroncc":"EE",
    "qs_pg:gn_country":"EE",
    "qs_pg:gn_fcode":"PPL",
    "qs_pg:gn_pop":93,
    "qs_pg:name":"P\u00f5hara",
    "qs_pg:name_adm0":"Eesti",
    "qs_pg:name_adm1":"P\u00e4rnumaa",
    "qs_pg:photos_9r":0,
    "qs_pg:photos_sr":0,
    "qs_pg:pop_sr":1,
    "qs_pg:qs_pg_placetype":"locality",
    "qs_pg:qs_pg_placetype_gp":"Town",
    "qs_pg:woe_adm0":23424805,
    "woe:adm0_id":23424805,
    "woe:name_adm0":"Eesti",
    "woe:name_adm1":"P\u00e4rnumaa",
    "woe:placetype":"Town",
    "wof:name":"P\u00f5hara",
    "wof:placetype":"locality",
    "wof:population":93
},
  "geometry": {"coordinates":[24.22333,58.46389],"type":"Point"}
}