{
  "type": "Feature",
  "properties": {
    "gn:admin1_code":"14.0",
    "gn:admin2_code":"714.0",
    "gn:admin3_code":"5190.0",
    "gn:asciiname":"Maeebe",
    "gn:country_code":"EE",
    "gn:dem":11,
    "gn:feature_class":"P",
    "gn:feature_code":"PPL",
    "gn:name":"M\u00e4ebe",
    "gn:population":0,
    "gn:timezone":"Europe/Tallinn",
    "iso:country":"EE",
    "name:und_x_variant":[
        "M\u00e4ep\u00e4\u00e4",
        "Myayebe",
        "Meit",
        "Meyepaa",
        "Maelie",
        "M\u00e4ebe"
    ],
    "wof:name":"Maeebe",
    "wof:placetype":"locality"
},
  "geometry": {"coordinates":[22.16139,57.97333],"type":"Point"}
}