{
  "type": "Feature",
  "properties": {
    "gn:admin1_code":"11.0",
    "gn:admin2_code":"430.0",
    "gn:admin3_code":"8663.0",
    "gn:asciiname":"Ullaste",
    "gn:country_code":"EE",
    "gn:dem":9,
    "gn:feature_class":"P",
    "gn:feature_code":"PPL",
    "gn:name":"Ullaste",
    "gn:population":0,
    "gn:timezone":"Europe/Tallinn",
    "iso:country":"EE",
    "name:deu_x_preferred":[
        "Ullaste"
    ],
    "name:est_x_preferred":[
        "Ullaste"
    ],
    "name:hye_x_preferred":[
        "\u0548\u0582\u056c\u056c\u0561\u057d\u057f\u0565"
    ],
    "name:nld_x_preferred":[
        "Ullaste"
    ],
    "name:pol_x_preferred":[
        "Ullaste"
    ],
    "name:spa_x_preferred":[
        "Ullaste"
    ],
    "name:ukr_x_preferred":[
        "\u0423\u043b\u043b\u0430\u0441\u0442\u0435"
    ],
    "name:vol_x_preferred":[
        "Ullaste"
    ],
    "wof:name":"Ullaste",
    "wof:placetype":"locality"
},
  "geometry": {"coordinates":[23.59944,58.69944],"type":"Point"}
}