{
  "type": "Feature",
  "properties": {
    "gn:admin1_code":"11.0",
    "gn:admin2_code":"430.0",
    "gn:admin3_code":"8663.0",
    "gn:asciiname":"Ullaste",
    "gn:country_code":"EE",
    "gn:dem":9,
    "gn:feature_class":"P",
    "gn:feature_code":"PPL",
    "gn:name":"Ullaste",
    "gn:population":0,
    "gn:timezone":"Europe/Tallinn",
    "iso:country":"EE",
    "wof:name":"Ullaste",
    "wof:placetype":"locality"
},
  "geometry": {"coordinates":[23.59944,58.69944],"type":"Point"}
}