{
  "type": "Feature",
  "properties": {
    "gn:gn_country":"EE",
    "gn:gn_fcode":"PPL",
    "gn:gn_pop":187,
    "gn:population":187,
    "iso:country":"EE",
    "name:eng_x_preferred":[
        "Palupera Parish"
    ],
    "name:est_x_preferred":[
        "Palupera vald"
    ],
    "name:fas_x_preferred":[
        "\u062f\u0647\u0633\u062a\u0627\u0646 \u067e\u0627\u0644\u0648\u067e\u0631\u0627"
    ],
    "name:fra_x_preferred":[
        "Commune de Palupera"
    ],
    "name:hye_x_preferred":[
        "\u054a\u0561\u056c\u0578\u0582\u057a\u0565\u057c\u0561"
    ],
    "name:kat_x_preferred":[
        "\u10de\u10d0\u10da\u10e3\u10de\u10d4\u10e0\u10d8\u10e1 \u10db\u10e3\u10dc\u10d8\u10ea\u10d8\u10de\u10d0\u10da\u10d8\u10e2\u10d4\u10e2\u10d8"
    ],
    "name:nor_x_preferred":[
        "Palupera kommune"
    ],
    "name:pol_x_preferred":[
        "Gmina Palupera"
    ],
    "name:ron_x_preferred":[
        "Comuna Palupera"
    ],
    "name:rus_x_preferred":[
        "\u041f\u0430\u043b\u0443\u043f\u0435\u0440\u0430"
    ],
    "name:ukr_x_preferred":[
        "\u041f\u0430\u043b\u0443\u043f\u0435\u0440\u0430"
    ],
    "name:unk_x_variant":[
        "Palupera Asundus"
    ],
    "qs_pg:aaroncc":"EE",
    "qs_pg:gn_country":"EE",
    "qs_pg:gn_fcode":"PPL",
    "qs_pg:gn_pop":187,
    "qs_pg:name":"Palupera",
    "qs_pg:name_adm0":"Eesti",
    "qs_pg:name_adm1":"Valgamaa",
    "qs_pg:photos_9k":1,
    "qs_pg:photos_9r":1,
    "qs_pg:photos_all":3,
    "qs_pg:photos_sr":0,
    "qs_pg:pop_sr":1,
    "qs_pg:qs_pg_placetype":"locality",
    "qs_pg:qs_pg_placetype_gp":"Town",
    "qs_pg:woe_adm0":23424805,
    "woe:adm0_id":23424805,
    "woe:name_adm0":"Eesti",
    "woe:name_adm1":"Valgamaa",
    "woe:placetype":"Town",
    "wof:name":"Palupera",
    "wof:placetype":"locality",
    "wof:population":187
},
  "geometry": {"coordinates":[26.34444,58.11917],"type":"Point"}
}