{
  "type": "Feature",
  "properties": {
    "gn:admin1_code":"3.0",
    "gn:admin2_code":"130.0",
    "gn:admin3_code":"6127.0",
    "gn:asciiname":"Permiskuela",
    "gn:country_code":"EE",
    "gn:dem":34,
    "gn:feature_class":"P",
    "gn:feature_code":"PPL",
    "gn:name":"Permisk\u00fcla",
    "gn:population":0,
    "gn:timezone":"Europe/Tallinn",
    "iso:country":"EE",
    "name:und_x_variant":[
        "Permiskyula",
        "Permisk\u00fcla"
    ],
    "wof:name":"Permiskuela",
    "wof:placetype":"locality"
},
  "geometry": {"coordinates":[27.7725,59.08694000000001],"type":"Point"}
}