{
  "type": "Feature",
  "properties": {
    "gn:admin1_code":"4.0",
    "gn:admin2_code":"255.0",
    "gn:admin3_code":"1371.0",
    "gn:asciiname":"Arukuela",
    "gn:country_code":"EE",
    "gn:dem":95,
    "gn:feature_class":"P",
    "gn:feature_code":"PPL",
    "gn:name":"Aruk\u00fcla",
    "gn:population":0,
    "gn:timezone":"Europe/Tallinn",
    "iso:country":"EE",
    "name:und_x_variant":[
        "Aruk\u00fcla"
    ],
    "wof:name":"Arukuela",
    "wof:placetype":"locality"
},
  "geometry": {"coordinates":[26.00528,58.95528],"type":"Point"}
}