{
  "type": "Feature",
  "properties": {
    "gn:admin1_code":"18.0",
    "gn:admin2_code":"171.0",
    "gn:admin3_code":"3412.0",
    "gn:asciiname":"Pagavere",
    "gn:country_code":"EE",
    "gn:dem":54,
    "gn:feature_class":"P",
    "gn:feature_code":"PPL",
    "gn:name":"Pagavere",
    "gn:population":0,
    "gn:timezone":"Europe/Tallinn",
    "iso:country":"EE",
    "name:und_x_variant":[
        "\u041f\u0430\u0433\u0433\u0430\u0432\u0435\u0440\u0435"
    ],
    "wof:name":"Pagavere",
    "wof:placetype":"locality"
},
  "geometry": {"coordinates":[26.25278,58.27889],"type":"Point"}
}