{
  "type": "Feature",
  "properties": {
    "gn:gn_country":"EE",
    "gn:gn_fcode":"PPL",
    "gn:gn_pop":130,
    "gn:population":130,
    "iso:country":"EE",
    "name:eng_x_preferred":[
        "Karjatnurme"
    ],
    "name:est_x_preferred":[
        "Karjatnurme"
    ],
    "name:fra_x_preferred":[
        "Karjatnurme"
    ],
    "name:hye_x_preferred":[
        "\u053f\u0561\u057c\u0575\u0561\u057f\u0576\u0578\u0582\u057c\u0574\u0565"
    ],
    "name:nld_x_preferred":[
        "Karjatnurme"
    ],
    "name:pol_x_preferred":[
        "Karjatnurme"
    ],
    "name:vol_x_preferred":[
        "Karjatnurme"
    ],
    "qs_pg:aaroncc":"EE",
    "qs_pg:gn_country":"EE",
    "qs_pg:gn_fcode":"PPL",
    "qs_pg:gn_pop":130,
    "qs_pg:name":"Karjatnurme",
    "qs_pg:photos_9r":0,
    "qs_pg:photos_sr":0,
    "qs_pg:pop_sr":1,
    "qs_pg:qs_pg_placetype":"locality",
    "wof:name":"Karjatnurme",
    "wof:placetype":"locality",
    "wof:population":130
},
  "geometry": {"coordinates":[25.77917,58.00389],"type":"Point"}
}