{
  "type": "Feature",
  "properties": {
    "gn:admin1_code":"14.0",
    "gn:admin2_code":"714.0",
    "gn:admin3_code":"4917.0",
    "gn:asciiname":"Metsaere",
    "gn:country_code":"EE",
    "gn:dem":21,
    "gn:feature_class":"P",
    "gn:feature_code":"PPL",
    "gn:name":"Metsaere",
    "gn:population":0,
    "gn:timezone":"Europe/Tallinn",
    "iso:country":"EE",
    "name:und_x_variant":[
        "Metsaare",
        "Metsaere",
        "Metsal\u00f5uka",
        "Metsa\u00e4\u00e4re"
    ],
    "wof:name":"Metsaere",
    "wof:placetype":"locality"
},
  "geometry": {"coordinates":[22.78972000000001,58.48694],"type":"Point"}
}