{
  "type": "Feature",
  "properties": {
    "gn:admin1_code":"21.0",
    "gn:admin2_code":"142.0",
    "gn:admin3_code":"4689.0",
    "gn:asciiname":"Luematu",
    "gn:country_code":"EE",
    "gn:dem":133,
    "gn:feature_class":"P",
    "gn:feature_code":"PPL",
    "gn:name":"L\u00fcmatu",
    "gn:population":0,
    "gn:timezone":"Europe/Tallinn",
    "iso:country":"EE",
    "wof:name":"Luematu",
    "wof:placetype":"locality"
},
  "geometry": {"coordinates":[26.61472,57.88889],"type":"Point"}
}