{
  "type": "Feature",
  "properties": {
    "gn:admin1_code":"8.0",
    "gn:admin2_code":"272.0",
    "gn:admin3_code":"9043.0",
    "gn:asciiname":"Vandu",
    "gn:country_code":"EE",
    "gn:dem":93,
    "gn:feature_class":"P",
    "gn:feature_code":"PPL",
    "gn:name":"Vandu",
    "gn:population":0,
    "gn:timezone":"Europe/Tallinn",
    "iso:country":"EE",
    "wof:name":"Vandu",
    "wof:placetype":"locality"
},
  "geometry": {"coordinates":[26.19861,59.32],"type":"Point"}
}