{
  "type": "Feature",
  "properties": {
    "gn:gn_country":"EE",
    "gn:gn_fcode":"PPL",
    "gn:gn_pop":370,
    "gn:population":370,
    "iso:country":"EE",
    "name:bul_x_preferred":[
        "\u0425\u0430\u0433\u0435"
    ],
    "name:ceb_x_preferred":[
        "Haage"
    ],
    "name:eng_x_preferred":[
        "Haage"
    ],
    "name:est_x_preferred":[
        "Haage"
    ],
    "name:fra_x_preferred":[
        "Haage"
    ],
    "name:hye_x_preferred":[
        "\u0540\u0561\u0561\u0563\u0565"
    ],
    "name:nld_x_preferred":[
        "Haage"
    ],
    "name:pol_x_preferred":[
        "Haage"
    ],
    "name:swe_x_preferred":[
        "Haage"
    ],
    "name:ukr_x_preferred":[
        "\u0413\u0430\u0430\u0491\u0435"
    ],
    "name:vol_x_preferred":[
        "Haage"
    ],
    "qs_pg:aaroncc":"EE",
    "qs_pg:gn_country":"EE",
    "qs_pg:gn_fcode":"PPL",
    "qs_pg:gn_pop":370,
    "qs_pg:name":"Haage",
    "qs_pg:name_adm0":"Eesti",
    "qs_pg:name_adm1":"Tartumaa",
    "qs_pg:photos_9r":0,
    "qs_pg:photos_sr":0,
    "qs_pg:pop_sr":2,
    "qs_pg:qs_pg_placetype":"locality",
    "qs_pg:qs_pg_placetype_gp":"Town",
    "qs_pg:woe_adm0":23424805,
    "woe:adm0_id":23424805,
    "woe:name_adm0":"Eesti",
    "woe:name_adm1":"Tartumaa",
    "woe:placetype":"Town",
    "wof:name":"Haage",
    "wof:placetype":"locality",
    "wof:population":370
},
  "geometry": {"coordinates":[26.62722,58.365],"type":"Point"}
}