{
  "type": "Feature",
  "properties": {
    "gn:admin1_code":"3.0",
    "gn:admin2_code":"130.0",
    "gn:admin3_code":"6391.0",
    "gn:asciiname":"Puhatu",
    "gn:cc2":"EE",
    "gn:country_code":"EE",
    "gn:dem":52,
    "gn:feature_class":"P",
    "gn:feature_code":"PPL",
    "gn:name":"Puhatu",
    "gn:population":0,
    "gn:timezone":"Europe/Tallinn",
    "iso:country":"EE",
    "name:deu_x_preferred":[
        "Puhatu"
    ],
    "name:est_x_preferred":[
        "Puhatu"
    ],
    "name:fra_x_preferred":[
        "Puhatu"
    ],
    "name:hye_x_preferred":[
        "\u054a\u0578\u0582\u0570\u0561\u057f\u0578\u0582"
    ],
    "name:nld_x_preferred":[
        "Puhatu"
    ],
    "name:pol_x_preferred":[
        "Puhatu"
    ],
    "name:spa_x_preferred":[
        "Puhatu"
    ],
    "name:swe_x_preferred":[
        "Puhatu"
    ],
    "name:und_x_variant":[
        "Pukhkhatu"
    ],
    "name:vol_x_preferred":[
        "Puhatu"
    ],
    "wof:name":"Puhatu",
    "wof:placetype":"locality"
},
  "geometry": {"coordinates":[27.57944,59.19389],"type":"Point"}
}