{
  "type": "Feature",
  "properties": {
    "gn:admin1_code":"11.0",
    "gn:admin2_code":"430.0",
    "gn:admin3_code":"2879.0",
    "gn:asciiname":"Kause",
    "gn:country_code":"EE",
    "gn:dem":9,
    "gn:feature_class":"P",
    "gn:feature_code":"PPL",
    "gn:name":"Kause",
    "gn:population":0,
    "gn:timezone":"Europe/Tallinn",
    "iso:country":"EE",
    "name:und_x_variant":[
        "Kaose",
        "Kaoze",
        "Kause"
    ],
    "wof:name":"Kause",
    "wof:placetype":"locality"
},
  "geometry": {"coordinates":[23.64806,58.61528000000001],"type":"Point"}
}