{
  "type": "Feature",
  "properties": {
    "gn:admin1_code":"7.0",
    "gn:admin2_code":"441.0",
    "gn:admin3_code":"3514.0",
    "gn:asciiname":"Voeoela",
    "gn:country_code":"EE",
    "gn:dem":6,
    "gn:feature_class":"P",
    "gn:feature_code":"PPL",
    "gn:name":"V\u00f6\u00f6la",
    "gn:population":0,
    "gn:timezone":"Europe/Tallinn",
    "iso:country":"EE",
    "name:swe_x_preferred":[
        "Bysholm"
    ],
    "name:und_x_variant":[
        "Vela",
        "V\u00f6\u00f6la"
    ],
    "wof:lang_x_official":[
        "est"
    ],
    "wof:lang_x_spoken":[
        "est"
    ],
    "wof:name":"Voeoela",
    "wof:placetype":"locality"
},
  "geometry": {"coordinates":[23.50111,59.07139],"type":"Point"}
}