{
  "type": "Feature",
  "properties": {
    "gn:admin1_code":"4.0",
    "gn:admin2_code":"255.0",
    "gn:admin3_code":"9430.0",
    "gn:asciiname":"Visusti",
    "gn:country_code":"EE",
    "gn:dem":100,
    "gn:feature_class":"P",
    "gn:feature_code":"PPL",
    "gn:name":"Visusti",
    "gn:population":0,
    "gn:timezone":"Europe/Tallinn",
    "iso:country":"EE",
    "name:und_x_variant":[
        "Vizusti",
        "Visusti"
    ],
    "wof:name":"Visusti",
    "wof:placetype":"locality"
},
  "geometry": {"coordinates":[25.98972,58.98417],"type":"Point"}
}