{
  "type": "Feature",
  "properties": {
    "gn:admin1_code":"4.0",
    "gn:admin2_code":"255.0",
    "gn:admin3_code":"9430.0",
    "gn:asciiname":"Visusti",
    "gn:country_code":"EE",
    "gn:dem":100,
    "gn:feature_class":"P",
    "gn:feature_code":"PPL",
    "gn:name":"Visusti",
    "gn:population":0,
    "gn:timezone":"Europe/Tallinn",
    "iso:country":"EE",
    "name:ceb_x_preferred":[
        "Visusti"
    ],
    "name:deu_x_preferred":[
        "Visusti"
    ],
    "name:est_x_preferred":[
        "Visusti"
    ],
    "name:hye_x_preferred":[
        "\u054e\u056b\u057d\u0578\u0582\u057d\u057f\u056b"
    ],
    "name:pol_x_preferred":[
        "Visusti"
    ],
    "name:spa_x_preferred":[
        "Visusti"
    ],
    "name:swe_x_preferred":[
        "Visusti"
    ],
    "name:und_x_variant":[
        "Vizusti",
        "Visusti"
    ],
    "name:vol_x_preferred":[
        "Visusti"
    ],
    "wof:name":"Visusti",
    "wof:placetype":"locality"
},
  "geometry": {"coordinates":[25.98972,58.98417],"type":"Point"}
}