{
  "type": "Feature",
  "properties": {
    "gn:admin1_code":"11.0",
    "gn:admin2_code":"809.0",
    "gn:admin3_code":"5036.0",
    "gn:asciiname":"Tani",
    "gn:country_code":"EE",
    "gn:dem":22,
    "gn:feature_class":"P",
    "gn:feature_code":"PPL",
    "gn:name":"Tani",
    "gn:population":0,
    "gn:timezone":"Europe/Tallinn",
    "iso:country":"EE",
    "name:ceb_x_preferred":[
        "Tani"
    ],
    "name:deu_x_preferred":[
        "Tani"
    ],
    "name:fin_x_preferred":[
        "Tani"
    ],
    "name:fra_x_preferred":[
        "Tani"
    ],
    "name:ita_x_preferred":[
        "Tani"
    ],
    "name:por_x_preferred":[
        "Tani"
    ],
    "name:swe_x_preferred":[
        "Tani"
    ],
    "wof:name":"Tani",
    "wof:placetype":"locality"
},
  "geometry": {"coordinates":[24.87083,58.51333],"type":"Point"}
}