{
  "type": "Feature",
  "properties": {
    "gn:admin1_code":"8.0",
    "gn:admin2_code":"901.0",
    "gn:admin3_code":"3252.0",
    "gn:asciiname":"Aruvaelja",
    "gn:country_code":"EE",
    "gn:dem":120,
    "gn:feature_class":"P",
    "gn:feature_code":"PPL",
    "gn:name":"Aruv\u00e4lja",
    "gn:population":0,
    "gn:timezone":"Europe/Tallinn",
    "iso:country":"EE",
    "wof:name":"Aruvaelja",
    "wof:placetype":"locality"
},
  "geometry": {"coordinates":[26.39611,59.2425],"type":"Point"}
}