{
  "type": "Feature",
  "properties": {
    "gn:admin1_code":"8.0",
    "gn:admin2_code":"901.0",
    "gn:admin3_code":"5794.0",
    "gn:asciiname":"Paasvere-Aru",
    "gn:country_code":"EE",
    "gn:dem":95,
    "gn:feature_class":"P",
    "gn:feature_code":"PPL",
    "gn:name":"Paasvere-Aru",
    "gn:population":0,
    "gn:timezone":"Europe/Tallinn",
    "iso:country":"EE",
    "name:und_x_variant":[
        "Arud",
        "Paasvere-Arud",
        "Pasvere",
        "Paasvere-Aru"
    ],
    "wof:name":"Paasvere-Aru",
    "wof:placetype":"locality"
},
  "geometry": {"coordinates":[26.62417,59.06056],"type":"Point"}
}