{
  "type": "Feature",
  "properties": {
    "gn:admin1_code":"11.0",
    "gn:admin2_code":"638.0",
    "gn:admin3_code":"7061.0",
    "gn:asciiname":"Kuninga",
    "gn:country_code":"EE",
    "gn:dem":23,
    "gn:feature_class":"P",
    "gn:feature_code":"PPL",
    "gn:name":"Kuninga",
    "gn:population":0,
    "gn:timezone":"Europe/Tallinn",
    "iso:country":"EE",
    "wof:name":"Kuninga",
    "wof:placetype":"locality"
},
  "geometry": {"coordinates":[24.41694,58.61666999999999],"type":"Point"}
}