{
  "type": "Feature",
  "properties": {
    "gn:admin1_code":"4.0",
    "gn:admin2_code":"834.0",
    "gn:admin3_code":"9425.0",
    "gn:asciiname":"Vissuvere",
    "gn:country_code":"EE",
    "gn:dem":69,
    "gn:feature_class":"P",
    "gn:feature_code":"PPL",
    "gn:name":"Vissuvere",
    "gn:population":0,
    "gn:timezone":"Europe/Tallinn",
    "iso:country":"EE",
    "name:eng_x_preferred":[
        "Vissuvere"
    ],
    "name:rus_x_preferred":[
        "\u0412\u0438\u0441\u0441\u0443\u0432\u0435\u0440\u0435"
    ],
    "wof:lang_x_official":[
        "est"
    ],
    "wof:lang_x_spoken":[
        "est"
    ],
    "wof:name":"Vissuvere",
    "wof:placetype":"locality"
},
  "geometry": {"coordinates":[25.405,58.94028],"type":"Point"}
}