{
  "type": "Feature",
  "properties": {
    "gn:admin1_code":"12.0",
    "gn:admin2_code":"622.0",
    "gn:admin3_code":"8353.0",
    "gn:asciiname":"Laano",
    "gn:country_code":"EE",
    "gn:dem":79,
    "gn:feature_class":"P",
    "gn:feature_code":"PPL",
    "gn:name":"Laan\u00f5",
    "gn:population":0,
    "gn:timezone":"Europe/Tallinn",
    "iso:country":"EE",
    "name:und_x_variant":[
        "Laan\u00f5",
        "Laane"
    ],
    "wof:name":"Laano",
    "wof:placetype":"locality"
},
  "geometry": {"coordinates":[27.12278,57.98694],"type":"Point"}
}