{
  "type": "Feature",
  "properties": {
    "gn:gn_country":"EE",
    "gn:gn_fcode":"PPL",
    "gn:gn_pop":0,
    "iso:country":"EE",
    "name:deu_x_preferred":[
        "Vainupea"
    ],
    "name:eng_x_preferred":[
        "Vainupea"
    ],
    "name:est_x_preferred":[
        "Vainupea"
    ],
    "name:fra_x_preferred":[
        "Vainupea"
    ],
    "name:hye_x_preferred":[
        "\u054e\u0561\u056b\u0576\u0578\u0582\u057a\u0565\u0561"
    ],
    "name:jpn_x_preferred":[
        "\u30f4\u30a1\u30a4\u30cc\u30da\u30a2"
    ],
    "name:nld_x_preferred":[
        "Vainupea"
    ],
    "name:pol_x_preferred":[
        "Vainupea"
    ],
    "name:rus_x_preferred":[
        "\u0412\u0430\u0439\u043d\u0443\u043f\u0435\u0430"
    ],
    "name:unk_x_variant":[
        "Vainopea"
    ],
    "name:vol_x_preferred":[
        "Vainupea"
    ],
    "qs_pg:aaroncc":"EE",
    "qs_pg:gn_country":"EE",
    "qs_pg:gn_fcode":"PPL",
    "qs_pg:gn_pop":0,
    "qs_pg:name":"Vainupea",
    "qs_pg:name_adm0":"Eesti",
    "qs_pg:name_adm1":"L\u00e4\u00e4ne-Virumaa",
    "qs_pg:photos":20,
    "qs_pg:photos_1k":4,
    "qs_pg:photos_9k":1,
    "qs_pg:photos_9r":1,
    "qs_pg:photos_all":20,
    "qs_pg:photos_sr":1,
    "qs_pg:pop_sr":0,
    "qs_pg:qs_pg_placetype":"locality",
    "qs_pg:qs_pg_placetype_gp":"Town",
    "qs_pg:woe_adm0":23424805,
    "woe:adm0_id":23424805,
    "woe:name_adm0":"Eesti",
    "woe:name_adm1":"L\u00e4\u00e4ne-Virumaa",
    "woe:placetype":"Town",
    "wof:name":"Vainupea",
    "wof:placetype":"locality"
},
  "geometry": {"coordinates":[26.27056,59.57778],"type":"Point"}
}