{
  "type": "Feature",
  "properties": {
    "gn:admin1_code":"11.0",
    "gn:admin2_code":"638.0",
    "gn:admin3_code":"2493.0",
    "gn:asciiname":"Kaelase",
    "gn:country_code":"EE",
    "gn:dem":30,
    "gn:feature_class":"P",
    "gn:feature_code":"PPL",
    "gn:name":"Kaelase",
    "gn:population":0,
    "gn:timezone":"Europe/Tallinn",
    "iso:country":"EE",
    "name:eng_x_preferred":[
        "Kaelase"
    ],
    "name:est_x_preferred":[
        "Kaelase"
    ],
    "name:hye_x_preferred":[
        "\u053f\u0561\u0565\u056c\u0561\u057d\u0565"
    ],
    "name:pol_x_preferred":[
        "Kaelase"
    ],
    "name:rus_x_preferred":[
        "\u041a\u0430\u044d\u043b\u0430\u0437\u0435"
    ],
    "name:spa_x_preferred":[
        "Kaelase"
    ],
    "name:vol_x_preferred":[
        "Kaelase"
    ],
    "wof:name":"Kaelase",
    "wof:placetype":"locality"
},
  "geometry": {"coordinates":[24.52556,58.69],"type":"Point"}
}