{
  "type": "Feature",
  "properties": {
    "gn:gn_country":"EE",
    "gn:gn_fcode":"PPL",
    "gn:gn_pop":162,
    "gn:population":162,
    "iso:country":"EE",
    "name:eng_x_preferred":[
        "Konguta"
    ],
    "name:rus_x_preferred":[
        "\u041a\u043e\u043d\u0433\u0443\u0442\u0430"
    ],
    "qs_pg:aaroncc":"EE",
    "qs_pg:gn_country":"EE",
    "qs_pg:gn_fcode":"PPL",
    "qs_pg:gn_pop":162,
    "qs_pg:name":"Konguta",
    "qs_pg:name_adm0":"Eesti",
    "qs_pg:name_adm1":"Tartumaa",
    "qs_pg:photos_9r":0,
    "qs_pg:photos_sr":0,
    "qs_pg:pop_sr":1,
    "qs_pg:qs_pg_placetype":"locality",
    "qs_pg:qs_pg_placetype_gp":"Town",
    "qs_pg:woe_adm0":23424805,
    "woe:adm0_id":23424805,
    "woe:name_adm0":"Eesti",
    "woe:name_adm1":"Tartumaa",
    "woe:placetype":"Town",
    "wof:name":"Konguta",
    "wof:placetype":"locality",
    "wof:population":162
},
  "geometry": {"coordinates":[26.29361,58.22528],"type":"Point"}
}