{
  "type": "Feature",
  "properties": {
    "gn:admin1_code":"4.0",
    "gn:admin2_code":"567.0",
    "gn:admin3_code":"5761.0",
    "gn:asciiname":"Otiku",
    "gn:country_code":"EE",
    "gn:dem":81,
    "gn:feature_class":"P",
    "gn:feature_code":"PPL",
    "gn:name":"Otiku",
    "gn:population":0,
    "gn:timezone":"Europe/Tallinn",
    "iso:country":"EE",
    "wof:name":"Otiku",
    "wof:placetype":"locality"
},
  "geometry": {"coordinates":[25.57056,58.98667],"type":"Point"}
}