{
  "type": "Feature",
  "properties": {
    "gn:gn_country":"EE",
    "gn:gn_fcode":"PPL",
    "gn:gn_pop":549,
    "gn:population":549,
    "iso:country":"EE",
    "name:arm_x_preferred":[
        "\u054e\u0565\u057c\u056b\u0578\u057c\u0561"
    ],
    "name:bul_x_preferred":[
        "\u0412\u0435\u0440\u0438\u043e\u0440\u0430"
    ],
    "name:eng_x_preferred":[
        "Veriora"
    ],
    "name:est_x_preferred":[
        "Veriora"
    ],
    "name:fre_x_preferred":[
        "Veriora"
    ],
    "name:per_x_preferred":[
        "\u0648\u0631\u06cc\u0631\u0627"
    ],
    "name:pol_x_preferred":[
        "Veriora"
    ],
    "name:swe_x_preferred":[
        "Veriora"
    ],
    "name:ukr_x_preferred":[
        "\u0412\u0435\u0440\u0456\u043e\u0440\u0430"
    ],
    "name:vol_x_preferred":[
        "Veriora"
    ],
    "qs_pg:aaroncc":"EE",
    "qs_pg:gn_country":"EE",
    "qs_pg:gn_fcode":"PPL",
    "qs_pg:gn_pop":549,
    "qs_pg:name":"Veriora",
    "qs_pg:name_adm0":"Eesti",
    "qs_pg:name_adm1":"P\u00f5lvamaa",
    "qs_pg:photos_9r":0,
    "qs_pg:photos_sr":0,
    "qs_pg:pop_sr":2,
    "qs_pg:qs_pg_placetype":"locality",
    "qs_pg:qs_pg_placetype_gp":"Town",
    "qs_pg:woe_adm0":23424805,
    "woe:adm0_id":23424805,
    "woe:name_adm0":"Eesti",
    "woe:name_adm1":"P\u00f5lvamaa",
    "woe:placetype":"Town",
    "wof:name":"Veriora",
    "wof:placetype":"locality",
    "wof:population":549
},
  "geometry": {"coordinates":[27.35194,58.00417],"type":"Point"}
}