{
  "type": "Feature",
  "properties": {
    "gn:admin1_code":"19.0",
    "gn:admin2_code":"824.0",
    "gn:admin3_code":"7113.0",
    "gn:asciiname":"Rulli",
    "gn:country_code":"EE",
    "gn:dem":42,
    "gn:feature_class":"P",
    "gn:feature_code":"PPL",
    "gn:name":"Rulli",
    "gn:population":0,
    "gn:timezone":"Europe/Tallinn",
    "iso:country":"EE",
    "wof:name":"Rulli",
    "wof:placetype":"locality"
},
  "geometry": {"coordinates":[25.97278,58.0375],"type":"Point"}
}