{
  "type": "Feature",
  "properties": {
    "gn:gn_country":"EE",
    "gn:gn_fcode":"PPL",
    "gn:gn_pop":109,
    "gn:population":109,
    "iso:country":"EE",
    "name:ceb_x_preferred":[
        "Saha"
    ],
    "name:deu_x_preferred":[
        "Saha"
    ],
    "name:eng_x_preferred":[
        "Saha"
    ],
    "name:est_x_preferred":[
        "Saha"
    ],
    "name:fra_x_preferred":[
        "Saha"
    ],
    "name:hye_x_preferred":[
        "\u054d\u0561\u0570\u0561"
    ],
    "name:nld_x_preferred":[
        "Saha"
    ],
    "name:pol_x_preferred":[
        "Saha"
    ],
    "name:spa_x_preferred":[
        "Saha"
    ],
    "name:ukr_x_preferred":[
        "\u0421\u0430\u0433\u0430"
    ],
    "name:unk_x_variant":[
        "Sakha"
    ],
    "name:urd_x_preferred":[
        "\u0633\u06c1\u0627\u060c \u0627\u06cc\u0633\u0679\u0648\u0646\u06cc\u0627"
    ],
    "name:urd_x_variant":[
        "\u0633\u06c1\u0627"
    ],
    "name:vol_x_preferred":[
        "Saha"
    ],
    "qs_pg:aaroncc":"EE",
    "qs_pg:gn_country":"EE",
    "qs_pg:gn_fcode":"PPL",
    "qs_pg:gn_pop":109,
    "qs_pg:name":"Saha",
    "qs_pg:name_adm0":"Eesti",
    "qs_pg:name_adm1":"Harjumaa",
    "qs_pg:photos":13,
    "qs_pg:photos_1k":3,
    "qs_pg:photos_9k":1,
    "qs_pg:photos_9r":1,
    "qs_pg:photos_all":13,
    "qs_pg:photos_sr":1,
    "qs_pg:pop_sr":1,
    "qs_pg:qs_pg_placetype":"locality",
    "qs_pg:qs_pg_placetype_gp":"Town",
    "qs_pg:woe_adm0":23424805,
    "woe:adm0_id":23424805,
    "woe:name_adm0":"Eesti",
    "woe:name_adm1":"Harjumaa",
    "woe:placetype":"Town",
    "wof:name":"Saha",
    "wof:placetype":"locality",
    "wof:population":109
},
  "geometry": {"coordinates":[24.96583,59.42139],"type":"Point"}
}