{
  "type": "Feature",
  "properties": {
    "gn:admin1_code":"21.0",
    "gn:admin2_code":"732.0",
    "gn:admin3_code":"2736.0",
    "gn:asciiname":"Rosna-Motsa",
    "gn:country_code":"EE",
    "gn:dem":42,
    "gn:feature_class":"P",
    "gn:feature_code":"PPL",
    "gn:name":"R\u00f5sna-M\u00f5tsa",
    "gn:population":0,
    "gn:timezone":"Europe/Tallinn",
    "iso:country":"EE",
    "name:und_x_variant":[
        "R\u00f5sna-M\u00f5tsa",
        "R\u00f5sna-Metsak\u00fcla"
    ],
    "wof:lang_x_official":[
        "est"
    ],
    "wof:lang_x_spoken":[
        "est"
    ],
    "wof:name":"Rosna-Motsa",
    "wof:placetype":"locality"
},
  "geometry": {"coordinates":[27.56139,57.96972],"type":"Point"}
}