{
  "type": "Feature",
  "properties": {
    "gn:admin1_code":"13.0",
    "gn:admin2_code":"317.0",
    "gn:admin3_code":"6140.0",
    "gn:asciiname":"Laisari",
    "gn:country_code":"EE",
    "gn:dem":64,
    "gn:feature_class":"P",
    "gn:feature_code":"PPL",
    "gn:name":"Laisari",
    "gn:population":0,
    "gn:timezone":"Europe/Tallinn",
    "iso:country":"EE",
    "name:und_x_variant":[
        "Laysari",
        "Laisari"
    ],
    "wof:name":"Laisari",
    "wof:placetype":"locality"
},
  "geometry": {"coordinates":[24.58361,59.13389],"type":"Point"}
}