{
  "type": "Feature",
  "properties": {
    "gn:admin1_code":"14.0",
    "gn:admin2_code":"714.0",
    "gn:admin3_code":"2292.0",
    "gn:asciiname":"Joori",
    "gn:cc2":"EE",
    "gn:country_code":"EE",
    "gn:dem":18,
    "gn:feature_class":"P",
    "gn:feature_code":"PPL",
    "gn:name":"J\u00f5\u00f5ri",
    "gn:population":0,
    "gn:timezone":"Europe/Tallinn",
    "iso:country":"EE",
    "name:und_x_variant":[
        "Iyri",
        "J\u00f5\u00f5ri"
    ],
    "wof:lang_x_official":[
        "est"
    ],
    "wof:lang_x_spoken":[
        "est"
    ],
    "wof:name":"Joori",
    "wof:placetype":"locality"
},
  "geometry": {"coordinates":[22.76722,58.42694],"type":"Point"}
}