{
  "type": "Feature",
  "properties": {
    "gn:gn_country":"EE",
    "gn:gn_fcode":"PPL",
    "gn:gn_pop":109,
    "gn:population":109,
    "iso:country":"EE",
    "name:deu_x_preferred":[
        "Omedu"
    ],
    "name:eng_x_preferred":[
        "Omedu"
    ],
    "name:est_x_preferred":[
        "Omedu"
    ],
    "name:fra_x_preferred":[
        "Omedu"
    ],
    "name:hye_x_preferred":[
        "\u0555\u0574\u0565\u0564\u0578\u0582"
    ],
    "name:nld_x_preferred":[
        "Omedu"
    ],
    "name:pol_x_preferred":[
        "Omedu"
    ],
    "name:rus_x_preferred":[
        "\u041e\u043c\u0435\u0434\u0443"
    ],
    "name:swe_x_preferred":[
        "Omedu"
    ],
    "name:ukr_x_preferred":[
        "\u041e\u043c\u0435\u0434\u0443"
    ],
    "name:vol_x_preferred":[
        "Omedu"
    ],
    "qs_pg:aaroncc":"EE",
    "qs_pg:gn_country":"EE",
    "qs_pg:gn_fcode":"PPL",
    "qs_pg:gn_pop":109,
    "qs_pg:name":"Omedu",
    "qs_pg:name_adm0":"Eesti",
    "qs_pg:name_adm1":"J\u00f5gevamaa",
    "qs_pg:photos_9k":1,
    "qs_pg:photos_9r":1,
    "qs_pg:photos_all":1,
    "qs_pg:photos_sr":0,
    "qs_pg:pop_sr":1,
    "qs_pg:qs_pg_placetype":"locality",
    "qs_pg:qs_pg_placetype_gp":"Town",
    "qs_pg:woe_adm0":23424805,
    "woe:adm0_id":23424805,
    "woe:name_adm0":"Eesti",
    "woe:name_adm1":"J\u00f5gevamaa",
    "woe:placetype":"Town",
    "wof:name":"Omedu",
    "wof:placetype":"locality",
    "wof:population":109
},
  "geometry": {"coordinates":[27.02639,58.76806],"type":"Point"}
}