{
  "type": "Feature",
  "properties": {
    "gn:admin1_code":"3.0",
    "gn:admin2_code":"130.0",
    "gn:admin3_code":"4374.0",
    "gn:asciiname":"Liivakuenka",
    "gn:country_code":"EE",
    "gn:dem":69,
    "gn:feature_class":"P",
    "gn:feature_code":"PPL",
    "gn:name":"Liivak\u00fcnka",
    "gn:population":0,
    "gn:timezone":"Europe/Tallinn",
    "iso:country":"EE",
    "name:deu_x_preferred":[
        "Liivak\u00fcnka"
    ],
    "name:est_x_preferred":[
        "Liivak\u00fcnka"
    ],
    "name:hye_x_preferred":[
        "\u053c\u056b\u056b\u057e\u0561\u056f\u0575\u0578\u0582\u0576\u056f\u0561"
    ],
    "name:nld_x_preferred":[
        "Liivak\u00fcnka"
    ],
    "name:pol_x_preferred":[
        "Liivak\u00fcnka"
    ],
    "name:spa_x_preferred":[
        "Liivak\u00fcnka"
    ],
    "name:und_x_variant":[
        "\u0421\u0435\u043b. \u041b\u0456\u0439\u0432\u0430\u043a\u044e\u043d\u043a\u0430"
    ],
    "name:vol_x_preferred":[
        "Liivak\u00fcnka"
    ],
    "wof:lang_x_official":[
        "est"
    ],
    "wof:lang_x_spoken":[
        "est"
    ],
    "wof:name":"Liivakuenka",
    "wof:placetype":"locality"
},
  "geometry": {"coordinates":[27.3025,59.24222],"type":"Point"}
}