{
  "type": "Feature",
  "properties": {
    "gn:admin1_code":"3.0",
    "gn:admin2_code":"130.0",
    "gn:admin3_code":"4374.0",
    "gn:asciiname":"Liivakuenka",
    "gn:country_code":"EE",
    "gn:dem":69,
    "gn:feature_class":"P",
    "gn:feature_code":"PPL",
    "gn:name":"Liivak\u00fcnka",
    "gn:population":0,
    "gn:timezone":"Europe/Tallinn",
    "iso:country":"EE",
    "name:und_x_variant":[
        "Liivak\u00fcnka",
        "\u0421\u0435\u043b. \u041b\u0456\u0439\u0432\u0430\u043a\u044e\u043d\u043a\u0430"
    ],
    "wof:name":"Liivakuenka",
    "wof:placetype":"locality"
},
  "geometry": {"coordinates":[27.3025,59.24222],"type":"Point"}
}