{
  "type": "Feature",
  "properties": {
    "gn:admin1_code":"1.0",
    "gn:admin2_code":"651.0",
    "gn:admin3_code":"2335.0",
    "gn:asciiname":"Kangla",
    "gn:country_code":"EE",
    "gn:dem":45,
    "gn:feature_class":"P",
    "gn:feature_code":"PPL",
    "gn:name":"Kangla",
    "gn:population":0,
    "gn:timezone":"Europe/Tallinn",
    "iso:country":"EE",
    "wof:lang_x_official":[
        "est"
    ],
    "wof:lang_x_spoken":[
        "est"
    ],
    "wof:name":"Kangla",
    "wof:placetype":"locality"
},
  "geometry": {"coordinates":[25.04639,59.35167],"type":"Point"}
}