{
  "type": "Feature",
  "properties": {
    "gn:admin1_code":"18.0",
    "gn:admin2_code":"171.0",
    "gn:admin3_code":"2351.0",
    "gn:asciiname":"Jaerve",
    "gn:country_code":"EE",
    "gn:dem":41,
    "gn:feature_class":"P",
    "gn:feature_code":"PPL",
    "gn:name":"J\u00e4rve",
    "gn:population":0,
    "gn:timezone":"Europe/Tallinn",
    "iso:country":"EE",
    "wof:lang_x_official":[
        "est"
    ],
    "wof:lang_x_spoken":[
        "est"
    ],
    "wof:name":"Jaerve",
    "wof:placetype":"locality"
},
  "geometry": {"coordinates":[26.15861,58.30944],"type":"Point"}
}