{
  "type": "Feature",
  "properties": {
    "gn:admin1_code":"7.0",
    "gn:admin2_code":"441.0",
    "gn:admin3_code":"6805.0",
    "gn:asciiname":"Rannajoe",
    "gn:country_code":"EE",
    "gn:dem":10,
    "gn:feature_class":"P",
    "gn:feature_code":"PPL",
    "gn:name":"Rannaj\u00f5e",
    "gn:population":0,
    "gn:timezone":"Europe/Tallinn",
    "iso:country":"EE",
    "name:und_x_variant":[
        "Rannaj\u00f5e"
    ],
    "wof:name":"Rannajoe",
    "wof:placetype":"locality"
},
  "geometry": {"coordinates":[23.79861,58.82333000000001],"type":"Point"}
}