{
  "type": "Feature",
  "properties": {
    "gn:admin1_code":"7.0",
    "gn:admin2_code":"441.0",
    "gn:admin3_code":"6805.0",
    "gn:asciiname":"Rannajoe",
    "gn:country_code":"EE",
    "gn:dem":10,
    "gn:feature_class":"P",
    "gn:feature_code":"PPL",
    "gn:name":"Rannaj\u00f5e",
    "gn:population":0,
    "gn:timezone":"Europe/Tallinn",
    "iso:country":"EE",
    "name:deu_x_preferred":[
        "Rannaj\u00f5e"
    ],
    "name:est_x_preferred":[
        "Rannaj\u00f5e"
    ],
    "name:hye_x_preferred":[
        "\u054c\u0561\u0576\u0576\u0561\u0575\u056b\u0565"
    ],
    "name:pol_x_preferred":[
        "Rannaj\u00f5e"
    ],
    "name:spa_x_preferred":[
        "Rannaj\u00f5e"
    ],
    "name:ukr_x_preferred":[
        "\u0420\u0430\u043d\u043d\u0430\u0439\u0438\u0435"
    ],
    "name:vol_x_preferred":[
        "Rannaj\u00f5e"
    ],
    "wof:coterminous":[
        1713312505
    ],
    "wof:lang_x_official":[
        "est"
    ],
    "wof:lang_x_spoken":[
        "est"
    ],
    "wof:name":"Rannajoe",
    "wof:placetype":"locality"
},
  "geometry": {"coordinates":[23.79861,58.82333],"type":"Point"}
}