{
  "type": "Feature",
  "properties": {
    "gn:gn_country":"EE",
    "gn:gn_fcode":"PPL",
    "gn:gn_pop":336,
    "gn:population":336,
    "iso:country":"EE",
    "name:eng_x_preferred":[
        "Kodila"
    ],
    "name:est_x_preferred":[
        "Kodila"
    ],
    "name:hye_x_preferred":[
        "\u053f\u0578\u0564\u056b\u056c\u0561"
    ],
    "name:nld_x_preferred":[
        "Kodila"
    ],
    "name:pol_x_preferred":[
        "Kodila"
    ],
    "name:rus_x_preferred":[
        "\u041a\u043e\u0434\u0438\u043b\u0430"
    ],
    "name:sco_x_preferred":[
        "Kodila"
    ],
    "name:vol_x_preferred":[
        "Kodila"
    ],
    "qs_pg:aaroncc":"EE",
    "qs_pg:gn_country":"EE",
    "qs_pg:gn_fcode":"PPL",
    "qs_pg:gn_pop":336,
    "qs_pg:name":"Kodila",
    "qs_pg:name_adm0":"Eesti",
    "qs_pg:name_adm1":"Raplamaa",
    "qs_pg:photos_9k":1,
    "qs_pg:photos_9r":1,
    "qs_pg:photos_all":1,
    "qs_pg:photos_sr":0,
    "qs_pg:pop_sr":2,
    "qs_pg:qs_pg_placetype":"locality",
    "qs_pg:qs_pg_placetype_gp":"Town",
    "qs_pg:woe_adm0":23424805,
    "woe:adm0_id":23424805,
    "woe:name_adm0":"Eesti",
    "woe:name_adm1":"Raplamaa",
    "woe:placetype":"Town",
    "wof:name":"Kodila",
    "wof:placetype":"locality",
    "wof:population":336
},
  "geometry": {"coordinates":[24.66833,59.0425],"type":"Point"}
}