{
  "type": "Feature",
  "properties": {
    "gn:admin1_code":"19.0",
    "gn:admin2_code":"855.0",
    "gn:admin3_code":"2016.0",
    "gn:asciiname":"Lueuedi",
    "gn:country_code":"EE",
    "gn:dem":45,
    "gn:feature_class":"P",
    "gn:feature_code":"PPL",
    "gn:name":"L\u00fc\u00fcdi",
    "gn:population":0,
    "gn:timezone":"Europe/Tallinn",
    "iso:country":"EE",
    "name:und_x_variant":[
        "L\u00fc\u00fcdi",
        "L\u00fcllem\u00e4e"
    ],
    "wof:lang_x_official":[
        "est"
    ],
    "wof:lang_x_spoken":[
        "est"
    ],
    "wof:name":"Lueuedi",
    "wof:placetype":"locality"
},
  "geometry": {"coordinates":[26.28417,57.82722],"type":"Point"}
}