{
  "type": "Feature",
  "properties": {
    "gn:admin1_code":"8.0",
    "gn:admin2_code":"901.0",
    "gn:admin3_code":"1025.0",
    "gn:asciiname":"Aarla",
    "gn:country_code":"EE",
    "gn:dem":65,
    "gn:feature_class":"P",
    "gn:feature_code":"PPL",
    "gn:name":"Aarla",
    "gn:population":0,
    "gn:timezone":"Europe/Tallinn",
    "iso:country":"EE",
    "wof:coterminous":[
        1713307781
    ],
    "wof:lang_x_official":[
        "est"
    ],
    "wof:lang_x_spoken":[
        "est"
    ],
    "wof:name":"Aarla",
    "wof:placetype":"locality"
},
  "geometry": {"coordinates":[26.61417,59.36056],"type":"Point"}
}