{
  "type": "Feature",
  "properties": {
    "gn:admin1_code":"14.0",
    "gn:admin2_code":"714.0",
    "gn:admin3_code":"5006.0",
    "gn:asciiname":"Mui",
    "gn:cc2":"EE",
    "gn:country_code":"EE",
    "gn:dem":8,
    "gn:feature_class":"P",
    "gn:feature_code":"PPL",
    "gn:name":"Mui",
    "gn:population":0,
    "gn:timezone":"Europe/Tallinn",
    "iso:country":"EE",
    "name:deu_x_preferred":[
        "Mui"
    ],
    "name:est_x_preferred":[
        "Mui"
    ],
    "name:hye_x_preferred":[
        "\u0544\u0578\u0582\u056b"
    ],
    "name:pol_x_preferred":[
        "Mui"
    ],
    "name:spa_x_preferred":[
        "Mui"
    ],
    "name:und_x_variant":[
        "Muik\u00fcla",
        "Muykyula",
        "Mui"
    ],
    "name:vol_x_preferred":[
        "Mui"
    ],
    "wof:name":"Mui",
    "wof:placetype":"locality"
},
  "geometry": {"coordinates":[23.11306,58.51333],"type":"Point"}
}