{
  "type": "Feature",
  "properties": {
    "gn:admin1_code":"21.0",
    "gn:admin2_code":"732.0",
    "gn:admin3_code":"8231.0",
    "gn:asciiname":"Tiklaso",
    "gn:country_code":"EE",
    "gn:dem":146,
    "gn:feature_class":"P",
    "gn:feature_code":"PPL",
    "gn:name":"Tiklas\u00f5",
    "gn:population":0,
    "gn:timezone":"Europe/Tallinn",
    "iso:country":"EE",
    "name:und_x_variant":[
        "Tiklas\u00f5",
        "Tiklitsa"
    ],
    "wof:name":"Tiklaso",
    "wof:placetype":"locality"
},
  "geometry": {"coordinates":[27.50889,57.73639],"type":"Point"}
}