{
  "type": "Feature",
  "properties": {
    "gn:admin1_code":"3.0",
    "gn:admin2_code":"130.0",
    "gn:admin3_code":"9106.0",
    "gn:asciiname":"Keskkuela",
    "gn:country_code":"EE",
    "gn:dem":51,
    "gn:feature_class":"P",
    "gn:feature_code":"PPL",
    "gn:name":"Keskk\u00fcla",
    "gn:population":0,
    "gn:timezone":"Europe/Tallinn",
    "iso:country":"EE",
    "name:und_x_variant":[
        "Keskk\u00fcla",
        "Vasavere-Keskk\u00fcla"
    ],
    "wof:name":"Keskkuela",
    "wof:placetype":"locality"
},
  "geometry": {"coordinates":[27.53417,59.29028],"type":"Point"}
}