{
  "type": "Feature",
  "properties": {
    "gn:admin1_code":"21.0",
    "gn:admin2_code":"732.0",
    "gn:admin3_code":"3470.0",
    "gn:asciiname":"Verhulitsa",
    "gn:country_code":"EE",
    "gn:dem":37,
    "gn:feature_class":"P",
    "gn:feature_code":"PPL",
    "gn:name":"Verhulitsa",
    "gn:population":0,
    "gn:timezone":"Europe/Tallinn",
    "iso:country":"EE",
    "wof:name":"Verhulitsa",
    "wof:placetype":"locality"
},
  "geometry": {"coordinates":[27.65528,57.94472],"type":"Point"}
}