{
  "type": "Feature",
  "properties": {
    "gn:admin1_code":"21.0",
    "gn:admin2_code":"732.0",
    "gn:admin3_code":"3470.0",
    "gn:asciiname":"Verhulitsa",
    "gn:country_code":"EE",
    "gn:dem":37,
    "gn:feature_class":"P",
    "gn:feature_code":"PPL",
    "gn:name":"Verhulitsa",
    "gn:population":0,
    "gn:timezone":"Europe/Tallinn",
    "iso:country":"EE",
    "name:est_x_preferred":[
        "Verhulitsa"
    ],
    "name:fas_x_preferred":[
        "\u0648\u0631\u0647\u0648\u0644\u06cc\u062a\u0633\u0627"
    ],
    "name:hye_x_preferred":[
        "\u054e\u0565\u057c\u0570\u0578\u0582\u056c\u056b\u0581\u0561"
    ],
    "name:pol_x_preferred":[
        "Verhulitsa"
    ],
    "name:sco_x_preferred":[
        "Verhulitsa"
    ],
    "name:spa_x_preferred":[
        "Verhulitsa"
    ],
    "name:swe_x_preferred":[
        "Verhulitsa"
    ],
    "name:ukr_x_preferred":[
        "\u0412\u0435\u0440\u0445\u0443\u043b\u0456\u0446\u0430"
    ],
    "name:vol_x_preferred":[
        "Verhulitsa"
    ],
    "wof:coterminous":[
        1713316453
    ],
    "wof:lang_x_official":[
        "est"
    ],
    "wof:lang_x_spoken":[
        "est"
    ],
    "wof:name":"Verhulitsa",
    "wof:placetype":"locality"
},
  "geometry": {"coordinates":[27.65528,57.94472],"type":"Point"}
}