{
  "type": "Feature",
  "properties": {
    "gn:admin1_code":"4.0",
    "gn:admin2_code":"255.0",
    "gn:admin3_code":"6771.0",
    "gn:asciiname":"Raka",
    "gn:country_code":"EE",
    "gn:dem":100,
    "gn:feature_class":"P",
    "gn:feature_code":"PPL",
    "gn:name":"Raka",
    "gn:population":0,
    "gn:timezone":"Europe/Tallinn",
    "iso:country":"EE",
    "name:est_x_preferred":[
        "Raka"
    ],
    "name:fra_x_preferred":[
        "Raka"
    ],
    "name:hye_x_preferred":[
        "\u054c\u0561\u056f\u0561"
    ],
    "name:pol_x_preferred":[
        "Raka"
    ],
    "name:sco_x_preferred":[
        "Raka"
    ],
    "name:spa_x_preferred":[
        "Raka"
    ],
    "name:ukr_x_preferred":[
        "\u0420\u0430\u043a\u0430"
    ],
    "name:vol_x_preferred":[
        "Raka"
    ],
    "wof:coterminous":[
        1713315183
    ],
    "wof:lang_x_official":[
        "est"
    ],
    "wof:lang_x_spoken":[
        "est"
    ],
    "wof:name":"Raka",
    "wof:placetype":"locality"
},
  "geometry": {"coordinates":[25.81667,59.18333],"type":"Point"}
}