{
  "type": "Feature",
  "properties": {
    "gn:admin1_code":"5.0",
    "gn:admin2_code":"618.0",
    "gn:admin3_code":"2379.0",
    "gn:asciiname":"Juerikuela",
    "gn:country_code":"EE",
    "gn:dem":55,
    "gn:feature_class":"P",
    "gn:feature_code":"PPL",
    "gn:name":"J\u00fcrik\u00fcla",
    "gn:population":0,
    "gn:timezone":"Europe/Tallinn",
    "iso:country":"EE",
    "wof:lang_x_official":[
        "est"
    ],
    "wof:lang_x_spoken":[
        "est"
    ],
    "wof:name":"Juerikuela",
    "wof:placetype":"locality"
},
  "geometry": {"coordinates":[26.27194,58.56222],"type":"Point"}
}