{
  "type": "Feature",
  "properties": {
    "gn:admin1_code":"21.0",
    "gn:admin2_code":"917.0",
    "gn:admin3_code":"4136.0",
    "gn:asciiname":"Lauga",
    "gn:country_code":"EE",
    "gn:dem":83,
    "gn:feature_class":"P",
    "gn:feature_code":"PPL",
    "gn:name":"Lauga",
    "gn:population":0,
    "gn:timezone":"Europe/Tallinn",
    "iso:country":"EE",
    "wof:name":"Lauga",
    "wof:placetype":"locality"
},
  "geometry": {"coordinates":[27.08389,57.93139],"type":"Point"}
}