{
  "type": "Feature",
  "properties": {
    "gn:gn_country":"EE",
    "gn:gn_fcode":"PPL",
    "gn:gn_pop":223,
    "gn:population":223,
    "iso:country":"EE",
    "name:arm_x_preferred":[
        "\u054c\u0561\u0576\u0576\u0578\u0582"
    ],
    "name:dut_x_preferred":[
        "Rannu"
    ],
    "name:eng_x_preferred":[
        "Rannu"
    ],
    "name:est_x_preferred":[
        "Rannu k\u00fcla"
    ],
    "name:fre_x_preferred":[
        "Rannu"
    ],
    "name:ger_x_preferred":[
        "Rannu"
    ],
    "name:pol_x_preferred":[
        "Rannu"
    ],
    "name:swe_x_preferred":[
        "Rannu k\u00fcla"
    ],
    "name:unk_x_variant":[
        "Vabatk\u00fcla"
    ],
    "name:vol_x_preferred":[
        "Rannu k\u00fcla"
    ],
    "qs_pg:aaroncc":"EE",
    "qs_pg:gn_country":"EE",
    "qs_pg:gn_fcode":"PPL",
    "qs_pg:gn_pop":223,
    "qs_pg:name":"Rannu",
    "qs_pg:name_adm0":"Eesti",
    "qs_pg:name_adm1":"Ida-Virumaa",
    "qs_pg:photos_9k":1,
    "qs_pg:photos_9r":1,
    "qs_pg:photos_all":2,
    "qs_pg:photos_sr":0,
    "qs_pg:pop_sr":2,
    "qs_pg:qs_pg_placetype":"locality",
    "qs_pg:qs_pg_placetype_gp":"Town",
    "qs_pg:woe_adm0":23424805,
    "woe:adm0_id":23424805,
    "woe:name_adm0":"Eesti",
    "woe:name_adm1":"Ida-Virumaa",
    "woe:placetype":"Town",
    "wof:name":"Rannu",
    "wof:placetype":"locality",
    "wof:population":223
},
  "geometry": {"coordinates":[26.84361,59.43361],"type":"Point"}
}