{
  "type": "Feature",
  "properties": {
    "gn:admin1_code":"18.0",
    "gn:admin2_code":"171.0",
    "gn:admin3_code":"6071.0",
    "gn:asciiname":"Pedaste",
    "gn:country_code":"EE",
    "gn:dem":90,
    "gn:feature_class":"P",
    "gn:feature_code":"PPL",
    "gn:name":"Pedaste",
    "gn:population":0,
    "gn:timezone":"Europe/Tallinn",
    "iso:country":"EE",
    "wof:name":"Pedaste",
    "wof:placetype":"locality"
},
  "geometry": {"coordinates":[26.22778,58.08944],"type":"Point"}
}