{
  "type": "Feature",
  "properties": {
    "gn:admin1_code":"11.0",
    "gn:admin2_code":"430.0",
    "gn:admin3_code":"9134.0",
    "gn:asciiname":"Vastupya",
    "gn:country_code":"EE",
    "gn:dem":16,
    "gn:feature_class":"P",
    "gn:feature_code":"PPL",
    "gn:name":"Vastupya",
    "gn:population":0,
    "gn:timezone":"Europe/Tallinn",
    "iso:country":"EE",
    "name:und_x_variant":[
        "Vastup\u00e4\u00e4"
    ],
    "wof:name":"Vastupya",
    "wof:placetype":"locality"
},
  "geometry": {"coordinates":[24.10583,58.66639],"type":"Point"}
}