{
  "type": "Feature",
  "properties": {
    "gn:admin1_code":"11.0",
    "gn:admin2_code":"638.0",
    "gn:admin3_code":"4586.0",
    "gn:asciiname":"Kaerneri",
    "gn:country_code":"EE",
    "gn:dem":41,
    "gn:feature_class":"P",
    "gn:feature_code":"PPL",
    "gn:name":"K\u00e4rneri",
    "gn:population":0,
    "gn:timezone":"Europe/Tallinn",
    "iso:country":"EE",
    "wof:name":"Kaerneri",
    "wof:placetype":"locality"
},
  "geometry": {"coordinates":[24.95472,58.6475],"type":"Point"}
}