{
  "type": "Feature",
  "properties": {
    "gn:admin1_code":"8.0",
    "gn:admin2_code":"272.0",
    "gn:admin3_code":"5620.0",
    "gn:asciiname":"Ohepalu",
    "gn:cc2":"EE",
    "gn:country_code":"EE",
    "gn:dem":104,
    "gn:feature_class":"P",
    "gn:feature_code":"PPL",
    "gn:name":"Ohepalu",
    "gn:population":0,
    "gn:timezone":"Europe/Tallinn",
    "iso:country":"EE",
    "name:eng_x_preferred":[
        "Ohepalu"
    ],
    "name:est_x_preferred":[
        "Ohepalu"
    ],
    "name:hye_x_preferred":[
        "\u0555\u0570\u0565\u057a\u0561\u056c\u0578\u0582"
    ],
    "name:pol_x_preferred":[
        "Ohepalu"
    ],
    "name:rus_x_preferred":[
        "\u041e\u0445\u0435\u043f\u0430\u043b\u0443"
    ],
    "name:und_x_variant":[
        "Okhepalo",
        "Okhepalu"
    ],
    "name:vol_x_preferred":[
        "Ohepalu"
    ],
    "wof:coterminous":[
        1713312521
    ],
    "wof:lang_x_official":[
        "est"
    ],
    "wof:lang_x_spoken":[
        "est"
    ],
    "wof:name":"Ohepalu",
    "wof:placetype":"locality"
},
  "geometry": {"coordinates":[25.95556,59.34556],"type":"Point"}
}