{
  "type": "Feature",
  "properties": {
    "gn:gn_country":"EE",
    "gn:gn_fcode":"PPL",
    "gn:gn_pop":407,
    "gn:population":407,
    "iso:country":"EE",
    "name:arm_x_preferred":[
        "\u0540\u0565\u056c\u0574\u0565"
    ],
    "name:dut_x_preferred":[
        "Helme"
    ],
    "name:eng_x_preferred":[
        "Helme"
    ],
    "name:epo_x_preferred":[
        "Helme"
    ],
    "name:est_x_preferred":[
        "Helme"
    ],
    "name:fre_x_preferred":[
        "Helme"
    ],
    "name:gre_x_preferred":[
        "\u03a7\u03ad\u03bb\u03bc\u03b5"
    ],
    "name:rus_x_preferred":[
        "\u0425\u0435\u043b\u044c\u043c\u0435"
    ],
    "name:swe_x_preferred":[
        "Helme"
    ],
    "name:unk_x_variant":[
        "Myza Khel\u2019me"
    ],
    "name:vol_x_preferred":[
        "Helme"
    ],
    "qs_pg:aaroncc":"EE",
    "qs_pg:gn_country":"EE",
    "qs_pg:gn_fcode":"PPL",
    "qs_pg:gn_pop":407,
    "qs_pg:name":"Helme",
    "qs_pg:name_adm0":"Eesti",
    "qs_pg:name_adm1":"Valgamaa",
    "qs_pg:photos_9k":1,
    "qs_pg:photos_9r":2,
    "qs_pg:photos_all":67,
    "qs_pg:photos_sr":0,
    "qs_pg:pop_sr":2,
    "qs_pg:qs_pg_placetype":"locality",
    "qs_pg:qs_pg_placetype_gp":"Town",
    "qs_pg:woe_adm0":23424805,
    "woe:adm0_id":23424805,
    "woe:name_adm0":"Eesti",
    "woe:name_adm1":"Valgamaa",
    "woe:placetype":"Town",
    "wof:name":"Helme",
    "wof:placetype":"locality",
    "wof:population":407
},
  "geometry": {"coordinates":[25.89722,58.01194],"type":"Point"}
}