{
  "type": "Feature",
  "properties": {
    "gn:admin1_code":"13.0",
    "gn:admin2_code":"503.0",
    "gn:admin3_code":"7003.0",
    "gn:asciiname":"Ringuta",
    "gn:country_code":"EE",
    "gn:dem":46,
    "gn:feature_class":"P",
    "gn:feature_code":"PPL",
    "gn:name":"Ringuta",
    "gn:population":0,
    "gn:timezone":"Europe/Tallinn",
    "iso:country":"EE",
    "wof:name":"Ringuta",
    "wof:placetype":"locality"
},
  "geometry": {"coordinates":[24.47629,58.93017],"type":"Point"}
}