{
  "type": "Feature",
  "properties": {
    "gn:admin1_code":"21.0",
    "gn:admin2_code":"917.0",
    "gn:admin3_code":"4715.0",
    "gn:asciiname":"Madala",
    "gn:country_code":"EE",
    "gn:dem":79,
    "gn:feature_class":"P",
    "gn:feature_code":"PPL",
    "gn:name":"Madala",
    "gn:population":0,
    "gn:timezone":"Europe/Tallinn",
    "iso:country":"EE",
    "name:urd_x_preferred":[
        "\u0645\u06cc\u0688\u0627\u0644\u0627"
    ],
    "wof:name":"Madala",
    "wof:placetype":"locality"
},
  "geometry": {"coordinates":[27.31,57.89833],"type":"Point"}
}