{
  "type": "Feature",
  "properties": {
    "gn:admin1_code":"8.0",
    "gn:admin2_code":"928.0",
    "gn:admin3_code":"9777.0",
    "gn:asciiname":"AEntu",
    "gn:country_code":"EE",
    "gn:dem":103,
    "gn:feature_class":"P",
    "gn:feature_code":"PPL",
    "gn:name":"\u00c4ntu",
    "gn:population":0,
    "gn:timezone":"Europe/Tallinn",
    "iso:country":"EE",
    "name:deu_x_preferred":[
        "\u00c4ntu"
    ],
    "name:est_x_preferred":[
        "\u00c4ntu"
    ],
    "name:hye_x_preferred":[
        "\u0537\u0576\u057f\u0578\u0582"
    ],
    "name:pol_x_preferred":[
        "\u00c4ntu"
    ],
    "name:und_x_variant":[
        "\u00c4ntu"
    ],
    "name:vol_x_preferred":[
        "\u00c4ntu"
    ],
    "wof:name":"AEntu",
    "wof:placetype":"locality"
},
  "geometry": {"coordinates":[26.26417,59.07889],"type":"Point"}
}