{
  "type": "Feature",
  "properties": {
    "gn:admin1_code":"8.0",
    "gn:admin2_code":"903.0",
    "gn:admin3_code":"4755.0",
    "gn:asciiname":"Kalda",
    "gn:country_code":"EE",
    "gn:dem":55,
    "gn:feature_class":"P",
    "gn:feature_code":"PPL",
    "gn:name":"Kalda",
    "gn:population":0,
    "gn:timezone":"Europe/Tallinn",
    "iso:country":"EE",
    "name:ceb_x_preferred":[
        "Kalda"
    ],
    "name:est_x_preferred":[
        "Kalda"
    ],
    "name:sco_x_preferred":[
        "Kalda"
    ],
    "name:und_x_variant":[
        "Talda"
    ],
    "wof:name":"Kalda",
    "wof:placetype":"locality"
},
  "geometry": {"coordinates":[26.56139000000001,59.50306],"type":"Point"}
}