{
  "type": "Feature",
  "properties": {
    "gn:admin1_code":"20.0",
    "gn:admin2_code":"480.0",
    "gn:admin3_code":"2628.0",
    "gn:asciiname":"Kalvre",
    "gn:country_code":"EE",
    "gn:dem":85,
    "gn:feature_class":"P",
    "gn:feature_code":"PPL",
    "gn:name":"Kalvre",
    "gn:population":0,
    "gn:timezone":"Europe/Tallinn",
    "iso:country":"EE",
    "wof:name":"Kalvre",
    "wof:placetype":"locality"
},
  "geometry": {"coordinates":[25.56806,58.185],"type":"Point"}
}