{
  "type": "Feature",
  "properties": {
    "gn:admin1_code":"5.0",
    "gn:admin2_code":"247.0",
    "gn:admin3_code":"8404.0",
    "gn:asciiname":"Tuimoisa",
    "gn:cc2":"EE",
    "gn:country_code":"EE",
    "gn:dem":102,
    "gn:feature_class":"P",
    "gn:feature_code":"PPL",
    "gn:name":"Tuim\u00f5isa",
    "gn:population":0,
    "gn:timezone":"Europe/Tallinn",
    "iso:country":"EE",
    "name:und_x_variant":[
        "Tuymyyza",
        "Tuim\u00f5isa"
    ],
    "wof:name":"Tuimoisa",
    "wof:placetype":"locality"
},
  "geometry": {"coordinates":[26.60389,58.89444],"type":"Point"}
}