{
  "type": "Feature",
  "properties": {
    "gn:admin1_code":"18.0",
    "gn:admin2_code":"291.0",
    "gn:admin3_code":"1167.0",
    "gn:asciiname":"Alakuela",
    "gn:country_code":"EE",
    "gn:dem":86,
    "gn:feature_class":"P",
    "gn:feature_code":"PPL",
    "gn:name":"Alak\u00fcla",
    "gn:population":0,
    "gn:timezone":"Europe/Tallinn",
    "iso:country":"EE",
    "name:est_x_preferred":[
        "Alak\u00fcla"
    ],
    "name:fas_x_preferred":[
        "\u0627\u0644\u0627\u06a9\u0648\u0644\u0627"
    ],
    "name:fra_x_preferred":[
        "Alak\u00fcla"
    ],
    "name:hye_x_preferred":[
        "\u0531\u056c\u0561\u056f\u0575\u0578\u0582\u056c\u0561"
    ],
    "name:pol_x_preferred":[
        "Alak\u00fcla"
    ],
    "name:spa_x_preferred":[
        "Alak\u00fcla"
    ],
    "name:ukr_x_preferred":[
        "\u0410\u043b\u0430\u043a\u044e\u043b\u0430"
    ],
    "name:und_x_variant":[
        "Ala"
    ],
    "name:vol_x_preferred":[
        "Alak\u00fcla"
    ],
    "wof:coterminous":[
        1713313509
    ],
    "wof:lang_x_official":[
        "est"
    ],
    "wof:lang_x_spoken":[
        "est"
    ],
    "wof:name":"Alakuela",
    "wof:placetype":"locality"
},
  "geometry": {"coordinates":[26.92528,58.23944],"type":"Point"}
}