{
  "type": "Feature",
  "properties": {
    "gn:admin1_code":"18.0",
    "gn:admin2_code":"291.0",
    "gn:admin3_code":"1167.0",
    "gn:asciiname":"Alakuela",
    "gn:country_code":"EE",
    "gn:dem":86,
    "gn:feature_class":"P",
    "gn:feature_code":"PPL",
    "gn:name":"Alak\u00fcla",
    "gn:population":0,
    "gn:timezone":"Europe/Tallinn",
    "iso:country":"EE",
    "name:und_x_variant":[
        "Alak\u00fcla",
        "Ala"
    ],
    "wof:name":"Alakuela",
    "wof:placetype":"locality"
},
  "geometry": {"coordinates":[26.92528,58.23944],"type":"Point"}
}