{
  "type": "Feature",
  "properties": {
    "gn:admin1_code":"7.0",
    "gn:admin2_code":"441.0",
    "gn:admin3_code":"6464.0",
    "gn:asciiname":"Putkaste",
    "gn:country_code":"EE",
    "gn:dem":12,
    "gn:feature_class":"P",
    "gn:feature_code":"PPL",
    "gn:name":"Putkaste",
    "gn:population":0,
    "gn:timezone":"Europe/Tallinn",
    "iso:country":"EE",
    "name:deu_x_preferred":[
        "Putkaste"
    ],
    "name:est_x_preferred":[
        "Putkaste"
    ],
    "name:hye_x_preferred":[
        "\u054a\u0578\u0582\u057f\u056f\u0561\u057d\u057f\u0565"
    ],
    "name:pol_x_preferred":[
        "Putkaste"
    ],
    "name:spa_x_preferred":[
        "Putkaste"
    ],
    "name:ukr_x_preferred":[
        "\u041f\u0443\u0442\u043a\u0430\u0441\u0442\u0435"
    ],
    "name:vol_x_preferred":[
        "Putkaste"
    ],
    "wof:name":"Putkaste",
    "wof:placetype":"locality"
},
  "geometry": {"coordinates":[23.8225,58.84194],"type":"Point"}
}