{
  "type": "Feature",
  "properties": {
    "gn:admin1_code":"7.0",
    "gn:admin2_code":"441.0",
    "gn:admin3_code":"6464.0",
    "gn:asciiname":"Putkaste",
    "gn:country_code":"EE",
    "gn:dem":12,
    "gn:feature_class":"P",
    "gn:feature_code":"PPL",
    "gn:name":"Putkaste",
    "gn:population":0,
    "gn:timezone":"Europe/Tallinn",
    "iso:country":"EE",
    "wof:name":"Putkaste",
    "wof:placetype":"locality"
},
  "geometry": {"coordinates":[23.8225,58.84194],"type":"Point"}
}