{
  "type": "Feature",
  "properties": {
    "gn:admin1_code":"1.0",
    "gn:admin2_code":"431.0",
    "gn:admin3_code":"3857.0",
    "gn:asciiname":"Kaeesalu",
    "gn:country_code":"EE",
    "gn:dem":30,
    "gn:feature_class":"P",
    "gn:feature_code":"PPL",
    "gn:name":"K\u00e4esalu",
    "gn:population":0,
    "gn:timezone":"Europe/Tallinn",
    "iso:country":"EE",
    "name:est_x_preferred":[
        "K\u00e4esalu"
    ],
    "name:fra_x_preferred":[
        "K\u00e4esalu"
    ],
    "name:hun_x_preferred":[
        "K\u00e4esalu"
    ],
    "name:hye_x_preferred":[
        "\u053f\u0575\u0561\u0565\u057d\u0561\u056c\u0578\u0582"
    ],
    "name:pol_x_preferred":[
        "K\u00e4esalu"
    ],
    "name:spa_x_preferred":[
        "K\u00e4esalu"
    ],
    "name:ukr_x_preferred":[
        "\u041a\u044f\u0435\u0441\u0430\u043b\u0443"
    ],
    "name:und_x_variant":[
        "Myza Kyaesalu",
        "Kaosalyu"
    ],
    "name:vol_x_preferred":[
        "K\u00e4esalu"
    ],
    "wof:name":"Kaeesalu",
    "wof:placetype":"locality"
},
  "geometry": {"coordinates":[24.27649,59.36426],"type":"Point"}
}