{
  "type": "Feature",
  "properties": {
    "gn:admin1_code":"1.0",
    "gn:admin2_code":"431.0",
    "gn:admin3_code":"3857.0",
    "gn:asciiname":"Kaeesalu",
    "gn:country_code":"EE",
    "gn:dem":30,
    "gn:feature_class":"P",
    "gn:feature_code":"PPL",
    "gn:name":"K\u00e4esalu",
    "gn:population":0,
    "gn:timezone":"Europe/Tallinn",
    "iso:country":"EE",
    "name:und_x_variant":[
        "Myza Kyaesalu",
        "Kaosalyu",
        "K\u00e4esalu"
    ],
    "wof:name":"Kaeesalu",
    "wof:placetype":"locality"
},
  "geometry": {"coordinates":[24.27649,59.36426],"type":"Point"}
}