{
  "type": "Feature",
  "properties": {
    "gn:admin1_code":"18.0",
    "gn:admin2_code":"171.0",
    "gn:admin3_code":"6890.0",
    "gn:asciiname":"Helmi",
    "gn:country_code":"EE",
    "gn:dem":62,
    "gn:feature_class":"P",
    "gn:feature_code":"PPL",
    "gn:name":"Helmi",
    "gn:population":0,
    "gn:timezone":"Europe/Tallinn",
    "iso:country":"EE",
    "name:deu_x_preferred":[
        "Helmi"
    ],
    "name:und_x_variant":[
        "Keisri"
    ],
    "wof:name":"Helmi",
    "wof:placetype":"locality"
},
  "geometry": {"coordinates":[26.14556,58.07333000000001],"type":"Point"}
}