{
  "type": "Feature",
  "properties": {
    "gn:admin1_code":"7.0",
    "gn:admin2_code":"441.0",
    "gn:admin3_code":"2266.0",
    "gn:asciiname":"Jogisoo",
    "gn:cc2":"EE",
    "gn:country_code":"EE",
    "gn:dem":20,
    "gn:feature_class":"P",
    "gn:feature_code":"PPL",
    "gn:name":"J\u00f5gisoo",
    "gn:population":0,
    "gn:timezone":"Europe/Tallinn",
    "iso:country":"EE",
    "name:deu_x_preferred":[
        "J\u00f5gisoo"
    ],
    "name:est_x_preferred":[
        "J\u00f5gisoo"
    ],
    "name:hye_x_preferred":[
        "\u0545\u056b\u0563\u056b\u057d\u0578\u0578"
    ],
    "name:nld_x_preferred":[
        "J\u00f5gisoo"
    ],
    "name:pol_x_preferred":[
        "J\u00f5gisoo"
    ],
    "name:spa_x_preferred":[
        "J\u00f5gisoo"
    ],
    "name:ukr_x_preferred":[
        "\u0419\u0438\u0491\u0456\u0441\u043e\u043e"
    ],
    "name:und_x_variant":[
        "Myza Iygiso",
        "J\u00f5gisoo Asundus"
    ],
    "name:vol_x_preferred":[
        "J\u00f5gisoo"
    ],
    "wof:coterminous":[
        1713309133
    ],
    "wof:lang_x_official":[
        "est"
    ],
    "wof:lang_x_spoken":[
        "est"
    ],
    "wof:name":"Jogisoo",
    "wof:placetype":"locality"
},
  "geometry": {"coordinates":[24.00944,58.86444],"type":"Point"}
}