{
  "type": "Feature",
  "properties": {
    "gn:admin1_code":"7.0",
    "gn:admin2_code":"441.0",
    "gn:admin3_code":"2266.0",
    "gn:asciiname":"Jogisoo",
    "gn:cc2":"EE",
    "gn:country_code":"EE",
    "gn:dem":20,
    "gn:feature_class":"P",
    "gn:feature_code":"PPL",
    "gn:name":"J\u00f5gisoo",
    "gn:population":0,
    "gn:timezone":"Europe/Tallinn",
    "iso:country":"EE",
    "name:und_x_variant":[
        "Myza Iygiso",
        "J\u00f5gisoo Asundus",
        "J\u00f5gisoo"
    ],
    "wof:name":"Jogisoo",
    "wof:placetype":"locality"
},
  "geometry": {"coordinates":[24.00944,58.86444],"type":"Point"}
}