{
  "type": "Feature",
  "properties": {
    "gn:admin1_code":"3.0",
    "gn:admin2_code":"321.0",
    "gn:admin3_code":"265.0",
    "gn:asciiname":"Vanalinn",
    "gn:country_code":"EE",
    "gn:dem":70,
    "gn:feature_class":"P",
    "gn:feature_code":"PPL",
    "gn:name":"Vanalinn",
    "gn:population":0,
    "gn:timezone":"Europe/Tallinn",
    "iso:country":"EE",
    "name:ara_x_preferred":[
        "\u0641\u0627\u0646\u0627\u0644\u064a\u0646"
    ],
    "name:deu_x_preferred":[
        "Vanalinn"
    ],
    "name:est_x_preferred":[
        "Vanalinna asum"
    ],
    "name:fas_x_preferred":[
        "\u0648\u0627\u0646\u0627\u0644\u06cc\u0646"
    ],
    "name:fin_x_preferred":[
        "Vanalinn"
    ],
    "name:fra_x_preferred":[
        "Vanalinn"
    ],
    "name:hye_x_preferred":[
        "\u054e\u0561\u0576\u0561\u056c\u056b\u0576"
    ],
    "name:nld_x_preferred":[
        "Vanalinn"
    ],
    "name:rus_x_preferred":[
        "\u0412\u0430\u043d\u0430\u043b\u0438\u043d\u043d"
    ],
    "name:und_x_variant":[
        "K\u00e4va"
    ],
    "wof:name":"Vanalinn",
    "wof:placetype":"locality"
},
  "geometry": {"coordinates":[27.26222000000001,59.39389],"type":"Point"}
}