{
  "type": "Feature",
  "properties": {
    "gn:admin1_code":"3.0",
    "gn:admin2_code":"321.0",
    "gn:admin3_code":"265.0",
    "gn:asciiname":"Vanalinn",
    "gn:country_code":"EE",
    "gn:dem":70,
    "gn:feature_class":"P",
    "gn:feature_code":"PPL",
    "gn:name":"Vanalinn",
    "gn:population":0,
    "gn:timezone":"Europe/Tallinn",
    "iso:country":"EE",
    "name:und_x_variant":[
        "K\u00e4va"
    ],
    "wof:name":"Vanalinn",
    "wof:placetype":"locality"
},
  "geometry": {"coordinates":[27.26222000000001,59.39389],"type":"Point"}
}