{
  "type": "Feature",
  "properties": {
    "gn:admin1_code":"20.0",
    "gn:admin2_code":"615.0",
    "gn:admin3_code":"8641.0",
    "gn:asciiname":"Uia",
    "gn:cc2":"EE",
    "gn:country_code":"EE",
    "gn:dem":48,
    "gn:feature_class":"P",
    "gn:feature_code":"PPL",
    "gn:name":"Uia",
    "gn:population":0,
    "gn:timezone":"Europe/Tallinn",
    "iso:country":"EE",
    "name:est_x_preferred":[
        "Uia"
    ],
    "name:hye_x_preferred":[
        "\u0548\u0582\u056b\u0561"
    ],
    "name:pol_x_preferred":[
        "Uia"
    ],
    "name:spa_x_preferred":[
        "Uia"
    ],
    "name:ukr_x_preferred":[
        "\u0423\u0439\u0430"
    ],
    "name:und_x_variant":[
        "Uiya",
        "Uia"
    ],
    "name:vol_x_preferred":[
        "Uia"
    ],
    "wof:name":"Uia",
    "wof:placetype":"locality"
},
  "geometry": {"coordinates":[25.24417,58.33778],"type":"Point"}
}