{
  "type": "Feature",
  "properties": {
    "gn:admin1_code":"8.0",
    "gn:admin2_code":"901.0",
    "gn:admin3_code":"1331.0",
    "gn:asciiname":"Aravuse",
    "gn:country_code":"EE",
    "gn:dem":88,
    "gn:feature_class":"P",
    "gn:feature_code":"PPL",
    "gn:name":"Aravuse",
    "gn:population":0,
    "gn:timezone":"Europe/Tallinn",
    "iso:country":"EE",
    "wof:name":"Aravuse",
    "wof:placetype":"locality"
},
  "geometry": {"coordinates":[26.65361,59.23528],"type":"Point"}
}