{
  "type": "Feature",
  "properties": {
    "gn:admin1_code":"21.0",
    "gn:admin2_code":"917.0",
    "gn:admin3_code":"6761.0",
    "gn:asciiname":"Kanariku",
    "gn:country_code":"EE",
    "gn:dem":91,
    "gn:feature_class":"P",
    "gn:feature_code":"PPL",
    "gn:name":"Kanariku",
    "gn:population":0,
    "gn:timezone":"Europe/Tallinn",
    "iso:country":"EE",
    "name:est_x_preferred":[
        "Kanariku j\u00e4rv"
    ],
    "name:fin_x_preferred":[
        "Kanariku j\u00e4rv"
    ],
    "name:hun_x_preferred":[
        "Kanariku-t\u00f3"
    ],
    "name:und_x_variant":[
        "\u041a\u0430\u043d\u0430\u0440\u0438\u043a\u043e"
    ],
    "wof:lang_x_official":[
        "est"
    ],
    "wof:lang_x_spoken":[
        "est"
    ],
    "wof:name":"Kanariku",
    "wof:placetype":"locality"
},
  "geometry": {"coordinates":[26.975,57.91667],"type":"Point"}
}