{
  "type": "Feature",
  "properties": {
    "gn:gn_country":"EE",
    "gn:gn_fcode":"PPL",
    "gn:gn_pop":102,
    "gn:population":102,
    "iso:country":"EE",
    "qs_pg:aaroncc":"EE",
    "qs_pg:gn_country":"EE",
    "qs_pg:gn_fcode":"PPL",
    "qs_pg:gn_pop":102,
    "qs_pg:name":"Karula",
    "qs_pg:photos_9r":0,
    "qs_pg:photos_sr":0,
    "qs_pg:pop_sr":1,
    "qs_pg:qs_pg_placetype":"locality",
    "wof:name":"Karula",
    "wof:placetype":"locality",
    "wof:population":102
},
  "geometry": {"coordinates":[26.30028,57.75528],"type":"Point"}
}