{
  "type": "Feature",
  "properties": {
    "gn:admin1_code":"1.0",
    "gn:admin2_code":"304.0",
    "gn:admin3_code":"7701.0",
    "gn:asciiname":"Sookaera",
    "gn:country_code":"EE",
    "gn:dem":52,
    "gn:feature_class":"P",
    "gn:feature_code":"PPL",
    "gn:name":"Sookaera",
    "gn:population":0,
    "gn:timezone":"Europe/Tallinn",
    "iso:country":"EE",
    "name:est_x_preferred":[
        "Sookaera"
    ],
    "name:fra_x_preferred":[
        "Sookaera"
    ],
    "name:hye_x_preferred":[
        "\u054d\u0578\u0578\u056f\u0561\u0565\u057c\u0561"
    ],
    "name:nld_x_preferred":[
        "Sookaera"
    ],
    "name:pol_x_preferred":[
        "Sookaera"
    ],
    "name:spa_x_preferred":[
        "Sookaera"
    ],
    "name:und_x_variant":[
        "Sookaara"
    ],
    "name:vol_x_preferred":[
        "Sookaera"
    ],
    "wof:name":"Sookaera",
    "wof:placetype":"locality"
},
  "geometry": {"coordinates":[24.79179,59.26859],"type":"Point"}
}