{
  "type": "Feature",
  "properties": {
    "gn:admin1_code":"1.0",
    "gn:admin2_code":"304.0",
    "gn:admin3_code":"7701.0",
    "gn:asciiname":"Sookaera",
    "gn:country_code":"EE",
    "gn:dem":52,
    "gn:feature_class":"P",
    "gn:feature_code":"PPL",
    "gn:name":"Sookaera",
    "gn:population":0,
    "gn:timezone":"Europe/Tallinn",
    "iso:country":"EE",
    "name:und_x_variant":[
        "Sookaara"
    ],
    "wof:name":"Sookaera",
    "wof:placetype":"locality"
},
  "geometry": {"coordinates":[24.79179,59.26859],"type":"Point"}
}