{
  "type": "Feature",
  "properties": {
    "gn:admin1_code":"11.0",
    "gn:admin2_code":"809.0",
    "gn:admin3_code":"7237.0",
    "gn:asciiname":"Ryagu-Myyzakyula",
    "gn:country_code":"EE",
    "gn:dem":16,
    "gn:feature_class":"P",
    "gn:feature_code":"PPL",
    "gn:name":"Ryagu-Myyzakyula",
    "gn:population":0,
    "gn:timezone":"Europe/Tallinn",
    "iso:country":"EE",
    "name:und_x_variant":[
        "R\u00e4\u00e4gu-M\u00f5isak\u00fcla"
    ],
    "wof:name":"Ryagu-Myyzakyula",
    "wof:placetype":"locality"
},
  "geometry": {"coordinates":[24.5425,58.48639],"type":"Point"}
}