{
  "type": "Feature",
  "properties": {
    "gn:admin1_code":"21.0",
    "gn:admin2_code":"698.0",
    "gn:admin3_code":"8762.0",
    "gn:asciiname":"Uue Saaluse",
    "gn:cc2":"EE",
    "gn:country_code":"EE",
    "gn:dem":220,
    "gn:feature_class":"P",
    "gn:feature_code":"PPL",
    "gn:name":"Uue Saaluse",
    "gn:population":0,
    "gn:timezone":"Europe/Tallinn",
    "iso:country":"EE",
    "name:und_x_variant":[
        "Saaluse Asundus",
        "Myza Us-Saluze",
        "Uus Saaluse",
        "Uue Saaluse"
    ],
    "wof:name":"Uue Saaluse",
    "wof:placetype":"locality"
},
  "geometry": {"coordinates":[27.10333,57.74778000000001],"type":"Point"}
}