{
  "type": "Feature",
  "properties": {
    "gn:admin1_code":"19.0",
    "gn:admin2_code":"557.0",
    "gn:admin3_code":"6549.0",
    "gn:asciiname":"Sauniku",
    "gn:country_code":"EE",
    "gn:dem":59,
    "gn:feature_class":"P",
    "gn:feature_code":"PPL",
    "gn:name":"Sauniku",
    "gn:population":0,
    "gn:timezone":"Europe/Tallinn",
    "iso:country":"EE",
    "wof:name":"Sauniku",
    "wof:placetype":"locality"
},
  "geometry": {"coordinates":[26.13694,58.03667],"type":"Point"}
}