{
  "type": "Feature",
  "properties": {
    "gn:admin1_code":"11.0",
    "gn:admin2_code":"624.0",
    "gn:admin3_code":"1628.0",
    "gn:asciiname":"Ermistu",
    "gn:country_code":"EE",
    "gn:dem":26,
    "gn:feature_class":"P",
    "gn:feature_code":"PPL",
    "gn:name":"Ermistu",
    "gn:population":0,
    "gn:timezone":"Europe/Tallinn",
    "iso:country":"EE",
    "name:eng_x_preferred":[
        "Ermistu"
    ],
    "name:est_x_preferred":[
        "Ermistu"
    ],
    "name:hye_x_preferred":[
        "\u0537\u057c\u0574\u056b\u057d\u057f\u0578\u0582"
    ],
    "name:pol_x_preferred":[
        "Ermistu"
    ],
    "name:rus_x_preferred":[
        "\u042d\u0440\u043c\u0438\u0441\u0442\u0443"
    ],
    "name:ukr_x_preferred":[
        "\u0415\u0440\u043c\u0456\u0441\u0442\u0443"
    ],
    "name:vol_x_preferred":[
        "Ermistu"
    ],
    "wof:lang_x_official":[
        "est"
    ],
    "wof:lang_x_spoken":[
        "est"
    ],
    "wof:name":"Ermistu",
    "wof:placetype":"locality"
},
  "geometry": {"coordinates":[24.01333,58.36528],"type":"Point"}
}