{
  "type": "Feature",
  "properties": {
    "gn:admin1_code":"14.0",
    "gn:admin2_code":"714.0",
    "gn:admin3_code":"9357.0",
    "gn:asciiname":"Vilsandi",
    "gn:country_code":"EE",
    "gn:dem":5,
    "gn:feature_class":"P",
    "gn:feature_code":"PPL",
    "gn:name":"Vilsandi",
    "gn:population":0,
    "gn:timezone":"Europe/Tallinn",
    "iso:country":"EE",
    "name:ceb_x_preferred":[
        "Vilsandi"
    ],
    "name:ces_x_preferred":[
        "Vilsandi"
    ],
    "name:deu_x_preferred":[
        "Vilsandi"
    ],
    "name:est_x_preferred":[
        "Vilsandi"
    ],
    "name:fin_x_preferred":[
        "Vilsandi"
    ],
    "name:fra_x_preferred":[
        "Vilsandi"
    ],
    "name:heb_x_preferred":[
        "\u05d5\u05d9\u05dc\u05e1\u05d0\u05e0\u05d3\u05d9"
    ],
    "name:hrv_x_preferred":[
        "Vilsandi"
    ],
    "name:hye_x_preferred":[
        "\u054e\u056b\u056c\u057d\u0561\u0576\u0564\u056b"
    ],
    "name:lav_x_preferred":[
        "Vilsandi"
    ],
    "name:lit_x_preferred":[
        "Vilsandis"
    ],
    "name:nld_x_preferred":[
        "Vilsandi"
    ],
    "name:nno_x_preferred":[
        "Vilsandi"
    ],
    "name:nor_x_preferred":[
        "Vilsandi"
    ],
    "name:pol_x_preferred":[
        "Vilsandi"
    ],
    "name:rus_x_preferred":[
        "\u0412\u0438\u043b\u044c\u0441\u0430\u043d\u0434\u0438"
    ],
    "name:spa_x_preferred":[
        "Vilsandi"
    ],
    "name:srp_x_preferred":[
        "\u0412\u0438\u043b\u0441\u0430\u043d\u0434\u0438"
    ],
    "name:swe_x_preferred":[
        "Vilsandi"
    ],
    "name:tur_x_preferred":[
        "Vilsandi"
    ],
    "name:ukr_x_preferred":[
        "\u0412\u0456\u043b\u044c\u0441\u0430\u043d\u0434\u0456"
    ],
    "wof:coterminous":[
        1713308599
    ],
    "wof:lang_x_official":[
        "est"
    ],
    "wof:lang_x_spoken":[
        "est"
    ],
    "wof:name":"Vilsandi",
    "wof:placetype":"locality"
},
  "geometry": {"coordinates":[21.84944,58.37583],"type":"Point"}
}