{
  "type": "Feature",
  "properties": {
    "gn:admin1_code":"12.0",
    "gn:admin2_code":"284.0",
    "gn:admin3_code":"1914.0",
    "gn:asciiname":"Hurmi",
    "gn:country_code":"EE",
    "gn:dem":141,
    "gn:feature_class":"P",
    "gn:feature_code":"PPL",
    "gn:name":"Hurmi",
    "gn:population":0,
    "gn:timezone":"Europe/Tallinn",
    "iso:country":"EE",
    "name:est_x_preferred":[
        "Hurmi"
    ],
    "name:hye_x_preferred":[
        "\u0540\u0578\u0582\u057c\u0574\u056b"
    ],
    "name:pol_x_preferred":[
        "Hurmi"
    ],
    "name:spa_x_preferred":[
        "Hurmi"
    ],
    "name:ukr_x_preferred":[
        "\u0425\u0443\u0440\u043c\u0456"
    ],
    "name:vol_x_preferred":[
        "Hurmi"
    ],
    "wof:name":"Hurmi",
    "wof:placetype":"locality"
},
  "geometry": {"coordinates":[26.86861,58.01306],"type":"Point"}
}