{
  "type": "Feature",
  "properties": {
    "gn:admin1_code":"21.0",
    "gn:admin2_code":"917.0",
    "gn:admin3_code":"4845.0",
    "gn:asciiname":"Meeliku",
    "gn:country_code":"EE",
    "gn:dem":128,
    "gn:feature_class":"P",
    "gn:feature_code":"PPL",
    "gn:name":"Meeliku",
    "gn:population":0,
    "gn:timezone":"Europe/Tallinn",
    "iso:country":"EE",
    "wof:name":"Meeliku",
    "wof:placetype":"locality"
},
  "geometry": {"coordinates":[26.98111,57.78722],"type":"Point"}
}