{
  "type": "Feature",
  "properties": {
    "gn:admin1_code":"1.0",
    "gn:admin2_code":"431.0",
    "gn:admin3_code":"1450.0",
    "gn:asciiname":"Jaennima",
    "gn:country_code":"EE",
    "gn:dem":36,
    "gn:feature_class":"P",
    "gn:feature_code":"PPL",
    "gn:name":"J\u00e4nnima",
    "gn:population":0,
    "gn:timezone":"Europe/Tallinn",
    "iso:country":"EE",
    "name:und_x_variant":[
        "Yannima",
        "J\u00e4nnima"
    ],
    "wof:name":"Jaennima",
    "wof:placetype":"locality"
},
  "geometry": {"coordinates":[24.06667,59.18333000000001],"type":"Point"}
}