{
  "type": "Feature",
  "properties": {
    "gn:admin1_code":"5.0",
    "gn:admin2_code":"618.0",
    "gn:admin3_code":"5166.0",
    "gn:asciiname":"Mortsi",
    "gn:country_code":"EE",
    "gn:dem":71,
    "gn:feature_class":"P",
    "gn:feature_code":"PPL",
    "gn:name":"M\u00f5rtsi",
    "gn:population":0,
    "gn:timezone":"Europe/Tallinn",
    "iso:country":"EE",
    "name:est_x_preferred":[
        "M\u00f5rtsi"
    ],
    "name:hye_x_preferred":[
        "\u0544\u056b\u057c\u0581\u056b"
    ],
    "name:pol_x_preferred":[
        "M\u00f5rtsi"
    ],
    "name:spa_x_preferred":[
        "M\u00f5rtsi"
    ],
    "name:ukr_x_preferred":[
        "\u041c\u0438\u0440\u0442\u0441\u0456"
    ],
    "name:und_x_variant":[
        "M\u00f6rtsi"
    ],
    "name:vol_x_preferred":[
        "M\u00f5rtsi"
    ],
    "wof:name":"Mortsi",
    "wof:placetype":"locality"
},
  "geometry": {"coordinates":[26.05833,58.70721999999999],"type":"Point"}
}