{
  "type": "Feature",
  "properties": {
    "gn:admin1_code":"5.0",
    "gn:admin2_code":"618.0",
    "gn:admin3_code":"5166.0",
    "gn:asciiname":"Mortsi",
    "gn:country_code":"EE",
    "gn:dem":71,
    "gn:feature_class":"P",
    "gn:feature_code":"PPL",
    "gn:name":"M\u00f5rtsi",
    "gn:population":0,
    "gn:timezone":"Europe/Tallinn",
    "iso:country":"EE",
    "name:und_x_variant":[
        "M\u00f5rtsi",
        "M\u00f6rtsi"
    ],
    "wof:name":"Mortsi",
    "wof:placetype":"locality"
},
  "geometry": {"coordinates":[26.05833,58.70721999999999],"type":"Point"}
}