{
  "type": "Feature",
  "properties": {
    "gn:admin1_code":"2.0",
    "gn:admin2_code":"205.0",
    "gn:admin3_code":"2533.0",
    "gn:asciiname":"Kaigutsi",
    "gn:cc2":"EE",
    "gn:country_code":"EE",
    "gn:dem":14,
    "gn:feature_class":"P",
    "gn:feature_code":"PPL",
    "gn:name":"Kaigutsi",
    "gn:population":0,
    "gn:timezone":"Europe/Tallinn",
    "iso:country":"EE",
    "name:deu_x_preferred":[
        "Kaigutsi"
    ],
    "name:est_x_preferred":[
        "Kaigutsi"
    ],
    "name:hye_x_preferred":[
        "\u053f\u0561\u056b\u0563\u0578\u0582\u0581\u056b"
    ],
    "name:pol_x_preferred":[
        "Kaigutsi"
    ],
    "name:spa_x_preferred":[
        "Kaigutsi"
    ],
    "name:und_x_variant":[
        "Kaykaotsa",
        "Kaigutsi"
    ],
    "name:vol_x_preferred":[
        "Kaigutsi"
    ],
    "wof:name":"Kaigutsi",
    "wof:placetype":"locality"
},
  "geometry": {"coordinates":[22.68417,58.83667],"type":"Point"}
}