{
  "type": "Feature",
  "properties": {
    "gn:admin1_code":"11.0",
    "gn:admin2_code":"712.0",
    "gn:admin3_code":"5640.0",
    "gn:asciiname":"Oissaare",
    "gn:country_code":"EE",
    "gn:dem":46,
    "gn:feature_class":"P",
    "gn:feature_code":"PPL",
    "gn:name":"Oissaare",
    "gn:population":0,
    "gn:timezone":"Europe/Tallinn",
    "iso:country":"EE",
    "name:est_x_preferred":[
        "Oissaare"
    ],
    "name:fra_x_preferred":[
        "Oissaare"
    ],
    "name:hye_x_preferred":[
        "\u0555\u056b\u057d\u0561\u0561\u057c\u0565"
    ],
    "name:spa_x_preferred":[
        "Oissaare"
    ],
    "name:und_x_variant":[
        "Oyssare"
    ],
    "wof:coterminous":[
        1713309589
    ],
    "wof:lang_x_official":[
        "est"
    ],
    "wof:lang_x_spoken":[
        "est"
    ],
    "wof:name":"Oissaare",
    "wof:placetype":"locality"
},
  "geometry": {"coordinates":[25.05,58.25],"type":"Point"}
}