{
  "type": "Feature",
  "properties": {
    "iso:country":"EE",
    "name:eng_x_preferred":[
        "Maekula"
    ],
    "name:eng_x_variant":[
        "Maekula"
    ],
    "name:est_x_preferred":[
        "M\u00e4ek\u00fcla"
    ],
    "name:nld_x_preferred":[
        "M\u00e4ek\u00fcla"
    ],
    "name:pol_x_preferred":[
        "M\u00e4ek\u00fcla"
    ],
    "name:und_x_colloquial":[
        "Maeekuela",
        "Vanamoisa-Maeekuela",
        "Vanamoisa-Maekula"
    ],
    "name:und_x_preferred":[
        "M\u00e4ek\u00fcla"
    ],
    "name:und_x_variant":[
        "Vanamyyza-Myaekyula",
        "Vanam\u00f5isa-M\u00e4ek\u00fcla"
    ],
    "name:unk_x_variant":[
        "Myaekyula",
        "M\u00e4ek\u00fcla"
    ],
    "name:vol_x_preferred":[
        "M\u00e4ek\u00fcla"
    ],
    "qs:gn_adm0_cc":"EE",
    "qs:gn_fcode":"PPL",
    "qs:gn_local":591472,
    "qs:gn_nam_loc":"Keila, Keila, Harjumaa, EE",
    "qs:gn_namadm1":"11",
    "qs:gn_name":"Myaekyula",
    "qs:local_max":84,
    "qs:local_sum":84,
    "qs:localhoods":1,
    "qs:name":"M\u00e4ek\u00fcla",
    "qs:name_adm0":"Eesti",
    "qs:name_adm1":"Harjumaa",
    "qs:name_adm2":"Saue Vald",
    "qs:name_en":"Maekula",
    "qs:name_local":"Keila",
    "qs:photo_max":19,
    "qs:photo_sum":84,
    "qs:placetype":"Suburb",
    "qs:quad_count":16,
    "qs:woe_adm0":23424805,
    "qs:woe_adm1":2345276,
    "qs:woe_adm2":29389832,
    "qs:woe_lau":0,
    "qs:woe_local":842867,
    "qs:woe_ver":"7.10.0",
    "wof:lang":[
        "unk"
    ],
    "wof:name":"M\u00e4ek\u00fcla",
    "wof:placetype":"neighbourhood"
},
  "geometry": {"coordinates":[24.551828,59.319844],"type":"Point"}
}