{
  "type": "Feature",
  "properties": {
    "gn:gn_country":"EE",
    "gn:gn_fcode":"PPLX",
    "gn:gn_pop":3488,
    "gn:population":3488,
    "iso:country":"EE",
    "qs_pg:aaroncc":"EE",
    "qs_pg:gn_country":"EE",
    "qs_pg:gn_fcode":"PPLX",
    "qs_pg:gn_pop":3488,
    "qs_pg:name":"Rummu",
    "qs_pg:photos_9r":0,
    "qs_pg:photos_sr":0,
    "qs_pg:pop_sr":4,
    "qs_pg:qs_pg_placetype":"neighbourhood",
    "wof:name":"Rummu",
    "wof:placetype":"neighbourhood",
    "wof:population":3488
},
  "geometry": {"coordinates":[24.79972,59.53528],"type":"Point"}
}