{
  "type": "Feature",
  "properties": {
    "gn:admin1_code":"2.0",
    "gn:admin2_code":"205.0",
    "gn:admin3_code":"6903.0",
    "gn:asciiname":"Reheselja",
    "gn:country_code":"EE",
    "gn:dem":13,
    "gn:feature_class":"P",
    "gn:feature_code":"PPL",
    "gn:name":"Reheselja",
    "gn:population":0,
    "gn:timezone":"Europe/Tallinn",
    "iso:country":"EE",
    "name:deu_x_preferred":[
        "Reheselja"
    ],
    "name:est_x_preferred":[
        "Reheselja"
    ],
    "name:fra_x_preferred":[
        "Reheselja"
    ],
    "name:hye_x_preferred":[
        "\u054c\u0565\u0570\u0565\u057d\u0565\u056c\u0575\u0561"
    ],
    "name:pol_x_preferred":[
        "Reheselja"
    ],
    "name:spa_x_preferred":[
        "Reheselja"
    ],
    "name:und_x_variant":[
        "Rekhesel\u2019ya"
    ],
    "name:vol_x_preferred":[
        "Reheselja"
    ],
    "wof:name":"Reheselja",
    "wof:placetype":"locality"
},
  "geometry": {"coordinates":[22.53056,58.7125],"type":"Point"}
}