{
  "type": "Feature",
  "properties": {
    "gn:admin1_code":"5.0",
    "gn:admin2_code":"486.0",
    "gn:admin3_code":"2616.0",
    "gn:asciiname":"Kalmakuela",
    "gn:country_code":"EE",
    "gn:dem":38,
    "gn:feature_class":"P",
    "gn:feature_code":"PPL",
    "gn:name":"Kalmak\u00fcla",
    "gn:population":0,
    "gn:timezone":"Europe/Tallinn",
    "iso:country":"EE",
    "name:deu_x_preferred":[
        "Kalmak\u00fcla"
    ],
    "name:eng_x_preferred":[
        "Kalmak\u00fcla"
    ],
    "name:est_x_preferred":[
        "Kalmak\u00fcla"
    ],
    "name:hye_x_preferred":[
        "\u053f\u0561\u056c\u0574\u0561\u056f\u0575\u0578\u0582\u056c\u0561"
    ],
    "name:pol_x_preferred":[
        "Kalmak\u00fcla"
    ],
    "name:rus_x_preferred":[
        "\u041a\u0430\u043b\u043c\u0430\u043a\u044e\u043b\u0430"
    ],
    "name:spa_x_preferred":[
        "Kalmak\u00fcla"
    ],
    "name:und_x_variant":[
        "Kalma"
    ],
    "name:vol_x_preferred":[
        "Kalmak\u00fcla"
    ],
    "wof:name":"Kalmakuela",
    "wof:placetype":"locality"
},
  "geometry": {"coordinates":[26.96694,58.89471999999999],"type":"Point"}
}