{
  "type": "Feature",
  "properties": {
    "gn:admin1_code":"11.0",
    "gn:admin2_code":"712.0",
    "gn:admin3_code":"3061.0",
    "gn:asciiname":"Vingerja",
    "gn:country_code":"EE",
    "gn:dem":25,
    "gn:feature_class":"P",
    "gn:feature_code":"PPL",
    "gn:name":"Vingerja",
    "gn:population":0,
    "gn:timezone":"Europe/Tallinn",
    "iso:country":"EE",
    "name:und_x_variant":[
        "Vinger\u2019ya",
        "Vingerja"
    ],
    "wof:name":"Vingerja",
    "wof:placetype":"locality"
},
  "geometry": {"coordinates":[24.80167,58.33333],"type":"Point"}
}