{
  "type": "Feature",
  "properties": {
    "gn:country":"EE",
    "gn:fcode":"PPL",
    "gn:population":111,
    "iso:country":"EE",
    "name:est_x_preferred":[
        "Veskim\u00e4e"
    ],
    "qs_pg:aaroncc":"EE",
    "qs_pg:gn_country":"EE",
    "qs_pg:gn_fcode":"PPL",
    "qs_pg:gn_pop":111,
    "qs_pg:name":"Veskim\u00e4e",
    "qs_pg:name_adm0":"Eesti",
    "qs_pg:name_adm1":"Viljandimaa",
    "qs_pg:photos_9r":0,
    "qs_pg:photos_sr":0,
    "qs_pg:pop_sr":1,
    "qs_pg:qs_pg_placetype":"locality",
    "qs_pg:qs_pg_placetype_gp":"Town",
    "qs_pg:woe_adm0":23424805,
    "woe:adm0_id":23424805,
    "woe:name_adm0":"Eesti",
    "woe:name_adm1":"Viljandimaa",
    "woe:placetype":"Town",
    "wof:coterminous":[
        1713311687
    ],
    "wof:lang_x_official":[
        "est"
    ],
    "wof:lang_x_spoken":[
        "est"
    ],
    "wof:name":"Veskim\u00e4e",
    "wof:placetype":"locality",
    "wof:population":111
},
  "geometry": {"coordinates":[25.35583,58.13278],"type":"Point"}
}