{
  "type": "Feature",
  "properties": {
    "gn:admin1_code":"4.0",
    "gn:admin2_code":"255.0",
    "gn:admin3_code":"4936.0",
    "gn:asciiname":"Jalalope",
    "gn:cc2":"EE",
    "gn:country_code":"EE",
    "gn:dem":97,
    "gn:feature_class":"P",
    "gn:feature_code":"PPL",
    "gn:name":"Jalal\u00f5pe",
    "gn:population":0,
    "gn:timezone":"Europe/Tallinn",
    "iso:country":"EE",
    "name:und_x_variant":[
        "Yalalype",
        "Jalal\u00f5pe"
    ],
    "wof:name":"Jalalope",
    "wof:placetype":"locality"
},
  "geometry": {"coordinates":[25.85361,59.05472],"type":"Point"}
}