{
  "type": "Feature",
  "properties": {
    "gn:admin1_code":"8.0",
    "gn:admin2_code":"901.0",
    "gn:admin3_code":"5471.0",
    "gn:asciiname":"Tonuvere",
    "gn:country_code":"EE",
    "gn:dem":121,
    "gn:feature_class":"P",
    "gn:feature_code":"PPL",
    "gn:name":"T\u00f5nuvere",
    "gn:population":0,
    "gn:timezone":"Europe/Tallinn",
    "iso:country":"EE",
    "name:und_x_variant":[
        "T\u00f5nuvere",
        "Tennowere"
    ],
    "wof:name":"Tonuvere",
    "wof:placetype":"locality"
},
  "geometry": {"coordinates":[26.33806,59.24278],"type":"Point"}
}