{
  "type": "Feature",
  "properties": {
    "gn:admin1_code":"20.0",
    "gn:admin2_code":"615.0",
    "gn:admin3_code":"2304.0",
    "gn:asciiname":"Nomme",
    "gn:country_code":"EE",
    "gn:dem":52,
    "gn:feature_class":"P",
    "gn:feature_code":"PPL",
    "gn:name":"N\u00f5mme",
    "gn:population":0,
    "gn:timezone":"Europe/Tallinn",
    "iso:country":"EE",
    "name:und_x_variant":[
        "N\u00f5mme",
        "Maltsare"
    ],
    "wof:name":"Nomme",
    "wof:placetype":"locality"
},
  "geometry": {"coordinates":[25.39528,58.60694],"type":"Point"}
}