{
  "type": "Feature",
  "properties": {
    "gn:admin1_code":"21.0",
    "gn:admin2_code":"917.0",
    "gn:admin3_code":"2184.0",
    "gn:asciiname":"Jeedaskuela",
    "gn:country_code":"EE",
    "gn:dem":171,
    "gn:feature_class":"P",
    "gn:feature_code":"PPL",
    "gn:name":"Jeedask\u00fcla",
    "gn:population":0,
    "gn:timezone":"Europe/Tallinn",
    "iso:country":"EE",
    "name:est_x_preferred":[
        "Jeedask\u00fcla"
    ],
    "name:hye_x_preferred":[
        "\u0535\u0565\u0564\u0561\u057d\u056f\u0575\u0578\u0582\u056c\u0561"
    ],
    "name:nld_x_preferred":[
        "Jeedask\u00fcla"
    ],
    "name:pol_x_preferred":[
        "Jeedask\u00fcla"
    ],
    "name:spa_x_preferred":[
        "Jeedask\u00fcla"
    ],
    "name:ukr_x_preferred":[
        "\u0404\u0435\u0434\u0430\u0441\u043a\u044e\u043b\u0430"
    ],
    "name:und_x_variant":[
        "Iedas"
    ],
    "name:vol_x_preferred":[
        "Jeedask\u00fcla"
    ],
    "wof:lang_x_official":[
        "est"
    ],
    "wof:lang_x_spoken":[
        "est"
    ],
    "wof:name":"Jeedaskuela",
    "wof:placetype":"locality"
},
  "geometry": {"coordinates":[27.2575,57.72306],"type":"Point"}
}