{
  "type": "Feature",
  "properties": {
    "gn:admin1_code":"13.0",
    "gn:admin2_code":"668.0",
    "gn:admin3_code":"1717.0",
    "gn:asciiname":"Purila-UElejoe",
    "gn:country_code":"EE",
    "gn:dem":75,
    "gn:feature_class":"P",
    "gn:feature_code":"PPL",
    "gn:name":"Purila-\u00dclej\u00f5e",
    "gn:population":0,
    "gn:timezone":"Europe/Tallinn",
    "iso:country":"EE",
    "name:und_x_variant":[
        "Purila-Yuleyye",
        "Purila-\u00dclej\u00f5e"
    ],
    "wof:name":"Purila-UElejoe",
    "wof:placetype":"locality"
},
  "geometry": {"coordinates":[24.83333,59.06667],"type":"Point"}
}