{
  "type": "Feature",
  "properties": {
    "gn:admin1_code":"4.0",
    "gn:admin2_code":"255.0",
    "gn:admin3_code":"2712.0",
    "gn:asciiname":"Kareda",
    "gn:country_code":"EE",
    "gn:dem":85,
    "gn:feature_class":"P",
    "gn:feature_code":"PPL",
    "gn:name":"Kareda",
    "gn:population":0,
    "gn:timezone":"Europe/Tallinn",
    "iso:country":"EE",
    "name:ara_x_preferred":[
        "\u0643\u0627\u0631\u064a\u062f\u0627"
    ],
    "name:eng_x_preferred":[
        "Kareda Parish"
    ],
    "name:est_x_preferred":[
        "Kareda vald"
    ],
    "name:fas_x_preferred":[
        "\u062f\u0647\u0633\u062a\u0627\u0646 \u06a9\u0627\u0631\u062f\u0627"
    ],
    "name:fra_x_preferred":[
        "Commune de Kareda"
    ],
    "name:hye_x_preferred":[
        "\u053f\u0561\u057c\u0565\u0564\u0561"
    ],
    "name:kat_x_preferred":[
        "\u10d9\u10d0\u10e0\u10d4\u10d3\u10d8\u10e1 \u10db\u10e3\u10dc\u10d8\u10ea\u10d8\u10de\u10d0\u10da\u10d8\u10e2\u10d4\u10e2\u10d8"
    ],
    "name:nor_x_preferred":[
        "Kareda kommune"
    ],
    "name:pol_x_preferred":[
        "Gmina Kareda"
    ],
    "name:ron_x_preferred":[
        "Comuna Kareda"
    ],
    "name:rus_x_preferred":[
        "\u041a\u0430\u0440\u0435\u0434\u0430"
    ],
    "name:ukr_x_preferred":[
        "\u041a\u0430\u0440\u0435\u0434\u0430"
    ],
    "wof:name":"Kareda",
    "wof:placetype":"locality"
},
  "geometry": {"coordinates":[25.81,58.96083],"type":"Point"}
}