{
  "type": "Feature",
  "properties": {
    "gn:admin1_code":"3.0",
    "gn:admin2_code":"130.0",
    "gn:admin3_code":"1526.0",
    "gn:asciiname":"Edivere",
    "gn:country_code":"EE",
    "gn:dem":65,
    "gn:feature_class":"P",
    "gn:feature_code":"PPL",
    "gn:name":"Edivere",
    "gn:population":0,
    "gn:timezone":"Europe/Tallinn",
    "iso:country":"EE",
    "wof:name":"Edivere",
    "wof:placetype":"locality"
},
  "geometry": {"coordinates":[27.51472,59.23611],"type":"Point"}
}