{
  "type": "Feature",
  "properties": {
    "gn:admin1_code":"18.0",
    "gn:admin2_code":"171.0",
    "gn:admin3_code":"9591.0",
    "gn:asciiname":"Vosivere",
    "gn:cc2":"EE",
    "gn:country_code":"EE",
    "gn:dem":51,
    "gn:feature_class":"P",
    "gn:feature_code":"PPL",
    "gn:name":"V\u00f5sivere",
    "gn:population":0,
    "gn:timezone":"Europe/Tallinn",
    "iso:country":"EE",
    "name:und_x_variant":[
        "Vyzivere",
        "V\u00f5sivere"
    ],
    "wof:name":"Vosivere",
    "wof:placetype":"locality"
},
  "geometry": {"coordinates":[26.42861,58.33722],"type":"Point"}
}