{
  "type": "Feature",
  "properties": {
    "gn:admin1_code":"19.0",
    "gn:admin2_code":"557.0",
    "gn:admin3_code":"6570.0",
    "gn:asciiname":"Mortsuka",
    "gn:country_code":"EE",
    "gn:dem":106,
    "gn:feature_class":"P",
    "gn:feature_code":"PPL",
    "gn:name":"M\u00f5rtsuka",
    "gn:population":0,
    "gn:timezone":"Europe/Tallinn",
    "iso:country":"EE",
    "wof:name":"Mortsuka",
    "wof:placetype":"locality"
},
  "geometry": {"coordinates":[26.47194,58.14333000000001],"type":"Point"}
}