{
  "type": "Feature",
  "properties": {
    "gn:admin1_code":"1.0",
    "gn:admin2_code":"431.0",
    "gn:admin3_code":"6062.0",
    "gn:asciiname":"Pedase",
    "gn:cc2":"EE",
    "gn:country_code":"EE",
    "gn:dem":14,
    "gn:feature_class":"P",
    "gn:feature_code":"PPL",
    "gn:name":"Pedase",
    "gn:population":0,
    "gn:timezone":"Europe/Tallinn",
    "iso:country":"EE",
    "name:est_x_preferred":[
        "Pedase"
    ],
    "name:fra_x_preferred":[
        "Pedase"
    ],
    "name:hye_x_preferred":[
        "\u054a\u0565\u0564\u0561\u057d\u0565"
    ],
    "name:pol_x_preferred":[
        "Pedase"
    ],
    "name:spa_x_preferred":[
        "Pedase"
    ],
    "name:swe_x_preferred":[
        "P\u00e4ts"
    ],
    "name:ukr_x_preferred":[
        "\u041f\u0435\u0434\u0430\u0437\u0435"
    ],
    "name:und_x_variant":[
        "Pedaso"
    ],
    "name:vol_x_preferred":[
        "Pedase"
    ],
    "wof:lang_x_official":[
        "est"
    ],
    "wof:lang_x_spoken":[
        "est"
    ],
    "wof:name":"Pedase",
    "wof:placetype":"locality"
},
  "geometry": {"coordinates":[23.90472,59.2725],"type":"Point"}
}