{
  "type": "Feature",
  "properties": {
    "gn:admin1_code":"4.0",
    "gn:admin2_code":"255.0",
    "gn:admin3_code":"2343.0",
    "gn:asciiname":"Jaerva-Madise",
    "gn:country_code":"EE",
    "gn:dem":84,
    "gn:feature_class":"P",
    "gn:feature_code":"PPL",
    "gn:name":"J\u00e4rva-Madise",
    "gn:population":0,
    "gn:timezone":"Europe/Tallinn",
    "iso:country":"EE",
    "name:deu_x_preferred":[
        "J\u00e4rva-Madise"
    ],
    "name:eng_x_preferred":[
        "J\u00e4rva-Madise"
    ],
    "name:est_x_preferred":[
        "J\u00e4rva-Madise"
    ],
    "name:fra_x_preferred":[
        "J\u00e4rva-Madise"
    ],
    "name:hye_x_preferred":[
        "\u0535\u057c\u057e\u0561-\u0544\u0561\u0564\u056b\u057d\u0565"
    ],
    "name:pol_x_preferred":[
        "J\u00e4rva-Madise"
    ],
    "name:rus_x_preferred":[
        "\u042f\u0440\u0432\u0430-\u041c\u0430\u0434\u0438\u0437\u0435"
    ],
    "name:spa_x_preferred":[
        "J\u00e4rva-Madise"
    ],
    "name:ukr_x_preferred":[
        "\u042f\u0440\u0432\u0430-\u041c\u0430\u0434\u0456\u0437\u0435"
    ],
    "name:und_x_variant":[
        "Sankt-Matth\u00e4i",
        "Madise",
        "Yarva-Madise",
        "Sankt Matt\u00e4i",
        "Svyatogo Mateya",
        "J\u00e4rva-Madise"
    ],
    "name:urd_x_preferred":[
        "\u062c\u0627\u0631\u0648\u0627-\u0645\u0627\u062f\u062b\u06d2"
    ],
    "name:vol_x_preferred":[
        "J\u00e4rva-Madise"
    ],
    "name:zho_x_preferred":[
        "\u8036\u723e\u74e6-\u99ac\u8fea\u585e"
    ],
    "wof:name":"Jaerva-Madise",
    "wof:placetype":"locality"
},
  "geometry": {"coordinates":[25.65861,59.11639],"type":"Point"}
}