{
  "type": "Feature",
  "properties": {
    "gn:admin1_code":"21.0",
    "gn:admin2_code":"698.0",
    "gn:admin3_code":"4158.0",
    "gn:asciiname":"Lauri",
    "gn:country_code":"EE",
    "gn:dem":120,
    "gn:feature_class":"P",
    "gn:feature_code":"PPL",
    "gn:name":"Lauri",
    "gn:population":0,
    "gn:timezone":"Europe/Tallinn",
    "iso:country":"EE",
    "name:ceb_x_preferred":[
        "Lauri"
    ],
    "name:est_x_preferred":[
        "Lauri"
    ],
    "name:fin_x_preferred":[
        "Lauri"
    ],
    "name:fra_x_preferred":[
        "Lauri"
    ],
    "name:hye_x_preferred":[
        "\u053c\u0561\u0578\u0582\u057c\u056b"
    ],
    "name:ita_x_preferred":[
        "Lauri"
    ],
    "name:lav_x_preferred":[
        "Lauri"
    ],
    "name:pol_x_preferred":[
        "Lauri"
    ],
    "name:ukr_x_preferred":[
        "\u041b\u0430\u0443\u0440\u0456"
    ],
    "name:vol_x_preferred":[
        "Lauri"
    ],
    "wof:name":"Lauri",
    "wof:placetype":"locality"
},
  "geometry": {"coordinates":[26.86722,57.75528000000001],"type":"Point"}
}