{
  "type": "Feature",
  "properties": {
    "gn:admin1_code":"7.0",
    "gn:admin2_code":"184.0",
    "gn:admin3_code":"9091.0",
    "gn:asciiname":"Varni",
    "gn:country_code":"EE",
    "gn:dem":9,
    "gn:feature_class":"P",
    "gn:feature_code":"PPL",
    "gn:name":"Varni",
    "gn:population":0,
    "gn:timezone":"Europe/Tallinn",
    "iso:country":"EE",
    "name:deu_x_preferred":[
        "Varni"
    ],
    "name:est_x_preferred":[
        "Varni"
    ],
    "name:fas_x_preferred":[
        "\u0648\u0631\u0646\u06cc"
    ],
    "name:hye_x_preferred":[
        "\u054e\u0561\u057c\u0576\u056b"
    ],
    "name:pol_x_preferred":[
        "Varni"
    ],
    "name:ukr_x_preferred":[
        "\u0412\u0430\u0440\u043d\u0456"
    ],
    "name:vol_x_preferred":[
        "Varni"
    ],
    "wof:lang_x_official":[
        "est"
    ],
    "wof:lang_x_spoken":[
        "est"
    ],
    "wof:name":"Varni",
    "wof:placetype":"locality"
},
  "geometry": {"coordinates":[23.53333,58.83333],"type":"Point"}
}