{
  "type": "Feature",
  "properties": {
    "gn:admin1_code":"7.0",
    "gn:admin2_code":"184.0",
    "gn:admin3_code":"9091.0",
    "gn:asciiname":"Varni",
    "gn:country_code":"EE",
    "gn:dem":9,
    "gn:feature_class":"P",
    "gn:feature_code":"PPL",
    "gn:name":"Varni",
    "gn:population":0,
    "gn:timezone":"Europe/Tallinn",
    "iso:country":"EE",
    "wof:name":"Varni",
    "wof:placetype":"locality"
},
  "geometry": {"coordinates":[23.53333,58.83333],"type":"Point"}
}