{
  "type": "Feature",
  "properties": {
    "gn:admin1_code":"5.0",
    "gn:admin2_code":"247.0",
    "gn:admin3_code":"8879.0",
    "gn:asciiname":"Oonurme",
    "gn:country_code":"EE",
    "gn:dem":88,
    "gn:feature_class":"P",
    "gn:feature_code":"PPL",
    "gn:name":"Oonurme",
    "gn:population":0,
    "gn:timezone":"Europe/Tallinn",
    "iso:country":"EE",
    "name:deu_x_preferred":[
        "Oonurme"
    ],
    "name:est_x_preferred":[
        "Oonurme"
    ],
    "name:hye_x_preferred":[
        "\u0555\u0578\u0576\u0578\u0582\u057c\u0574\u0565"
    ],
    "name:nld_x_preferred":[
        "Oonurme"
    ],
    "name:pol_x_preferred":[
        "Oonurme"
    ],
    "name:spa_x_preferred":[
        "Oonurme"
    ],
    "name:und_x_variant":[
        "\u041e\u043d\u0443\u0440\u043c\u0435"
    ],
    "name:vol_x_preferred":[
        "Oonurme"
    ],
    "wof:name":"Oonurme",
    "wof:placetype":"locality"
},
  "geometry": {"coordinates":[26.25861,58.78917],"type":"Point"}
}