{
  "type": "Feature",
  "properties": {
    "gn:admin1_code":"21.0",
    "gn:admin2_code":"142.0",
    "gn:admin3_code":"8801.0",
    "gn:asciiname":"Peebu",
    "gn:country_code":"EE",
    "gn:dem":96,
    "gn:feature_class":"P",
    "gn:feature_code":"PPL",
    "gn:name":"Peebu",
    "gn:population":0,
    "gn:timezone":"Europe/Tallinn",
    "iso:country":"EE",
    "name:est_x_preferred":[
        "Peebu"
    ],
    "name:hye_x_preferred":[
        "\u054a\u0565\u0565\u0562\u0578\u0582"
    ],
    "name:pol_x_preferred":[
        "Peebu"
    ],
    "name:spa_x_preferred":[
        "Peebu"
    ],
    "name:swe_x_preferred":[
        "Peebu"
    ],
    "name:ukr_x_preferred":[
        "\u041f\u0435\u0435\u0431\u0443"
    ],
    "name:und_x_variant":[
        "Soe"
    ],
    "name:vol_x_preferred":[
        "Peebu"
    ],
    "wof:lang_x_official":[
        "est"
    ],
    "wof:lang_x_spoken":[
        "est"
    ],
    "wof:name":"Peebu",
    "wof:placetype":"locality"
},
  "geometry": {"coordinates":[26.62444,57.84778],"type":"Point"}
}