{
  "type": "Feature",
  "properties": {
    "gn:admin1_code":"21.0",
    "gn:admin2_code":"142.0",
    "gn:admin3_code":"8801.0",
    "gn:asciiname":"Peebu",
    "gn:country_code":"EE",
    "gn:dem":96,
    "gn:feature_class":"P",
    "gn:feature_code":"PPL",
    "gn:name":"Peebu",
    "gn:population":0,
    "gn:timezone":"Europe/Tallinn",
    "iso:country":"EE",
    "name:und_x_variant":[
        "Soe"
    ],
    "wof:name":"Peebu",
    "wof:placetype":"locality"
},
  "geometry": {"coordinates":[26.62444,57.84778000000001],"type":"Point"}
}