{
  "type": "Feature",
  "properties": {
    "gn:gn_country":"EE",
    "gn:gn_fcode":"PPL",
    "gn:gn_pop":112,
    "gn:population":112,
    "iso:country":"EE",
    "name:deu_x_preferred":[
        "V\u00f5\u00f5psu"
    ],
    "name:eng_x_preferred":[
        "V\u00f5\u00f5psu"
    ],
    "name:est_x_preferred":[
        "V\u00f5\u00f5psu k\u00fcla"
    ],
    "name:fra_x_preferred":[
        "V\u00f5\u00f5psu"
    ],
    "name:hye_x_preferred":[
        "\u054e\u056b\u056b\u057a\u057d\u0578\u0582"
    ],
    "name:nld_x_preferred":[
        "V\u00f5\u00f5psu village"
    ],
    "name:pol_x_preferred":[
        "V\u00f5\u00f5psu"
    ],
    "name:rus_x_preferred":[
        "\u0412\u044b\u044b\u043f\u0441\u0443"
    ],
    "name:swe_x_preferred":[
        "V\u00f5\u00f5psu k\u00fcla"
    ],
    "name:ukr_x_preferred":[
        "\u0412\u0438\u0438\u043f\u0441\u0443"
    ],
    "name:unk_x_variant":[
        "Novo-Rappin"
    ],
    "name:vol_x_preferred":[
        "V\u00f5\u00f5psu k\u00fcla"
    ],
    "qs_pg:aaroncc":"EE",
    "qs_pg:gn_country":"EE",
    "qs_pg:gn_fcode":"PPL",
    "qs_pg:gn_pop":112,
    "qs_pg:name":"V\u00f5\u00f5psu",
    "qs_pg:name_adm0":"Eesti",
    "qs_pg:name_adm1":"P\u00f5lvamaa",
    "qs_pg:photos_9k":1,
    "qs_pg:photos_9r":1,
    "qs_pg:photos_all":1,
    "qs_pg:photos_sr":0,
    "qs_pg:pop_sr":1,
    "qs_pg:qs_pg_placetype":"locality",
    "qs_pg:qs_pg_placetype_gp":"Town",
    "qs_pg:woe_adm0":23424805,
    "woe:adm0_id":23424805,
    "woe:name_adm0":"Eesti",
    "woe:name_adm1":"P\u00f5lvamaa",
    "woe:placetype":"Town",
    "wof:name":"V\u00f5\u00f5psu",
    "wof:placetype":"locality",
    "wof:population":112
},
  "geometry": {"coordinates":[27.54528,58.07833],"type":"Point"}
}