{
  "type": "Feature",
  "properties": {
    "gn:admin1_code":"4.0",
    "gn:admin2_code":"255.0",
    "gn:admin3_code":"2164.0",
    "gn:asciiname":"Jalgsema",
    "gn:country_code":"EE",
    "gn:dem":111,
    "gn:feature_class":"P",
    "gn:feature_code":"PPL",
    "gn:name":"Jalgsema",
    "gn:population":0,
    "gn:timezone":"Europe/Tallinn",
    "iso:country":"EE",
    "name:est_x_preferred":[
        "Jalgsema"
    ],
    "name:hye_x_preferred":[
        "\u0545\u0561\u056c\u0563\u057d\u0565\u0574\u0561"
    ],
    "name:pol_x_preferred":[
        "Jalgsema"
    ],
    "name:sco_x_preferred":[
        "Jalgsema"
    ],
    "name:spa_x_preferred":[
        "Jalgsema"
    ],
    "name:ukr_x_preferred":[
        "\u042f\u043b\u0491\u0441\u0435\u043c\u0430"
    ],
    "name:urd_x_preferred":[
        "\u062c\u0644\u06af\u0633\u0645\u06c1"
    ],
    "name:vol_x_preferred":[
        "Jalgsema"
    ],
    "wof:name":"Jalgsema",
    "wof:placetype":"locality"
},
  "geometry": {"coordinates":[25.89806,59.09056],"type":"Point"}
}