{
  "type": "Feature",
  "properties": {
    "gn:admin1_code":"4.0",
    "gn:admin2_code":"255.0",
    "gn:admin3_code":"2164.0",
    "gn:asciiname":"Jalgsema",
    "gn:country_code":"EE",
    "gn:dem":111,
    "gn:feature_class":"P",
    "gn:feature_code":"PPL",
    "gn:name":"Jalgsema",
    "gn:population":0,
    "gn:timezone":"Europe/Tallinn",
    "iso:country":"EE",
    "wof:name":"Jalgsema",
    "wof:placetype":"locality"
},
  "geometry": {"coordinates":[25.89806,59.09056],"type":"Point"}
}