{
  "type": "Feature",
  "properties": {
    "gn:admin1_code":"11.0",
    "gn:admin2_code":"809.0",
    "gn:admin3_code":"2251.0",
    "gn:asciiname":"Puista",
    "gn:country_code":"EE",
    "gn:dem":23,
    "gn:feature_class":"P",
    "gn:feature_code":"PPL",
    "gn:name":"Puista",
    "gn:population":0,
    "gn:timezone":"Europe/Tallinn",
    "iso:country":"EE",
    "name:und_x_variant":[
        "Puysta",
        "Puista"
    ],
    "wof:name":"Puista",
    "wof:placetype":"locality"
},
  "geometry": {"coordinates":[24.90222,58.48528],"type":"Point"}
}