{
  "type": "Feature",
  "properties": {
    "gn:admin1_code":"12.0",
    "gn:admin2_code":"284.0",
    "gn:admin3_code":"2007.0",
    "gn:asciiname":"Hilba",
    "gn:country_code":"EE",
    "gn:dem":116,
    "gn:feature_class":"P",
    "gn:feature_code":"PPL",
    "gn:name":"Hilba",
    "gn:population":0,
    "gn:timezone":"Europe/Tallinn",
    "iso:country":"EE",
    "name:deu_x_preferred":[
        "Hilba j\u00e4rv"
    ],
    "name:est_x_preferred":[
        "Hilba j\u00e4rv"
    ],
    "name:und_x_variant":[
        "T\u00e4ik\u00fcl\u00e4",
        "Hilba"
    ],
    "wof:name":"Hilba",
    "wof:placetype":"locality"
},
  "geometry": {"coordinates":[26.86889,58.06111],"type":"Point"}
}