{
  "type": "Feature",
  "properties": {
    "gn:admin1_code":"13.0",
    "gn:admin2_code":"293.0",
    "gn:admin3_code":"5498.0",
    "gn:asciiname":"Allika",
    "gn:cc2":"EE",
    "gn:country_code":"EE",
    "gn:dem":50,
    "gn:feature_class":"P",
    "gn:feature_code":"PPL",
    "gn:name":"Allika",
    "gn:population":0,
    "gn:timezone":"Europe/Tallinn",
    "iso:country":"EE",
    "name:und_x_variant":[
        "Allikak\u00fcla",
        "Allika"
    ],
    "wof:name":"Allika",
    "wof:placetype":"locality"
},
  "geometry": {"coordinates":[24.73194,58.80389],"type":"Point"}
}