{
  "type": "Feature",
  "properties": {
    "gn:admin1_code":"18.0",
    "gn:admin2_code":"291.0",
    "gn:admin3_code":"8107.0",
    "gn:asciiname":"Tammevaldma",
    "gn:cc2":"EE",
    "gn:country_code":"EE",
    "gn:dem":51,
    "gn:feature_class":"P",
    "gn:feature_code":"PPL",
    "gn:name":"Tammevaldma",
    "gn:population":0,
    "gn:timezone":"Europe/Tallinn",
    "iso:country":"EE",
    "name:est_x_preferred":[
        "Tammevaldma"
    ],
    "name:hye_x_preferred":[
        "\u054f\u0561\u0574\u0587\u0561\u056c\u0564\u0574\u0561"
    ],
    "name:pol_x_preferred":[
        "Tammevaldma"
    ],
    "name:spa_x_preferred":[
        "Tammevaldma"
    ],
    "name:ukr_x_preferred":[
        "\u0422\u0430\u043c\u043c\u0435\u0432\u0430\u043b\u0434\u043c\u0430"
    ],
    "name:und_x_variant":[
        "Tamme"
    ],
    "name:vol_x_preferred":[
        "Tammevaldma"
    ],
    "wof:lang_x_official":[
        "est"
    ],
    "wof:lang_x_spoken":[
        "est"
    ],
    "wof:name":"Tammevaldma",
    "wof:placetype":"locality"
},
  "geometry": {"coordinates":[27.01333,58.33333],"type":"Point"}
}