{
  "type": "Feature",
  "properties": {
    "gn:admin1_code":"21.0",
    "gn:admin2_code":"917.0",
    "gn:admin3_code":"5734.0",
    "gn:asciiname":"Tahma",
    "gn:country_code":"EE",
    "gn:dem":172,
    "gn:feature_class":"P",
    "gn:feature_code":"PPL",
    "gn:name":"Tahma",
    "gn:population":0,
    "gn:timezone":"Europe/Tallinn",
    "iso:country":"EE",
    "name:und_x_variant":[
        "\u0422\u0430\u0445\u043c\u0430"
    ],
    "wof:name":"Tahma",
    "wof:placetype":"locality"
},
  "geometry": {"coordinates":[27.25528,57.78056],"type":"Point"}
}