{
  "type": "Feature",
  "properties": {
    "gn:admin1_code":"21.0",
    "gn:admin2_code":"732.0",
    "gn:admin3_code":"4434.0",
    "gn:asciiname":"Slobotka",
    "gn:country_code":"EE",
    "gn:dem":43,
    "gn:feature_class":"P",
    "gn:feature_code":"PPL",
    "gn:name":"Slobotka",
    "gn:population":0,
    "gn:timezone":"Europe/Tallinn",
    "iso:country":"EE",
    "name:est_x_preferred":[
        "Lobotka"
    ],
    "name:hye_x_preferred":[
        "\u053c\u0578\u0562\u0578\u057f\u056f\u0561"
    ],
    "name:pol_x_preferred":[
        "Lobotka"
    ],
    "name:sco_x_preferred":[
        "Lobotka"
    ],
    "name:spa_x_preferred":[
        "Lobotka"
    ],
    "name:ukr_x_preferred":[
        "\u041b\u043e\u0431\u043e\u0442\u043a\u0430"
    ],
    "name:und_x_variant":[
        "Slobotka"
    ],
    "name:vol_x_preferred":[
        "Lobotka"
    ],
    "wof:coterminous":[
        1713316439
    ],
    "wof:lang_x_official":[
        "est"
    ],
    "wof:lang_x_spoken":[
        "est"
    ],
    "wof:name":"Slobotka",
    "wof:placetype":"locality"
},
  "geometry": {"coordinates":[27.61667,57.95861],"type":"Point"}
}