{
  "type": "Feature",
  "properties": {
    "gn:admin1_code":"21.0",
    "gn:admin2_code":"732.0",
    "gn:admin3_code":"4434.0",
    "gn:asciiname":"Slobotka",
    "gn:country_code":"EE",
    "gn:dem":43,
    "gn:feature_class":"P",
    "gn:feature_code":"PPL",
    "gn:name":"Slobotka",
    "gn:population":0,
    "gn:timezone":"Europe/Tallinn",
    "iso:country":"EE",
    "name:und_x_variant":[
        "Lobotka",
        "Slobotka"
    ],
    "wof:name":"Slobotka",
    "wof:placetype":"locality"
},
  "geometry": {"coordinates":[27.61667000000001,57.95861],"type":"Point"}
}