{
  "type": "Feature",
  "properties": {
    "gn:admin1_code":"18.0",
    "gn:admin2_code":"586.0",
    "gn:admin3_code":"4889.0",
    "gn:asciiname":"Kirepi",
    "gn:country_code":"EE",
    "gn:dem":76,
    "gn:feature_class":"P",
    "gn:feature_code":"PPL",
    "gn:name":"Kirepi",
    "gn:population":0,
    "gn:timezone":"Europe/Tallinn",
    "iso:country":"EE",
    "wof:name":"Kirepi",
    "wof:placetype":"locality"
},
  "geometry": {"coordinates":[27.06083,58.54278000000001],"type":"Point"}
}