{
  "type": "Feature",
  "properties": {
    "gn:admin1_code":"14.0",
    "gn:admin2_code":"714.0",
    "gn:admin3_code":"7513.0",
    "gn:asciiname":"Selgase",
    "gn:country_code":"EE",
    "gn:dem":26,
    "gn:feature_class":"P",
    "gn:feature_code":"PPL",
    "gn:name":"Selgase",
    "gn:population":0,
    "gn:timezone":"Europe/Tallinn",
    "iso:country":"EE",
    "wof:name":"Selgase",
    "wof:placetype":"locality"
},
  "geometry": {"coordinates":[22.18694,58.43167],"type":"Point"}
}