{
  "type": "Feature",
  "properties": {
    "gn:admin1_code":"11.0",
    "gn:admin2_code":"214.0",
    "gn:admin3_code":"5984.0",
    "gn:asciiname":"Ojasoo",
    "gn:country_code":"EE",
    "gn:dem":20,
    "gn:feature_class":"P",
    "gn:feature_code":"PPL",
    "gn:name":"Ojasoo",
    "gn:population":0,
    "gn:timezone":"Europe/Tallinn",
    "iso:country":"EE",
    "name:ceb_x_preferred":[
        "Ojasoo"
    ],
    "name:est_x_preferred":[
        "Ojasoo"
    ],
    "name:fra_x_preferred":[
        "Ojasoo"
    ],
    "name:hye_x_preferred":[
        "\u0555\u0575\u0561\u057d\u0578\u0578"
    ],
    "name:pol_x_preferred":[
        "Ojasoo"
    ],
    "name:spa_x_preferred":[
        "Ojasoo"
    ],
    "name:swe_x_preferred":[
        "Ojasoo"
    ],
    "name:und_x_variant":[
        "Oyaso",
        "Ojasoo"
    ],
    "name:vol_x_preferred":[
        "Ojasoo"
    ],
    "wof:name":"Ojasoo",
    "wof:placetype":"locality"
},
  "geometry": {"coordinates":[24.535,58.08583],"type":"Point"}
}