{
  "type": "Feature",
  "properties": {
    "gn:admin1_code":"8.0",
    "gn:admin2_code":"792.0",
    "gn:admin3_code":"7358.0",
    "gn:asciiname":"Metspere",
    "gn:country_code":"EE",
    "gn:dem":127,
    "gn:feature_class":"P",
    "gn:feature_code":"PPL",
    "gn:name":"Metspere",
    "gn:population":0,
    "gn:timezone":"Europe/Tallinn",
    "iso:country":"EE",
    "name:und_x_variant":[
        "Metsiku"
    ],
    "wof:name":"Metspere",
    "wof:placetype":"locality"
},
  "geometry": {"coordinates":[26.14028,59.25611],"type":"Point"}
}