{
  "type": "Feature",
  "properties": {
    "gn:gn_country":"EE",
    "gn:gn_fcode":"PPL",
    "gn:gn_pop":0,
    "iso:country":"EE",
    "name:bul_x_preferred":[
        "\u0410\u043b\u0442\u044f"
    ],
    "name:deu_x_preferred":[
        "Altja"
    ],
    "name:eng_x_preferred":[
        "Altja"
    ],
    "name:est_x_preferred":[
        "Altja"
    ],
    "name:fas_x_preferred":[
        "\u0627\u0644\u062a\u062c\u0627"
    ],
    "name:fra_x_preferred":[
        "Altja"
    ],
    "name:hye_x_preferred":[
        "\u0531\u056c\u057f\u0575\u0561"
    ],
    "name:nld_x_preferred":[
        "Altja"
    ],
    "name:pol_x_preferred":[
        "Altja"
    ],
    "name:rus_x_preferred":[
        "\u0410\u043b\u0442\u044c\u044f"
    ],
    "name:swe_x_preferred":[
        "Altja"
    ],
    "name:ukr_x_preferred":[
        "\u0410\u043b\u0442\u044c\u044f"
    ],
    "name:unk_x_variant":[
        "Al\u2019t\u2019ya"
    ],
    "name:vol_x_preferred":[
        "Altja"
    ],
    "qs_pg:aaroncc":"EE",
    "qs_pg:gn_country":"EE",
    "qs_pg:gn_fcode":"PPL",
    "qs_pg:gn_pop":0,
    "qs_pg:name":"Altja",
    "qs_pg:name_adm0":"Eesti",
    "qs_pg:name_adm1":"L\u00e4\u00e4ne-Virumaa",
    "qs_pg:photos":59,
    "qs_pg:photos_1k":12,
    "qs_pg:photos_9k":1,
    "qs_pg:photos_9r":2,
    "qs_pg:photos_all":59,
    "qs_pg:photos_sr":2,
    "qs_pg:pop_sr":0,
    "qs_pg:qs_pg_placetype":"locality",
    "qs_pg:qs_pg_placetype_gp":"Town",
    "qs_pg:woe_adm0":23424805,
    "woe:adm0_id":23424805,
    "woe:name_adm0":"Eesti",
    "woe:name_adm1":"L\u00e4\u00e4ne-Virumaa",
    "woe:placetype":"Town",
    "wof:name":"Altja",
    "wof:placetype":"locality"
},
  "geometry": {"coordinates":[26.11333,59.58083],"type":"Point"}
}