{
  "type": "Feature",
  "properties": {
    "gn:admin1_code":"8.0",
    "gn:admin2_code":"928.0",
    "gn:admin3_code":"1484.0",
    "gn:asciiname":"Unikuela",
    "gn:country_code":"EE",
    "gn:dem":123,
    "gn:feature_class":"P",
    "gn:feature_code":"PPL",
    "gn:name":"Unik\u00fcla",
    "gn:population":0,
    "gn:timezone":"Europe/Tallinn",
    "iso:country":"EE",
    "wof:name":"Unikuela",
    "wof:placetype":"locality"
},
  "geometry": {"coordinates":[26.39222,59.10639000000001],"type":"Point"}
}