{
  "type": "Feature",
  "properties": {
    "gn:country":"EE",
    "gn:fcode":"PPL",
    "gn:population":105,
    "iso:country":"EE",
    "name:ara_x_preferred":[
        "\u0641\u0627\u0646\u0627 \u0643\u0648\u064a\u0648\u0644\u0627"
    ],
    "name:ceb_x_preferred":[
        "Vana-Koiola"
    ],
    "name:deu_x_preferred":[
        "Vana-Koiola"
    ],
    "name:eng_x_preferred":[
        "Vana-Koiola"
    ],
    "name:est_x_preferred":[
        "Vana-Koiola"
    ],
    "name:fas_x_preferred":[
        "\u0648\u0627\u0646\u0627 \u06a9\u06cc\u0644\u0627"
    ],
    "name:hye_x_preferred":[
        "\u054e\u0561\u0576\u0561-\u053f\u0578\u056b\u0578\u056c\u0561"
    ],
    "name:nld_x_preferred":[
        "Vana-Koiola"
    ],
    "name:pol_x_preferred":[
        "Vana-Koiola"
    ],
    "name:rus_x_preferred":[
        "\u0412\u0430\u043d\u0430-\u041a\u043e\u0439\u043b\u0430"
    ],
    "name:sco_x_preferred":[
        "Vana-Koiola"
    ],
    "name:spa_x_preferred":[
        "Vana-Koiola"
    ],
    "name:swe_x_preferred":[
        "Vana-Koiola"
    ],
    "name:ukr_x_preferred":[
        "\u0412\u0430\u043d\u0430-\u041a\u043e\u0439\u043e\u043b\u0430"
    ],
    "name:und_x_variant":[
        "Myza Vana-Koyola"
    ],
    "name:vol_x_preferred":[
        "Vana-Koiola"
    ],
    "name:vro_x_preferred":[
        "Vana-Koiola"
    ],
    "qs_pg:aaroncc":"EE",
    "qs_pg:gn_country":"EE",
    "qs_pg:gn_fcode":"PPL",
    "qs_pg:gn_pop":105,
    "qs_pg:name":"Vana-Koiola",
    "qs_pg:name_adm0":"Eesti",
    "qs_pg:name_adm1":"P\u00f5lvamaa",
    "qs_pg:photos_9k":1,
    "qs_pg:photos_9r":1,
    "qs_pg:photos_all":2,
    "qs_pg:photos_sr":0,
    "qs_pg:pop_sr":1,
    "qs_pg:qs_pg_placetype":"locality",
    "qs_pg:qs_pg_placetype_gp":"Town",
    "qs_pg:woe_adm0":23424805,
    "woe:adm0_id":23424805,
    "woe:name_adm0":"Eesti",
    "woe:name_adm1":"P\u00f5lvamaa",
    "woe:placetype":"Town",
    "wof:name":"Vana-Koiola",
    "wof:placetype":"locality",
    "wof:population":105
},
  "geometry": {"coordinates":[27.04889,57.96111],"type":"Point"}
}