{
  "type": "Feature",
  "properties": {
    "gn:admin1_code":"11.0",
    "gn:admin2_code":"712.0",
    "gn:admin3_code":"4440.0",
    "gn:asciiname":"Kauoja",
    "gn:cc2":"EE",
    "gn:country_code":"EE",
    "gn:dem":52,
    "gn:feature_class":"P",
    "gn:feature_code":"PPL",
    "gn:name":"Kauoja",
    "gn:population":0,
    "gn:timezone":"Europe/Tallinn",
    "iso:country":"EE",
    "name:und_x_variant":[
        "Kauoya",
        "Kauoja"
    ],
    "wof:name":"Kauoja",
    "wof:placetype":"locality"
},
  "geometry": {"coordinates":[24.86667000000001,58.11666999999999],"type":"Point"}
}