{
  "type": "Feature",
  "properties": {
    "gn:admin1_code":"11.0",
    "gn:admin2_code":"638.0",
    "gn:admin3_code":"9372.0",
    "gn:asciiname":"Viluvere",
    "gn:country_code":"EE",
    "gn:dem":47,
    "gn:feature_class":"P",
    "gn:feature_code":"PPL",
    "gn:name":"Viluvere",
    "gn:population":0,
    "gn:timezone":"Europe/Tallinn",
    "iso:country":"EE",
    "name:eng_x_preferred":[
        "Viluvere"
    ],
    "name:rus_x_preferred":[
        "\u0412\u0438\u043b\u0443\u0432\u0435\u0440\u0435"
    ],
    "wof:name":"Viluvere",
    "wof:placetype":"locality"
},
  "geometry": {"coordinates":[24.87889,58.64972],"type":"Point"}
}