{
  "type": "Feature",
  "properties": {
    "gn:admin1_code":"11.0",
    "gn:admin2_code":"638.0",
    "gn:admin3_code":"9372.0",
    "gn:asciiname":"Viluvere",
    "gn:country_code":"EE",
    "gn:dem":47,
    "gn:feature_class":"P",
    "gn:feature_code":"PPL",
    "gn:name":"Viluvere",
    "gn:population":0,
    "gn:timezone":"Europe/Tallinn",
    "iso:country":"EE",
    "name:cat_x_preferred":[
        "Viluvere"
    ],
    "name:eng_x_preferred":[
        "Viluvere"
    ],
    "name:est_x_preferred":[
        "Viluvere"
    ],
    "name:hye_x_preferred":[
        "\u054e\u056b\u056c\u0578\u0582\u057e\u0565\u057c\u0565"
    ],
    "name:pol_x_preferred":[
        "Viluvere"
    ],
    "name:rus_x_preferred":[
        "\u0412\u0438\u043b\u0443\u0432\u0435\u0440\u0435"
    ],
    "name:spa_x_preferred":[
        "Viluvere"
    ],
    "name:vol_x_preferred":[
        "Viluvere"
    ],
    "wof:coterminous":[
        1713313821
    ],
    "wof:lang_x_official":[
        "est"
    ],
    "wof:lang_x_spoken":[
        "est"
    ],
    "wof:name":"Viluvere",
    "wof:placetype":"locality"
},
  "geometry": {"coordinates":[24.87889,58.64972],"type":"Point"}
}