{
  "type": "Feature",
  "properties": {
    "gn:gn_country":"EE",
    "gn:gn_fcode":"PPL",
    "gn:gn_pop":630,
    "gn:population":630,
    "iso:country":"EE",
    "name:eng_x_preferred":[
        "V\u00f5nnu"
    ],
    "name:est_x_preferred":[
        "V\u00f5nnu alevik"
    ],
    "name:fra_x_preferred":[
        "V\u00f5nnu alevik"
    ],
    "name:hye_x_preferred":[
        "\u054e\u056b\u0576\u0576\u0578\u0582"
    ],
    "name:unk_x_variant":[
        "Mys Vynnu"
    ],
    "name:vol_x_preferred":[
        "V\u00f5nnu"
    ],
    "qs_pg:aaroncc":"EE",
    "qs_pg:gn_country":"EE",
    "qs_pg:gn_fcode":"PPL",
    "qs_pg:gn_pop":630,
    "qs_pg:name":"V\u00f5nnu",
    "qs_pg:name_adm0":"Eesti",
    "qs_pg:name_adm1":"Tartumaa",
    "qs_pg:photos_9k":1,
    "qs_pg:photos_9r":3,
    "qs_pg:photos_all":93,
    "qs_pg:photos_sr":0,
    "qs_pg:pop_sr":2,
    "qs_pg:qs_pg_placetype":"locality",
    "qs_pg:qs_pg_placetype_gp":"Town",
    "qs_pg:woe_adm0":23424805,
    "woe:adm0_id":23424805,
    "woe:name_adm0":"Eesti",
    "woe:name_adm1":"Tartumaa",
    "woe:placetype":"Town",
    "wof:name":"V\u00f5nnu",
    "wof:placetype":"locality",
    "wof:population":630
},
  "geometry": {"coordinates":[27.04806,58.27833],"type":"Point"}
}