{
  "type": "Feature",
  "properties": {
    "gn:gn_country":"EE",
    "gn:gn_fcode":"PPL",
    "gn:gn_pop":273,
    "gn:population":273,
    "iso:country":"EE",
    "name:ceb_x_preferred":[
        "Kamara"
    ],
    "name:deu_x_preferred":[
        "Kamara"
    ],
    "name:ell_x_preferred":[
        "\u039a\u03b1\u03bc\u03ac\u03c1\u03b1"
    ],
    "name:fin_x_preferred":[
        "Kamara"
    ],
    "name:fra_x_preferred":[
        "Kamara"
    ],
    "name:heb_x_preferred":[
        "\u05e7\u05de\u05d0\u05e8\u05d4"
    ],
    "name:ita_x_preferred":[
        "Kamara"
    ],
    "name:lav_x_preferred":[
        "Kamara"
    ],
    "name:que_x_preferred":[
        "Kamara"
    ],
    "name:rus_x_preferred":[
        "\u041a\u0430\u043c\u0430\u0440\u0430"
    ],
    "name:swe_x_preferred":[
        "Kamara"
    ],
    "qs_pg:aaroncc":"EE",
    "qs_pg:gn_country":"EE",
    "qs_pg:gn_fcode":"PPL",
    "qs_pg:gn_pop":273,
    "qs_pg:name":"Kamara",
    "qs_pg:name_adm0":"Eesti",
    "qs_pg:name_adm1":"Viljandimaa",
    "qs_pg:photos_9r":0,
    "qs_pg:photos_sr":0,
    "qs_pg:pop_sr":2,
    "qs_pg:qs_pg_placetype":"locality",
    "qs_pg:qs_pg_placetype_gp":"Town",
    "qs_pg:woe_adm0":23424805,
    "woe:adm0_id":23424805,
    "woe:name_adm0":"Eesti",
    "woe:name_adm1":"Viljandimaa",
    "woe:placetype":"Town",
    "wof:name":"Kamara",
    "wof:placetype":"locality",
    "wof:population":273
},
  "geometry": {"coordinates":[25.19444,58.12083],"type":"Point"}
}