{
  "type": "Feature",
  "properties": {
    "gn:admin1_code":"18.0",
    "gn:admin2_code":"171.0",
    "gn:admin3_code":"5957.0",
    "gn:asciiname":"Palupohja",
    "gn:cc2":"EE",
    "gn:country_code":"EE",
    "gn:dem":37,
    "gn:feature_class":"P",
    "gn:feature_code":"PPL",
    "gn:name":"Palup\u00f5hja",
    "gn:population":0,
    "gn:timezone":"Europe/Tallinn",
    "iso:country":"EE",
    "name:und_x_variant":[
        "Palupykh\u2019ya",
        "Palup\u00f5hja"
    ],
    "wof:name":"Palupohja",
    "wof:placetype":"locality"
},
  "geometry": {"coordinates":[26.23139,58.42167],"type":"Point"}
}