{
  "type": "Feature",
  "properties": {
    "gn:admin1_code":"18.0",
    "gn:admin2_code":"171.0",
    "gn:admin3_code":"5957.0",
    "gn:asciiname":"Palupohja",
    "gn:cc2":"EE",
    "gn:country_code":"EE",
    "gn:dem":37,
    "gn:feature_class":"P",
    "gn:feature_code":"PPL",
    "gn:name":"Palup\u00f5hja",
    "gn:population":0,
    "gn:timezone":"Europe/Tallinn",
    "iso:country":"EE",
    "name:est_x_preferred":[
        "Palup\u00f5hja"
    ],
    "name:hye_x_preferred":[
        "\u054a\u0561\u056c\u0578\u0582\u057a\u056b\u0570\u0575\u0561"
    ],
    "name:pol_x_preferred":[
        "Palup\u00f5hja"
    ],
    "name:spa_x_preferred":[
        "Palup\u00f5hja"
    ],
    "name:ukr_x_preferred":[
        "\u041f\u0430\u043b\u0443\u043f\u0438\u0433'\u044f"
    ],
    "name:und_x_variant":[
        "Palupykh\u2019ya"
    ],
    "name:vol_x_preferred":[
        "Palup\u00f5hja"
    ],
    "wof:coterminous":[
        1713312599
    ],
    "wof:lang_x_official":[
        "est"
    ],
    "wof:lang_x_spoken":[
        "est"
    ],
    "wof:name":"Palupohja",
    "wof:placetype":"locality"
},
  "geometry": {"coordinates":[26.23139,58.42167],"type":"Point"}
}