{
  "type": "Feature",
  "properties": {
    "gn:admin1_code":"3.0",
    "gn:admin2_code":"251.0",
    "gn:admin3_code":"3477.0",
    "gn:asciiname":"Kotinuka",
    "gn:country_code":"EE",
    "gn:dem":58,
    "gn:feature_class":"P",
    "gn:feature_code":"PPL",
    "gn:name":"Kotinuka",
    "gn:population":0,
    "gn:timezone":"Europe/Tallinn",
    "iso:country":"EE",
    "name:deu_x_preferred":[
        "Kotinuka"
    ],
    "name:est_x_preferred":[
        "Kotinuka"
    ],
    "name:fra_x_preferred":[
        "Kotinuka"
    ],
    "name:hye_x_preferred":[
        "\u053f\u0578\u057f\u056b\u0576\u0578\u0582\u056f\u0561"
    ],
    "name:nld_x_preferred":[
        "Kotinuka"
    ],
    "name:pol_x_preferred":[
        "Kotinuka"
    ],
    "name:spa_x_preferred":[
        "Kotinuka"
    ],
    "name:vol_x_preferred":[
        "Kotinuka"
    ],
    "wof:name":"Kotinuka",
    "wof:placetype":"locality"
},
  "geometry": {"coordinates":[27.42222000000001,59.38194],"type":"Point"}
}