{
  "type": "Feature",
  "properties": {
    "gn:admin1_code":"21.0",
    "gn:admin2_code":"698.0",
    "gn:admin3_code":"1676.0",
    "gn:asciiname":"Haabsilla",
    "gn:country_code":"EE",
    "gn:dem":102,
    "gn:feature_class":"P",
    "gn:feature_code":"PPL",
    "gn:name":"Haabsilla",
    "gn:population":0,
    "gn:timezone":"Europe/Tallinn",
    "iso:country":"EE",
    "name:und_x_variant":[
        "T\u00fcviste"
    ],
    "wof:coterminous":[
        1713314725
    ],
    "wof:lang_x_official":[
        "est"
    ],
    "wof:lang_x_spoken":[
        "est"
    ],
    "wof:name":"Haabsilla",
    "wof:placetype":"locality"
},
  "geometry": {"coordinates":[26.76083,57.71278],"type":"Point"}
}