{
  "type": "Feature",
  "properties": {
    "gn:admin1_code":"20.0",
    "gn:admin2_code":"899.0",
    "gn:admin3_code":"6697.0",
    "gn:asciiname":"Raassilla",
    "gn:cc2":"EE",
    "gn:country_code":"EE",
    "gn:dem":85,
    "gn:feature_class":"P",
    "gn:feature_code":"PPL",
    "gn:name":"Raassilla",
    "gn:population":0,
    "gn:timezone":"Europe/Tallinn",
    "iso:country":"EE",
    "name:und_x_variant":[
        "Rasilla",
        "Raasilla",
        "Raassilla"
    ],
    "wof:name":"Raassilla",
    "wof:placetype":"locality"
},
  "geometry": {"coordinates":[25.73667,58.24444],"type":"Point"}
}