{
  "type": "Feature",
  "properties": {
    "gn:admin1_code":"20.0",
    "gn:admin2_code":"899.0",
    "gn:admin3_code":"6697.0",
    "gn:asciiname":"Raassilla",
    "gn:cc2":"EE",
    "gn:country_code":"EE",
    "gn:dem":85,
    "gn:feature_class":"P",
    "gn:feature_code":"PPL",
    "gn:name":"Raassilla",
    "gn:population":0,
    "gn:timezone":"Europe/Tallinn",
    "iso:country":"EE",
    "name:ces_x_preferred":[
        "Raassilla"
    ],
    "name:est_x_preferred":[
        "Raassilla"
    ],
    "name:hye_x_preferred":[
        "\u054c\u0561\u0561\u057d\u056b\u056c\u056c\u0561"
    ],
    "name:pol_x_preferred":[
        "Raassilla"
    ],
    "name:spa_x_preferred":[
        "Raassilla"
    ],
    "name:ukr_x_preferred":[
        "\u0420\u0430\u0430\u0441\u0441\u0456\u043b\u043b\u0430"
    ],
    "name:und_x_variant":[
        "Rasilla",
        "Raasilla"
    ],
    "name:vol_x_preferred":[
        "Raassilla"
    ],
    "wof:coterminous":[
        1713309815
    ],
    "wof:lang_x_official":[
        "est"
    ],
    "wof:lang_x_spoken":[
        "est"
    ],
    "wof:name":"Raassilla",
    "wof:placetype":"locality"
},
  "geometry": {"coordinates":[25.73667,58.24444],"type":"Point"}
}