{
  "type": "Feature",
  "properties": {
    "gn:admin1_code":"7.0",
    "gn:admin2_code":"184.0",
    "gn:admin3_code":"3090.0",
    "gn:asciiname":"Kiltsi",
    "gn:country_code":"EE",
    "gn:dem":9,
    "gn:feature_class":"P",
    "gn:feature_code":"PPL",
    "gn:name":"Kiltsi",
    "gn:population":0,
    "gn:timezone":"Europe/Tallinn",
    "iso:country":"EE",
    "name:deu_x_preferred":[
        "Kiltsi"
    ],
    "name:est_x_preferred":[
        "Kiltsi k\u00fcla"
    ],
    "name:hye_x_preferred":[
        "\u053f\u056b\u056c\u0581\u056b"
    ],
    "name:nld_x_preferred":[
        "Kiltsi"
    ],
    "name:pol_x_preferred":[
        "Kiltsi"
    ],
    "name:ukr_x_preferred":[
        "\u041a\u0456\u043b\u0442\u0441\u0456"
    ],
    "name:und_x_variant":[
        "Kilsi Asundus",
        "Myza Kilsi"
    ],
    "name:vol_x_preferred":[
        "Kiltsi k\u00fcla"
    ],
    "wof:name":"Kiltsi",
    "wof:placetype":"locality"
},
  "geometry": {"coordinates":[23.525,58.92611],"type":"Point"}
}