{
  "type": "Feature",
  "properties": {
    "gn:admin1_code":"20.0",
    "gn:admin2_code":"899.0",
    "gn:admin3_code":"4981.0",
    "gn:asciiname":"Roo",
    "gn:cc2":"EE",
    "gn:country_code":"EE",
    "gn:dem":55,
    "gn:feature_class":"P",
    "gn:feature_code":"PPL",
    "gn:name":"Roo",
    "gn:population":0,
    "gn:timezone":"Europe/Tallinn",
    "iso:country":"EE",
    "name:eml_x_preferred":[
        "Ro"
    ],
    "name:fin_x_preferred":[
        "Ruu"
    ],
    "name:fra_x_preferred":[
        "Petit Gourou"
    ],
    "name:heb_x_preferred":[
        "\u05e8\u05d5"
    ],
    "name:hrv_x_preferred":[
        "Roo"
    ],
    "name:hun_x_preferred":[
        "Zsebibaba"
    ],
    "name:hye_x_preferred":[
        "\u0543\u057d\u057f\u056b\u056f \u054c\u0578\u0582"
    ],
    "name:ita_x_preferred":[
        "Ro"
    ],
    "name:pol_x_preferred":[
        "Male\u0144stwo"
    ],
    "name:por_x_preferred":[
        "Guru"
    ],
    "name:rus_x_preferred":[
        "\u041a\u0440\u043e\u0448\u043a\u0430 \u0420\u0443"
    ],
    "wof:name":"Roo",
    "wof:placetype":"locality"
},
  "geometry": {"coordinates":[25.76,58.46389],"type":"Point"}
}