{
  "type": "Feature",
  "properties": {
    "gn:admin1_code":"20.0",
    "gn:admin2_code":"615.0",
    "gn:admin3_code":"6502.0",
    "gn:asciiname":"Lahmuse",
    "gn:cc2":"EE",
    "gn:country_code":"EE",
    "gn:dem":66,
    "gn:feature_class":"P",
    "gn:feature_code":"PPL",
    "gn:name":"Lahmuse",
    "gn:population":0,
    "gn:timezone":"Europe/Tallinn",
    "iso:country":"EE",
    "name:und_x_variant":[
        "Myza Lakhmuse",
        "Lahmuse"
    ],
    "wof:name":"Lahmuse",
    "wof:placetype":"locality"
},
  "geometry": {"coordinates":[25.43,58.55528],"type":"Point"}
}