{
  "type": "Feature",
  "properties": {
    "gn:admin1_code":"8.0",
    "gn:admin2_code":"901.0",
    "gn:admin3_code":"2036.0",
    "gn:asciiname":"Ilistvere",
    "gn:country_code":"EE",
    "gn:dem":83,
    "gn:feature_class":"P",
    "gn:feature_code":"PPL",
    "gn:name":"Ilistvere",
    "gn:population":0,
    "gn:timezone":"Europe/Tallinn",
    "iso:country":"EE",
    "wof:name":"Ilistvere",
    "wof:placetype":"locality"
},
  "geometry": {"coordinates":[26.72167,59.03611],"type":"Point"}
}