{
  "type": "Feature",
  "properties": {
    "gn:admin1_code":"11.0",
    "gn:admin2_code":"624.0",
    "gn:admin3_code":"3746.0",
    "gn:asciiname":"Koima",
    "gn:cc2":"EE",
    "gn:country_code":"EE",
    "gn:dem":11,
    "gn:feature_class":"P",
    "gn:feature_code":"PPL",
    "gn:name":"K\u00f5ima",
    "gn:population":0,
    "gn:timezone":"Europe/Tallinn",
    "iso:country":"EE",
    "name:ceb_x_preferred":[
        "K\u00f5ima"
    ],
    "name:ces_x_preferred":[
        "K\u00f5ima"
    ],
    "name:est_x_preferred":[
        "K\u00f5ima"
    ],
    "name:hye_x_preferred":[
        "\u053f\u056b\u056b\u0574\u0561"
    ],
    "name:pol_x_preferred":[
        "K\u00f5ima"
    ],
    "name:spa_x_preferred":[
        "K\u00f5ima"
    ],
    "name:swe_x_preferred":[
        "K\u00f5ima"
    ],
    "name:und_x_variant":[
        "Kyyma"
    ],
    "name:vol_x_preferred":[
        "K\u00f5ima"
    ],
    "wof:name":"Koima",
    "wof:placetype":"locality"
},
  "geometry": {"coordinates":[24.25806,58.36444],"type":"Point"}
}