{
  "type": "Feature",
  "properties": {
    "gn:admin1_code":"18.0",
    "gn:admin2_code":"586.0",
    "gn:admin3_code":"6432.0",
    "gn:asciiname":"Kantkuela",
    "gn:country_code":"EE",
    "gn:dem":65,
    "gn:feature_class":"P",
    "gn:feature_code":"PPL",
    "gn:name":"Kantk\u00fcla",
    "gn:population":0,
    "gn:timezone":"Europe/Tallinn",
    "iso:country":"EE",
    "name:und_x_variant":[
        "Kantk\u00fcla",
        "Kogri"
    ],
    "wof:name":"Kantkuela",
    "wof:placetype":"locality"
},
  "geometry": {"coordinates":[27.08722,58.68778],"type":"Point"}
}