{
  "type": "Feature",
  "properties": {
    "gn:admin1_code":"1.0",
    "gn:admin2_code":"726.0",
    "gn:admin3_code":"1449.0",
    "gn:asciiname":"Aude",
    "gn:country_code":"EE",
    "gn:dem":34,
    "gn:feature_class":"P",
    "gn:feature_code":"PPL",
    "gn:name":"Aude",
    "gn:population":0,
    "gn:timezone":"Europe/Tallinn",
    "iso:country":"EE",
    "name:est_x_preferred":[
        "Aude"
    ],
    "name:fra_x_preferred":[
        "Aude"
    ],
    "name:hye_x_preferred":[
        "\u0531\u0578\u0582\u0564\u0565"
    ],
    "name:pol_x_preferred":[
        "Aude"
    ],
    "name:spa_x_preferred":[
        "Aude"
    ],
    "name:ukr_x_preferred":[
        "\u0410\u0443\u0434\u0435"
    ],
    "name:vol_x_preferred":[
        "Aude"
    ],
    "wof:lang_x_official":[
        "est"
    ],
    "wof:lang_x_spoken":[
        "est"
    ],
    "wof:name":"Aude",
    "wof:placetype":"locality"
},
  "geometry": {"coordinates":[24.24778,59.16389],"type":"Point"}
}