{
  "type": "Feature",
  "properties": {
    "gn:gn_country":"EE",
    "gn:gn_fcode":"PPL",
    "gn:gn_pop":559,
    "gn:population":559,
    "iso:country":"EE",
    "name:arm_x_preferred":[
        "\u0531\u057c\u0564\u0578\u0582"
    ],
    "name:bul_x_preferred":[
        "\u0410\u0440\u0434\u0443"
    ],
    "name:eng_x_preferred":[
        "Ardu"
    ],
    "name:est_x_preferred":[
        "Ardu"
    ],
    "name:fre_x_preferred":[
        "Ardu"
    ],
    "name:pol_x_preferred":[
        "Ardu"
    ],
    "name:rus_x_preferred":[
        "\u0410\u0440\u0434\u0443"
    ],
    "name:sco_x_preferred":[
        "Ardu"
    ],
    "name:swe_x_preferred":[
        "Ardu"
    ],
    "name:unk_x_variant":[
        "Hardu"
    ],
    "name:vol_x_preferred":[
        "Ardu"
    ],
    "qs_pg:aaroncc":"EE",
    "qs_pg:gn_country":"EE",
    "qs_pg:gn_fcode":"PPL",
    "qs_pg:gn_pop":559,
    "qs_pg:name":"Ardu",
    "qs_pg:name_adm0":"Eesti",
    "qs_pg:name_adm1":"Harjumaa",
    "qs_pg:photos_9k":1,
    "qs_pg:photos_9r":1,
    "qs_pg:photos_all":1,
    "qs_pg:photos_sr":0,
    "qs_pg:pop_sr":2,
    "qs_pg:qs_pg_placetype":"locality",
    "qs_pg:qs_pg_placetype_gp":"Town",
    "qs_pg:woe_adm0":23424805,
    "woe:adm0_id":23424805,
    "woe:name_adm0":"Eesti",
    "woe:name_adm1":"Harjumaa",
    "woe:placetype":"Town",
    "wof:name":"Ardu",
    "wof:placetype":"locality",
    "wof:population":559
},
  "geometry": {"coordinates":[25.37083,59.10056],"type":"Point"}
}