{
  "type": "Feature",
  "properties": {
    "gn:country":"EE",
    "gn:fcode":"PPL",
    "gn:population":95,
    "iso:country":"EE",
    "name:eng_x_preferred":[
        "Haaslava"
    ],
    "name:est_x_preferred":[
        "Haaslava"
    ],
    "name:fra_x_preferred":[
        "Haaslava"
    ],
    "name:hye_x_preferred":[
        "\u0540\u0561\u0561\u057d\u056c\u0561\u057e\u0561"
    ],
    "name:nld_x_preferred":[
        "Haaslava"
    ],
    "name:pol_x_preferred":[
        "Haaslava"
    ],
    "name:rus_x_preferred":[
        "\u0425\u0430\u0430\u0441\u043b\u0430\u0432\u0430"
    ],
    "name:spa_x_preferred":[
        "Haaslava"
    ],
    "name:ukr_x_preferred":[
        "\u0413\u0430\u0430\u0441\u043b\u0430\u0432\u0430"
    ],
    "name:und_x_variant":[
        "Myza Khaslava"
    ],
    "name:urd_x_preferred":[
        "\u06c1\u0627\u0633\u0644\u0627\u0648\u0627"
    ],
    "name:vol_x_preferred":[
        "Haaslava"
    ],
    "qs_pg:aaroncc":"EE",
    "qs_pg:gn_country":"EE",
    "qs_pg:gn_fcode":"PPL",
    "qs_pg:gn_pop":95,
    "qs_pg:name":"Haaslava",
    "qs_pg:name_adm0":"Eesti",
    "qs_pg:name_adm1":"Tartumaa",
    "qs_pg:photos_9k":1,
    "qs_pg:photos_9r":1,
    "qs_pg:photos_all":1,
    "qs_pg:photos_sr":0,
    "qs_pg:pop_sr":1,
    "qs_pg:qs_pg_placetype":"locality",
    "qs_pg:qs_pg_placetype_gp":"Town",
    "qs_pg:woe_adm0":23424805,
    "woe:adm0_id":23424805,
    "woe:name_adm0":"Eesti",
    "woe:name_adm1":"Tartumaa",
    "woe:placetype":"Town",
    "wof:name":"Haaslava",
    "wof:placetype":"locality",
    "wof:population":95
},
  "geometry": {"coordinates":[26.78,58.32722],"type":"Point"}
}