{
  "type": "Feature",
  "properties": {
    "gn:admin1_code":"1.0",
    "gn:admin2_code":"338.0",
    "gn:admin3_code":"1174.0",
    "gn:asciiname":"Alansi",
    "gn:country_code":"EE",
    "gn:dem":71,
    "gn:feature_class":"P",
    "gn:feature_code":"PPL",
    "gn:name":"Alansi",
    "gn:population":0,
    "gn:timezone":"Europe/Tallinn",
    "iso:country":"EE",
    "wof:name":"Alansi",
    "wof:placetype":"locality"
},
  "geometry": {"coordinates":[25.15694,59.11806],"type":"Point"}
}