{
  "type": "Feature",
  "properties": {
    "gn:admin1_code":"1.0",
    "gn:admin2_code":"338.0",
    "gn:admin3_code":"1174.0",
    "gn:asciiname":"Alansi",
    "gn:country_code":"EE",
    "gn:dem":71,
    "gn:feature_class":"P",
    "gn:feature_code":"PPL",
    "gn:name":"Alansi",
    "gn:population":0,
    "gn:timezone":"Europe/Tallinn",
    "iso:country":"EE",
    "name:est_x_preferred":[
        "Alansi"
    ],
    "name:fas_x_preferred":[
        "\u0627\u0644\u0627\u0646\u0633\u06cc"
    ],
    "name:fra_x_preferred":[
        "Alansi"
    ],
    "name:hye_x_preferred":[
        "\u0531\u056c\u0561\u0576\u057d\u056b"
    ],
    "name:pol_x_preferred":[
        "Alansi"
    ],
    "name:sco_x_preferred":[
        "Alansi"
    ],
    "name:spa_x_preferred":[
        "Alansi"
    ],
    "name:vol_x_preferred":[
        "Alansi"
    ],
    "wof:coterminous":[
        1713306323
    ],
    "wof:lang_x_official":[
        "est"
    ],
    "wof:lang_x_spoken":[
        "est"
    ],
    "wof:name":"Alansi",
    "wof:placetype":"locality"
},
  "geometry": {"coordinates":[25.15694,59.11806],"type":"Point"}
}