{
  "type": "Feature",
  "properties": {
    "gn:admin1_code":"12.0",
    "gn:admin2_code":"284.0",
    "gn:admin3_code":"8455.0",
    "gn:asciiname":"Axelshof",
    "gn:country_code":"EE",
    "gn:dem":129,
    "gn:feature_class":"P",
    "gn:feature_code":"PPL",
    "gn:name":"Axelshof",
    "gn:population":0,
    "gn:timezone":"Europe/Tallinn",
    "iso:country":"EE",
    "name:und_x_variant":[
        "Alak\u00fcl\u00e4",
        "Axelshof"
    ],
    "wof:name":"Axelshof",
    "wof:placetype":"locality"
},
  "geometry": {"coordinates":[26.81972,58.07],"type":"Point"}
}