{
  "type": "Feature",
  "properties": {
    "gn:admin1_code":"1.0",
    "gn:admin2_code":"431.0",
    "gn:admin3_code":"3224.0",
    "gn:asciiname":"Kobru",
    "gn:country_code":"EE",
    "gn:dem":39,
    "gn:feature_class":"P",
    "gn:feature_code":"PPL",
    "gn:name":"Kobru",
    "gn:population":0,
    "gn:timezone":"Europe/Tallinn",
    "iso:country":"EE",
    "name:est_x_preferred":[
        "Kobru"
    ],
    "name:fra_x_preferred":[
        "Kobru"
    ],
    "name:hye_x_preferred":[
        "\u053f\u0578\u0562\u057c\u0578\u0582"
    ],
    "name:pol_x_preferred":[
        "Kobru"
    ],
    "name:spa_x_preferred":[
        "Kobru"
    ],
    "name:ukr_x_preferred":[
        "\u041a\u043e\u0431\u0440\u0443"
    ],
    "name:vol_x_preferred":[
        "Kobru"
    ],
    "wof:lang_x_official":[
        "est"
    ],
    "wof:lang_x_spoken":[
        "est"
    ],
    "wof:name":"Kobru",
    "wof:placetype":"locality"
},
  "geometry": {"coordinates":[24.15778,59.16972],"type":"Point"}
}