{
  "type": "Feature",
  "properties": {
    "gn:admin1_code":"18.0",
    "gn:admin2_code":"283.0",
    "gn:admin3_code":"2433.0",
    "gn:asciiname":"Tapu-Soe",
    "gn:country_code":"EE",
    "gn:dem":94,
    "gn:feature_class":"P",
    "gn:feature_code":"PPL",
    "gn:name":"Tapu-Soe",
    "gn:population":0,
    "gn:timezone":"Europe/Tallinn",
    "iso:country":"EE",
    "name:und_x_variant":[
        "Tapu"
    ],
    "wof:name":"Tapu-Soe",
    "wof:placetype":"locality"
},
  "geometry": {"coordinates":[26.76639,58.19528],"type":"Point"}
}