{
  "type": "Feature",
  "properties": {
    "gn:admin1_code":"1.0",
    "gn:admin2_code":"653.0",
    "gn:admin3_code":"9832.0",
    "gn:asciiname":"Vanapere",
    "gn:country_code":"EE",
    "gn:dem":44,
    "gn:feature_class":"P",
    "gn:feature_code":"PPL",
    "gn:name":"Vanapere",
    "gn:population":0,
    "gn:timezone":"Europe/Tallinn",
    "iso:country":"EE",
    "wof:name":"Vanapere",
    "wof:placetype":"locality"
},
  "geometry": {"coordinates":[24.92114,59.41543000000001],"type":"Point"}
}