{
  "type": "Feature",
  "properties": {
    "gn:admin1_code":"8.0",
    "gn:admin2_code":"661.0",
    "gn:admin3_code":"2744.0",
    "gn:asciiname":"Laanemoisa",
    "gn:country_code":"EE",
    "gn:dem":84,
    "gn:feature_class":"P",
    "gn:feature_code":"PPL",
    "gn:name":"Laanem\u00f5isa",
    "gn:population":0,
    "gn:timezone":"Europe/Tallinn",
    "iso:country":"EE",
    "wof:lang_x_official":[
        "est"
    ],
    "wof:lang_x_spoken":[
        "est"
    ],
    "wof:name":"Laanemoisa",
    "wof:placetype":"locality"
},
  "geometry": {"coordinates":[26.24306,59.35556],"type":"Point"}
}