{
  "type": "Feature",
  "properties": {
    "gn:admin1_code":"12.0",
    "gn:admin2_code":"622.0",
    "gn:admin3_code":"4986.0",
    "gn:asciiname":"Ellakuelae",
    "gn:country_code":"EE",
    "gn:dem":51,
    "gn:feature_class":"P",
    "gn:feature_code":"PPL",
    "gn:name":"Ellak\u00fcl\u00e4",
    "gn:population":0,
    "gn:timezone":"Europe/Tallinn",
    "iso:country":"EE",
    "wof:name":"Ellakuelae",
    "wof:placetype":"locality"
},
  "geometry": {"coordinates":[27.17639,58.15889],"type":"Point"}
}