{
  "type": "Feature",
  "properties": {
    "gn:admin1_code":"5.0",
    "gn:admin2_code":"247.0",
    "gn:admin3_code":"1598.0",
    "gn:asciiname":"Tirma",
    "gn:country_code":"EE",
    "gn:dem":84,
    "gn:feature_class":"P",
    "gn:feature_code":"PPL",
    "gn:name":"Tirma",
    "gn:population":0,
    "gn:timezone":"Europe/Tallinn",
    "iso:country":"EE",
    "wof:name":"Tirma",
    "wof:placetype":"locality"
},
  "geometry": {"coordinates":[26.21528,58.80028000000001],"type":"Point"}
}