{
  "type": "Feature",
  "properties": {
    "gn:admin1_code":"1.0",
    "gn:admin2_code":"141.0",
    "gn:admin3_code":"6828.0",
    "gn:asciiname":"Rasivere",
    "gn:country_code":"EE",
    "gn:dem":69,
    "gn:feature_class":"P",
    "gn:feature_code":"PPL",
    "gn:name":"Rasivere",
    "gn:population":0,
    "gn:timezone":"Europe/Tallinn",
    "iso:country":"EE",
    "wof:name":"Rasivere",
    "wof:placetype":"locality"
},
  "geometry": {"coordinates":[25.37333,59.2225],"type":"Point"}
}