{
  "type": "Feature",
  "properties": {
    "gn:admin1_code":"1.0",
    "gn:admin2_code":"141.0",
    "gn:admin3_code":"6828.0",
    "gn:asciiname":"Rasivere",
    "gn:country_code":"EE",
    "gn:dem":69,
    "gn:feature_class":"P",
    "gn:feature_code":"PPL",
    "gn:name":"Rasivere",
    "gn:population":0,
    "gn:timezone":"Europe/Tallinn",
    "iso:country":"EE",
    "name:est_x_preferred":[
        "Rasivere"
    ],
    "name:fra_x_preferred":[
        "Rasivere"
    ],
    "name:hye_x_preferred":[
        "\u054c\u0561\u057d\u056b\u057e\u0565\u057c\u0565"
    ],
    "name:nld_x_preferred":[
        "Rasivere"
    ],
    "name:pol_x_preferred":[
        "Rasivere"
    ],
    "name:sco_x_preferred":[
        "Rasivere"
    ],
    "name:slk_x_preferred":[
        "Rasivere"
    ],
    "name:spa_x_preferred":[
        "Rasivere"
    ],
    "name:vol_x_preferred":[
        "Rasivere"
    ],
    "wof:coterminous":[
        1713307173
    ],
    "wof:lang_x_official":[
        "est"
    ],
    "wof:lang_x_spoken":[
        "est"
    ],
    "wof:name":"Rasivere",
    "wof:placetype":"locality"
},
  "geometry": {"coordinates":[25.37333,59.2225],"type":"Point"}
}