{
  "type": "Feature",
  "properties": {
    "gn:admin1_code":"21.0",
    "gn:admin2_code":"917.0",
    "gn:admin3_code":"6002.0",
    "gn:asciiname":"Pari",
    "gn:country_code":"EE",
    "gn:dem":212,
    "gn:feature_class":"P",
    "gn:feature_code":"PPL",
    "gn:name":"Pari",
    "gn:population":0,
    "gn:timezone":"Europe/Tallinn",
    "iso:country":"EE",
    "name:est_x_preferred":[
        "Pari"
    ],
    "name:hye_x_preferred":[
        "\u054a\u0561\u057c\u056b"
    ],
    "name:pol_x_preferred":[
        "Pari"
    ],
    "name:spa_x_preferred":[
        "Pari"
    ],
    "name:ukr_x_preferred":[
        "\u041f\u0430\u0440\u0456"
    ],
    "name:vol_x_preferred":[
        "Pari"
    ],
    "wof:lang_x_official":[
        "est"
    ],
    "wof:lang_x_spoken":[
        "est"
    ],
    "wof:name":"Pari",
    "wof:placetype":"locality"
},
  "geometry": {"coordinates":[27.15278,57.67139],"type":"Point"}
}