{
  "type": "Feature",
  "properties": {
    "gn:admin1_code":"21.0",
    "gn:admin2_code":"732.0",
    "gn:admin3_code":"6474.0",
    "gn:asciiname":"Puugnitsa",
    "gn:country_code":"EE",
    "gn:dem":38,
    "gn:feature_class":"P",
    "gn:feature_code":"PPL",
    "gn:name":"Puugnitsa",
    "gn:population":0,
    "gn:timezone":"Europe/Tallinn",
    "iso:country":"EE",
    "name:deu_x_preferred":[
        "Puugnitsa"
    ],
    "name:est_x_preferred":[
        "Puugnitsa"
    ],
    "name:fra_x_preferred":[
        "Puugnitsa"
    ],
    "name:hye_x_preferred":[
        "\u054a\u0578\u0582\u0578\u0582\u0563\u0576\u056b\u0581\u0561"
    ],
    "name:pol_x_preferred":[
        "Puugnitsa"
    ],
    "name:spa_x_preferred":[
        "Puugnitsa"
    ],
    "name:ukr_x_preferred":[
        "\u041f\u0443\u0443\u0433\u043d\u0456\u0446\u0430"
    ],
    "name:vol_x_preferred":[
        "Puugnitsa"
    ],
    "wof:lang_x_official":[
        "est"
    ],
    "wof:lang_x_spoken":[
        "est"
    ],
    "wof:name":"Puugnitsa",
    "wof:placetype":"locality"
},
  "geometry": {"coordinates":[27.48306,57.98694],"type":"Point"}
}