{
  "type": "Feature",
  "properties": {
    "gn:admin1_code":"21.0",
    "gn:admin2_code":"732.0",
    "gn:admin3_code":"6474.0",
    "gn:asciiname":"Puugnitsa",
    "gn:country_code":"EE",
    "gn:dem":38,
    "gn:feature_class":"P",
    "gn:feature_code":"PPL",
    "gn:name":"Puugnitsa",
    "gn:population":0,
    "gn:timezone":"Europe/Tallinn",
    "iso:country":"EE",
    "wof:name":"Puugnitsa",
    "wof:placetype":"locality"
},
  "geometry": {"coordinates":[27.48306,57.98694],"type":"Point"}
}