{
  "type": "Feature",
  "properties": {
    "gn:admin1_code":"20.0",
    "gn:admin2_code":"899.0",
    "gn:admin3_code":"6697.0",
    "gn:asciiname":"Vahemotsa",
    "gn:country_code":"EE",
    "gn:dem":88,
    "gn:feature_class":"P",
    "gn:feature_code":"PPL",
    "gn:name":"Vahem\u00f5tsa",
    "gn:population":0,
    "gn:timezone":"Europe/Tallinn",
    "iso:country":"EE",
    "wof:name":"Vahemotsa",
    "wof:placetype":"locality"
},
  "geometry": {"coordinates":[25.7075,58.22722],"type":"Point"}
}