{
  "type": "Feature",
  "properties": {
    "gn:admin1_code":"14.0",
    "gn:admin2_code":"714.0",
    "gn:admin3_code":"8697.0",
    "gn:asciiname":"Unimaee",
    "gn:country_code":"EE",
    "gn:dem":4,
    "gn:feature_class":"P",
    "gn:feature_code":"PPL",
    "gn:name":"Unim\u00e4e",
    "gn:population":0,
    "gn:timezone":"Europe/Tallinn",
    "iso:country":"EE",
    "name:und_x_variant":[
        "Unimyae",
        "Unim\u00e4e"
    ],
    "wof:name":"Unimaee",
    "wof:placetype":"locality"
},
  "geometry": {"coordinates":[22.47556,58.28278],"type":"Point"}
}