{
  "type": "Feature",
  "properties": {
    "gn:admin1_code":"8.0",
    "gn:admin2_code":"792.0",
    "gn:admin3_code":"4920.0",
    "gn:asciiname":"Metskaevu",
    "gn:country_code":"EE",
    "gn:dem":137,
    "gn:feature_class":"P",
    "gn:feature_code":"PPL",
    "gn:name":"Metskaevu",
    "gn:population":0,
    "gn:timezone":"Europe/Tallinn",
    "iso:country":"EE",
    "name:est_x_preferred":[
        "Metskaevu"
    ],
    "name:hye_x_preferred":[
        "\u0544\u0565\u0581\u056f\u0561\u0587\u0578\u0582"
    ],
    "name:ukr_x_preferred":[
        "\u041c\u0435\u0442\u0441\u043a\u0430\u0435\u0432\u0443"
    ],
    "name:vol_x_preferred":[
        "Metskaevu"
    ],
    "wof:name":"Metskaevu",
    "wof:placetype":"locality"
},
  "geometry": {"coordinates":[26.15,59.15],"type":"Point"}
}