{
  "type": "Feature",
  "properties": {
    "gn:admin1_code":"14.0",
    "gn:admin2_code":"714.0",
    "gn:admin3_code":"2215.0",
    "gn:asciiname":"Jursi",
    "gn:cc2":"EE",
    "gn:country_code":"EE",
    "gn:dem":13,
    "gn:feature_class":"P",
    "gn:feature_code":"PPL",
    "gn:name":"Jursi",
    "gn:population":0,
    "gn:timezone":"Europe/Tallinn",
    "iso:country":"EE",
    "name:und_x_variant":[
        "Yursi",
        "J\u00fcrsi",
        "Jursi"
    ],
    "wof:name":"Jursi",
    "wof:placetype":"locality"
},
  "geometry": {"coordinates":[22.83833,58.39333000000001],"type":"Point"}
}