{
  "type": "Feature",
  "properties": {
    "gn:admin1_code":"14.0",
    "gn:admin2_code":"714.0",
    "gn:admin3_code":"2215.0",
    "gn:asciiname":"Jursi",
    "gn:cc2":"EE",
    "gn:country_code":"EE",
    "gn:dem":13,
    "gn:feature_class":"P",
    "gn:feature_code":"PPL",
    "gn:name":"Jursi",
    "gn:population":0,
    "gn:timezone":"Europe/Tallinn",
    "iso:country":"EE",
    "name:deu_x_preferred":[
        "Jursi"
    ],
    "name:est_x_preferred":[
        "Jursi"
    ],
    "name:hye_x_preferred":[
        "\u0545\u0578\u0582\u057c\u057d\u056b"
    ],
    "name:pol_x_preferred":[
        "Jursi"
    ],
    "name:spa_x_preferred":[
        "Jursi"
    ],
    "name:ukr_x_preferred":[
        "\u042e\u0440\u0441\u0456"
    ],
    "name:und_x_variant":[
        "Yursi",
        "J\u00fcrsi"
    ],
    "name:vol_x_preferred":[
        "Jursi"
    ],
    "wof:coterminous":[
        1713307569
    ],
    "wof:lang_x_official":[
        "est"
    ],
    "wof:lang_x_spoken":[
        "est"
    ],
    "wof:name":"Jursi",
    "wof:placetype":"locality"
},
  "geometry": {"coordinates":[22.83833,58.39333],"type":"Point"}
}