{
  "type": "Feature",
  "properties": {
    "gn:admin1_code":"14.0",
    "gn:admin2_code":"714.0",
    "gn:admin3_code":"6997.0",
    "gn:asciiname":"Riksu",
    "gn:country_code":"EE",
    "gn:dem":5,
    "gn:feature_class":"P",
    "gn:feature_code":"PPL",
    "gn:name":"Riksu",
    "gn:population":0,
    "gn:timezone":"Europe/Tallinn",
    "iso:country":"EE",
    "wof:name":"Riksu",
    "wof:placetype":"locality"
},
  "geometry": {"coordinates":[22.09194,58.19833000000001],"type":"Point"}
}