{
  "type": "Feature",
  "properties": {
    "gn:admin1_code":"11.0",
    "gn:admin2_code":"624.0",
    "gn:admin3_code":"4617.0",
    "gn:asciiname":"Nautsi",
    "gn:country_code":"EE",
    "gn:dem":17,
    "gn:feature_class":"P",
    "gn:feature_code":"PPL",
    "gn:name":"Nautsi",
    "gn:population":0,
    "gn:timezone":"Europe/Tallinn",
    "iso:country":"EE",
    "name:fin_x_preferred":[
        "Nautsi"
    ],
    "name:rus_x_preferred":[
        "\u041d\u0430\u0443\u0442\u0441\u0438"
    ],
    "name:swe_x_preferred":[
        "Nautsk"
    ],
    "wof:name":"Nautsi",
    "wof:placetype":"locality"
},
  "geometry": {"coordinates":[24.05139,58.32222],"type":"Point"}
}