{
  "type": "Feature",
  "properties": {
    "gn:admin1_code":"21.0",
    "gn:admin2_code":"732.0",
    "gn:admin3_code":"5387.0",
    "gn:asciiname":"Suuro-Nedsaejae",
    "gn:country_code":"EE",
    "gn:dem":63,
    "gn:feature_class":"P",
    "gn:feature_code":"PPL",
    "gn:name":"Suur\u00f5-Neds\u00e4j\u00e4",
    "gn:population":0,
    "gn:timezone":"Europe/Tallinn",
    "iso:country":"EE",
    "wof:lang_x_official":[
        "est"
    ],
    "wof:lang_x_spoken":[
        "est"
    ],
    "wof:name":"Suuro-Nedsaejae",
    "wof:placetype":"locality"
},
  "geometry": {"coordinates":[27.55722,57.90056],"type":"Point"}
}