{
  "type": "Feature",
  "properties": {
    "gn:admin1_code":"20.0",
    "gn:admin2_code":"480.0",
    "gn:admin3_code":"5411.0",
    "gn:asciiname":"Veere",
    "gn:country_code":"EE",
    "gn:dem":79,
    "gn:feature_class":"P",
    "gn:feature_code":"PPL",
    "gn:name":"Veere",
    "gn:population":0,
    "gn:timezone":"Europe/Tallinn",
    "iso:country":"EE",
    "wof:name":"Veere",
    "wof:placetype":"locality"
},
  "geometry": {"coordinates":[25.40972,58.21471999999999],"type":"Point"}
}