{
  "type": "Feature",
  "properties": {
    "gn:admin1_code":"3.0",
    "gn:admin2_code":"514.0",
    "gn:admin3_code":"6265.0",
    "gn:asciiname":"Pimestiku",
    "gn:country_code":"EE",
    "gn:dem":36,
    "gn:feature_class":"P",
    "gn:feature_code":"PPL",
    "gn:name":"Pimestiku",
    "gn:population":0,
    "gn:timezone":"Europe/Tallinn",
    "iso:country":"EE",
    "name:deu_x_preferred":[
        "Pimestiku"
    ],
    "name:est_x_preferred":[
        "Pimestiku"
    ],
    "name:hye_x_preferred":[
        "\u054a\u056b\u0574\u0565\u057d\u057f\u056b\u056f\u0578\u0582"
    ],
    "name:ukr_x_preferred":[
        "\u041f\u0456\u043c\u0435\u0441\u0442\u0456\u043a\u0443"
    ],
    "name:vol_x_preferred":[
        "Pimestiku"
    ],
    "wof:coterminous":[
        1713307729
    ],
    "wof:lang_x_official":[
        "est"
    ],
    "wof:lang_x_spoken":[
        "est"
    ],
    "wof:name":"Pimestiku",
    "wof:placetype":"locality"
},
  "geometry": {"coordinates":[27.86068,59.39279],"type":"Point"}
}