{
  "type": "Feature",
  "properties": {
    "gn:admin1_code":"20.0",
    "gn:admin2_code":"615.0",
    "gn:admin3_code":"8566.0",
    "gn:asciiname":"Rulli",
    "gn:country_code":"EE",
    "gn:dem":99,
    "gn:feature_class":"P",
    "gn:feature_code":"PPL",
    "gn:name":"Rulli",
    "gn:population":0,
    "gn:timezone":"Europe/Tallinn",
    "iso:country":"EE",
    "name:est_x_preferred":[
        "Rulli"
    ],
    "name:hye_x_preferred":[
        "\u054c\u0578\u0582\u056c\u056c\u056b"
    ],
    "name:pol_x_preferred":[
        "Rulli"
    ],
    "name:spa_x_preferred":[
        "Rulli"
    ],
    "name:ukr_x_preferred":[
        "\u0420\u0443\u043b\u043b\u0456"
    ],
    "name:vol_x_preferred":[
        "Rulli"
    ],
    "wof:lang_x_official":[
        "est"
    ],
    "wof:lang_x_spoken":[
        "est"
    ],
    "wof:name":"Rulli",
    "wof:placetype":"locality"
},
  "geometry": {"coordinates":[25.53417,58.51472],"type":"Point"}
}