{
  "type": "Feature",
  "properties": {
    "gn:admin1_code":"3.0",
    "gn:admin2_code":"130.0",
    "gn:admin3_code":"3644.0",
    "gn:asciiname":"Laehtepea",
    "gn:country_code":"EE",
    "gn:dem":52,
    "gn:feature_class":"P",
    "gn:feature_code":"PPL",
    "gn:name":"L\u00e4htepea",
    "gn:population":0,
    "gn:timezone":"Europe/Tallinn",
    "iso:country":"EE",
    "name:und_x_variant":[
        "Lehtep\u00e4\u00e4",
        "Lekhtep\u2019ya",
        "L\u00e4htepea"
    ],
    "wof:name":"Laehtepea",
    "wof:placetype":"locality"
},
  "geometry": {"coordinates":[27.5325,59.20944],"type":"Point"}
}