{
  "type": "Feature",
  "properties": {
    "gn:admin1_code":"3.0",
    "gn:admin2_code":"514.0",
    "gn:admin3_code":"1472.0",
    "gn:asciiname":"Auvere",
    "gn:country_code":"EE",
    "gn:dem":42,
    "gn:feature_class":"P",
    "gn:feature_code":"PPL",
    "gn:name":"Auvere",
    "gn:population":0,
    "gn:timezone":"Europe/Tallinn",
    "iso:country":"EE",
    "name:eng_x_preferred":[
        "Auvere"
    ],
    "name:rus_x_preferred":[
        "\u0410\u0443\u0432\u0435\u0440\u0435"
    ],
    "wof:name":"Auvere",
    "wof:placetype":"locality"
},
  "geometry": {"coordinates":[27.9375,59.34583000000001],"type":"Point"}
}