{
  "type": "Feature",
  "properties": {
    "gn:admin1_code":"8.0",
    "gn:admin2_code":"901.0",
    "gn:admin3_code":"6768.0",
    "gn:asciiname":"Rajakuela",
    "gn:country_code":"EE",
    "gn:dem":105,
    "gn:feature_class":"P",
    "gn:feature_code":"PPL",
    "gn:name":"Rajak\u00fcla",
    "gn:population":0,
    "gn:timezone":"Europe/Tallinn",
    "iso:country":"EE",
    "name:und_x_variant":[
        "Raja",
        "Raya",
        "Rajak\u00fcla"
    ],
    "wof:name":"Rajakuela",
    "wof:placetype":"locality"
},
  "geometry": {"coordinates":[26.58083,59.11417],"type":"Point"}
}