{
  "type": "Feature",
  "properties": {
    "gn:admin1_code":"5.0",
    "gn:admin2_code":"247.0",
    "gn:admin3_code":"6344.0",
    "gn:asciiname":"Praaklima",
    "gn:country_code":"EE",
    "gn:dem":70,
    "gn:feature_class":"P",
    "gn:feature_code":"PPL",
    "gn:name":"Praaklima",
    "gn:population":0,
    "gn:timezone":"Europe/Tallinn",
    "iso:country":"EE",
    "name:est_x_preferred":[
        "Praaklima"
    ],
    "name:hye_x_preferred":[
        "\u054a\u057c\u0561\u0561\u056f\u056c\u056b\u0574\u0561"
    ],
    "name:pol_x_preferred":[
        "Praaklima"
    ],
    "name:spa_x_preferred":[
        "Praaklima"
    ],
    "name:vol_x_preferred":[
        "Praaklima"
    ],
    "wof:name":"Praaklima",
    "wof:placetype":"locality"
},
  "geometry": {"coordinates":[26.62444,58.60778000000001],"type":"Point"}
}