{
  "type": "Feature",
  "properties": {
    "gn:gn_country":"EE",
    "gn:gn_fcode":"PPL",
    "gn:gn_pop":103,
    "gn:population":103,
    "iso:country":"EE",
    "name:arm_x_preferred":[
        "\u054d\u0561\u0578\u0582\u056c\u0561"
    ],
    "name:dut_x_preferred":[
        "Saula"
    ],
    "name:eng_x_preferred":[
        "Saula"
    ],
    "name:est_x_preferred":[
        "Saula"
    ],
    "name:fre_x_preferred":[
        "Saula"
    ],
    "name:pol_x_preferred":[
        "Saula"
    ],
    "name:rus_x_preferred":[
        "\u0421\u0430\u0443\u043b\u0430"
    ],
    "name:swe_x_preferred":[
        "Saula"
    ],
    "name:vol_x_preferred":[
        "Saula"
    ],
    "qs_pg:aaroncc":"EE",
    "qs_pg:gn_country":"EE",
    "qs_pg:gn_fcode":"PPL",
    "qs_pg:gn_pop":103,
    "qs_pg:name":"Saula",
    "qs_pg:photos_9r":0,
    "qs_pg:photos_sr":0,
    "qs_pg:pop_sr":1,
    "qs_pg:qs_pg_placetype":"locality",
    "wof:name":"Saula",
    "wof:placetype":"locality",
    "wof:population":103
},
  "geometry": {"coordinates":[25.02917,59.19444],"type":"Point"}
}