{
  "type": "Feature",
  "properties": {
    "gn:admin1_code":"7.0",
    "gn:admin2_code":"441.0",
    "gn:admin3_code":"2126.0",
    "gn:asciiname":"Jaakna",
    "gn:cc2":"EE",
    "gn:country_code":"EE",
    "gn:dem":42,
    "gn:feature_class":"P",
    "gn:feature_code":"PPL",
    "gn:name":"Jaakna",
    "gn:population":0,
    "gn:timezone":"Europe/Tallinn",
    "iso:country":"EE",
    "name:deu_x_preferred":[
        "Jaakna"
    ],
    "name:est_x_preferred":[
        "Jaakna"
    ],
    "name:fra_x_preferred":[
        "Jaakna"
    ],
    "name:hye_x_preferred":[
        "\u0545\u0561\u0561\u056f\u0576\u0561"
    ],
    "name:nld_x_preferred":[
        "Jaakna"
    ],
    "name:pol_x_preferred":[
        "Jaakna"
    ],
    "name:spa_x_preferred":[
        "Jaakna"
    ],
    "name:ukr_x_preferred":[
        "\u042f\u0430\u043a\u043d\u0430"
    ],
    "name:und_x_variant":[
        "Val\u2019geristi",
        "Yaakna"
    ],
    "name:urd_x_preferred":[
        "\u062c\u0627\u06a9\u0646\u0627"
    ],
    "name:vol_x_preferred":[
        "Jaakna"
    ],
    "wof:lang_x_official":[
        "est"
    ],
    "wof:lang_x_spoken":[
        "est"
    ],
    "wof:name":"Jaakna",
    "wof:placetype":"locality"
},
  "geometry": {"coordinates":[23.99556,58.98139],"type":"Point"}
}