{
  "type": "Feature",
  "properties": {
    "gn:admin1_code":"3.0",
    "gn:admin2_code":"803.0",
    "gn:admin3_code":"7063.0",
    "gn:asciiname":"Roodu",
    "gn:country_code":"EE",
    "gn:dem":56,
    "gn:feature_class":"P",
    "gn:feature_code":"PPL",
    "gn:name":"Roodu",
    "gn:population":0,
    "gn:timezone":"Europe/Tallinn",
    "iso:country":"EE",
    "wof:name":"Roodu",
    "wof:placetype":"locality"
},
  "geometry": {"coordinates":[27.17222000000001,59.36472],"type":"Point"}
}