{
  "type": "Feature",
  "properties": {
    "gn:admin1_code":"12.0",
    "gn:admin2_code":"622.0",
    "gn:admin3_code":"4938.0",
    "gn:asciiname":"Meemaste",
    "gn:country_code":"EE",
    "gn:dem":79,
    "gn:feature_class":"P",
    "gn:feature_code":"PPL",
    "gn:name":"Meemaste",
    "gn:population":0,
    "gn:timezone":"Europe/Tallinn",
    "iso:country":"EE",
    "name:est_x_preferred":[
        "Meemaste"
    ],
    "name:hye_x_preferred":[
        "\u0544\u0565\u0565\u0574\u0561\u057d\u057f\u0565"
    ],
    "name:spa_x_preferred":[
        "Meemaste"
    ],
    "name:ukr_x_preferred":[
        "\u041c\u0435\u0435\u043c\u0430\u0441\u0442\u0435"
    ],
    "name:vol_x_preferred":[
        "Meemaste"
    ],
    "wof:lang_x_official":[
        "est"
    ],
    "wof:lang_x_spoken":[
        "est"
    ],
    "wof:name":"Meemaste",
    "wof:placetype":"locality"
},
  "geometry": {"coordinates":[27.05444,58.00472],"type":"Point"}
}