{
  "type": "Feature",
  "properties": {
    "gn:country":"EE",
    "gn:fcode":"PPL",
    "gn:population":406,
    "iso:country":"EE",
    "name:bel_x_preferred":[
        "\u0412\u0430\u0440\u0430"
    ],
    "name:ceb_x_preferred":[
        "Vara vald"
    ],
    "name:deu_x_preferred":[
        "Vara"
    ],
    "name:eng_x_preferred":[
        "Vara Parish"
    ],
    "name:est_x_preferred":[
        "Vara vald"
    ],
    "name:fas_x_preferred":[
        "\u0648\u0627\u0631\u0627 \u067e\u0627\u0631\u06cc\u0634"
    ],
    "name:fra_x_preferred":[
        "Commune de Vara"
    ],
    "name:hye_x_preferred":[
        "\u054e\u0561\u057c\u0561"
    ],
    "name:ita_x_preferred":[
        "Vara"
    ],
    "name:kat_x_preferred":[
        "\u10d5\u10d0\u10e0\u10d8\u10e1 \u10db\u10e3\u10dc\u10d8\u10ea\u10d8\u10de\u10d0\u10da\u10d8\u10e2\u10d4\u10e2\u10d8"
    ],
    "name:nld_x_preferred":[
        "Vara"
    ],
    "name:nob_x_preferred":[
        "Vara kommune"
    ],
    "name:pol_x_preferred":[
        "Gmina Vara"
    ],
    "name:por_x_preferred":[
        "Vara"
    ],
    "name:ron_x_preferred":[
        "Comuna Vara"
    ],
    "name:rus_x_preferred":[
        "\u0412\u0430\u0440\u0430"
    ],
    "name:swe_x_preferred":[
        "Vara"
    ],
    "name:swe_x_variant":[
        "Vara kommun"
    ],
    "name:ukr_x_preferred":[
        "\u0412\u0430\u0440\u0430"
    ],
    "name:und_x_variant":[
        "Myza Vara"
    ],
    "qs_pg:aaroncc":"EE",
    "qs_pg:gn_country":"EE",
    "qs_pg:gn_fcode":"PPL",
    "qs_pg:gn_pop":406,
    "qs_pg:name":"Vara",
    "qs_pg:name_adm0":"Eesti",
    "qs_pg:name_adm1":"Tartumaa",
    "qs_pg:photos_9k":1,
    "qs_pg:photos_9r":1,
    "qs_pg:photos_all":1,
    "qs_pg:photos_sr":0,
    "qs_pg:pop_sr":2,
    "qs_pg:qs_pg_placetype":"locality",
    "qs_pg:qs_pg_placetype_gp":"Town",
    "qs_pg:woe_adm0":23424805,
    "woe:adm0_id":23424805,
    "woe:name_adm0":"Eesti",
    "woe:name_adm1":"Tartumaa",
    "woe:placetype":"Town",
    "wof:lang_x_official":[
        "est"
    ],
    "wof:lang_x_spoken":[
        "est"
    ],
    "wof:name":"Vara",
    "wof:placetype":"locality",
    "wof:population":406
},
  "geometry": {"coordinates":[26.88167,58.52083],"type":"Point"}
}