{
  "type": "Feature",
  "properties": {
    "gn:admin1_code":"12.0",
    "gn:admin2_code":"708.0",
    "gn:admin3_code":"4842.0",
    "gn:asciiname":"Vana-Pihosto",
    "gn:country_code":"EE",
    "gn:dem":33,
    "gn:feature_class":"P",
    "gn:feature_code":"PPL",
    "gn:name":"Vana-Pihost\u00f5",
    "gn:population":0,
    "gn:timezone":"Europe/Tallinn",
    "iso:country":"EE",
    "name:und_x_variant":[
        "Vana-Pihost\u00f5",
        "Vana"
    ],
    "wof:name":"Vana-Pihosto",
    "wof:placetype":"locality"
},
  "geometry": {"coordinates":[27.45528,58.25361],"type":"Point"}
}