{
  "type": "Feature",
  "properties": {
    "gn:admin1_code":"18.0",
    "gn:admin2_code":"171.0",
    "gn:admin3_code":"3881.0",
    "gn:asciiname":"Lauri",
    "gn:country_code":"EE",
    "gn:dem":77,
    "gn:feature_class":"P",
    "gn:feature_code":"PPL",
    "gn:name":"Lauri",
    "gn:population":0,
    "gn:timezone":"Europe/Tallinn",
    "iso:country":"EE",
    "name:und_x_variant":[
        "Lapetukma"
    ],
    "wof:name":"Lauri",
    "wof:placetype":"locality"
},
  "geometry": {"coordinates":[26.35,58.20583000000001],"type":"Point"}
}