{
  "type": "Feature",
  "properties": {
    "gn:admin1_code":"20.0",
    "gn:admin2_code":"899.0",
    "gn:admin3_code":"3313.0",
    "gn:asciiname":"Kokaviidika",
    "gn:country_code":"EE",
    "gn:dem":92,
    "gn:feature_class":"P",
    "gn:feature_code":"PPL",
    "gn:name":"Kokaviidika",
    "gn:population":0,
    "gn:timezone":"Europe/Tallinn",
    "iso:country":"EE",
    "wof:name":"Kokaviidika",
    "wof:placetype":"locality"
},
  "geometry": {"coordinates":[25.64361,58.42],"type":"Point"}
}