{
  "type": "Feature",
  "properties": {
    "gn:admin1_code":"20.0",
    "gn:admin2_code":"899.0",
    "gn:admin3_code":"3313.0",
    "gn:asciiname":"Kokaviidika",
    "gn:country_code":"EE",
    "gn:dem":92,
    "gn:feature_class":"P",
    "gn:feature_code":"PPL",
    "gn:name":"Kokaviidika",
    "gn:population":0,
    "gn:timezone":"Europe/Tallinn",
    "iso:country":"EE",
    "name:est_x_preferred":[
        "Kokaviidika"
    ],
    "name:fra_x_preferred":[
        "Kokaviidika"
    ],
    "name:hye_x_preferred":[
        "\u053f\u0578\u056f\u0561\u057e\u056b\u056b\u0564\u056b\u056f\u0561"
    ],
    "name:pol_x_preferred":[
        "Kokaviidika"
    ],
    "name:spa_x_preferred":[
        "Kokaviidika"
    ],
    "name:ukr_x_preferred":[
        "\u041a\u043e\u043a\u0430\u0432\u0456\u0439\u0434\u0456\u043a\u0430"
    ],
    "name:vol_x_preferred":[
        "Kokaviidika"
    ],
    "wof:lang_x_official":[
        "est"
    ],
    "wof:lang_x_spoken":[
        "est"
    ],
    "wof:name":"Kokaviidika",
    "wof:placetype":"locality"
},
  "geometry": {"coordinates":[25.64361,58.42],"type":"Point"}
}