{
  "type": "Feature",
  "properties": {
    "gn:admin1_code":"1.0",
    "gn:admin2_code":"651.0",
    "gn:admin3_code":"6122.0",
    "gn:asciiname":"Liivaaugu",
    "gn:country_code":"EE",
    "gn:dem":61,
    "gn:feature_class":"P",
    "gn:feature_code":"PPL",
    "gn:name":"Liivaaugu",
    "gn:population":0,
    "gn:timezone":"Europe/Tallinn",
    "iso:country":"EE",
    "name:und_x_variant":[
        "Kadakotsa",
        "Liyvaaugu",
        "Liivaaugu"
    ],
    "wof:name":"Liivaaugu",
    "wof:placetype":"locality"
},
  "geometry": {"coordinates":[25.21583,59.27583000000001],"type":"Point"}
}