{
  "type": "Feature",
  "properties": {
    "gn:admin1_code":"5.0",
    "gn:admin2_code":"486.0",
    "gn:admin3_code":"3842.0",
    "gn:asciiname":"Mustametsa",
    "gn:country_code":"EE",
    "gn:dem":65,
    "gn:feature_class":"P",
    "gn:feature_code":"PPL",
    "gn:name":"Mustametsa",
    "gn:population":0,
    "gn:timezone":"Europe/Tallinn",
    "iso:country":"EE",
    "wof:name":"Mustametsa",
    "wof:placetype":"locality"
},
  "geometry": {"coordinates":[26.80361,58.9875],"type":"Point"}
}