{
  "type": "Feature",
  "properties": {
    "gn:admin1_code":"4.0",
    "gn:admin2_code":"567.0",
    "gn:admin3_code":"7508.0",
    "gn:asciiname":"Seinapalu",
    "gn:cc2":"EE",
    "gn:country_code":"EE",
    "gn:dem":68,
    "gn:feature_class":"P",
    "gn:feature_code":"PPL",
    "gn:name":"Seinapalu",
    "gn:population":0,
    "gn:timezone":"Europe/Tallinn",
    "iso:country":"EE",
    "name:est_x_preferred":[
        "Seinapalu"
    ],
    "name:hye_x_preferred":[
        "\u054d\u0565\u056b\u0576\u0561\u057a\u0561\u056c\u0578\u0582"
    ],
    "name:pol_x_preferred":[
        "Seinapalu"
    ],
    "name:ukr_x_preferred":[
        "\u0421\u0435\u0439\u043d\u0430\u043f\u0430\u043b\u0443"
    ],
    "name:und_x_variant":[
        "Seynapalu",
        "Seinapalu"
    ],
    "name:vol_x_preferred":[
        "Seinapalu"
    ],
    "wof:name":"Seinapalu",
    "wof:placetype":"locality"
},
  "geometry": {"coordinates":[25.61528,58.85611],"type":"Point"}
}