{
  "type": "Feature",
  "properties": {
    "gn:admin1_code":"7.0",
    "gn:admin2_code":"441.0",
    "gn:admin3_code":"1964.0",
    "gn:asciiname":"Hoebringi",
    "gn:country_code":"EE",
    "gn:dem":25,
    "gn:feature_class":"P",
    "gn:feature_code":"PPL",
    "gn:name":"H\u00f6bringi",
    "gn:population":0,
    "gn:timezone":"Europe/Tallinn",
    "iso:country":"EE",
    "name:deu_x_preferred":[
        "H\u00f6bringi"
    ],
    "name:est_x_preferred":[
        "H\u00f6bringi"
    ],
    "name:hye_x_preferred":[
        "\u0540\u0578\u0578\u0562\u057c\u056b\u0576\u0563\u056b"
    ],
    "name:nld_x_preferred":[
        "H\u00f6bringi"
    ],
    "name:pol_x_preferred":[
        "H\u00f6bringi"
    ],
    "name:spa_x_preferred":[
        "H\u00f6bringi"
    ],
    "name:swe_x_preferred":[
        "H\u00f6bring"
    ],
    "name:ukr_x_preferred":[
        "\u0413\u0454\u0431\u0440\u0456\u043d\u0491\u0456"
    ],
    "name:und_x_variant":[
        "Khyubringi"
    ],
    "name:vol_x_preferred":[
        "H\u00f6bringi"
    ],
    "wof:coterminous":[
        1713308743
    ],
    "wof:lang_x_official":[
        "est"
    ],
    "wof:lang_x_spoken":[
        "est"
    ],
    "wof:name":"Hoebringi",
    "wof:placetype":"locality"
},
  "geometry": {"coordinates":[23.57944,59.13278],"type":"Point"}
}