{
  "type": "Feature",
  "properties": {
    "gn:admin1_code":"7.0",
    "gn:admin2_code":"441.0",
    "gn:admin3_code":"1964.0",
    "gn:asciiname":"Hoebringi",
    "gn:country_code":"EE",
    "gn:dem":25,
    "gn:feature_class":"P",
    "gn:feature_code":"PPL",
    "gn:name":"H\u00f6bringi",
    "gn:population":0,
    "gn:timezone":"Europe/Tallinn",
    "iso:country":"EE",
    "name:swe_x_preferred":[
        "H\u00f6bring"
    ],
    "name:und_x_variant":[
        "Khyubringi",
        "H\u00f6bringi"
    ],
    "wof:name":"Hoebringi",
    "wof:placetype":"locality"
},
  "geometry": {"coordinates":[23.57944,59.13278],"type":"Point"}
}