{
  "type": "Feature",
  "properties": {
    "gn:admin1_code":"5.0",
    "gn:admin2_code":"247.0",
    "gn:admin3_code":"5548.0",
    "gn:asciiname":"Naeduvere",
    "gn:country_code":"EE",
    "gn:dem":80,
    "gn:feature_class":"P",
    "gn:feature_code":"PPL",
    "gn:name":"N\u00e4duvere",
    "gn:population":0,
    "gn:timezone":"Europe/Tallinn",
    "iso:country":"EE",
    "wof:name":"Naeduvere",
    "wof:placetype":"locality"
},
  "geometry": {"coordinates":[26.72556,58.84556],"type":"Point"}
}