{
  "type": "Feature",
  "properties": {
    "gn:admin1_code":"11.0",
    "gn:admin2_code":"809.0",
    "gn:admin3_code":"3084.0",
    "gn:asciiname":"Piiri",
    "gn:country_code":"EE",
    "gn:dem":30,
    "gn:feature_class":"P",
    "gn:feature_code":"PPL",
    "gn:name":"Piiri",
    "gn:population":0,
    "gn:timezone":"Europe/Tallinn",
    "iso:country":"EE",
    "name:deu_x_preferred":[
        "Piiri"
    ],
    "name:est_x_preferred":[
        "Piiri"
    ],
    "name:fin_x_preferred":[
        "Piiri"
    ],
    "name:nld_x_preferred":[
        "Piiri"
    ],
    "name:pol_x_preferred":[
        "Piiri"
    ],
    "name:ukr_x_preferred":[
        "\u041f\u0456\u0439\u0440\u0456"
    ],
    "name:und_x_variant":[
        "Piyri"
    ],
    "name:vol_x_preferred":[
        "Piiri"
    ],
    "wof:name":"Piiri",
    "wof:placetype":"locality"
},
  "geometry": {"coordinates":[24.63333,58.46666999999999],"type":"Point"}
}