{
  "type": "Feature",
  "properties": {
    "gn:admin1_code":"19.0",
    "gn:admin2_code":"824.0",
    "gn:admin3_code":"6257.0",
    "gn:asciiname":"Jaerve",
    "gn:country_code":"EE",
    "gn:dem":101,
    "gn:feature_class":"P",
    "gn:feature_code":"PPL",
    "gn:name":"J\u00e4rve",
    "gn:population":0,
    "gn:timezone":"Europe/Tallinn",
    "iso:country":"EE",
    "name:und_x_variant":[
        "J\u00e4rve",
        "Suuresilma"
    ],
    "wof:name":"Jaerve",
    "wof:placetype":"locality"
},
  "geometry": {"coordinates":[25.61028,57.95194],"type":"Point"}
}