{
  "type": "Feature",
  "properties": {
    "gn:admin1_code":"8.0",
    "gn:admin2_code":"661.0",
    "gn:admin3_code":"3582.0",
    "gn:asciiname":"Kullaaru",
    "gn:country_code":"EE",
    "gn:dem":82,
    "gn:feature_class":"P",
    "gn:feature_code":"PPL",
    "gn:name":"Kullaaru",
    "gn:population":0,
    "gn:timezone":"Europe/Tallinn",
    "iso:country":"EE",
    "wof:name":"Kullaaru",
    "wof:placetype":"locality"
},
  "geometry": {"coordinates":[26.31611,59.35528000000001],"type":"Point"}
}