{
  "type": "Feature",
  "properties": {
    "gn:admin1_code":"2.0",
    "gn:admin2_code":"205.0",
    "gn:admin3_code":"7014.0",
    "gn:asciiname":"Ristivaelja",
    "gn:country_code":"EE",
    "gn:dem":10,
    "gn:feature_class":"P",
    "gn:feature_code":"PPL",
    "gn:name":"Ristiv\u00e4lja",
    "gn:population":0,
    "gn:timezone":"Europe/Tallinn",
    "iso:country":"EE",
    "name:deu_x_preferred":[
        "Ristiv\u00e4lja"
    ],
    "name:est_x_preferred":[
        "Ristiv\u00e4lja"
    ],
    "name:hye_x_preferred":[
        "\u054c\u056b\u057d\u057f\u056b\u057e\u0565\u056c\u0575\u0561"
    ],
    "name:pol_x_preferred":[
        "Ristiv\u00e4lja"
    ],
    "name:spa_x_preferred":[
        "Ristiv\u00e4lja"
    ],
    "name:und_x_variant":[
        "Ristivyal\u2019ya"
    ],
    "name:vol_x_preferred":[
        "Ristiv\u00e4lja"
    ],
    "wof:name":"Ristivaelja",
    "wof:placetype":"locality"
},
  "geometry": {"coordinates":[22.77139,58.85056],"type":"Point"}
}