{
  "type": "Feature",
  "properties": {
    "gn:country":"EE",
    "gn:fcode":"PPL",
    "gn:population":250,
    "iso:country":"EE",
    "name:ceb_x_preferred":[
        "Suurej\u00f5e"
    ],
    "name:eng_x_preferred":[
        "Suurej\u00f5e"
    ],
    "name:est_x_preferred":[
        "Suurej\u00f5e"
    ],
    "name:hye_x_preferred":[
        "\u054d\u0578\u0582\u0578\u0582\u057c\u0565\u0575\u056b\u0565"
    ],
    "name:nld_x_preferred":[
        "Suurej\u00f5e"
    ],
    "name:pol_x_preferred":[
        "Suurej\u00f5e"
    ],
    "name:rus_x_preferred":[
        "\u0421\u0443\u0443\u0440\u0435\u0439\u044b\u044d"
    ],
    "name:spa_x_preferred":[
        "Suurej\u00f5e"
    ],
    "name:swe_x_preferred":[
        "Suurej\u00f5e"
    ],
    "name:und_x_variant":[
        "Neu-Fennern"
    ],
    "name:vol_x_preferred":[
        "Suurej\u00f5e"
    ],
    "qs_pg:aaroncc":"EE",
    "qs_pg:gn_country":"EE",
    "qs_pg:gn_fcode":"PPL",
    "qs_pg:gn_pop":250,
    "qs_pg:name":"Suurej\u00f5e",
    "qs_pg:name_adm0":"Eesti",
    "qs_pg:name_adm1":"P\u00e4rnumaa",
    "qs_pg:photos_9k":1,
    "qs_pg:photos_9r":1,
    "qs_pg:photos_all":1,
    "qs_pg:photos_sr":0,
    "qs_pg:pop_sr":2,
    "qs_pg:qs_pg_placetype":"locality",
    "qs_pg:qs_pg_placetype_gp":"Town",
    "qs_pg:woe_adm0":23424805,
    "woe:adm0_id":23424805,
    "woe:name_adm0":"Eesti",
    "woe:name_adm1":"P\u00e4rnumaa",
    "woe:placetype":"Town",
    "wof:name":"Suurej\u00f5e",
    "wof:placetype":"locality",
    "wof:population":250
},
  "geometry": {"coordinates":[25.09694,58.61583],"type":"Point"}
}