{
  "type": "Feature",
  "properties": {
    "gn:admin1_code":"5.0",
    "gn:admin2_code":"486.0",
    "gn:admin3_code":"3826.0",
    "gn:asciiname":"Korvemetsa",
    "gn:country_code":"EE",
    "gn:dem":58,
    "gn:feature_class":"P",
    "gn:feature_code":"PPL",
    "gn:name":"K\u00f5rvemetsa",
    "gn:population":0,
    "gn:timezone":"Europe/Tallinn",
    "iso:country":"EE",
    "name:und_x_variant":[
        "K\u00f5rvemetsa"
    ],
    "wof:name":"Korvemetsa",
    "wof:placetype":"locality"
},
  "geometry": {"coordinates":[26.77556,58.89917],"type":"Point"}
}