{
  "type": "Feature",
  "properties": {
    "gn:country":"EE",
    "gn:fcode":"PPL",
    "gn:population":198,
    "iso:country":"EE",
    "name:bul_x_preferred":[
        "\u0415\u0434\u0438\u0441\u0435"
    ],
    "name:ceb_x_preferred":[
        "Edise"
    ],
    "name:deu_x_preferred":[
        "Edise"
    ],
    "name:eng_x_preferred":[
        "Edise"
    ],
    "name:est_x_preferred":[
        "Edise"
    ],
    "name:fra_x_preferred":[
        "Edise"
    ],
    "name:hye_x_preferred":[
        "\u0537\u0564\u056b\u057d\u0565"
    ],
    "name:nld_x_preferred":[
        "Edise"
    ],
    "name:pol_x_preferred":[
        "Edise"
    ],
    "name:spa_x_preferred":[
        "Edise"
    ],
    "name:swe_x_preferred":[
        "Edise"
    ],
    "name:vol_x_preferred":[
        "Edise"
    ],
    "qs_pg:aaroncc":"EE",
    "qs_pg:gn_country":"EE",
    "qs_pg:gn_fcode":"PPL",
    "qs_pg:gn_pop":198,
    "qs_pg:name":"Edise",
    "qs_pg:name_adm0":"Eesti",
    "qs_pg:name_adm1":"Ida-Virumaa",
    "qs_pg:photos_9k":1,
    "qs_pg:photos_9r":1,
    "qs_pg:photos_all":6,
    "qs_pg:photos_sr":0,
    "qs_pg:pop_sr":1,
    "qs_pg:qs_pg_placetype":"locality",
    "qs_pg:qs_pg_placetype_gp":"Town",
    "qs_pg:woe_adm0":23424805,
    "woe:adm0_id":23424805,
    "woe:name_adm0":"Eesti",
    "woe:name_adm1":"Ida-Virumaa",
    "woe:placetype":"Town",
    "wof:name":"Edise",
    "wof:placetype":"locality",
    "wof:population":198
},
  "geometry": {"coordinates":[27.36778,59.36417],"type":"Point"}
}