{
  "type": "Feature",
  "properties": {
    "gn:admin1_code":"21.0",
    "gn:admin2_code":"917.0",
    "gn:admin3_code":"6761.0",
    "gn:asciiname":"Voitra",
    "gn:country_code":"EE",
    "gn:dem":90,
    "gn:feature_class":"P",
    "gn:feature_code":"PPL",
    "gn:name":"V\u00f5itra",
    "gn:population":0,
    "gn:timezone":"Europe/Tallinn",
    "iso:country":"EE",
    "name:und_x_variant":[
        "V\u00f5itra",
        "V\u00e4imela-Suurk\u00fcla"
    ],
    "wof:name":"Voitra",
    "wof:placetype":"locality"
},
  "geometry": {"coordinates":[26.95778,57.91194],"type":"Point"}
}