{
  "type": "Feature",
  "properties": {
    "gn:admin1_code":"21.0",
    "gn:admin2_code":"917.0",
    "gn:admin3_code":"6896.0",
    "gn:asciiname":"Rebasmaee",
    "gn:country_code":"EE",
    "gn:dem":51,
    "gn:feature_class":"P",
    "gn:feature_code":"PPL",
    "gn:name":"Rebasm\u00e4e",
    "gn:population":0,
    "gn:timezone":"Europe/Tallinn",
    "iso:country":"EE",
    "name:und_x_variant":[
        "Rebasm\u00e4e"
    ],
    "wof:name":"Rebasmaee",
    "wof:placetype":"locality"
},
  "geometry": {"coordinates":[27.42028,57.94667],"type":"Point"}
}