{
  "type": "Feature",
  "properties": {
    "gn:country":"EE",
    "gn:fcode":"PPL",
    "gn:population":317,
    "iso:country":"EE",
    "name:ceb_x_preferred":[
        "Kaagj\u00e4rve"
    ],
    "name:eng_x_preferred":[
        "Kaagj\u00e4rve"
    ],
    "name:est_x_preferred":[
        "Kaagj\u00e4rve"
    ],
    "name:hye_x_preferred":[
        "\u053f\u0561\u0561\u0563\u0575\u0565\u057c\u057e\u0565"
    ],
    "name:nld_x_preferred":[
        "Kaagj\u00e4rve"
    ],
    "name:pol_x_preferred":[
        "Kaagj\u00e4rve"
    ],
    "name:spa_x_preferred":[
        "Kaagj\u00e4rve"
    ],
    "name:swe_x_preferred":[
        "Kaagj\u00e4rve"
    ],
    "name:ukr_x_preferred":[
        "\u041a\u0430\u0430\u0491'\u044f\u0440\u0432\u0435"
    ],
    "name:und_x_variant":[
        "Myza Kagyarve"
    ],
    "name:vol_x_preferred":[
        "Kaagj\u00e4rve"
    ],
    "qs_pg:aaroncc":"EE",
    "qs_pg:gn_country":"EE",
    "qs_pg:gn_fcode":"PPL",
    "qs_pg:gn_pop":317,
    "qs_pg:name":"Kaagj\u00e4rve",
    "qs_pg:name_adm0":"Eesti",
    "qs_pg:name_adm1":"Valgamaa",
    "qs_pg:photos_9r":0,
    "qs_pg:photos_sr":0,
    "qs_pg:pop_sr":2,
    "qs_pg:qs_pg_placetype":"locality",
    "qs_pg:qs_pg_placetype_gp":"Town",
    "qs_pg:woe_adm0":23424805,
    "woe:adm0_id":23424805,
    "woe:name_adm0":"Eesti",
    "woe:name_adm1":"Valgamaa",
    "woe:placetype":"Town",
    "wof:name":"Kaagj\u00e4rve",
    "wof:placetype":"locality",
    "wof:population":317
},
  "geometry": {"coordinates":[26.17722,57.76722],"type":"Point"}
}