{
  "type": "Feature",
  "properties": {
    "gn:admin1_code":"5.0",
    "gn:admin2_code":"618.0",
    "gn:admin3_code":"7220.0",
    "gn:asciiname":"Raesna",
    "gn:country_code":"EE",
    "gn:dem":59,
    "gn:feature_class":"P",
    "gn:feature_code":"PPL",
    "gn:name":"R\u00e4sna",
    "gn:population":0,
    "gn:timezone":"Europe/Tallinn",
    "iso:country":"EE",
    "name:und_x_variant":[
        "Ryasna",
        "R\u00e4sna"
    ],
    "wof:name":"Raesna",
    "wof:placetype":"locality"
},
  "geometry": {"coordinates":[25.80639,58.67611],"type":"Point"}
}