{
  "type": "Feature",
  "properties": {
    "gn:admin1_code":"4.0",
    "gn:admin2_code":"255.0",
    "gn:admin3_code":"2712.0",
    "gn:asciiname":"Esna",
    "gn:cc2":"EE",
    "gn:country_code":"EE",
    "gn:dem":87,
    "gn:feature_class":"P",
    "gn:feature_code":"PPL",
    "gn:name":"Esna",
    "gn:population":0,
    "gn:timezone":"Europe/Tallinn",
    "iso:country":"EE",
    "name:eng_x_preferred":[
        "Esna"
    ],
    "name:rus_x_preferred":[
        "\u042d\u0441\u043d\u0430"
    ],
    "name:und_x_variant":[
        "Kareda Esna",
        "Kareda",
        "Esna"
    ],
    "wof:name":"Esna",
    "wof:placetype":"locality"
},
  "geometry": {"coordinates":[25.78361,58.96694],"type":"Point"}
}