{
  "type": "Feature",
  "properties": {
    "gn:admin1_code":"13.0",
    "gn:admin2_code":"503.0",
    "gn:admin3_code":"8182.0",
    "gn:asciiname":"Altkuela",
    "gn:country_code":"EE",
    "gn:dem":16,
    "gn:feature_class":"P",
    "gn:feature_code":"PPL",
    "gn:name":"Altk\u00fcla",
    "gn:population":0,
    "gn:timezone":"Europe/Tallinn",
    "iso:country":"EE",
    "name:und_x_variant":[
        "Al\u2019tkyula",
        "Altk\u00fcla"
    ],
    "wof:lang_x_official":[
        "est"
    ],
    "wof:lang_x_spoken":[
        "est"
    ],
    "wof:name":"Altkuela",
    "wof:placetype":"locality"
},
  "geometry": {"coordinates":[24.18639,58.815],"type":"Point"}
}