{
  "type": "Feature",
  "properties": {
    "gn:admin1_code":"19.0",
    "gn:admin2_code":"824.0",
    "gn:admin3_code":"2757.0",
    "gn:asciiname":"Koriste",
    "gn:country_code":"EE",
    "gn:dem":91,
    "gn:feature_class":"P",
    "gn:feature_code":"PPL",
    "gn:name":"Koriste",
    "gn:population":0,
    "gn:timezone":"Europe/Tallinn",
    "iso:country":"EE",
    "name:und_x_variant":[
        "\u041a\u0430\u0440\u043e\u0442\u0435"
    ],
    "wof:name":"Koriste",
    "wof:placetype":"locality"
},
  "geometry": {"coordinates":[25.82222,58.02667],"type":"Point"}
}