{
  "type": "Feature",
  "properties": {
    "gn:admin1_code":"21.0",
    "gn:admin2_code":"698.0",
    "gn:admin3_code":"7125.0",
    "gn:asciiname":"Siksali",
    "gn:country_code":"EE",
    "gn:dem":242,
    "gn:feature_class":"P",
    "gn:feature_code":"PPL",
    "gn:name":"Siksali",
    "gn:population":0,
    "gn:timezone":"Europe/Tallinn",
    "iso:country":"EE",
    "name:und_x_variant":[
        "Siks\u00e4l\u00e4",
        "Siksali"
    ],
    "wof:name":"Siksali",
    "wof:placetype":"locality"
},
  "geometry": {"coordinates":[27.0625,57.62416999999999],"type":"Point"}
}