{
  "type": "Feature",
  "properties": {
    "gn:admin1_code":"13.0",
    "gn:admin2_code":"668.0",
    "gn:admin3_code":"3724.0",
    "gn:asciiname":"Lipstu",
    "gn:country_code":"EE",
    "gn:dem":51,
    "gn:feature_class":"P",
    "gn:feature_code":"PPL",
    "gn:name":"Lipstu",
    "gn:population":0,
    "gn:timezone":"Europe/Tallinn",
    "iso:country":"EE",
    "name:est_x_preferred":[
        "Lipstu"
    ],
    "name:hye_x_preferred":[
        "\u053c\u056b\u057a\u057d\u057f\u0578\u0582"
    ],
    "name:pol_x_preferred":[
        "Lipstu"
    ],
    "name:sco_x_preferred":[
        "Lipstu"
    ],
    "name:spa_x_preferred":[
        "Lipstu"
    ],
    "name:vol_x_preferred":[
        "Lipstu"
    ],
    "wof:name":"Lipstu",
    "wof:placetype":"locality"
},
  "geometry": {"coordinates":[24.66667,58.98306],"type":"Point"}
}