{
  "type": "Feature",
  "properties": {
    "gn:admin1_code":"13.0",
    "gn:admin2_code":"668.0",
    "gn:admin3_code":"3724.0",
    "gn:asciiname":"Lipstu",
    "gn:country_code":"EE",
    "gn:dem":51,
    "gn:feature_class":"P",
    "gn:feature_code":"PPL",
    "gn:name":"Lipstu",
    "gn:population":0,
    "gn:timezone":"Europe/Tallinn",
    "iso:country":"EE",
    "wof:name":"Lipstu",
    "wof:placetype":"locality"
},
  "geometry": {"coordinates":[24.66667,58.98306],"type":"Point"}
}