{
  "type": "Feature",
  "properties": {
    "gn:admin1_code":"12.0",
    "gn:admin2_code":"708.0",
    "gn:admin3_code":"7981.0",
    "gn:asciiname":"UElejoe",
    "gn:country_code":"EE",
    "gn:dem":63,
    "gn:feature_class":"P",
    "gn:feature_code":"PPL",
    "gn:name":"\u00dclej\u00f5e",
    "gn:population":0,
    "gn:timezone":"Europe/Tallinn",
    "iso:country":"EE",
    "name:und_x_variant":[
        "\u00dclej\u00f5e",
        "V\u00e4ndramaarjms"
    ],
    "wof:lang_x_official":[
        "est"
    ],
    "wof:lang_x_spoken":[
        "est"
    ],
    "wof:name":"UElejoe",
    "wof:placetype":"locality"
},
  "geometry": {"coordinates":[27.21806,57.9875],"type":"Point"}
}