{
  "type": "Feature",
  "properties": {
    "gn:admin1_code":"14.0",
    "gn:admin2_code":"714.0",
    "gn:admin3_code":"4409.0",
    "gn:asciiname":"Purtsa",
    "gn:country_code":"EE",
    "gn:dem":23,
    "gn:feature_class":"P",
    "gn:feature_code":"PPL",
    "gn:name":"Purtsa",
    "gn:population":0,
    "gn:timezone":"Europe/Tallinn",
    "iso:country":"EE",
    "wof:name":"Purtsa",
    "wof:placetype":"locality"
},
  "geometry": {"coordinates":[22.55806,58.49278],"type":"Point"}
}