{
  "type": "Feature",
  "properties": {
    "gn:admin1_code":"8.0",
    "gn:admin2_code":"661.0",
    "gn:admin3_code":"1536.0",
    "gn:asciiname":"Eeskuela",
    "gn:country_code":"EE",
    "gn:dem":113,
    "gn:feature_class":"P",
    "gn:feature_code":"PPL",
    "gn:name":"Eesk\u00fcla",
    "gn:population":0,
    "gn:timezone":"Europe/Tallinn",
    "iso:country":"EE",
    "name:und_x_variant":[
        "Eesk\u00fcla"
    ],
    "wof:name":"Eeskuela",
    "wof:placetype":"locality"
},
  "geometry": {"coordinates":[26.29583,59.30028000000001],"type":"Point"}
}