{
  "type": "Feature",
  "properties": {
    "gn:admin1_code":"8.0",
    "gn:admin2_code":"661.0",
    "gn:admin3_code":"1536.0",
    "gn:asciiname":"Eeskuela",
    "gn:country_code":"EE",
    "gn:dem":113,
    "gn:feature_class":"P",
    "gn:feature_code":"PPL",
    "gn:name":"Eesk\u00fcla",
    "gn:population":0,
    "gn:timezone":"Europe/Tallinn",
    "iso:country":"EE",
    "name:est_x_preferred":[
        "Eesk\u00fcla"
    ],
    "name:fra_x_preferred":[
        "Eesk\u00fcla"
    ],
    "name:hye_x_preferred":[
        "\u0537\u0565\u057d\u056f\u0575\u0578\u0582\u056c\u0561"
    ],
    "name:vol_x_preferred":[
        "Eesk\u00fcla"
    ],
    "wof:coterminous":[
        1713308039
    ],
    "wof:lang_x_official":[
        "est"
    ],
    "wof:lang_x_spoken":[
        "est"
    ],
    "wof:name":"Eeskuela",
    "wof:placetype":"locality"
},
  "geometry": {"coordinates":[26.29583,59.30028],"type":"Point"}
}