{
  "type": "Feature",
  "properties": {
    "gn:admin1_code":"14.0",
    "gn:admin2_code":"714.0",
    "gn:admin3_code":"9630.0",
    "gn:asciiname":"Vohma",
    "gn:country_code":"EE",
    "gn:dem":16,
    "gn:feature_class":"P",
    "gn:feature_code":"PPL",
    "gn:name":"V\u00f5hma",
    "gn:population":0,
    "gn:timezone":"Europe/Tallinn",
    "iso:country":"EE",
    "name:und_x_variant":[
        "Vykhma",
        "V\u00f5hma"
    ],
    "wof:name":"Vohma",
    "wof:placetype":"locality"
},
  "geometry": {"coordinates":[22.85722,58.58221999999999],"type":"Point"}
}