{
  "type": "Feature",
  "properties": {
    "gn:admin1_code":"21.0",
    "gn:admin2_code":"917.0",
    "gn:admin3_code":"3333.0",
    "gn:asciiname":"Soemotsa",
    "gn:country_code":"EE",
    "gn:dem":220,
    "gn:feature_class":"P",
    "gn:feature_code":"PPL",
    "gn:name":"Soem\u00f5tsa",
    "gn:population":0,
    "gn:timezone":"Europe/Tallinn",
    "iso:country":"EE",
    "name:und_x_variant":[
        "Soem\u00f5tsa",
        "Soemetsa"
    ],
    "wof:lang_x_official":[
        "est"
    ],
    "wof:lang_x_spoken":[
        "est"
    ],
    "wof:name":"Soemotsa",
    "wof:placetype":"locality"
},
  "geometry": {"coordinates":[27.07472,57.76417],"type":"Point"}
}