{
  "type": "Feature",
  "properties": {
    "gn:gn_country":"EE",
    "gn:gn_fcode":"PPLX",
    "gn:gn_pop":2232,
    "iso:country":"EE",
    "name:ces_x_preferred":[
        "Kose"
    ],
    "name:dan_x_preferred":[
        "Kose"
    ],
    "name:est_x_preferred":[
        "Kose"
    ],
    "name:fra_x_preferred":[
        "Kose"
    ],
    "name:hye_x_preferred":[
        "\u053f\u0578\u057d\u0565"
    ],
    "name:nld_x_preferred":[
        "Kose"
    ],
    "name:pol_x_preferred":[
        "Kose"
    ],
    "name:rus_x_preferred":[
        "\u041a\u043e\u0437\u0435"
    ],
    "name:sco_x_preferred":[
        "Kose"
    ],
    "name:spa_x_preferred":[
        "Kose"
    ],
    "name:swe_x_preferred":[
        "Kose"
    ],
    "name:ukr_x_preferred":[
        "\u041a\u043e\u0437\u0435"
    ],
    "name:vol_x_preferred":[
        "Kose"
    ],
    "qs_pg:aaroncc":"EE",
    "qs_pg:gn_country":"EE",
    "qs_pg:gn_fcode":"PPLX",
    "qs_pg:gn_pop":2232,
    "qs_pg:name":"Kose",
    "qs_pg:name_adm0":"Eesti",
    "qs_pg:name_adm1":"Harjumaa",
    "qs_pg:photos":241,
    "qs_pg:photos_1k":49,
    "qs_pg:photos_9k":1,
    "qs_pg:photos_9r":4,
    "qs_pg:photos_all":241,
    "qs_pg:photos_sr":4,
    "qs_pg:pop_sr":4,
    "qs_pg:qs_pg_placetype":"neighbourhood",
    "qs_pg:qs_pg_placetype_gp":"Suburb",
    "qs_pg:woe_adm0":23424805,
    "woe:adm0_id":23424805,
    "woe:name_adm0":"Eesti",
    "woe:name_adm1":"Harjumaa",
    "woe:placetype":"Suburb",
    "wof:name":"Kose",
    "wof:placetype":"neighbourhood",
    "wof:population":2232
},
  "geometry": {"coordinates":[24.87833,59.45806],"type":"Point"}
}