{
  "type": "Feature",
  "properties": {
    "gn:admin1_code":"3.0",
    "gn:admin2_code":"511.0",
    "gn:asciiname":"Kreenholmi",
    "gn:cc2":"EE",
    "gn:country_code":"EE",
    "gn:dem":27,
    "gn:feature_class":"P",
    "gn:feature_code":"PPL",
    "gn:name":"Kreenholmi",
    "gn:population":0,
    "gn:timezone":"Europe/Tallinn",
    "iso:country":"EE",
    "name:und_x_variant":[
        "Kr\u00e4hnholm",
        "Kr\u00e4nholm",
        "Krengol\u2019m",
        "Kreenholm"
    ],
    "wof:name":"Kreenholmi",
    "wof:placetype":"locality"
},
  "geometry": {"coordinates":[28.17,59.36221999999999],"type":"Point"}
}