{
  "type": "Feature",
  "properties": {
    "gn:admin1_code":"3.0",
    "gn:admin2_code":"511.0",
    "gn:asciiname":"Kreenholmi",
    "gn:cc2":"EE",
    "gn:country_code":"EE",
    "gn:dem":27,
    "gn:feature_class":"P",
    "gn:feature_code":"PPL",
    "gn:name":"Kreenholmi",
    "gn:population":0,
    "gn:timezone":"Europe/Tallinn",
    "iso:country":"EE",
    "name:ces_x_preferred":[
        "Kreenholm"
    ],
    "name:deu_x_preferred":[
        "Kreenholm"
    ],
    "name:est_x_preferred":[
        "Kreenholm"
    ],
    "name:fra_x_preferred":[
        "Kreenholm"
    ],
    "name:hye_x_preferred":[
        "\u053f\u0580\u056b\u0576\u0570\u0578\u056c\u0574"
    ],
    "name:lit_x_preferred":[
        "Kr\u0117nholmas"
    ],
    "name:rus_x_preferred":[
        "\u041a\u0440\u0435\u043d\u0433\u043e\u043b\u044c\u043c"
    ],
    "name:swe_x_preferred":[
        "Kreenholm"
    ],
    "name:ukr_x_preferred":[
        "\u041a\u0440\u0435\u043d\u0433\u043e\u043b\u044c\u043c"
    ],
    "name:und_x_variant":[
        "Kr\u00e4hnholm",
        "Kr\u00e4nholm",
        "Krengol\u2019m"
    ],
    "wof:lang_x_official":[
        "est"
    ],
    "wof:lang_x_spoken":[
        "est"
    ],
    "wof:name":"Kreenholmi",
    "wof:placetype":"locality"
},
  "geometry": {"coordinates":[28.17,59.36222],"type":"Point"}
}