{
  "type": "Feature",
  "properties": {
    "gn:admin1_code":"18.0",
    "gn:admin2_code":"586.0",
    "gn:admin3_code":"3350.0",
    "gn:asciiname":"Vaeike-Kolkja",
    "gn:country_code":"EE",
    "gn:dem":37,
    "gn:feature_class":"P",
    "gn:feature_code":"PPL",
    "gn:name":"V\u00e4ike-Kolkja",
    "gn:population":0,
    "gn:timezone":"Europe/Tallinn",
    "iso:country":"EE",
    "name:und_x_variant":[
        "Vyayke Kolk\u2019ya",
        "Kolkja V\u00e4ike",
        "V\u00e4ike-Kolkja"
    ],
    "wof:lang_x_official":[
        "est"
    ],
    "wof:lang_x_spoken":[
        "est"
    ],
    "wof:name":"Vaeike-Kolkja",
    "wof:placetype":"locality"
},
  "geometry": {"coordinates":[27.21306,58.555],"type":"Point"}
}