{
  "type": "Feature",
  "properties": {
    "gn:admin1_code":"11.0",
    "gn:admin2_code":"712.0",
    "gn:admin3_code":"6919.0",
    "gn:asciiname":"Soosaare",
    "gn:cc2":"EE",
    "gn:country_code":"EE",
    "gn:dem":62,
    "gn:feature_class":"P",
    "gn:feature_code":"PPL",
    "gn:name":"Soosaare",
    "gn:population":0,
    "gn:timezone":"Europe/Tallinn",
    "iso:country":"EE",
    "name:und_x_variant":[
        "Sosare",
        "Soosaare"
    ],
    "wof:name":"Soosaare",
    "wof:placetype":"locality"
},
  "geometry": {"coordinates":[24.75222,58.01611],"type":"Point"}
}