{
  "type": "Feature",
  "properties": {
    "gn:admin1_code":"18.0",
    "gn:admin2_code":"796.0",
    "gn:admin3_code":"9680.0",
    "gn:asciiname":"Vaeaegvere",
    "gn:country_code":"EE",
    "gn:dem":53,
    "gn:feature_class":"P",
    "gn:feature_code":"PPL",
    "gn:name":"V\u00e4\u00e4gvere",
    "gn:population":0,
    "gn:timezone":"Europe/Tallinn",
    "iso:country":"EE",
    "wof:lang_x_official":[
        "est"
    ],
    "wof:lang_x_spoken":[
        "est"
    ],
    "wof:name":"Vaeaegvere",
    "wof:placetype":"locality"
},
  "geometry": {"coordinates":[26.84944,58.47389],"type":"Point"}
}