{
  "type": "Feature",
  "properties": {
    "gn:gn_country":"EE",
    "gn:gn_fcode":"PPL",
    "gn:gn_pop":212,
    "gn:population":212,
    "iso:country":"EE",
    "name:bul_x_preferred":[
        "\u0412\u0430\u0442\u043b\u0430"
    ],
    "name:ceb_x_preferred":[
        "Vatla"
    ],
    "name:deu_x_preferred":[
        "Vatla"
    ],
    "name:eng_x_preferred":[
        "Vatla"
    ],
    "name:est_x_preferred":[
        "Vatla"
    ],
    "name:fas_x_preferred":[
        "\u0648\u062a\u0644\u0627"
    ],
    "name:hye_x_preferred":[
        "\u054e\u0561\u057f\u056c\u0561"
    ],
    "name:nld_x_preferred":[
        "Vatla"
    ],
    "name:pol_x_preferred":[
        "Vatla"
    ],
    "name:spa_x_preferred":[
        "Vatla"
    ],
    "name:swe_x_preferred":[
        "Vatla"
    ],
    "name:ukr_x_preferred":[
        "\u0412\u0430\u0442\u043b\u0430"
    ],
    "name:unk_x_variant":[
        "Myza Vatla"
    ],
    "name:vol_x_preferred":[
        "Vatla"
    ],
    "qs_pg:aaroncc":"EE",
    "qs_pg:gn_country":"EE",
    "qs_pg:gn_fcode":"PPL",
    "qs_pg:gn_pop":212,
    "qs_pg:name":"Vatla",
    "qs_pg:name_adm0":"Eesti",
    "qs_pg:name_adm1":"L\u00e4\u00e4nemaa",
    "qs_pg:photos_9r":0,
    "qs_pg:photos_sr":0,
    "qs_pg:pop_sr":2,
    "qs_pg:qs_pg_placetype":"locality",
    "qs_pg:qs_pg_placetype_gp":"Town",
    "qs_pg:woe_adm0":23424805,
    "woe:adm0_id":23424805,
    "woe:name_adm0":"Eesti",
    "woe:name_adm1":"L\u00e4\u00e4nemaa",
    "woe:placetype":"Town",
    "wof:name":"Vatla",
    "wof:placetype":"locality",
    "wof:population":212
},
  "geometry": {"coordinates":[23.74056,58.55944],"type":"Point"}
}