{
  "type": "Feature",
  "properties": {
    "gn:admin1_code":"18.0",
    "gn:admin2_code":"171.0",
    "gn:admin3_code":"9211.0",
    "gn:asciiname":"Verevi",
    "gn:country_code":"EE",
    "gn:dem":42,
    "gn:feature_class":"P",
    "gn:feature_code":"PPL",
    "gn:name":"Verevi",
    "gn:population":0,
    "gn:timezone":"Europe/Tallinn",
    "iso:country":"EE",
    "name:eng_x_preferred":[
        "Verevi"
    ],
    "name:rus_x_preferred":[
        "\u0412\u0435\u0440\u0435\u0432\u0438"
    ],
    "wof:name":"Verevi",
    "wof:placetype":"locality"
},
  "geometry": {"coordinates":[26.19056,58.37667],"type":"Point"}
}