{
  "type": "Feature",
  "properties": {
    "gn:admin1_code":"18.0",
    "gn:admin2_code":"171.0",
    "gn:admin3_code":"9211.0",
    "gn:asciiname":"Verevi",
    "gn:country_code":"EE",
    "gn:dem":42,
    "gn:feature_class":"P",
    "gn:feature_code":"PPL",
    "gn:name":"Verevi",
    "gn:population":0,
    "gn:timezone":"Europe/Tallinn",
    "iso:country":"EE",
    "name:eng_x_preferred":[
        "Verevi"
    ],
    "name:est_x_preferred":[
        "Verevi"
    ],
    "name:fas_x_preferred":[
        "\u0648\u0631\u0648\u06cc"
    ],
    "name:hye_x_preferred":[
        "\u054e\u0565\u057c\u0587\u056b"
    ],
    "name:pol_x_preferred":[
        "Verevi"
    ],
    "name:rus_x_preferred":[
        "\u0412\u0435\u0440\u0435\u0432\u0438"
    ],
    "name:spa_x_preferred":[
        "Verevi"
    ],
    "name:ukr_x_preferred":[
        "\u0412\u0435\u0440\u0435\u0432\u0456"
    ],
    "name:vol_x_preferred":[
        "Verevi"
    ],
    "wof:coterminous":[
        1713313869
    ],
    "wof:lang_x_official":[
        "est"
    ],
    "wof:lang_x_spoken":[
        "est"
    ],
    "wof:name":"Verevi",
    "wof:placetype":"locality"
},
  "geometry": {"coordinates":[26.19056,58.37667],"type":"Point"}
}