{
  "type": "Feature",
  "properties": {
    "gn:admin1_code":"21.0",
    "gn:admin2_code":"142.0",
    "gn:admin3_code":"1303.0",
    "gn:asciiname":"Antsu",
    "gn:country_code":"EE",
    "gn:dem":62,
    "gn:feature_class":"P",
    "gn:feature_code":"PPL",
    "gn:name":"Antsu",
    "gn:population":0,
    "gn:timezone":"Europe/Tallinn",
    "iso:country":"EE",
    "name:est_x_preferred":[
        "Antsu"
    ],
    "name:hye_x_preferred":[
        "\u0531\u0576\u0581\u0578\u0582"
    ],
    "name:pol_x_preferred":[
        "Antsu"
    ],
    "name:sco_x_preferred":[
        "Antsu"
    ],
    "name:spa_x_preferred":[
        "Antsu"
    ],
    "name:ukr_x_preferred":[
        "\u0410\u043d\u0442\u0441\u0443"
    ],
    "name:vol_x_preferred":[
        "Antsu"
    ],
    "wof:name":"Antsu",
    "wof:placetype":"locality"
},
  "geometry": {"coordinates":[26.4475,57.85417],"type":"Point"}
}