{
  "type": "Feature",
  "properties": {
    "gn:admin1_code":"13.0",
    "gn:admin2_code":"503.0",
    "gn:admin3_code":"5921.0",
    "gn:asciiname":"Palase",
    "gn:country_code":"EE",
    "gn:dem":25,
    "gn:feature_class":"P",
    "gn:feature_code":"PPL",
    "gn:name":"Palase",
    "gn:population":0,
    "gn:timezone":"Europe/Tallinn",
    "iso:country":"EE",
    "name:est_x_preferred":[
        "Palase"
    ],
    "name:hye_x_preferred":[
        "\u054a\u0561\u056c\u0561\u057d\u0565"
    ],
    "name:pol_x_preferred":[
        "Palase"
    ],
    "name:sco_x_preferred":[
        "Palase"
    ],
    "name:spa_x_preferred":[
        "Palase"
    ],
    "name:swe_x_preferred":[
        "Palase"
    ],
    "wof:name":"Palase",
    "wof:placetype":"locality"
},
  "geometry": {"coordinates":[24.44972000000001,58.74278],"type":"Point"}
}