{
  "type": "Feature",
  "properties": {
    "gn:admin1_code":"21.0",
    "gn:admin2_code":"917.0",
    "gn:admin3_code":"8040.0",
    "gn:asciiname":"Kanamotsa",
    "gn:country_code":"EE",
    "gn:dem":95,
    "gn:feature_class":"P",
    "gn:feature_code":"PPL",
    "gn:name":"Kanam\u00f5tsa",
    "gn:population":0,
    "gn:timezone":"Europe/Tallinn",
    "iso:country":"EE",
    "name:und_x_variant":[
        "Kanam\u00f5tsa",
        "Kanametsa"
    ],
    "wof:name":"Kanamotsa",
    "wof:placetype":"locality"
},
  "geometry": {"coordinates":[26.90944,57.88721999999999],"type":"Point"}
}