{
  "type": "Feature",
  "properties": {
    "gn:admin1_code":"14.0",
    "gn:admin2_code":"714.0",
    "gn:admin3_code":"1466.0",
    "gn:asciiname":"Aula",
    "gn:country_code":"EE",
    "gn:dem":27,
    "gn:feature_class":"P",
    "gn:feature_code":"PPL",
    "gn:name":"Aula",
    "gn:population":0,
    "gn:timezone":"Europe/Tallinn",
    "iso:country":"EE",
    "wof:name":"Aula",
    "wof:placetype":"locality"
},
  "geometry": {"coordinates":[22.41944,58.38],"type":"Point"}
}