{
  "type": "Feature",
  "properties": {
    "gn:admin1_code":"13.0",
    "gn:admin2_code":"668.0",
    "gn:admin3_code":"3294.0",
    "gn:asciiname":"Koikse",
    "gn:cc2":"EE",
    "gn:country_code":"EE",
    "gn:dem":58,
    "gn:feature_class":"P",
    "gn:feature_code":"PPL",
    "gn:name":"Koikse",
    "gn:population":0,
    "gn:timezone":"Europe/Tallinn",
    "iso:country":"EE",
    "name:est_x_preferred":[
        "Koikse"
    ],
    "name:hye_x_preferred":[
        "\u053f\u0578\u056b\u056f\u057d\u0565"
    ],
    "name:pol_x_preferred":[
        "Koikse"
    ],
    "name:rus_x_preferred":[
        "\u041a\u043e\u0439\u043a\u0441\u0435"
    ],
    "name:sco_x_preferred":[
        "Koikse"
    ],
    "name:spa_x_preferred":[
        "Koikse"
    ],
    "name:und_x_variant":[
        "Koykse"
    ],
    "name:vol_x_preferred":[
        "Koikse"
    ],
    "wof:coterminous":[
        1713314593
    ],
    "wof:lang_x_official":[
        "est"
    ],
    "wof:lang_x_spoken":[
        "est"
    ],
    "wof:name":"Koikse",
    "wof:placetype":"locality"
},
  "geometry": {"coordinates":[24.67889,58.95889],"type":"Point"}
}