{
  "type": "Feature",
  "properties": {
    "gn:admin1_code":"4.0",
    "gn:admin2_code":"255.0",
    "gn:admin3_code":"5281.0",
    "gn:asciiname":"Maerjandi",
    "gn:country_code":"EE",
    "gn:dem":112,
    "gn:feature_class":"P",
    "gn:feature_code":"PPL",
    "gn:name":"M\u00e4rjandi",
    "gn:population":0,
    "gn:timezone":"Europe/Tallinn",
    "iso:country":"EE",
    "name:est_x_preferred":[
        "M\u00e4rjandi"
    ],
    "name:hye_x_preferred":[
        "\u0544\u0565\u057c\u0575\u0561\u0576\u0564\u056b"
    ],
    "name:pol_x_preferred":[
        "M\u00e4rjandi"
    ],
    "name:spa_x_preferred":[
        "M\u00e4rjandi"
    ],
    "name:ukr_x_preferred":[
        "\u041c\u044f\u0440'\u044f\u043d\u0434\u0456"
    ],
    "name:vol_x_preferred":[
        "M\u00e4rjandi"
    ],
    "wof:lang_x_official":[
        "est"
    ],
    "wof:lang_x_spoken":[
        "est"
    ],
    "wof:name":"Maerjandi",
    "wof:placetype":"locality"
},
  "geometry": {"coordinates":[25.78389,59.17028],"type":"Point"}
}