{
  "type": "Feature",
  "properties": {
    "gn:admin1_code":"20.0",
    "gn:admin2_code":"615.0",
    "gn:admin3_code":"2674.0",
    "gn:asciiname":"Kangrussaare",
    "gn:cc2":"EE",
    "gn:country_code":"EE",
    "gn:dem":50,
    "gn:feature_class":"P",
    "gn:feature_code":"PPL",
    "gn:name":"Kangrussaare",
    "gn:population":0,
    "gn:timezone":"Europe/Tallinn",
    "iso:country":"EE",
    "name:und_x_variant":[
        "Kangrusare",
        "Kangrusaare",
        "Kangrussaare"
    ],
    "wof:name":"Kangrussaare",
    "wof:placetype":"locality"
},
  "geometry": {"coordinates":[25.72972,58.62028000000001],"type":"Point"}
}