{
  "type": "Feature",
  "properties": {
    "gn:admin1_code":"13.0",
    "gn:admin2_code":"293.0",
    "gn:admin3_code":"4038.0",
    "gn:asciiname":"Laeste",
    "gn:country_code":"EE",
    "gn:dem":64,
    "gn:feature_class":"P",
    "gn:feature_code":"PPL",
    "gn:name":"Laeste",
    "gn:population":0,
    "gn:timezone":"Europe/Tallinn",
    "iso:country":"EE",
    "name:est_x_preferred":[
        "Laeste"
    ],
    "name:hye_x_preferred":[
        "\u053c\u0561\u0565\u057d\u057f\u0565"
    ],
    "name:pol_x_preferred":[
        "Laeste"
    ],
    "name:sco_x_preferred":[
        "Laeste"
    ],
    "name:spa_x_preferred":[
        "Laeste"
    ],
    "name:urd_x_preferred":[
        "\u0644\u0627\u06cc\u0633\u0679\u06cc"
    ],
    "name:vol_x_preferred":[
        "Laeste"
    ],
    "wof:name":"Laeste",
    "wof:placetype":"locality"
},
  "geometry": {"coordinates":[24.82917,58.88111],"type":"Point"}
}