{
  "type": "Feature",
  "properties": {
    "gn:country":"EE",
    "gn:fcode":"PPL",
    "gn:population":163,
    "iso:country":"EE",
    "name:ceb_x_preferred":[
        "\u00dcksnurme"
    ],
    "name:eng_x_preferred":[
        "\u00dcksnurme"
    ],
    "name:est_x_preferred":[
        "\u00dcksnurme"
    ],
    "name:fra_x_preferred":[
        "\u00dcksnurme"
    ],
    "name:hye_x_preferred":[
        "\u0545\u0578\u0582\u056f\u057d\u0576\u0578\u0582\u057c\u0574\u0565"
    ],
    "name:jpn_x_preferred":[
        "\u30a8\u30af\u30b9\u30cc\u30eb\u30e1"
    ],
    "name:mlg_x_preferred":[
        "\u00dcksnurme"
    ],
    "name:nld_x_preferred":[
        "\u00dcksnurme"
    ],
    "name:pol_x_preferred":[
        "\u00dcksnurme"
    ],
    "name:rus_x_preferred":[
        "\u042e\u043a\u0441\u043d\u0443\u0440\u043c\u0435"
    ],
    "name:spa_x_preferred":[
        "\u00dcksnurme"
    ],
    "name:swe_x_preferred":[
        "\u00dcksnurme"
    ],
    "name:und_x_variant":[
        "Yuksnurme"
    ],
    "name:vol_x_preferred":[
        "\u00dcksnurme"
    ],
    "qs_pg:aaroncc":"EE",
    "qs_pg:gn_country":"EE",
    "qs_pg:gn_fcode":"PPL",
    "qs_pg:gn_pop":163,
    "qs_pg:name":"\u00dcksnurme",
    "qs_pg:name_adm0":"Eesti",
    "qs_pg:name_adm1":"Harjumaa",
    "qs_pg:photos_9k":1,
    "qs_pg:photos_9r":1,
    "qs_pg:photos_all":11,
    "qs_pg:photos_sr":0,
    "qs_pg:pop_sr":1,
    "qs_pg:qs_pg_placetype":"locality",
    "qs_pg:qs_pg_placetype_gp":"Town",
    "qs_pg:woe_adm0":23424805,
    "woe:adm0_id":23424805,
    "woe:name_adm0":"Eesti",
    "woe:name_adm1":"Harjumaa",
    "woe:placetype":"Town",
    "wof:lang_x_official":[
        "est"
    ],
    "wof:lang_x_spoken":[
        "est"
    ],
    "wof:name":"\u00dcksnurme",
    "wof:placetype":"locality",
    "wof:population":163
},
  "geometry": {"coordinates":[24.61111,59.29194],"type":"Point"}
}