{
  "type": "Feature",
  "properties": {
    "gn:admin1_code":"21.0",
    "gn:admin2_code":"142.0",
    "gn:admin3_code":"2242.0",
    "gn:asciiname":"Andsi",
    "gn:country_code":"EE",
    "gn:dem":90,
    "gn:feature_class":"P",
    "gn:feature_code":"PPL",
    "gn:name":"Andsi",
    "gn:population":0,
    "gn:timezone":"Europe/Tallinn",
    "iso:country":"EE",
    "wof:name":"Andsi",
    "wof:placetype":"locality"
},
  "geometry": {"coordinates":[26.58833,57.76917],"type":"Point"}
}