{
  "type": "Feature",
  "properties": {
    "gn:admin1_code":"21.0",
    "gn:admin2_code":"698.0",
    "gn:admin3_code":"1968.0",
    "gn:asciiname":"Keraeandsu",
    "gn:country_code":"EE",
    "gn:dem":78,
    "gn:feature_class":"P",
    "gn:feature_code":"PPL",
    "gn:name":"Ker\u00e4andsu",
    "gn:population":0,
    "gn:timezone":"Europe/Tallinn",
    "iso:country":"EE",
    "name:und_x_variant":[
        "Ker\u00e4andsu",
        "Kerahansu"
    ],
    "wof:lang_x_official":[
        "est"
    ],
    "wof:lang_x_spoken":[
        "est"
    ],
    "wof:name":"Keraeandsu",
    "wof:placetype":"locality"
},
  "geometry": {"coordinates":[26.58028,57.62778],"type":"Point"}
}