{
  "type": "Feature",
  "properties": {
    "gn:admin1_code":"13.0",
    "gn:admin2_code":"293.0",
    "gn:admin3_code":"6937.0",
    "gn:asciiname":"Ellamaa",
    "gn:country_code":"EE",
    "gn:dem":47,
    "gn:feature_class":"P",
    "gn:feature_code":"PPL",
    "gn:name":"Ellamaa",
    "gn:population":0,
    "gn:timezone":"Europe/Tallinn",
    "iso:country":"EE",
    "name:est_x_preferred":[
        "Ellamaa"
    ],
    "name:hye_x_preferred":[
        "\u0537\u056c\u056c\u0561\u0574\u0561\u0561"
    ],
    "name:pol_x_preferred":[
        "Ellamaa"
    ],
    "name:sco_x_preferred":[
        "Ellamaa"
    ],
    "name:spa_x_preferred":[
        "Ellamaa"
    ],
    "name:und_x_variant":[
        "Ellama",
        "Ellamaa"
    ],
    "name:vol_x_preferred":[
        "Ellamaa"
    ],
    "wof:name":"Ellamaa",
    "wof:placetype":"locality"
},
  "geometry": {"coordinates":[24.94639,58.71333000000001],"type":"Point"}
}