{
  "type": "Feature",
  "properties": {
    "gn:admin1_code":"4.0",
    "gn:admin2_code":"255.0",
    "gn:admin3_code":"9623.0",
    "gn:asciiname":"Vaeike-Kareda",
    "gn:country_code":"EE",
    "gn:dem":73,
    "gn:feature_class":"P",
    "gn:feature_code":"PPL",
    "gn:name":"V\u00e4ike-Kareda",
    "gn:population":0,
    "gn:timezone":"Europe/Tallinn",
    "iso:country":"EE",
    "name:eng_x_preferred":[
        "V\u00e4ike-Kareda"
    ],
    "name:est_x_preferred":[
        "V\u00e4ike-Kareda"
    ],
    "name:fra_x_preferred":[
        "V\u00e4ike-Kareda"
    ],
    "name:hye_x_preferred":[
        "\u054e\u0565\u056b\u056f\u0565-\u053f\u0561\u057c\u0565\u0564\u0561"
    ],
    "name:pol_x_preferred":[
        "V\u00e4ike-Kareda"
    ],
    "name:rus_x_preferred":[
        "\u0412\u044f\u0439\u043a\u0435-\u041a\u044f\u0440\u0435\u0434\u0430"
    ],
    "name:spa_x_preferred":[
        "V\u00e4ike-Kareda"
    ],
    "name:ukr_x_preferred":[
        "\u0412\u044f\u0439\u043a\u0435-\u041a\u0430\u0440\u0435\u0434\u0430"
    ],
    "name:und_x_variant":[
        "Kareda V\u00e4ike",
        "V\u00e4ika-Kareda",
        "Vyayke Kareda",
        "V\u00e4ike-Kareda"
    ],
    "name:vol_x_preferred":[
        "V\u00e4ike-Kareda"
    ],
    "wof:name":"Vaeike-Kareda",
    "wof:placetype":"locality"
},
  "geometry": {"coordinates":[25.805,58.88166999999999],"type":"Point"}
}