{
  "type": "Feature",
  "properties": {
    "gn:admin1_code":"3.0",
    "gn:admin2_code":"442.0",
    "gn:admin3_code":"5652.0",
    "gn:asciiname":"Ojamaa",
    "gn:country_code":"EE",
    "gn:dem":50,
    "gn:feature_class":"P",
    "gn:feature_code":"PPL",
    "gn:name":"Ojamaa",
    "gn:population":0,
    "gn:timezone":"Europe/Tallinn",
    "iso:country":"EE",
    "name:und_x_variant":[
        "Ojama"
    ],
    "wof:name":"Ojamaa",
    "wof:placetype":"locality"
},
  "geometry": {"coordinates":[27.11389,59.28694],"type":"Point"}
}