{
  "type": "Feature",
  "properties": {
    "gn:admin1_code":"12.0",
    "gn:admin2_code":"284.0",
    "gn:admin3_code":"3280.0",
    "gn:asciiname":"Koigera",
    "gn:country_code":"EE",
    "gn:dem":121,
    "gn:feature_class":"P",
    "gn:feature_code":"PPL",
    "gn:name":"Koigera",
    "gn:population":0,
    "gn:timezone":"Europe/Tallinn",
    "iso:country":"EE",
    "name:est_x_preferred":[
        "Koigera"
    ],
    "name:hye_x_preferred":[
        "\u053f\u0578\u056b\u0563\u0565\u057c\u0561"
    ],
    "name:pol_x_preferred":[
        "Koigera"
    ],
    "name:spa_x_preferred":[
        "Koigera"
    ],
    "name:ukr_x_preferred":[
        "\u041a\u043e\u0457\u0433\u0435\u0440\u0430"
    ],
    "name:vol_x_preferred":[
        "Koigera"
    ],
    "wof:coterminous":[
        1713316081
    ],
    "wof:lang_x_official":[
        "est"
    ],
    "wof:lang_x_spoken":[
        "est"
    ],
    "wof:name":"Koigera",
    "wof:placetype":"locality"
},
  "geometry": {"coordinates":[26.75417,57.93361],"type":"Point"}
}