{
  "type": "Feature",
  "properties": {
    "gn:admin1_code":"21.0",
    "gn:admin2_code":"698.0",
    "gn:admin3_code":"5732.0",
    "gn:asciiname":"Ortumaee",
    "gn:country_code":"EE",
    "gn:dem":215,
    "gn:feature_class":"P",
    "gn:feature_code":"PPL",
    "gn:name":"Ortum\u00e4e",
    "gn:population":0,
    "gn:timezone":"Europe/Tallinn",
    "iso:country":"EE",
    "name:est_x_preferred":[
        "Ortum\u00e4e"
    ],
    "name:hye_x_preferred":[
        "\u0555\u057c\u057f\u0578\u0582\u0574\u0575\u0561\u0565"
    ],
    "name:myv_x_preferred":[
        "\u041e\u0440\u0442\u0443\u043c\u044f\u044d"
    ],
    "name:pol_x_preferred":[
        "Ortum\u00e4e"
    ],
    "name:spa_x_preferred":[
        "Ortum\u00e4e"
    ],
    "name:ukr_x_preferred":[
        "\u041e\u0440\u0442\u0443\u043c\u044f\u0435"
    ],
    "name:und_x_variant":[
        "Ortim\u00e4e"
    ],
    "name:vol_x_preferred":[
        "Ortum\u00e4e"
    ],
    "wof:coterminous":[
        1713314797
    ],
    "wof:lang_x_official":[
        "est"
    ],
    "wof:lang_x_spoken":[
        "est"
    ],
    "wof:name":"Ortumaee",
    "wof:placetype":"locality"
},
  "geometry": {"coordinates":[26.99833,57.67111],"type":"Point"}
}