{
  "type": "Feature",
  "properties": {
    "gn:admin1_code":"18.0",
    "gn:admin2_code":"283.0",
    "gn:admin3_code":"2119.0",
    "gn:asciiname":"Ivaste",
    "gn:country_code":"EE",
    "gn:dem":143,
    "gn:feature_class":"P",
    "gn:feature_code":"PPL",
    "gn:name":"Ivaste",
    "gn:population":0,
    "gn:timezone":"Europe/Tallinn",
    "iso:country":"EE",
    "name:est_x_preferred":[
        "Ivaste"
    ],
    "name:fra_x_preferred":[
        "Ivaste"
    ],
    "name:hye_x_preferred":[
        "\u053b\u057e\u0561\u057d\u057f\u0565"
    ],
    "name:pol_x_preferred":[
        "Ivaste"
    ],
    "name:spa_x_preferred":[
        "Ivaste"
    ],
    "name:ukr_x_preferred":[
        "\u0406\u0432\u0430\u0441\u0442\u0435"
    ],
    "name:vol_x_preferred":[
        "Ivaste"
    ],
    "wof:name":"Ivaste",
    "wof:placetype":"locality"
},
  "geometry": {"coordinates":[26.63667,58.1625],"type":"Point"}
}