{
  "type": "Feature",
  "properties": {
    "gn:admin1_code":"3.0",
    "gn:admin2_code":"130.0",
    "gn:admin3_code":"2586.0",
    "gn:asciiname":"Kalina",
    "gn:country_code":"EE",
    "gn:dem":77,
    "gn:feature_class":"P",
    "gn:feature_code":"PPL",
    "gn:name":"Kalina",
    "gn:population":0,
    "gn:timezone":"Europe/Tallinn",
    "iso:country":"EE",
    "name:deu_x_preferred":[
        "Kalina"
    ],
    "name:est_x_preferred":[
        "Kalina"
    ],
    "name:hye_x_preferred":[
        "\u053f\u0561\u056c\u056b\u0576\u0561"
    ],
    "name:nld_x_preferred":[
        "Kalina"
    ],
    "name:pol_x_preferred":[
        "Kalina"
    ],
    "name:spa_x_preferred":[
        "Kalina"
    ],
    "name:vol_x_preferred":[
        "Kalina"
    ],
    "wof:name":"Kalina",
    "wof:placetype":"locality"
},
  "geometry": {"coordinates":[27.33361,59.26778],"type":"Point"}
}