{
  "type": "Feature",
  "properties": {
    "gn:admin1_code":"21.0",
    "gn:admin2_code":"142.0",
    "gn:admin3_code":"9290.0",
    "gn:asciiname":"Kaudsi",
    "gn:country_code":"EE",
    "gn:dem":79,
    "gn:feature_class":"P",
    "gn:feature_code":"PPL",
    "gn:name":"Kaudsi",
    "gn:population":0,
    "gn:timezone":"Europe/Tallinn",
    "iso:country":"EE",
    "name:und_x_variant":[
        "Kautsi"
    ],
    "wof:name":"Kaudsi",
    "wof:placetype":"locality"
},
  "geometry": {"coordinates":[26.58167000000001,57.70222],"type":"Point"}
}