{
  "type": "Feature",
  "properties": {
    "gn:admin1_code":"8.0",
    "gn:admin2_code":"901.0",
    "gn:admin3_code":"9153.0",
    "gn:asciiname":"Leo",
    "gn:country_code":"EE",
    "gn:dem":134,
    "gn:feature_class":"P",
    "gn:feature_code":"PPL",
    "gn:name":"Leo",
    "gn:population":0,
    "gn:timezone":"Europe/Tallinn",
    "iso:country":"EE",
    "name:und_x_variant":[
        "Loo",
        "Leo"
    ],
    "wof:name":"Leo",
    "wof:placetype":"locality"
},
  "geometry": {"coordinates":[26.39389000000001,59.21556],"type":"Point"}
}