{
  "type": "Feature",
  "properties": {
    "gn:country":"EE",
    "gn:fcode":"PPL",
    "gn:population":164,
    "iso:country":"EE",
    "name:bul_x_preferred":[
        "\u041f\u0430\u043b\u0432\u0435\u0440\u0435"
    ],
    "name:ceb_x_preferred":[
        "Palvere"
    ],
    "name:eng_x_preferred":[
        "Palvere"
    ],
    "name:est_x_preferred":[
        "Palvere"
    ],
    "name:fra_x_preferred":[
        "Palvere"
    ],
    "name:hye_x_preferred":[
        "\u054a\u0561\u056c\u057e\u0565\u057c\u0565"
    ],
    "name:nld_x_preferred":[
        "Palvere"
    ],
    "name:pol_x_preferred":[
        "Palvere"
    ],
    "name:spa_x_preferred":[
        "Palvere"
    ],
    "name:swe_x_preferred":[
        "Palvere"
    ],
    "name:vol_x_preferred":[
        "Palvere"
    ],
    "qs_pg:aaroncc":"EE",
    "qs_pg:gn_country":"EE",
    "qs_pg:gn_fcode":"PPL",
    "qs_pg:gn_pop":164,
    "qs_pg:name":"Palvere",
    "qs_pg:name_adm0":"Eesti",
    "qs_pg:name_adm1":"Harjumaa",
    "qs_pg:photos_9r":0,
    "qs_pg:photos_sr":0,
    "qs_pg:pop_sr":1,
    "qs_pg:qs_pg_placetype":"locality",
    "qs_pg:qs_pg_placetype_gp":"Town",
    "qs_pg:woe_adm0":23424805,
    "woe:adm0_id":23424805,
    "woe:name_adm0":"Eesti",
    "woe:name_adm1":"Harjumaa",
    "woe:placetype":"Town",
    "wof:lang_x_official":[
        "est"
    ],
    "wof:lang_x_spoken":[
        "est"
    ],
    "wof:name":"Palvere",
    "wof:placetype":"locality",
    "wof:population":164
},
  "geometry": {"coordinates":[25.25611,59.19778],"type":"Point"}
}