{
  "type": "Feature",
  "properties": {
    "gn:admin1_code":"18.0",
    "gn:admin2_code":"586.0",
    "gn:admin3_code":"9150.0",
    "gn:asciiname":"Kogri",
    "gn:country_code":"EE",
    "gn:dem":84,
    "gn:feature_class":"P",
    "gn:feature_code":"PPL",
    "gn:name":"Kogri",
    "gn:population":0,
    "gn:timezone":"Europe/Tallinn",
    "iso:country":"EE",
    "name:und_x_variant":[
        "Konsa"
    ],
    "wof:name":"Kogri",
    "wof:placetype":"locality"
},
  "geometry": {"coordinates":[26.95083,58.62889000000001],"type":"Point"}
}