{
  "type": "Feature",
  "properties": {
    "gn:admin1_code":"18.0",
    "gn:admin2_code":"586.0",
    "gn:admin3_code":"9150.0",
    "gn:asciiname":"Kogri",
    "gn:country_code":"EE",
    "gn:dem":84,
    "gn:feature_class":"P",
    "gn:feature_code":"PPL",
    "gn:name":"Kogri",
    "gn:population":0,
    "gn:timezone":"Europe/Tallinn",
    "iso:country":"EE",
    "name:deu_x_preferred":[
        "Kogri"
    ],
    "name:est_x_preferred":[
        "Kogri"
    ],
    "name:hye_x_preferred":[
        "\u053f\u0578\u0563\u057c\u056b"
    ],
    "name:pol_x_preferred":[
        "Kogri"
    ],
    "name:spa_x_preferred":[
        "Kogri"
    ],
    "name:und_x_variant":[
        "Konsa"
    ],
    "name:vol_x_preferred":[
        "Kogri"
    ],
    "wof:lang_x_official":[
        "est"
    ],
    "wof:lang_x_spoken":[
        "est"
    ],
    "wof:name":"Kogri",
    "wof:placetype":"locality"
},
  "geometry": {"coordinates":[26.95083,58.62889],"type":"Point"}
}