{
  "type": "Feature",
  "properties": {
    "gn:gn_country":"EE",
    "iso:country":"EE",
    "name:deu_x_preferred":[
        "V\u00f5ik\u00fcla"
    ],
    "name:eng_x_preferred":[
        "V\u00f5ik\u00fcla"
    ],
    "name:est_x_preferred":[
        "V\u00f5ik\u00fcla"
    ],
    "name:hye_x_preferred":[
        "\u054e\u056b\u056b\u056f\u0575\u0578\u0582\u056c\u0561"
    ],
    "name:nld_x_preferred":[
        "V\u00f5ik\u00fcla"
    ],
    "name:pol_x_preferred":[
        "V\u00f5ik\u00fcla"
    ],
    "name:spa_x_preferred":[
        "V\u00f5ik\u00fcla"
    ],
    "name:vol_x_preferred":[
        "V\u00f5ik\u00fcla"
    ],
    "qs_pg:aaroncc":"EE",
    "qs_pg:gn_country":"EE",
    "qs_pg:name":"V\u00f5ik\u00fcla",
    "qs_pg:name_adm0":"Eesti",
    "qs_pg:name_adm1":"Saaremaa",
    "qs_pg:photos":1,
    "qs_pg:photos_1k":1,
    "qs_pg:photos_9k":1,
    "qs_pg:photos_9r":1,
    "qs_pg:photos_all":1,
    "qs_pg:photos_sr":1,
    "qs_pg:pop_sr":0,
    "qs_pg:qs_pg_placetype":"locality",
    "qs_pg:qs_pg_placetype_gp":"Town",
    "qs_pg:woe_adm0":23424805,
    "woe:adm0_id":23424805,
    "woe:name_adm0":"Eesti",
    "woe:name_adm1":"Saaremaa",
    "woe:placetype":"Town",
    "wof:name":"V\u00f5ik\u00fcla",
    "wof:placetype":"locality"
},
  "geometry": {"coordinates":[23.44345,58.57416],"type":"Point"}
}