{
  "type": "Feature",
  "properties": {
    "gn:admin1_code":"11.0",
    "gn:admin2_code":"430.0",
    "gn:admin3_code":"4881.0",
    "gn:asciiname":"Mereaeaerse",
    "gn:country_code":"EE",
    "gn:dem":15,
    "gn:feature_class":"P",
    "gn:feature_code":"PPL",
    "gn:name":"Mere\u00e4\u00e4rse",
    "gn:population":0,
    "gn:timezone":"Europe/Tallinn",
    "iso:country":"EE",
    "name:est_x_preferred":[
        "Mere\u00e4\u00e4rse"
    ],
    "name:hye_x_preferred":[
        "\u0544\u0565\u057c\u0565\u0565\u057c\u057d\u0565"
    ],
    "name:pol_x_preferred":[
        "Mere\u00e4\u00e4rse"
    ],
    "name:spa_x_preferred":[
        "Mere\u00e4\u00e4rse"
    ],
    "name:vol_x_preferred":[
        "Mere\u00e4\u00e4rse"
    ],
    "wof:lang_x_official":[
        "est"
    ],
    "wof:lang_x_spoken":[
        "est"
    ],
    "wof:name":"Mereaeaerse",
    "wof:placetype":"locality"
},
  "geometry": {"coordinates":[23.70194,58.45694],"type":"Point"}
}