{
  "type": "Feature",
  "properties": {
    "gn:admin1_code":"11.0",
    "gn:admin2_code":"712.0",
    "gn:admin3_code":"2370.0",
    "gn:asciiname":"Kiisa",
    "gn:country_code":"EE",
    "gn:dem":62,
    "gn:feature_class":"P",
    "gn:feature_code":"PPL",
    "gn:name":"Kiisa",
    "gn:population":0,
    "gn:timezone":"Europe/Tallinn",
    "iso:country":"EE",
    "name:und_x_variant":[
        "Kiissa"
    ],
    "wof:name":"Kiisa",
    "wof:placetype":"locality"
},
  "geometry": {"coordinates":[25.0075,58.02028000000001],"type":"Point"}
}