{
  "type": "Feature",
  "properties": {
    "gn:admin1_code":"12.0",
    "gn:admin2_code":"708.0",
    "gn:admin3_code":"2140.0",
    "gn:asciiname":"Palopaeae",
    "gn:country_code":"EE",
    "gn:dem":50,
    "gn:feature_class":"P",
    "gn:feature_code":"PPL",
    "gn:name":"Palop\u00e4\u00e4",
    "gn:population":0,
    "gn:timezone":"Europe/Tallinn",
    "iso:country":"EE",
    "wof:lang_x_official":[
        "est"
    ],
    "wof:lang_x_spoken":[
        "est"
    ],
    "wof:name":"Palopaeae",
    "wof:placetype":"locality"
},
  "geometry": {"coordinates":[27.33139,58.07556],"type":"Point"}
}