{
  "type": "Feature",
  "properties": {
    "gn:admin1_code":"19.0",
    "gn:admin2_code":"855.0",
    "gn:admin3_code":"3951.0",
    "gn:asciiname":"Kaeaerikmaee",
    "gn:country_code":"EE",
    "gn:dem":105,
    "gn:feature_class":"P",
    "gn:feature_code":"PPL",
    "gn:name":"K\u00e4\u00e4rikm\u00e4e",
    "gn:population":0,
    "gn:timezone":"Europe/Tallinn",
    "iso:country":"EE",
    "name:est_x_preferred":[
        "K\u00e4\u00e4rikm\u00e4e"
    ],
    "name:hye_x_preferred":[
        "\u053f\u0565\u0565\u057c\u056b\u056f\u0574\u0575\u0561\u0565"
    ],
    "name:pol_x_preferred":[
        "K\u00e4\u00e4rikm\u00e4e"
    ],
    "name:spa_x_preferred":[
        "K\u00e4\u00e4rikm\u00e4e"
    ],
    "name:ukr_x_preferred":[
        "\u041a\u044f\u0435\u0440\u0456\u043a\u043c\u044f\u0435"
    ],
    "name:vol_x_preferred":[
        "K\u00e4\u00e4rikm\u00e4e"
    ],
    "wof:name":"Kaeaerikmaee",
    "wof:placetype":"locality"
},
  "geometry": {"coordinates":[26.34694,57.75778],"type":"Point"}
}