{
  "type": "Feature",
  "properties": {
    "gn:gn_country":"EE",
    "gn:gn_fcode":"PPL",
    "gn:gn_pop":150,
    "gn:population":150,
    "iso:country":"EE",
    "name:arm_x_preferred":[
        "\u0535\u057f\u056b"
    ],
    "name:dut_x_preferred":[
        "Jeti"
    ],
    "name:eng_x_preferred":[
        "Jeti"
    ],
    "name:est_x_preferred":[
        "Jeti"
    ],
    "name:pol_x_preferred":[
        "Jeti"
    ],
    "name:swe_x_preferred":[
        "Jeti"
    ],
    "name:vol_x_preferred":[
        "Jeti"
    ],
    "qs_pg:aaroncc":"EE",
    "qs_pg:gn_country":"EE",
    "qs_pg:gn_fcode":"PPL",
    "qs_pg:gn_pop":150,
    "qs_pg:name":"Jeti",
    "qs_pg:name_adm0":"Eesti",
    "qs_pg:name_adm1":"Valgamaa",
    "qs_pg:photos_9k":1,
    "qs_pg:photos_9r":1,
    "qs_pg:photos_all":6,
    "qs_pg:photos_sr":0,
    "qs_pg:pop_sr":1,
    "qs_pg:qs_pg_placetype":"locality",
    "qs_pg:qs_pg_placetype_gp":"Town",
    "qs_pg:woe_adm0":23424805,
    "woe:adm0_id":23424805,
    "woe:name_adm0":"Eesti",
    "woe:name_adm1":"Valgamaa",
    "woe:placetype":"Town",
    "wof:name":"Jeti",
    "wof:placetype":"locality",
    "wof:population":150
},
  "geometry": {"coordinates":[25.88083,57.92167],"type":"Point"}
}