{
  "type": "Feature",
  "properties": {
    "gn:admin1_code":"11.0",
    "gn:admin2_code":"638.0",
    "gn:admin3_code":"3666.0",
    "gn:asciiname":"Kurgja",
    "gn:country_code":"EE",
    "gn:dem":51,
    "gn:feature_class":"P",
    "gn:feature_code":"PPL",
    "gn:name":"Kurgja",
    "gn:population":0,
    "gn:timezone":"Europe/Tallinn",
    "iso:country":"EE",
    "name:est_x_preferred":[
        "Kurgja"
    ],
    "name:fra_x_preferred":[
        "Kurgja"
    ],
    "name:hye_x_preferred":[
        "\u053f\u0578\u0582\u057c\u0563\u0575\u0561"
    ],
    "name:pol_x_preferred":[
        "Kurgja"
    ],
    "name:spa_x_preferred":[
        "Kurgja"
    ],
    "name:vol_x_preferred":[
        "Kurgja"
    ],
    "wof:name":"Kurgja",
    "wof:placetype":"locality"
},
  "geometry": {"coordinates":[25.24861,58.66806],"type":"Point"}
}