{
  "type": "Feature",
  "properties": {
    "gn:admin1_code":"14.0",
    "gn:admin2_code":"714.0",
    "gn:admin3_code":"2097.0",
    "gn:asciiname":"Irase",
    "gn:country_code":"EE",
    "gn:dem":17,
    "gn:feature_class":"P",
    "gn:feature_code":"PPL",
    "gn:name":"Irase",
    "gn:population":0,
    "gn:timezone":"Europe/Tallinn",
    "iso:country":"EE",
    "wof:name":"Irase",
    "wof:placetype":"locality"
},
  "geometry": {"coordinates":[22.43917,58.33111],"type":"Point"}
}