{
  "type": "Feature",
  "properties": {
    "gn:admin1_code":"21.0",
    "gn:admin2_code":"917.0",
    "gn:admin3_code":"8081.0",
    "gn:asciiname":"Plessi",
    "gn:country_code":"EE",
    "gn:dem":144,
    "gn:feature_class":"P",
    "gn:feature_code":"PPL",
    "gn:name":"Plessi",
    "gn:population":0,
    "gn:timezone":"Europe/Tallinn",
    "iso:country":"EE",
    "name:est_x_preferred":[
        "Plessi"
    ],
    "name:hye_x_preferred":[
        "\u054a\u056c\u0565\u057d\u057d\u056b"
    ],
    "name:nld_x_preferred":[
        "Plessi"
    ],
    "name:pol_x_preferred":[
        "Plessi"
    ],
    "name:spa_x_preferred":[
        "Plessi"
    ],
    "name:ukr_x_preferred":[
        "\u041f\u043b\u0435\u0441\u0441\u0456"
    ],
    "name:vol_x_preferred":[
        "Plessi"
    ],
    "wof:name":"Plessi",
    "wof:placetype":"locality"
},
  "geometry": {"coordinates":[27.36417,57.7425],"type":"Point"}
}