{
  "type": "Feature",
  "properties": {
    "gn:admin1_code":"21.0",
    "gn:admin2_code":"917.0",
    "gn:admin3_code":"8081.0",
    "gn:asciiname":"Plessi",
    "gn:country_code":"EE",
    "gn:dem":144,
    "gn:feature_class":"P",
    "gn:feature_code":"PPL",
    "gn:name":"Plessi",
    "gn:population":0,
    "gn:timezone":"Europe/Tallinn",
    "iso:country":"EE",
    "wof:name":"Plessi",
    "wof:placetype":"locality"
},
  "geometry": {"coordinates":[27.36417,57.7425],"type":"Point"}
}