{
  "type": "Feature",
  "properties": {
    "gn:admin1_code":"5.0",
    "gn:admin2_code":"618.0",
    "gn:admin3_code":"8113.0",
    "gn:asciiname":"Alaveski",
    "gn:country_code":"EE",
    "gn:dem":55,
    "gn:feature_class":"P",
    "gn:feature_code":"PPL",
    "gn:name":"Alaveski",
    "gn:population":0,
    "gn:timezone":"Europe/Tallinn",
    "iso:country":"EE",
    "wof:lang_x_official":[
        "est"
    ],
    "wof:lang_x_spoken":[
        "est"
    ],
    "wof:name":"Alaveski",
    "wof:placetype":"locality"
},
  "geometry": {"coordinates":[26.33333,58.63333],"type":"Point"}
}