{
  "type": "Feature",
  "properties": {
    "gn:admin1_code":"8.0",
    "gn:admin2_code":"191.0",
    "gn:admin3_code":"4331.0",
    "gn:asciiname":"Lihulope",
    "gn:country_code":"EE",
    "gn:dem":87,
    "gn:feature_class":"P",
    "gn:feature_code":"PPL",
    "gn:name":"Lihul\u00f5pe",
    "gn:population":0,
    "gn:timezone":"Europe/Tallinn",
    "iso:country":"EE",
    "name:est_x_preferred":[
        "Lihul\u00f5pe"
    ],
    "name:hye_x_preferred":[
        "\u053c\u056b\u0570\u0578\u0582\u056c\u056b\u057a\u0565"
    ],
    "name:pol_x_preferred":[
        "Lihul\u00f5pe"
    ],
    "name:vol_x_preferred":[
        "Lihul\u00f5pe"
    ],
    "wof:coterminous":[
        1713314531
    ],
    "wof:lang_x_official":[
        "est"
    ],
    "wof:lang_x_spoken":[
        "est"
    ],
    "wof:name":"Lihulope",
    "wof:placetype":"locality"
},
  "geometry": {"coordinates":[26.23722,59.4125],"type":"Point"}
}