{
  "type": "Feature",
  "properties": {
    "gn:admin1_code":"14.0",
    "gn:admin2_code":"714.0",
    "gn:admin3_code":"2922.0",
    "gn:asciiname":"Kehila",
    "gn:cc2":"EE",
    "gn:country_code":"EE",
    "gn:dem":22,
    "gn:feature_class":"P",
    "gn:feature_code":"PPL",
    "gn:name":"Kehila",
    "gn:population":0,
    "gn:timezone":"Europe/Tallinn",
    "iso:country":"EE",
    "name:und_x_variant":[
        "Kekhila",
        "Kehtla",
        "Kehila"
    ],
    "wof:name":"Kehila",
    "wof:placetype":"locality"
},
  "geometry": {"coordinates":[22.05917,58.41361],"type":"Point"}
}