{
  "type": "Feature",
  "properties": {
    "gn:admin1_code":"14.0",
    "gn:admin2_code":"714.0",
    "gn:admin3_code":"2922.0",
    "gn:asciiname":"Kehila",
    "gn:cc2":"EE",
    "gn:country_code":"EE",
    "gn:dem":22,
    "gn:feature_class":"P",
    "gn:feature_code":"PPL",
    "gn:name":"Kehila",
    "gn:population":0,
    "gn:timezone":"Europe/Tallinn",
    "iso:country":"EE",
    "name:deu_x_preferred":[
        "Kehila"
    ],
    "name:est_x_preferred":[
        "Kehila"
    ],
    "name:fra_x_preferred":[
        "Kehila"
    ],
    "name:hye_x_preferred":[
        "\u053f\u0565\u0570\u056b\u056c\u0561"
    ],
    "name:pol_x_preferred":[
        "Kehila"
    ],
    "name:spa_x_preferred":[
        "Kehila"
    ],
    "name:und_x_variant":[
        "Kekhila",
        "Kehtla",
        "Kehila"
    ],
    "name:vol_x_preferred":[
        "Kehila"
    ],
    "wof:name":"Kehila",
    "wof:placetype":"locality"
},
  "geometry": {"coordinates":[22.05917,58.41361],"type":"Point"}
}