{
  "type": "Feature",
  "properties": {
    "gn:admin1_code":"18.0",
    "gn:admin2_code":"796.0",
    "gn:admin3_code":"5769.0",
    "gn:asciiname":"Kadrina",
    "gn:country_code":"EE",
    "gn:dem":62,
    "gn:feature_class":"P",
    "gn:feature_code":"PPL",
    "gn:name":"Kadrina",
    "gn:population":0,
    "gn:timezone":"Europe/Tallinn",
    "iso:country":"EE",
    "name:ceb_x_preferred":[
        "Kadrina"
    ],
    "name:ces_x_preferred":[
        "Kadrina"
    ],
    "name:est_x_preferred":[
        "Kadrina"
    ],
    "name:fra_x_preferred":[
        "Kadrina"
    ],
    "name:hye_x_preferred":[
        "\u053f\u0561\u0564\u057c\u056b\u0576\u0561"
    ],
    "name:lit_x_preferred":[
        "Kadrina"
    ],
    "name:nld_x_preferred":[
        "Kadrina"
    ],
    "name:ron_x_preferred":[
        "Kadrina"
    ],
    "name:rus_x_preferred":[
        "\u041a\u0430\u0434\u0440\u0438\u043d\u0430"
    ],
    "name:swe_x_preferred":[
        "Kadrina"
    ],
    "name:und_x_variant":[
        "Karlsberg"
    ],
    "name:vol_x_preferred":[
        "Kadrina"
    ],
    "name:zho_x_preferred":[
        "\u5361\u5fb7\u91cc\u7d0d"
    ],
    "wof:lang_x_official":[
        "est"
    ],
    "wof:lang_x_spoken":[
        "est"
    ],
    "wof:name":"Kadrina",
    "wof:placetype":"locality"
},
  "geometry": {"coordinates":[26.69806,58.60722],"type":"Point"}
}