{
  "type": "Feature",
  "properties": {
    "gn:admin1_code":"21.0",
    "gn:admin2_code":"698.0",
    "gn:admin3_code":"1791.0",
    "gn:asciiname":"Heibri",
    "gn:country_code":"EE",
    "gn:dem":144,
    "gn:feature_class":"P",
    "gn:feature_code":"PPL",
    "gn:name":"Heibri",
    "gn:population":0,
    "gn:timezone":"Europe/Tallinn",
    "iso:country":"EE",
    "name:est_x_preferred":[
        "Heibri"
    ],
    "name:hye_x_preferred":[
        "\u0540\u0565\u056b\u0562\u057c\u056b"
    ],
    "name:myv_x_preferred":[
        "\u0425\u0435\u0439\u0431\u0440\u0438"
    ],
    "name:pol_x_preferred":[
        "Heibri"
    ],
    "name:spa_x_preferred":[
        "Heibri"
    ],
    "name:ukr_x_preferred":[
        "\u0425\u0435\u0439\u0431\u0440\u0456"
    ],
    "name:vol_x_preferred":[
        "Heibri"
    ],
    "wof:name":"Heibri",
    "wof:placetype":"locality"
},
  "geometry": {"coordinates":[26.91778,57.69917],"type":"Point"}
}