{
  "type": "Feature",
  "properties": {
    "gn:admin1_code":"8.0",
    "gn:admin2_code":"901.0",
    "gn:admin3_code":"5923.0",
    "gn:asciiname":"Palasi",
    "gn:cc2":"EE",
    "gn:country_code":"EE",
    "gn:dem":80,
    "gn:feature_class":"P",
    "gn:feature_code":"PPL",
    "gn:name":"Palasi",
    "gn:population":0,
    "gn:timezone":"Europe/Tallinn",
    "iso:country":"EE",
    "name:est_x_preferred":[
        "Palasi"
    ],
    "name:hye_x_preferred":[
        "\u054a\u0561\u056c\u0561\u057d\u056b"
    ],
    "name:pol_x_preferred":[
        "Palasi"
    ],
    "name:und_x_variant":[
        "Palase"
    ],
    "name:vol_x_preferred":[
        "Palasi"
    ],
    "wof:name":"Palasi",
    "wof:placetype":"locality"
},
  "geometry": {"coordinates":[26.775,59.23139000000001],"type":"Point"}
}