{
  "type": "Feature",
  "properties": {
    "gn:admin1_code":"14.0",
    "gn:admin2_code":"714.0",
    "gn:admin3_code":"1466.0",
    "gn:asciiname":"Ohtja",
    "gn:cc2":"EE",
    "gn:country_code":"EE",
    "gn:dem":43,
    "gn:feature_class":"P",
    "gn:feature_code":"PPL",
    "gn:name":"Ohtja",
    "gn:population":0,
    "gn:timezone":"Europe/Tallinn",
    "iso:country":"EE",
    "name:deu_x_preferred":[
        "Ohtja"
    ],
    "name:est_x_preferred":[
        "Ohtja"
    ],
    "name:hye_x_preferred":[
        "\u0555\u0570\u057f\u0575\u0561"
    ],
    "name:pol_x_preferred":[
        "Ohtja"
    ],
    "name:spa_x_preferred":[
        "Ohtja"
    ],
    "name:und_x_variant":[
        "Okht\u2019ya",
        "Ohtja"
    ],
    "name:vol_x_preferred":[
        "Ohtja"
    ],
    "wof:name":"Ohtja",
    "wof:placetype":"locality"
},
  "geometry": {"coordinates":[22.34611,58.42611],"type":"Point"}
}