{
  "type": "Feature",
  "properties": {
    "gn:admin1_code":"8.0",
    "gn:admin2_code":"928.0",
    "gn:admin3_code":"9783.0",
    "gn:asciiname":"AErina",
    "gn:country_code":"EE",
    "gn:dem":128,
    "gn:feature_class":"P",
    "gn:feature_code":"PPL",
    "gn:name":"\u00c4rina",
    "gn:population":0,
    "gn:timezone":"Europe/Tallinn",
    "iso:country":"EE",
    "name:est_x_preferred":[
        "\u00c4rina"
    ],
    "name:hye_x_preferred":[
        "\u0537\u057c\u056b\u0576\u0561"
    ],
    "name:pol_x_preferred":[
        "\u00c4rina"
    ],
    "name:und_x_variant":[
        "Myza Erinal\u2019",
        "\u00c4rina Asundus",
        "Myza Erina"
    ],
    "name:vol_x_preferred":[
        "\u00c4rina"
    ],
    "wof:coterminous":[
        1713311623
    ],
    "wof:lang_x_official":[
        "est"
    ],
    "wof:lang_x_spoken":[
        "est"
    ],
    "wof:name":"AErina",
    "wof:placetype":"locality"
},
  "geometry": {"coordinates":[26.23361,59.14694],"type":"Point"}
}