{
  "type": "Feature",
  "properties": {
    "gn:admin1_code":"2.0",
    "gn:admin2_code":"205.0",
    "gn:admin3_code":"3759.0",
    "gn:asciiname":"Kolunomme",
    "gn:country_code":"EE",
    "gn:dem":11,
    "gn:feature_class":"P",
    "gn:feature_code":"PPL",
    "gn:name":"K\u00f5lun\u00f5mme",
    "gn:population":0,
    "gn:timezone":"Europe/Tallinn",
    "iso:country":"EE",
    "name:deu_x_preferred":[
        "K\u00f5lun\u00f5mme"
    ],
    "name:est_x_preferred":[
        "K\u00f5lun\u00f5mme"
    ],
    "name:hye_x_preferred":[
        "\u053f\u056b\u056c\u0578\u0582\u0576\u056b\u0574\u0574\u0565"
    ],
    "name:pol_x_preferred":[
        "K\u00f5lun\u00f5mme"
    ],
    "name:spa_x_preferred":[
        "K\u00f5lun\u00f5mme"
    ],
    "name:und_x_variant":[
        "K\u00f5lu",
        "K\u00f5lun\u00f5mme"
    ],
    "name:vol_x_preferred":[
        "K\u00f5lun\u00f5mme"
    ],
    "wof:name":"Kolunomme",
    "wof:placetype":"locality"
},
  "geometry": {"coordinates":[22.87821,58.97128000000001],"type":"Point"}
}