{
  "type": "Feature",
  "properties": {
    "gn:admin1_code":"21.0",
    "gn:admin2_code":"917.0",
    "gn:admin3_code":"7576.0",
    "gn:asciiname":"Sika",
    "gn:country_code":"EE",
    "gn:dem":140,
    "gn:feature_class":"P",
    "gn:feature_code":"PPL",
    "gn:name":"Sika",
    "gn:population":0,
    "gn:timezone":"Europe/Tallinn",
    "iso:country":"EE",
    "name:ceb_x_preferred":[
        "Sika"
    ],
    "name:ces_x_preferred":[
        "Sika"
    ],
    "name:deu_x_preferred":[
        "Sika"
    ],
    "name:est_x_preferred":[
        "Sika"
    ],
    "name:fas_x_preferred":[
        "\u0633\u06cc\u06a9\u0627"
    ],
    "name:fin_x_preferred":[
        "Sika"
    ],
    "name:fra_x_preferred":[
        "Sika"
    ],
    "name:swe_x_preferred":[
        "Sika"
    ],
    "name:ukr_x_preferred":[
        "\u0421\u0456\u043a\u0430"
    ],
    "name:vol_x_preferred":[
        "Sika"
    ],
    "wof:lang_x_official":[
        "est"
    ],
    "wof:lang_x_spoken":[
        "est"
    ],
    "wof:name":"Sika",
    "wof:placetype":"locality"
},
  "geometry": {"coordinates":[27.06056,57.79361],"type":"Point"}
}