{
  "type": "Feature",
  "properties": {
    "gn:country":"EE",
    "gn:fcode":"PPL",
    "gn:population":551,
    "iso:country":"EE",
    "name:bul_x_preferred":[
        "\u041a\u0438\u0441\u0430"
    ],
    "name:ceb_x_preferred":[
        "Kiisa"
    ],
    "name:eng_x_preferred":[
        "Kiisa"
    ],
    "name:est_x_preferred":[
        "Kiisa"
    ],
    "name:fra_x_preferred":[
        "Kiisa"
    ],
    "name:hye_x_preferred":[
        "\u053f\u056b\u056b\u057d\u0561"
    ],
    "name:jpn_x_preferred":[
        "\u30ad\u30fc\u30b5"
    ],
    "name:lit_x_preferred":[
        "Kysa"
    ],
    "name:nld_x_preferred":[
        "Kiisa"
    ],
    "name:pol_x_preferred":[
        "Kiisa"
    ],
    "name:rus_x_preferred":[
        "\u041a\u0438\u0439\u0437\u0430"
    ],
    "name:sco_x_preferred":[
        "Kiisa"
    ],
    "name:spa_x_preferred":[
        "Kiisa"
    ],
    "name:swe_x_preferred":[
        "Kiisa"
    ],
    "name:ukr_x_preferred":[
        "\u041a\u0456\u0439\u0437\u0430"
    ],
    "name:und_x_variant":[
        "Kiza"
    ],
    "name:vol_x_preferred":[
        "Kiisa"
    ],
    "name:vro_x_preferred":[
        "Kiisa"
    ],
    "qs_pg:aaroncc":"EE",
    "qs_pg:gn_country":"EE",
    "qs_pg:gn_fcode":"PPL",
    "qs_pg:gn_pop":551,
    "qs_pg:name":"Kiisa",
    "qs_pg:name_adm0":"Eesti",
    "qs_pg:name_adm1":"Harjumaa",
    "qs_pg:photos":103,
    "qs_pg:photos_1k":21,
    "qs_pg:photos_9k":1,
    "qs_pg:photos_9r":3,
    "qs_pg:photos_all":103,
    "qs_pg:photos_sr":3,
    "qs_pg:pop_sr":2,
    "qs_pg:qs_pg_placetype":"locality",
    "qs_pg:qs_pg_placetype_gp":"Town",
    "qs_pg:woe_adm0":23424805,
    "woe:adm0_id":23424805,
    "woe:name_adm0":"Eesti",
    "woe:name_adm1":"Harjumaa",
    "woe:placetype":"Town",
    "wof:name":"Kiisa",
    "wof:placetype":"locality",
    "wof:population":551
},
  "geometry": {"coordinates":[24.68889,59.23694],"type":"Point"}
}