{
  "type": "Feature",
  "properties": {
    "gn:admin1_code":"11.0",
    "gn:admin2_code":"624.0",
    "gn:admin3_code":"8540.0",
    "gn:asciiname":"Araka",
    "gn:country_code":"EE",
    "gn:dem":16,
    "gn:feature_class":"P",
    "gn:feature_code":"PPL",
    "gn:name":"Araka",
    "gn:population":0,
    "gn:timezone":"Europe/Tallinn",
    "iso:country":"EE",
    "name:und_x_variant":[
        "Arake",
        "Araka"
    ],
    "wof:name":"Araka",
    "wof:placetype":"locality"
},
  "geometry": {"coordinates":[23.97083,58.34444000000001],"type":"Point"}
}