{
  "type": "Feature",
  "properties": {
    "gn:admin1_code":"4.0",
    "gn:admin2_code":"255.0",
    "gn:admin3_code":"2230.0",
    "gn:asciiname":"Joekuela",
    "gn:country_code":"EE",
    "gn:dem":76,
    "gn:feature_class":"P",
    "gn:feature_code":"PPL",
    "gn:name":"J\u00f5ek\u00fcla",
    "gn:population":0,
    "gn:timezone":"Europe/Tallinn",
    "iso:country":"EE",
    "name:und_x_variant":[
        "J\u00f5ek\u00fcla",
        "J\u00f5e"
    ],
    "wof:name":"Joekuela",
    "wof:placetype":"locality"
},
  "geometry": {"coordinates":[26.07833,58.83722],"type":"Point"}
}