{
  "type": "Feature",
  "properties": {
    "gn:gn_country":"EE",
    "gn:gn_fcode":"PPL",
    "gn:gn_pop":2544,
    "gn:population":2544,
    "iso:country":"EE",
    "name:eng_x_preferred":[
        "V\u00e4ndra"
    ],
    "name:rus_x_preferred":[
        "\u0412\u044f\u043d\u0434\u0440\u0430"
    ],
    "name:unk_x_variant":[
        "Alt-Fennern"
    ],
    "qs_pg:aaroncc":"EE",
    "qs_pg:gn_country":"EE",
    "qs_pg:gn_fcode":"PPL",
    "qs_pg:gn_pop":2544,
    "qs_pg:name":"V\u00e4ndra",
    "qs_pg:name_adm0":"Eesti",
    "qs_pg:name_adm1":"P\u00e4rnumaa",
    "qs_pg:photos_9r":0,
    "qs_pg:photos_sr":0,
    "qs_pg:pop_sr":4,
    "qs_pg:qs_pg_placetype":"locality",
    "qs_pg:qs_pg_placetype_gp":"Town",
    "qs_pg:woe_adm0":23424805,
    "woe:adm0_id":23424805,
    "woe:name_adm0":"Eesti",
    "woe:name_adm1":"P\u00e4rnumaa",
    "woe:placetype":"Town",
    "wof:name":"V\u00e4ndra",
    "wof:placetype":"locality",
    "wof:population":2544
},
  "geometry": {"coordinates":[25.03611,58.64806],"type":"Point"}
}