{
  "type": "Feature",
  "properties": {
    "gn:admin1_code":"21.0",
    "gn:admin2_code":"917.0",
    "gn:admin3_code":"3446.0",
    "gn:asciiname":"Korgomoisa",
    "gn:country_code":"EE",
    "gn:dem":88,
    "gn:feature_class":"P",
    "gn:feature_code":"PPL",
    "gn:name":"Korg\u00f5m\u00f5isa",
    "gn:population":0,
    "gn:timezone":"Europe/Tallinn",
    "iso:country":"EE",
    "name:deu_x_preferred":[
        "Korg\u00f5m\u00f5isa"
    ],
    "name:est_x_preferred":[
        "Korg\u00f5m\u00f5isa"
    ],
    "name:hye_x_preferred":[
        "\u053f\u0578\u057c\u0563\u056b\u0574\u056b\u056b\u057d\u0561"
    ],
    "name:pol_x_preferred":[
        "Korg\u00f5m\u00f5isa"
    ],
    "name:spa_x_preferred":[
        "Korg\u00f5m\u00f5isa"
    ],
    "name:ukr_x_preferred":[
        "\u041a\u043e\u0440\u0491\u0438\u043c\u0438\u0439\u0441\u0430"
    ],
    "name:und_x_variant":[
        "Korg\u00f5m\u00f5isa",
        "K\u00f5rgem\u00f5isa"
    ],
    "name:vol_x_preferred":[
        "Korg\u00f5m\u00f5isa"
    ],
    "wof:name":"Korgomoisa",
    "wof:placetype":"locality"
},
  "geometry": {"coordinates":[27.47139,57.875],"type":"Point"}
}