{
  "type": "Feature",
  "properties": {
    "gn:admin1_code":"21.0",
    "gn:admin2_code":"917.0",
    "gn:admin3_code":"3446.0",
    "gn:asciiname":"Korgomoisa",
    "gn:country_code":"EE",
    "gn:dem":88,
    "gn:feature_class":"P",
    "gn:feature_code":"PPL",
    "gn:name":"Korg\u00f5m\u00f5isa",
    "gn:population":0,
    "gn:timezone":"Europe/Tallinn",
    "iso:country":"EE",
    "name:und_x_variant":[
        "Korg\u00f5m\u00f5isa",
        "K\u00f5rgem\u00f5isa"
    ],
    "wof:name":"Korgomoisa",
    "wof:placetype":"locality"
},
  "geometry": {"coordinates":[27.47139,57.875],"type":"Point"}
}