{
  "type": "Feature",
  "properties": {
    "gn:admin1_code":"3.0",
    "gn:admin2_code":"321.0",
    "gn:admin3_code":"265.0",
    "gn:asciiname":"Pohjaelurajoon",
    "gn:country_code":"EE",
    "gn:dem":63,
    "gn:feature_class":"P",
    "gn:feature_code":"PPL",
    "gn:name":"P\u00f5hjaelurajoon",
    "gn:population":0,
    "gn:timezone":"Europe/Tallinn",
    "iso:country":"EE",
    "name:und_x_variant":[
        "P\u00f5hjaelurajoon",
        "Vanak\u00fcla"
    ],
    "wof:name":"Pohjaelurajoon",
    "wof:placetype":"locality"
},
  "geometry": {"coordinates":[27.28444,59.40861],"type":"Point"}
}