{
  "type": "Feature",
  "properties": {
    "gn:admin1_code":"14.0",
    "gn:admin2_code":"714.0",
    "gn:admin3_code":"2662.0",
    "gn:asciiname":"Kandla",
    "gn:cc2":"EE",
    "gn:country_code":"EE",
    "gn:dem":20,
    "gn:feature_class":"P",
    "gn:feature_code":"PPL",
    "gn:name":"Kandla",
    "gn:population":0,
    "gn:timezone":"Europe/Tallinn",
    "iso:country":"EE",
    "name:und_x_variant":[
        "Kandla Asundus",
        "Kandla"
    ],
    "wof:name":"Kandla",
    "wof:placetype":"locality"
},
  "geometry": {"coordinates":[22.29306,58.36666999999999],"type":"Point"}
}