{
  "type": "Feature",
  "properties": {
    "gn:admin1_code":"14.0",
    "gn:admin2_code":"714.0",
    "gn:admin3_code":"2662.0",
    "gn:asciiname":"Kandla",
    "gn:cc2":"EE",
    "gn:country_code":"EE",
    "gn:dem":20,
    "gn:feature_class":"P",
    "gn:feature_code":"PPL",
    "gn:name":"Kandla",
    "gn:population":0,
    "gn:timezone":"Europe/Tallinn",
    "iso:country":"EE",
    "name:deu_x_preferred":[
        "Kandla"
    ],
    "name:est_x_preferred":[
        "Kandla"
    ],
    "name:fra_x_preferred":[
        "Kandla"
    ],
    "name:hye_x_preferred":[
        "\u053f\u0561\u0576\u0564\u056c\u0561"
    ],
    "name:pol_x_preferred":[
        "Kandla"
    ],
    "name:spa_x_preferred":[
        "Kandla"
    ],
    "name:ukr_x_preferred":[
        "\u041a\u0430\u043d\u0434\u043b\u0430"
    ],
    "name:und_x_variant":[
        "Kandla Asundus"
    ],
    "name:vol_x_preferred":[
        "Kandla"
    ],
    "wof:name":"Kandla",
    "wof:placetype":"locality"
},
  "geometry": {"coordinates":[22.29306,58.36666999999999],"type":"Point"}
}