{
  "type": "Feature",
  "properties": {
    "gn:admin1_code":"21.0",
    "gn:admin2_code":"917.0",
    "gn:admin3_code":"3838.0",
    "gn:asciiname":"Kovera",
    "gn:country_code":"EE",
    "gn:dem":60,
    "gn:feature_class":"P",
    "gn:feature_code":"PPL",
    "gn:name":"K\u00f5vera",
    "gn:population":0,
    "gn:timezone":"Europe/Tallinn",
    "iso:country":"EE",
    "name:und_x_variant":[
        "K\u00f5vera",
        "K\u00f5v\u00f5ra"
    ],
    "wof:name":"Kovera",
    "wof:placetype":"locality"
},
  "geometry": {"coordinates":[27.51694,57.90194],"type":"Point"}
}