{
  "type": "Feature",
  "properties": {
    "gn:admin1_code":"21.0",
    "gn:admin2_code":"917.0",
    "gn:admin3_code":"3838.0",
    "gn:asciiname":"Kovera",
    "gn:country_code":"EE",
    "gn:dem":60,
    "gn:feature_class":"P",
    "gn:feature_code":"PPL",
    "gn:name":"K\u00f5vera",
    "gn:population":0,
    "gn:timezone":"Europe/Tallinn",
    "iso:country":"EE",
    "name:deu_x_preferred":[
        "K\u00f5vera"
    ],
    "name:est_x_preferred":[
        "K\u00f5vera"
    ],
    "name:hye_x_preferred":[
        "\u053f\u056b\u057e\u0565\u057c\u0561"
    ],
    "name:spa_x_preferred":[
        "K\u00f5vera"
    ],
    "name:ukr_x_preferred":[
        "\u041a\u0438\u0432\u0435\u0440\u0430"
    ],
    "name:und_x_variant":[
        "K\u00f5v\u00f5ra"
    ],
    "name:vol_x_preferred":[
        "K\u00f5vera"
    ],
    "wof:coterminous":[
        1713316353
    ],
    "wof:lang_x_official":[
        "est"
    ],
    "wof:lang_x_spoken":[
        "est"
    ],
    "wof:name":"Kovera",
    "wof:placetype":"locality"
},
  "geometry": {"coordinates":[27.51694,57.90194],"type":"Point"}
}