{
  "type": "Feature",
  "properties": {
    "gn:admin1_code":"4.0",
    "gn:admin2_code":"834.0",
    "gn:admin3_code":"9828.0",
    "gn:asciiname":"UElejoe",
    "gn:country_code":"EE",
    "gn:dem":74,
    "gn:feature_class":"P",
    "gn:feature_code":"PPL",
    "gn:name":"\u00dclej\u00f5e",
    "gn:population":0,
    "gn:timezone":"Europe/Tallinn",
    "iso:country":"EE",
    "wof:name":"UElejoe",
    "wof:placetype":"locality"
},
  "geometry": {"coordinates":[25.4625,58.89111],"type":"Point"}
}