{
  "type": "Feature",
  "properties": {
    "gn:admin1_code":"20.0",
    "gn:admin2_code":"899.0",
    "gn:admin3_code":"4462.0",
    "gn:asciiname":"Loime",
    "gn:country_code":"EE",
    "gn:dem":44,
    "gn:feature_class":"P",
    "gn:feature_code":"PPL",
    "gn:name":"Loime",
    "gn:population":0,
    "gn:timezone":"Europe/Tallinn",
    "iso:country":"EE",
    "wof:name":"Loime",
    "wof:placetype":"locality"
},
  "geometry": {"coordinates":[25.90806,58.38944],"type":"Point"}
}