{
  "type": "Feature",
  "properties": {
    "gn:admin1_code":"18.0",
    "gn:admin2_code":"586.0",
    "gn:admin3_code":"4685.0",
    "gn:asciiname":"Luemati",
    "gn:country_code":"EE",
    "gn:dem":63,
    "gn:feature_class":"P",
    "gn:feature_code":"PPL",
    "gn:name":"L\u00fcmati",
    "gn:population":0,
    "gn:timezone":"Europe/Tallinn",
    "iso:country":"EE",
    "name:und_x_variant":[
        "Lyumatu",
        "L\u00fcmatu",
        "L\u00fcmati"
    ],
    "wof:name":"Luemati",
    "wof:placetype":"locality"
},
  "geometry": {"coordinates":[27.06667,58.71056],"type":"Point"}
}