{
  "type": "Feature",
  "properties": {
    "gn:admin1_code":"13.0",
    "gn:admin2_code":"503.0",
    "gn:admin3_code":"4554.0",
    "gn:asciiname":"Luiste Asundus",
    "gn:country_code":"EE",
    "gn:dem":31,
    "gn:feature_class":"P",
    "gn:feature_code":"PPL",
    "gn:name":"Luiste Asundus",
    "gn:population":0,
    "gn:timezone":"Europe/Tallinn",
    "iso:country":"EE",
    "name:und_x_variant":[
        "Myza Luyste",
        "Luiste",
        "Luiste Asundus"
    ],
    "wof:name":"Luiste Asundus",
    "wof:placetype":"locality"
},
  "geometry": {"coordinates":[24.22722000000001,58.87139000000001],"type":"Point"}
}