{
  "type": "Feature",
  "properties": {
    "gn:admin1_code":"11.0",
    "gn:admin2_code":"809.0",
    "gn:admin3_code":"6012.0",
    "gn:asciiname":"Parisselja",
    "gn:cc2":"EE",
    "gn:country_code":"EE",
    "gn:dem":19,
    "gn:feature_class":"P",
    "gn:feature_code":"PPL",
    "gn:name":"Parisselja",
    "gn:population":0,
    "gn:timezone":"Europe/Tallinn",
    "iso:country":"EE",
    "name:und_x_variant":[
        "Parissel\u2019ya",
        "Parisselja"
    ],
    "wof:name":"Parisselja",
    "wof:placetype":"locality"
},
  "geometry": {"coordinates":[24.53196,58.54217],"type":"Point"}
}