{
  "type": "Feature",
  "properties": {
    "gn:admin1_code":"11.0",
    "gn:admin2_code":"638.0",
    "gn:admin3_code":"6113.0",
    "gn:asciiname":"Perekuela",
    "gn:country_code":"EE",
    "gn:dem":25,
    "gn:feature_class":"P",
    "gn:feature_code":"PPL",
    "gn:name":"Perek\u00fcla",
    "gn:population":0,
    "gn:timezone":"Europe/Tallinn",
    "iso:country":"EE",
    "name:est_x_preferred":[
        "Perek\u00fcla"
    ],
    "name:hye_x_preferred":[
        "\u054a\u0565\u057c\u0565\u056f\u0575\u0578\u0582\u056c\u0561"
    ],
    "name:pol_x_preferred":[
        "Perek\u00fcla"
    ],
    "name:spa_x_preferred":[
        "Perek\u00fcla"
    ],
    "name:und_x_variant":[
        "Perekyula",
        "Perek\u00fcla"
    ],
    "name:vol_x_preferred":[
        "Perek\u00fcla"
    ],
    "wof:name":"Perekuela",
    "wof:placetype":"locality"
},
  "geometry": {"coordinates":[24.31917,58.60639000000001],"type":"Point"}
}