{
  "type": "Feature",
  "properties": {
    "gn:admin1_code":"14.0",
    "gn:admin2_code":"714.0",
    "gn:admin3_code":"6899.0",
    "gn:asciiname":"Aruste",
    "gn:country_code":"EE",
    "gn:dem":33,
    "gn:feature_class":"P",
    "gn:feature_code":"PPL",
    "gn:name":"Aruste",
    "gn:population":0,
    "gn:timezone":"Europe/Tallinn",
    "iso:country":"EE",
    "name:deu_x_preferred":[
        "Aruste"
    ],
    "name:est_x_preferred":[
        "Aruste"
    ],
    "name:hye_x_preferred":[
        "\u0531\u057c\u0578\u0582\u057d\u057f\u0565"
    ],
    "name:nld_x_preferred":[
        "Aruste"
    ],
    "name:pol_x_preferred":[
        "Aruste"
    ],
    "name:spa_x_preferred":[
        "Aruste"
    ],
    "name:vol_x_preferred":[
        "Aruste"
    ],
    "wof:name":"Aruste",
    "wof:placetype":"locality"
},
  "geometry": {"coordinates":[22.68472,58.39528000000001],"type":"Point"}
}