{
  "type": "Feature",
  "properties": {
    "gn:admin1_code":"11.0",
    "gn:admin2_code":"624.0",
    "gn:admin3_code":"2289.0",
    "gn:asciiname":"Metsakuela",
    "gn:country_code":"EE",
    "gn:dem":13,
    "gn:feature_class":"P",
    "gn:feature_code":"PPL",
    "gn:name":"Metsak\u00fcla",
    "gn:population":0,
    "gn:timezone":"Europe/Tallinn",
    "iso:country":"EE",
    "name:und_x_variant":[
        "Metskyula",
        "Metsk\u00fcla",
        "Metsak\u00fcla"
    ],
    "wof:lang_x_official":[
        "est"
    ],
    "wof:lang_x_spoken":[
        "est"
    ],
    "wof:name":"Metsakuela",
    "wof:placetype":"locality"
},
  "geometry": {"coordinates":[24.33722,58.49722],"type":"Point"}
}