{
  "type": "Feature",
  "properties": {
    "gn:admin1_code":"1.0",
    "gn:admin2_code":"353.0",
    "gn:admin3_code":"8125.0",
    "gn:asciiname":"Tammistu",
    "gn:country_code":"EE",
    "gn:dem":15,
    "gn:feature_class":"P",
    "gn:feature_code":"PPL",
    "gn:name":"Tammistu",
    "gn:population":0,
    "gn:timezone":"Europe/Tallinn",
    "iso:country":"EE",
    "name:est_x_preferred":[
        "Tammistu"
    ],
    "name:fra_x_preferred":[
        "Tammistu"
    ],
    "name:hye_x_preferred":[
        "\u054f\u0561\u0574\u056b\u057d\u057f\u0578\u0582"
    ],
    "name:nld_x_preferred":[
        "Tammistu"
    ],
    "name:pol_x_preferred":[
        "Tammistu"
    ],
    "name:rus_x_preferred":[
        "\u0422\u0430\u043c\u043c\u0438\u0441\u0442\u0443"
    ],
    "name:spa_x_preferred":[
        "Tammistu"
    ],
    "name:und_x_variant":[
        "Tammisto",
        "Tammistu"
    ],
    "name:vol_x_preferred":[
        "Tammistu"
    ],
    "wof:name":"Tammistu",
    "wof:placetype":"locality"
},
  "geometry": {"coordinates":[25.50028,59.625],"type":"Point"}
}