{
  "type": "Feature",
  "properties": {
    "gn:admin1_code":"13.0",
    "gn:admin2_code":"668.0",
    "gn:admin3_code":"2742.0",
    "gn:asciiname":"Karitsa",
    "gn:country_code":"EE",
    "gn:dem":71,
    "gn:feature_class":"P",
    "gn:feature_code":"PPL",
    "gn:name":"Karitsa",
    "gn:population":0,
    "gn:timezone":"Europe/Tallinn",
    "iso:country":"EE",
    "wof:name":"Karitsa",
    "wof:placetype":"locality"
},
  "geometry": {"coordinates":[25.03917,58.99417],"type":"Point"}
}