{
  "type": "Feature",
  "properties": {
    "gn:admin1_code":"5.0",
    "gn:admin2_code":"247.0",
    "gn:admin3_code":"2079.0",
    "gn:asciiname":"Ronivere",
    "gn:country_code":"EE",
    "gn:dem":98,
    "gn:feature_class":"P",
    "gn:feature_code":"PPL",
    "gn:name":"Ronivere",
    "gn:population":0,
    "gn:timezone":"Europe/Tallinn",
    "iso:country":"EE",
    "name:est_x_preferred":[
        "Ronivere"
    ],
    "name:hye_x_preferred":[
        "\u054c\u0578\u0576\u056b\u057e\u0565\u057c\u0565"
    ],
    "name:pol_x_preferred":[
        "Ronivere"
    ],
    "name:spa_x_preferred":[
        "Ronivere"
    ],
    "name:vol_x_preferred":[
        "Ronivere"
    ],
    "wof:name":"Ronivere",
    "wof:placetype":"locality"
},
  "geometry": {"coordinates":[26.65639,58.72611],"type":"Point"}
}