{
  "type": "Feature",
  "properties": {
    "gn:gn_country":"EE",
    "gn:gn_fcode":"PPL",
    "gn:gn_pop":150,
    "gn:population":150,
    "iso:country":"EE",
    "name:bul_x_preferred":[
        "\u041e\u0445\u0442\u0443"
    ],
    "name:ceb_x_preferred":[
        "Ohtu"
    ],
    "name:eng_x_preferred":[
        "Ohtu"
    ],
    "name:est_x_preferred":[
        "Ohtu"
    ],
    "name:fra_x_preferred":[
        "Ohtu"
    ],
    "name:hye_x_preferred":[
        "\u0555\u0570\u057f\u0578\u0582"
    ],
    "name:nld_x_preferred":[
        "Ohtu"
    ],
    "name:pol_x_preferred":[
        "Ohtu"
    ],
    "name:spa_x_preferred":[
        "Ohtu"
    ],
    "name:swe_x_preferred":[
        "Ohtu"
    ],
    "name:ukr_x_preferred":[
        "\u041e\u0433\u0442\u0443"
    ],
    "name:unk_x_variant":[
        "Okhtu"
    ],
    "name:vol_x_preferred":[
        "Ohtu"
    ],
    "qs_pg:aaroncc":"EE",
    "qs_pg:gn_country":"EE",
    "qs_pg:gn_fcode":"PPL",
    "qs_pg:gn_pop":150,
    "qs_pg:name":"\u00d5hu",
    "qs_pg:name_adm0":"Eesti",
    "qs_pg:name_adm1":"P\u00e4rnumaa",
    "qs_pg:photos_9r":0,
    "qs_pg:photos_sr":0,
    "qs_pg:pop_sr":1,
    "qs_pg:qs_pg_placetype":"locality",
    "qs_pg:qs_pg_placetype_gp":"Town",
    "qs_pg:woe_adm0":23424805,
    "woe:adm0_id":23424805,
    "woe:name_adm0":"Eesti",
    "woe:name_adm1":"P\u00e4rnumaa",
    "woe:placetype":"Town",
    "wof:name":"\u00d5hu",
    "wof:placetype":"locality",
    "wof:population":150
},
  "geometry": {"coordinates":[24.36278,59.27833],"type":"Point"}
}