{
  "type": "Feature",
  "properties": {
    "gn:admin1_code":"8.0",
    "gn:admin2_code":"903.0",
    "gn:admin3_code":"5804.0",
    "gn:asciiname":"Pada",
    "gn:country_code":"EE",
    "gn:dem":69,
    "gn:feature_class":"P",
    "gn:feature_code":"PPL",
    "gn:name":"Pada",
    "gn:population":0,
    "gn:timezone":"Europe/Tallinn",
    "iso:country":"EE",
    "wof:name":"Pada",
    "wof:placetype":"locality"
},
  "geometry": {"coordinates":[26.71694,59.41861],"type":"Point"}
}