{
  "type": "Feature",
  "properties": {
    "gn:admin1_code":"4.0",
    "gn:admin2_code":"255.0",
    "gn:admin3_code":"1188.0",
    "gn:asciiname":"Arukuela",
    "gn:country_code":"EE",
    "gn:dem":88,
    "gn:feature_class":"P",
    "gn:feature_code":"PPL",
    "gn:name":"Aruk\u00fcla",
    "gn:population":0,
    "gn:timezone":"Europe/Tallinn",
    "iso:country":"EE",
    "name:und_x_variant":[
        "Aruk\u00fcla",
        "Aru"
    ],
    "wof:name":"Arukuela",
    "wof:placetype":"locality"
},
  "geometry": {"coordinates":[25.67222000000001,59.1375],"type":"Point"}
}