{
  "type": "Feature",
  "properties": {
    "gn:admin1_code":"12.0",
    "gn:admin2_code":"708.0",
    "gn:admin3_code":"6743.0",
    "gn:asciiname":"Palo",
    "gn:country_code":"EE",
    "gn:dem":43,
    "gn:feature_class":"P",
    "gn:feature_code":"PPL",
    "gn:name":"Palo",
    "gn:population":0,
    "gn:timezone":"Europe/Tallinn",
    "iso:country":"EE",
    "name:ceb_x_preferred":[
        "Palo"
    ],
    "name:deu_x_preferred":[
        "Palo"
    ],
    "name:fin_x_preferred":[
        "Palo"
    ],
    "name:ita_x_preferred":[
        "Palo"
    ],
    "name:nld_x_preferred":[
        "Palo"
    ],
    "name:pol_x_preferred":[
        "Palo"
    ],
    "name:slk_x_preferred":[
        "Palo"
    ],
    "name:spa_x_preferred":[
        "Palo"
    ],
    "name:swe_x_preferred":[
        "Palo"
    ],
    "name:tgl_x_preferred":[
        "Palo"
    ],
    "name:und_x_variant":[
        "Palok\u00fcl\u00e4",
        "Palo"
    ],
    "name:vol_x_preferred":[
        "Palo"
    ],
    "name:war_x_preferred":[
        "Palo"
    ],
    "wof:name":"Palo",
    "wof:placetype":"locality"
},
  "geometry": {"coordinates":[27.42278,58.05],"type":"Point"}
}