{
  "type": "Feature",
  "properties": {
    "gn:admin1_code":"11.0",
    "gn:admin2_code":"638.0",
    "gn:admin3_code":"1314.0",
    "gn:asciiname":"Arase",
    "gn:country_code":"EE",
    "gn:dem":35,
    "gn:feature_class":"P",
    "gn:feature_code":"PPL",
    "gn:name":"Arase",
    "gn:population":0,
    "gn:timezone":"Europe/Tallinn",
    "iso:country":"EE",
    "wof:name":"Arase",
    "wof:placetype":"locality"
},
  "geometry": {"coordinates":[24.49833,58.68083000000001],"type":"Point"}
}