{
  "type": "Feature",
  "properties": {
    "gn:admin1_code":"1.0",
    "gn:admin2_code":"726.0",
    "gn:admin3_code":"4289.0",
    "gn:asciiname":"Lepaste",
    "gn:country_code":"EE",
    "gn:dem":64,
    "gn:feature_class":"P",
    "gn:feature_code":"PPL",
    "gn:name":"Lepaste",
    "gn:population":0,
    "gn:timezone":"Europe/Tallinn",
    "iso:country":"EE",
    "wof:name":"Lepaste",
    "wof:placetype":"locality"
},
  "geometry": {"coordinates":[24.15722,59.07028],"type":"Point"}
}