{
  "type": "Feature",
  "properties": {
    "gn:admin1_code":"14.0",
    "gn:admin2_code":"714.0",
    "gn:admin3_code":"5034.0",
    "gn:asciiname":"Muraja",
    "gn:cc2":"EE",
    "gn:country_code":"EE",
    "gn:dem":9,
    "gn:feature_class":"P",
    "gn:feature_code":"PPL",
    "gn:name":"Muraja",
    "gn:population":0,
    "gn:timezone":"Europe/Tallinn",
    "iso:country":"EE",
    "name:und_x_variant":[
        "Muraya",
        "Muraja"
    ],
    "wof:name":"Muraja",
    "wof:placetype":"locality"
},
  "geometry": {"coordinates":[23.22917,58.465],"type":"Point"}
}