{
  "type": "Feature",
  "properties": {
    "gn:admin1_code":"13.0",
    "gn:admin2_code":"293.0",
    "gn:admin3_code":"5015.0",
    "gn:asciiname":"Mukri",
    "gn:cc2":"EE",
    "gn:country_code":"EE",
    "gn:dem":53,
    "gn:feature_class":"P",
    "gn:feature_code":"PPL",
    "gn:name":"Mukri",
    "gn:population":0,
    "gn:timezone":"Europe/Tallinn",
    "iso:country":"EE",
    "name:est_x_preferred":[
        "Mukri"
    ],
    "name:hye_x_preferred":[
        "\u0544\u0578\u0582\u056f\u057c\u056b"
    ],
    "name:pol_x_preferred":[
        "Mukri"
    ],
    "name:sco_x_preferred":[
        "Mukri"
    ],
    "name:spa_x_preferred":[
        "Mukri"
    ],
    "name:und_x_variant":[
        "Mukre",
        "Mukri"
    ],
    "name:vol_x_preferred":[
        "Mukri"
    ],
    "wof:name":"Mukri",
    "wof:placetype":"locality"
},
  "geometry": {"coordinates":[25.03222,58.72],"type":"Point"}
}