{
  "type": "Feature",
  "properties": {
    "gn:admin1_code":"21.0",
    "gn:admin2_code":"732.0",
    "gn:admin3_code":"2736.0",
    "gn:asciiname":"Karisilla",
    "gn:country_code":"EE",
    "gn:dem":43,
    "gn:feature_class":"P",
    "gn:feature_code":"PPL",
    "gn:name":"Karisilla",
    "gn:population":0,
    "gn:timezone":"Europe/Tallinn",
    "iso:country":"EE",
    "name:deu_x_preferred":[
        "Karisilla"
    ],
    "name:est_x_preferred":[
        "Karisilla"
    ],
    "name:fra_x_preferred":[
        "Karisilla"
    ],
    "name:hye_x_preferred":[
        "\u053f\u0561\u057c\u056b\u057d\u056b\u056c\u056c\u0561"
    ],
    "name:pol_x_preferred":[
        "Karisilla"
    ],
    "name:rus_x_preferred":[
        "\u041a\u0430\u0440\u0438\u0441\u0438\u043b\u043b\u0430"
    ],
    "name:sco_x_preferred":[
        "Karisilla"
    ],
    "name:spa_x_preferred":[
        "Karisilla"
    ],
    "name:ukr_x_preferred":[
        "\u041a\u0430\u0440\u0456\u0441\u0456\u043b\u043b\u0430"
    ],
    "name:vol_x_preferred":[
        "Karisilla"
    ],
    "wof:lang_x_official":[
        "est"
    ],
    "wof:lang_x_spoken":[
        "est"
    ],
    "wof:name":"Karisilla",
    "wof:placetype":"locality"
},
  "geometry": {"coordinates":[27.58194,57.97556],"type":"Point"}
}