{
  "type": "Feature",
  "properties": {
    "gn:gn_country":"EE",
    "gn:gn_fcode":"PPL",
    "gn:gn_pop":0,
    "iso:country":"EE",
    "name:arm_x_preferred":[
        "\u053f\u0575\u0578\u0582\u056f\u056b\u057f\u0561"
    ],
    "name:dut_x_preferred":[
        "K\u00fckita"
    ],
    "name:eng_x_preferred":[
        "K\u00fckita"
    ],
    "name:est_x_preferred":[
        "K\u00fckita"
    ],
    "name:fre_x_preferred":[
        "K\u00fckita"
    ],
    "name:pol_x_preferred":[
        "K\u00fckita"
    ],
    "name:ukr_x_preferred":[
        "\u041a\u044e\u043a\u0456\u0442\u0430"
    ],
    "name:vol_x_preferred":[
        "K\u00fckita"
    ],
    "qs_pg:aaroncc":"EE",
    "qs_pg:gn_country":"EE",
    "qs_pg:gn_fcode":"PPL",
    "qs_pg:gn_pop":0,
    "qs_pg:name":"K\u00fckita",
    "qs_pg:name_adm0":"Eesti",
    "qs_pg:name_adm1":"J\u00f5gevamaa",
    "qs_pg:photos":15,
    "qs_pg:photos_1k":3,
    "qs_pg:photos_9k":1,
    "qs_pg:photos_9r":1,
    "qs_pg:photos_all":15,
    "qs_pg:photos_sr":1,
    "qs_pg:pop_sr":0,
    "qs_pg:qs_pg_placetype":"locality",
    "qs_pg:qs_pg_placetype_gp":"Town",
    "qs_pg:woe_adm0":23424805,
    "woe:adm0_id":23424805,
    "woe:name_adm0":"Eesti",
    "woe:name_adm1":"J\u00f5gevamaa",
    "woe:placetype":"Town",
    "wof:name":"K\u00fckita",
    "wof:placetype":"locality"
},
  "geometry": {"coordinates":[26.94727,58.81227],"type":"Point"}
}