{
  "type": "Feature",
  "properties": {
    "gn:admin1_code":"12.0",
    "gn:admin2_code":"708.0",
    "gn:admin3_code":"2140.0",
    "gn:asciiname":"Punni",
    "gn:country_code":"EE",
    "gn:dem":47,
    "gn:feature_class":"P",
    "gn:feature_code":"PPL",
    "gn:name":"Punni",
    "gn:population":0,
    "gn:timezone":"Europe/Tallinn",
    "iso:country":"EE",
    "wof:name":"Punni",
    "wof:placetype":"locality"
},
  "geometry": {"coordinates":[27.36222,58.08971999999999],"type":"Point"}
}