{
  "type": "Feature",
  "properties": {
    "gn:admin1_code":"14.0",
    "gn:admin2_code":"714.0",
    "gn:admin3_code":"3601.0",
    "gn:asciiname":"Kuusnomme",
    "gn:cc2":"EE",
    "gn:country_code":"EE",
    "gn:dem":16,
    "gn:feature_class":"P",
    "gn:feature_code":"PPL",
    "gn:name":"Kuusn\u00f5mme",
    "gn:population":0,
    "gn:timezone":"Europe/Tallinn",
    "iso:country":"EE",
    "name:deu_x_preferred":[
        "Kuusn\u00f5mme"
    ],
    "name:est_x_preferred":[
        "Kuusn\u00f5mme"
    ],
    "name:fra_x_preferred":[
        "Kuusn\u00f5mme"
    ],
    "name:hye_x_preferred":[
        "\u053f\u0578\u0582\u0578\u0582\u057d\u0576\u056b\u0574\u0565"
    ],
    "name:pol_x_preferred":[
        "Kuusn\u00f5mme"
    ],
    "name:spa_x_preferred":[
        "Kuusn\u00f5mme"
    ],
    "name:swe_x_preferred":[
        "Kuusn\u00f5mme"
    ],
    "name:ukr_x_preferred":[
        "\u041a\u0443\u0443\u0441\u043d\u0438\u043c\u043c\u0435"
    ],
    "name:und_x_variant":[
        "Kusnymme",
        "Kusnem",
        "Kuusnymme",
        "Kuusn\u00f5mme"
    ],
    "name:vol_x_preferred":[
        "Kuusn\u00f5mme"
    ],
    "wof:name":"Kuusnomme",
    "wof:placetype":"locality"
},
  "geometry": {"coordinates":[21.985,58.31333000000001],"type":"Point"}
}