{
  "type": "Feature",
  "properties": {
    "gn:admin1_code":"21.0",
    "gn:admin2_code":"698.0",
    "gn:admin3_code":"7609.0",
    "gn:asciiname":"Singa",
    "gn:country_code":"EE",
    "gn:dem":78,
    "gn:feature_class":"P",
    "gn:feature_code":"PPL",
    "gn:name":"Singa",
    "gn:population":0,
    "gn:timezone":"Europe/Tallinn",
    "iso:country":"EE",
    "name:ceb_x_preferred":[
        "Singa"
    ],
    "name:deu_x_preferred":[
        "Singa"
    ],
    "name:fra_x_preferred":[
        "Singa"
    ],
    "name:ita_x_preferred":[
        "Singa"
    ],
    "name:new_x_preferred":[
        "\u0938\u093f\u0902\u0917\u093e"
    ],
    "name:nld_x_preferred":[
        "Singa"
    ],
    "name:por_x_preferred":[
        "Singa"
    ],
    "name:swe_x_preferred":[
        "Singa"
    ],
    "wof:name":"Singa",
    "wof:placetype":"locality"
},
  "geometry": {"coordinates":[26.55389000000001,57.6375],"type":"Point"}
}