{
  "type": "Feature",
  "properties": {
    "gn:admin1_code":"21.0",
    "gn:admin2_code":"698.0",
    "gn:admin3_code":"7609.0",
    "gn:asciiname":"Singa",
    "gn:country_code":"EE",
    "gn:dem":78,
    "gn:feature_class":"P",
    "gn:feature_code":"PPL",
    "gn:name":"Singa",
    "gn:population":0,
    "gn:timezone":"Europe/Tallinn",
    "iso:country":"EE",
    "wof:name":"Singa",
    "wof:placetype":"locality"
},
  "geometry": {"coordinates":[26.55389000000001,57.6375],"type":"Point"}
}