{
  "type": "Feature",
  "properties": {
    "gn:admin1_code":"3.0",
    "gn:admin2_code":"803.0",
    "gn:admin3_code":"1253.0",
    "gn:asciiname":"Amula",
    "gn:country_code":"EE",
    "gn:dem":60,
    "gn:feature_class":"P",
    "gn:feature_code":"PPL",
    "gn:name":"Amula",
    "gn:population":0,
    "gn:timezone":"Europe/Tallinn",
    "iso:country":"EE",
    "name:deu_x_preferred":[
        "Amula"
    ],
    "name:est_x_preferred":[
        "Amula"
    ],
    "name:fas_x_preferred":[
        "\u0639\u0645\u0648\u0644\u0627"
    ],
    "name:hye_x_preferred":[
        "\u0531\u0574\u0578\u0582\u056c\u0561"
    ],
    "name:nld_x_preferred":[
        "Amula"
    ],
    "name:pol_x_preferred":[
        "Amula"
    ],
    "name:spa_x_preferred":[
        "Amula"
    ],
    "name:vol_x_preferred":[
        "Amula"
    ],
    "wof:coterminous":[
        1713313301
    ],
    "wof:lang_x_official":[
        "est"
    ],
    "wof:lang_x_spoken":[
        "est"
    ],
    "wof:name":"Amula",
    "wof:placetype":"locality"
},
  "geometry": {"coordinates":[27.32139,59.41694],"type":"Point"}
}