{
  "type": "Feature",
  "properties": {
    "gn:admin1_code":"12.0",
    "gn:admin2_code":"622.0",
    "gn:admin3_code":"6461.0",
    "gn:asciiname":"Puskaru",
    "gn:country_code":"EE",
    "gn:dem":99,
    "gn:feature_class":"P",
    "gn:feature_code":"PPL",
    "gn:name":"Puskaru",
    "gn:population":0,
    "gn:timezone":"Europe/Tallinn",
    "iso:country":"EE",
    "name:est_x_preferred":[
        "Puskaru"
    ],
    "name:hye_x_preferred":[
        "\u054a\u0578\u0582\u057d\u056f\u0561\u057c\u0578\u0582"
    ],
    "name:pol_x_preferred":[
        "Puskaru"
    ],
    "name:spa_x_preferred":[
        "Puskaru"
    ],
    "name:ukr_x_preferred":[
        "\u041f\u0443\u0441\u043a\u0430\u0440\u0443"
    ],
    "name:vol_x_preferred":[
        "Puskaru"
    ],
    "wof:name":"Puskaru",
    "wof:placetype":"locality"
},
  "geometry": {"coordinates":[26.92972,58.00528000000001],"type":"Point"}
}