{
  "type": "Feature",
  "properties": {
    "gn:admin1_code":"8.0",
    "gn:admin2_code":"792.0",
    "gn:admin3_code":"8549.0",
    "gn:asciiname":"Leesi",
    "gn:country_code":"EE",
    "gn:dem":95,
    "gn:feature_class":"P",
    "gn:feature_code":"PPL",
    "gn:name":"Leesi",
    "gn:population":0,
    "gn:timezone":"Europe/Tallinn",
    "iso:country":"EE",
    "name:und_x_variant":[
        "Lesi",
        "Leesi Asundus",
        "Leesi"
    ],
    "wof:name":"Leesi",
    "wof:placetype":"locality"
},
  "geometry": {"coordinates":[25.84167,59.28333000000001],"type":"Point"}
}