{
  "type": "Feature",
  "properties": {
    "gn:admin1_code":"8.0",
    "gn:admin2_code":"191.0",
    "gn:admin3_code":"3345.0",
    "gn:asciiname":"Koljaku",
    "gn:cc2":"EE",
    "gn:country_code":"EE",
    "gn:dem":42,
    "gn:feature_class":"P",
    "gn:feature_code":"PPL",
    "gn:name":"Koljaku",
    "gn:population":0,
    "gn:timezone":"Europe/Tallinn",
    "iso:country":"EE",
    "name:und_x_variant":[
        "V\u00f5sa-Metsanurga",
        "Koljaku"
    ],
    "wof:name":"Koljaku",
    "wof:placetype":"locality"
},
  "geometry": {"coordinates":[25.95694,59.54806],"type":"Point"}
}