{
  "type": "Feature",
  "properties": {
    "gn:admin1_code":"5.0",
    "gn:admin2_code":"618.0",
    "gn:admin3_code":"2582.0",
    "gn:asciiname":"Kalikuela",
    "gn:country_code":"EE",
    "gn:dem":57,
    "gn:feature_class":"P",
    "gn:feature_code":"PPL",
    "gn:name":"Kalik\u00fcla",
    "gn:population":0,
    "gn:timezone":"Europe/Tallinn",
    "iso:country":"EE",
    "name:und_x_variant":[
        "Kalik\u00fcla"
    ],
    "wof:name":"Kalikuela",
    "wof:placetype":"locality"
},
  "geometry": {"coordinates":[26.07917,58.63916999999999],"type":"Point"}
}