{
  "type": "Feature",
  "properties": {
    "gn:admin1_code":"5.0",
    "gn:admin2_code":"618.0",
    "gn:admin3_code":"2582.0",
    "gn:asciiname":"Kalikuela",
    "gn:country_code":"EE",
    "gn:dem":57,
    "gn:feature_class":"P",
    "gn:feature_code":"PPL",
    "gn:name":"Kalik\u00fcla",
    "gn:population":0,
    "gn:timezone":"Europe/Tallinn",
    "iso:country":"EE",
    "name:est_x_preferred":[
        "Kalik\u00fcla"
    ],
    "name:hye_x_preferred":[
        "\u053f\u0561\u056c\u056b\u056f\u0575\u0578\u0582\u056c\u0561"
    ],
    "name:pol_x_preferred":[
        "Kalik\u00fcla"
    ],
    "name:spa_x_preferred":[
        "Kalik\u00fcla"
    ],
    "name:vol_x_preferred":[
        "Kalik\u00fcla"
    ],
    "wof:lang_x_official":[
        "est"
    ],
    "wof:lang_x_spoken":[
        "est"
    ],
    "wof:name":"Kalikuela",
    "wof:placetype":"locality"
},
  "geometry": {"coordinates":[26.07917,58.63917],"type":"Point"}
}