{
  "type": "Feature",
  "properties": {
    "gn:admin1_code":"5.0",
    "gn:admin2_code":"247.0",
    "gn:admin3_code":"7232.0",
    "gn:asciiname":"Aoveski",
    "gn:country_code":"EE",
    "gn:dem":83,
    "gn:feature_class":"P",
    "gn:feature_code":"PPL",
    "gn:name":"Aoveski",
    "gn:population":0,
    "gn:timezone":"Europe/Tallinn",
    "iso:country":"EE",
    "name:und_x_variant":[
        "M\u00e4eall"
    ],
    "wof:name":"Aoveski",
    "wof:placetype":"locality"
},
  "geometry": {"coordinates":[26.665,58.76694000000001],"type":"Point"}
}