{
  "type": "Feature",
  "properties": {
    "gn:admin1_code":"21.0",
    "gn:admin2_code":"917.0",
    "gn:admin3_code":"8669.0",
    "gn:asciiname":"Umbsaare",
    "gn:country_code":"EE",
    "gn:dem":81,
    "gn:feature_class":"P",
    "gn:feature_code":"PPL",
    "gn:name":"Umbsaare",
    "gn:population":0,
    "gn:timezone":"Europe/Tallinn",
    "iso:country":"EE",
    "wof:coterminous":[
        1713316217
    ],
    "wof:lang_x_official":[
        "est"
    ],
    "wof:lang_x_spoken":[
        "est"
    ],
    "wof:name":"Umbsaare",
    "wof:placetype":"locality"
},
  "geometry": {"coordinates":[27.12278,57.82306],"type":"Point"}
}