{
  "type": "Feature",
  "properties": {
    "gn:admin1_code":"5.0",
    "gn:admin2_code":"247.0",
    "gn:admin3_code":"2861.0",
    "gn:asciiname":"Altkuela",
    "gn:country_code":"EE",
    "gn:dem":97,
    "gn:feature_class":"P",
    "gn:feature_code":"PPL",
    "gn:name":"Altk\u00fcla",
    "gn:population":0,
    "gn:timezone":"Europe/Tallinn",
    "iso:country":"EE",
    "name:und_x_variant":[
        "Altk\u00fcla",
        "\u0410\u043b\u043b\u043a\u044e\u043b\u044f"
    ],
    "wof:name":"Altkuela",
    "wof:placetype":"locality"
},
  "geometry": {"coordinates":[26.59583,58.7625],"type":"Point"}
}