{
  "type": "Feature",
  "properties": {
    "gn:admin1_code":"1.0",
    "gn:admin2_code":"353.0",
    "gn:admin3_code":"8193.0",
    "gn:asciiname":"Toreska",
    "gn:country_code":"EE",
    "gn:dem":92,
    "gn:feature_class":"P",
    "gn:feature_code":"PPL",
    "gn:name":"T\u00f5reska",
    "gn:population":0,
    "gn:timezone":"Europe/Tallinn",
    "iso:country":"EE",
    "name:est_x_preferred":[
        "T\u00f5reska"
    ],
    "name:fas_x_preferred":[
        "\u062a\u0648\u0631\u0633\u06a9\u0627"
    ],
    "name:fra_x_preferred":[
        "T\u00f5reska"
    ],
    "name:hye_x_preferred":[
        "\u054f\u056b\u057c\u0565\u057d\u056f\u0561"
    ],
    "name:pol_x_preferred":[
        "T\u00f5reska"
    ],
    "name:rus_x_preferred":[
        "\u0422\u044b\u0440\u0435\u0441\u043a\u0430"
    ],
    "name:spa_x_preferred":[
        "T\u00f5reska"
    ],
    "name:und_x_variant":[
        "Tereska"
    ],
    "name:vol_x_preferred":[
        "T\u00f5reska"
    ],
    "wof:coterminous":[
        1713314515
    ],
    "wof:lang_x_official":[
        "est"
    ],
    "wof:lang_x_spoken":[
        "est"
    ],
    "wof:name":"Toreska",
    "wof:placetype":"locality"
},
  "geometry": {"coordinates":[25.84222,59.40972],"type":"Point"}
}