{
  "type": "Feature",
  "properties": {
    "gn:admin1_code":"14.0",
    "gn:admin2_code":"714.0",
    "gn:admin3_code":"9145.0",
    "gn:asciiname":"Vatskuela",
    "gn:country_code":"EE",
    "gn:dem":12,
    "gn:feature_class":"P",
    "gn:feature_code":"PPL",
    "gn:name":"Vatsk\u00fcla",
    "gn:population":0,
    "gn:timezone":"Europe/Tallinn",
    "iso:country":"EE",
    "name:und_x_variant":[
        "Vatskyula",
        "Vatsk\u00fcla"
    ],
    "wof:name":"Vatskuela",
    "wof:placetype":"locality"
},
  "geometry": {"coordinates":[22.62889,58.27528],"type":"Point"}
}