{
  "type": "Feature",
  "properties": {
    "gn:admin1_code":"14.0",
    "gn:admin2_code":"714.0",
    "gn:admin3_code":"9145.0",
    "gn:asciiname":"Vatskuela",
    "gn:country_code":"EE",
    "gn:dem":12,
    "gn:feature_class":"P",
    "gn:feature_code":"PPL",
    "gn:name":"Vatsk\u00fcla",
    "gn:population":0,
    "gn:timezone":"Europe/Tallinn",
    "iso:country":"EE",
    "name:deu_x_preferred":[
        "Vatsk\u00fcla"
    ],
    "name:est_x_preferred":[
        "Vatsk\u00fcla"
    ],
    "name:fas_x_preferred":[
        "\u0648\u062a\u0633\u06a9\u0648\u0644\u0627"
    ],
    "name:fra_x_preferred":[
        "Vatsk\u00fcla"
    ],
    "name:hye_x_preferred":[
        "\u054e\u0561\u0581\u056f\u0575\u0578\u0582\u056c\u0561"
    ],
    "name:nld_x_preferred":[
        "Vatsk\u00fcla"
    ],
    "name:pol_x_preferred":[
        "Vatsk\u00fcla"
    ],
    "name:spa_x_preferred":[
        "Vatsk\u00fcla"
    ],
    "name:ukr_x_preferred":[
        "\u0412\u0430\u0442\u0441\u043a\u044e\u043b\u0430"
    ],
    "name:und_x_variant":[
        "Vatskyula",
        "Vatsk\u00fcla"
    ],
    "name:vol_x_preferred":[
        "Vatsk\u00fcla"
    ],
    "wof:name":"Vatskuela",
    "wof:placetype":"locality"
},
  "geometry": {"coordinates":[22.62889,58.27528],"type":"Point"}
}