{
  "type": "Feature",
  "properties": {
    "gn:admin1_code":"5.0",
    "gn:admin2_code":"618.0",
    "gn:admin3_code":"2461.0",
    "gn:asciiname":"Kablakuela",
    "gn:country_code":"EE",
    "gn:dem":55,
    "gn:feature_class":"P",
    "gn:feature_code":"PPL",
    "gn:name":"Kablak\u00fcla",
    "gn:population":0,
    "gn:timezone":"Europe/Tallinn",
    "iso:country":"EE",
    "name:est_x_preferred":[
        "Kablak\u00fcla"
    ],
    "name:hye_x_preferred":[
        "\u053f\u0561\u0562\u056c\u0561\u056f\u0575\u0578\u0582\u056c\u0561"
    ],
    "name:pol_x_preferred":[
        "Kablak\u00fcla"
    ],
    "name:spa_x_preferred":[
        "Kablak\u00fcla"
    ],
    "name:und_x_variant":[
        "Kabla"
    ],
    "name:vol_x_preferred":[
        "Kablak\u00fcla"
    ],
    "wof:coterminous":[
        1713312159
    ],
    "wof:lang_x_official":[
        "est"
    ],
    "wof:lang_x_spoken":[
        "est"
    ],
    "wof:name":"Kablakuela",
    "wof:placetype":"locality"
},
  "geometry": {"coordinates":[26.06639,58.61194],"type":"Point"}
}