{
  "type": "Feature",
  "properties": {
    "gn:admin1_code":"14.0",
    "gn:admin2_code":"714.0",
    "gn:admin3_code":"1313.0",
    "gn:asciiname":"Somera",
    "gn:cc2":"EE",
    "gn:country_code":"EE",
    "gn:dem":15,
    "gn:feature_class":"P",
    "gn:feature_code":"PPL",
    "gn:name":"S\u00f5mera",
    "gn:population":0,
    "gn:timezone":"Europe/Tallinn",
    "iso:country":"EE",
    "name:deu_x_preferred":[
        "S\u00f5mera"
    ],
    "name:est_x_preferred":[
        "S\u00f5mera"
    ],
    "name:fra_x_preferred":[
        "S\u00f5mera"
    ],
    "name:hye_x_preferred":[
        "\u054d\u056b\u0574\u0565\u057c\u0561"
    ],
    "name:pol_x_preferred":[
        "S\u00f5mera"
    ],
    "name:spa_x_preferred":[
        "S\u00f5mera"
    ],
    "name:ukr_x_preferred":[
        "\u0421\u0438\u043c\u0435\u0440\u0430"
    ],
    "name:und_x_variant":[
        "Symera"
    ],
    "name:vol_x_preferred":[
        "S\u00f5mera"
    ],
    "wof:coterminous":[
        1713308135
    ],
    "wof:lang_x_official":[
        "est"
    ],
    "wof:lang_x_spoken":[
        "est"
    ],
    "wof:name":"Somera",
    "wof:placetype":"locality"
},
  "geometry": {"coordinates":[22.25889,58.29528],"type":"Point"}
}