{
  "type": "Feature",
  "properties": {
    "gn:admin1_code":"21.0",
    "gn:admin2_code":"698.0",
    "gn:admin3_code":"5770.0",
    "gn:asciiname":"Paaburissa",
    "gn:country_code":"EE",
    "gn:dem":212,
    "gn:feature_class":"P",
    "gn:feature_code":"PPL",
    "gn:name":"Paaburissa",
    "gn:population":0,
    "gn:timezone":"Europe/Tallinn",
    "iso:country":"EE",
    "name:und_x_variant":[
        "Paborissa"
    ],
    "wof:name":"Paaburissa",
    "wof:placetype":"locality"
},
  "geometry": {"coordinates":[26.97556,57.71028],"type":"Point"}
}