{
  "type": "Feature",
  "properties": {
    "gn:country":"EE",
    "gn:fcode":"PPL",
    "gn:population":133,
    "iso:country":"EE",
    "name:bul_x_preferred":[
        "\u041f\u0430\u0435\u043a\u043d\u0430"
    ],
    "name:ceb_x_preferred":[
        "Paekna"
    ],
    "name:eng_x_preferred":[
        "Paekna"
    ],
    "name:est_x_preferred":[
        "Paekna"
    ],
    "name:fra_x_preferred":[
        "Paekna"
    ],
    "name:hye_x_preferred":[
        "\u054a\u0561\u0565\u056f\u0576\u0561"
    ],
    "name:nld_x_preferred":[
        "Paekna"
    ],
    "name:pol_x_preferred":[
        "Paekna"
    ],
    "name:rus_x_preferred":[
        "\u041f\u0430\u044d\u043a\u043d\u0430"
    ],
    "name:spa_x_preferred":[
        "Paekna"
    ],
    "name:swe_x_preferred":[
        "Paekna"
    ],
    "name:vol_x_preferred":[
        "Paekna"
    ],
    "qs_pg:aaroncc":"EE",
    "qs_pg:gn_country":"EE",
    "qs_pg:gn_fcode":"PPL",
    "qs_pg:gn_pop":133,
    "qs_pg:name":"Paekna",
    "qs_pg:name_adm0":"Eesti",
    "qs_pg:name_adm1":"Harjumaa",
    "qs_pg:photos_9r":0,
    "qs_pg:photos_sr":0,
    "qs_pg:pop_sr":1,
    "qs_pg:qs_pg_placetype":"locality",
    "qs_pg:qs_pg_placetype_gp":"Town",
    "qs_pg:woe_adm0":23424805,
    "woe:adm0_id":23424805,
    "woe:name_adm0":"Eesti",
    "woe:name_adm1":"Harjumaa",
    "woe:placetype":"Town",
    "wof:coterminous":[
        1713312889
    ],
    "wof:lang_x_official":[
        "est"
    ],
    "wof:lang_x_spoken":[
        "est"
    ],
    "wof:name":"Paekna",
    "wof:placetype":"locality",
    "wof:population":133
},
  "geometry": {"coordinates":[24.82222,59.27028],"type":"Point"}
}