{
  "type": "Feature",
  "properties": {
    "gn:admin1_code":"7.0",
    "gn:admin2_code":"184.0",
    "gn:admin3_code":"1201.0",
    "gn:asciiname":"Allika",
    "gn:country_code":"EE",
    "gn:dem":8,
    "gn:feature_class":"P",
    "gn:feature_code":"PPL",
    "gn:name":"Allika",
    "gn:population":0,
    "gn:timezone":"Europe/Tallinn",
    "iso:country":"EE",
    "name:und_x_variant":[
        "Alliku",
        "Allika"
    ],
    "wof:name":"Allika",
    "wof:placetype":"locality"
},
  "geometry": {"coordinates":[23.55167,58.835],"type":"Point"}
}