{
  "type": "Feature",
  "properties": {
    "gn:admin1_code":"4.0",
    "gn:admin2_code":"255.0",
    "gn:admin3_code":"8137.0",
    "gn:asciiname":"Tamsi",
    "gn:country_code":"EE",
    "gn:dem":72,
    "gn:feature_class":"P",
    "gn:feature_code":"PPL",
    "gn:name":"Tamsi",
    "gn:population":0,
    "gn:timezone":"Europe/Tallinn",
    "iso:country":"EE",
    "name:est_x_preferred":[
        "Tamsi"
    ],
    "name:hye_x_preferred":[
        "\u054f\u0561\u0574\u057d\u056b"
    ],
    "name:pol_x_preferred":[
        "Tamsi"
    ],
    "name:spa_x_preferred":[
        "Tamsi"
    ],
    "name:ukr_x_preferred":[
        "\u0422\u0430\u043c\u0441\u0456"
    ],
    "name:vol_x_preferred":[
        "Tamsi"
    ],
    "wof:name":"Tamsi",
    "wof:placetype":"locality"
},
  "geometry": {"coordinates":[25.78333,58.83333],"type":"Point"}
}