{
  "type": "Feature",
  "properties": {
    "gn:admin1_code":"4.0",
    "gn:admin2_code":"255.0",
    "gn:admin3_code":"8137.0",
    "gn:asciiname":"Tamsi",
    "gn:country_code":"EE",
    "gn:dem":72,
    "gn:feature_class":"P",
    "gn:feature_code":"PPL",
    "gn:name":"Tamsi",
    "gn:population":0,
    "gn:timezone":"Europe/Tallinn",
    "iso:country":"EE",
    "wof:name":"Tamsi",
    "wof:placetype":"locality"
},
  "geometry": {"coordinates":[25.78333,58.83333],"type":"Point"}
}