{
  "type": "Feature",
  "properties": {
    "gn:admin1_code":"21.0",
    "gn:admin2_code":"698.0",
    "gn:admin3_code":"6858.0",
    "gn:asciiname":"Hallimaee",
    "gn:country_code":"EE",
    "gn:dem":88,
    "gn:feature_class":"P",
    "gn:feature_code":"PPL",
    "gn:name":"Hallim\u00e4e",
    "gn:population":0,
    "gn:timezone":"Europe/Tallinn",
    "iso:country":"EE",
    "name:und_x_variant":[
        "Hallim\u00e4e",
        "M\u00e4ek\u00fcla"
    ],
    "wof:lang_x_official":[
        "est"
    ],
    "wof:lang_x_spoken":[
        "est"
    ],
    "wof:name":"Hallimaee",
    "wof:placetype":"locality"
},
  "geometry": {"coordinates":[26.68611,57.64472],"type":"Point"}
}