{
  "type": "Feature",
  "properties": {
    "gn:country":"EE",
    "gn:fcode":"PPL",
    "gn:population":0,
    "iso:country":"EE",
    "name:deu_x_preferred":[
        "Nohipalo"
    ],
    "name:eng_x_preferred":[
        "Nohipalo"
    ],
    "name:est_x_preferred":[
        "Nohipalo"
    ],
    "name:fra_x_preferred":[
        "Nohipalo"
    ],
    "name:hye_x_preferred":[
        "\u0546\u0578\u0570\u056b\u057a\u0561\u056c\u0578"
    ],
    "name:nan_x_preferred":[
        "Nohipalo"
    ],
    "name:nld_x_preferred":[
        "Nohipalo"
    ],
    "name:pol_x_preferred":[
        "Nohipalo"
    ],
    "name:spa_x_preferred":[
        "Nohipalo"
    ],
    "name:tat_x_preferred":[
        "\u041d\u043e\u04bb\u0438\u043f\u0430\u043b\u043e"
    ],
    "name:ukr_x_preferred":[
        "\u041d\u043e\u0445\u0456\u043f\u0430\u043b\u043e"
    ],
    "name:vol_x_preferred":[
        "Nohipalo"
    ],
    "name:vro_x_preferred":[
        "Nohipalo k\u00fcl\u00e4"
    ],
    "qs_pg:aaroncc":"EE",
    "qs_pg:gn_country":"EE",
    "qs_pg:gn_fcode":"PPL",
    "qs_pg:gn_pop":0,
    "qs_pg:name":"Nohipalo",
    "qs_pg:name_adm0":"Eesti",
    "qs_pg:name_adm1":"P\u00f5lvamaa",
    "qs_pg:photos":85,
    "qs_pg:photos_1k":17,
    "qs_pg:photos_9k":1,
    "qs_pg:photos_9r":3,
    "qs_pg:photos_all":85,
    "qs_pg:photos_sr":3,
    "qs_pg:pop_sr":0,
    "qs_pg:qs_pg_placetype":"locality",
    "qs_pg:qs_pg_placetype_gp":"Town",
    "qs_pg:woe_adm0":23424805,
    "woe:adm0_id":23424805,
    "woe:name_adm0":"Eesti",
    "woe:name_adm1":"P\u00f5lvamaa",
    "woe:placetype":"Town",
    "wof:coterminous":[
        1713315747
    ],
    "wof:lang_x_official":[
        "est"
    ],
    "wof:lang_x_spoken":[
        "est"
    ],
    "wof:name":"Nohipalo",
    "wof:placetype":"locality"
},
  "geometry": {"coordinates":[27.33528,57.93861],"type":"Point"}
}