{
  "type": "Feature",
  "properties": {
    "gn:admin1_code":"14.0",
    "gn:admin2_code":"714.0",
    "gn:admin3_code":"2864.0",
    "gn:asciiname":"Kaugatuma",
    "gn:cc2":"EE",
    "gn:country_code":"EE",
    "gn:dem":9,
    "gn:feature_class":"P",
    "gn:feature_code":"PPL",
    "gn:name":"Kaugatuma",
    "gn:population":0,
    "gn:timezone":"Europe/Tallinn",
    "iso:country":"EE",
    "name:und_x_variant":[
        "Kaugatoma",
        "Kaugatooma",
        "Kaugatuma"
    ],
    "wof:name":"Kaugatuma",
    "wof:placetype":"locality"
},
  "geometry": {"coordinates":[22.20917,58.12],"type":"Point"}
}