{
  "type": "Feature",
  "properties": {
    "gn:admin1_code":"12.0",
    "gn:admin2_code":"284.0",
    "gn:admin3_code":"9229.0",
    "gn:asciiname":"Palu",
    "gn:country_code":"EE",
    "gn:dem":129,
    "gn:feature_class":"P",
    "gn:feature_code":"PPL",
    "gn:name":"Palu",
    "gn:population":0,
    "gn:timezone":"Europe/Tallinn",
    "iso:country":"EE",
    "name:und_x_variant":[
        "Ihamaru"
    ],
    "wof:name":"Palu",
    "wof:placetype":"locality"
},
  "geometry": {"coordinates":[26.74778,58.13083],"type":"Point"}
}