{
  "type": "Feature",
  "properties": {
    "gn:admin1_code":"12.0",
    "gn:admin2_code":"284.0",
    "gn:admin3_code":"9229.0",
    "gn:asciiname":"Palu",
    "gn:country_code":"EE",
    "gn:dem":129,
    "gn:feature_class":"P",
    "gn:feature_code":"PPL",
    "gn:name":"Palu",
    "gn:population":0,
    "gn:timezone":"Europe/Tallinn",
    "iso:country":"EE",
    "name:ace_x_preferred":[
        "Palu"
    ],
    "name:ara_x_preferred":[
        "\u0628\u0627\u0644\u0648"
    ],
    "name:azb_x_preferred":[
        "\u067e\u0627\u0644\u0648"
    ],
    "name:bel_x_preferred":[
        "\u041f\u0430\u043b\u0443"
    ],
    "name:ceb_x_preferred":[
        "Kota Palu"
    ],
    "name:deu_x_preferred":[
        "Palu"
    ],
    "name:est_x_preferred":[
        "Palu"
    ],
    "name:eus_x_preferred":[
        "Palu"
    ],
    "name:fas_x_preferred":[
        "\u067e\u0627\u0644\u0648"
    ],
    "name:fij_x_preferred":[
        "Palu"
    ],
    "name:fin_x_preferred":[
        "Palu"
    ],
    "name:fra_x_preferred":[
        "Palu"
    ],
    "name:gor_x_preferred":[
        "Kota Palu"
    ],
    "name:hin_x_preferred":[
        "\u092a\u093e\u0932\u0942"
    ],
    "name:hun_x_preferred":[
        "Palu"
    ],
    "name:ind_x_preferred":[
        "Kota Palu"
    ],
    "name:ita_x_preferred":[
        "Palu"
    ],
    "name:jav_x_preferred":[
        "Kutha Palu"
    ],
    "name:jpn_x_preferred":[
        "\u30d1\u30eb"
    ],
    "name:lit_x_preferred":[
        "Palu"
    ],
    "name:mlg_x_preferred":[
        "Kota Palu"
    ],
    "name:msa_x_preferred":[
        "Kota Palu"
    ],
    "name:nld_x_preferred":[
        "Palu"
    ],
    "name:nor_x_preferred":[
        "Palu"
    ],
    "name:pnb_x_preferred":[
        "\u067e\u0627\u0644\u0648"
    ],
    "name:pol_x_preferred":[
        "Palu"
    ],
    "name:por_x_preferred":[
        "Palu"
    ],
    "name:ron_x_preferred":[
        "Palu"
    ],
    "name:rus_x_preferred":[
        "\u041f\u0430\u043b\u0443"
    ],
    "name:spa_x_preferred":[
        "Palu"
    ],
    "name:sqi_x_preferred":[
        "Palu"
    ],
    "name:swe_x_preferred":[
        "Palu"
    ],
    "name:tha_x_preferred":[
        "\u0e1b\u0e32\u0e25\u0e39"
    ],
    "name:tur_x_preferred":[
        "Palu"
    ],
    "name:ukr_x_preferred":[
        "\u041f\u0430\u043b\u0443"
    ],
    "name:und_x_variant":[
        "Ihamaru"
    ],
    "name:urd_x_preferred":[
        "\u067e\u0627\u0644\u0648"
    ],
    "name:vie_x_preferred":[
        "Palu"
    ],
    "name:war_x_preferred":[
        "Palu"
    ],
    "name:wuu_x_preferred":[
        "\u5e15\u76e7"
    ],
    "name:xmf_x_preferred":[
        "\u10de\u10d0\u10da\u10e3"
    ],
    "wof:lang_x_official":[
        "est"
    ],
    "wof:lang_x_spoken":[
        "est"
    ],
    "wof:name":"Palu",
    "wof:placetype":"locality"
},
  "geometry": {"coordinates":[26.74778,58.13083],"type":"Point"}
}