{
  "type": "Feature",
  "properties": {
    "gn:admin1_code":"21.0",
    "gn:admin2_code":"698.0",
    "gn:admin3_code":"2145.0",
    "gn:asciiname":"Tulbasuu",
    "gn:country_code":"EE",
    "gn:dem":200,
    "gn:feature_class":"P",
    "gn:feature_code":"PPL",
    "gn:name":"Tulbasuu",
    "gn:population":0,
    "gn:timezone":"Europe/Tallinn",
    "iso:country":"EE",
    "name:und_x_variant":[
        "Tulbasoo"
    ],
    "wof:name":"Tulbasuu",
    "wof:placetype":"locality"
},
  "geometry": {"coordinates":[27.03083,57.75694],"type":"Point"}
}