{
  "type": "Feature",
  "properties": {
    "gn:admin1_code":"18.0",
    "gn:admin2_code":"796.0",
    "gn:admin3_code":"8629.0",
    "gn:asciiname":"Uhmardu",
    "gn:country_code":"EE",
    "gn:dem":54,
    "gn:feature_class":"P",
    "gn:feature_code":"PPL",
    "gn:name":"Uhmardu",
    "gn:population":0,
    "gn:timezone":"Europe/Tallinn",
    "iso:country":"EE",
    "wof:name":"Uhmardu",
    "wof:placetype":"locality"
},
  "geometry": {"coordinates":[26.78361,58.62056],"type":"Point"}
}