{
  "type": "Feature",
  "properties": {
    "gn:admin1_code":"21.0",
    "gn:admin2_code":"732.0",
    "gn:admin3_code":"2512.0",
    "gn:asciiname":"Kahkva",
    "gn:cc2":"EE",
    "gn:country_code":"EE",
    "gn:dem":40,
    "gn:feature_class":"P",
    "gn:feature_code":"PPL",
    "gn:name":"Kahkva",
    "gn:population":0,
    "gn:timezone":"Europe/Tallinn",
    "iso:country":"EE",
    "name:deu_x_preferred":[
        "Kahkva"
    ],
    "name:est_x_preferred":[
        "Kahkva"
    ],
    "name:fra_x_preferred":[
        "Kahkva"
    ],
    "name:hye_x_preferred":[
        "\u053f\u0561\u0570\u056f\u057e\u0561"
    ],
    "name:pol_x_preferred":[
        "Kahkva"
    ],
    "name:sco_x_preferred":[
        "Kahkva"
    ],
    "name:spa_x_preferred":[
        "Kahkva"
    ],
    "name:ukr_x_preferred":[
        "\u041a\u0430\u0445\u043a\u0432\u0430"
    ],
    "name:und_x_variant":[
        "Myza Kyakhkva",
        "Kahkva Asundus"
    ],
    "name:vol_x_preferred":[
        "Kahkva"
    ],
    "wof:name":"Kahkva",
    "wof:placetype":"locality"
},
  "geometry": {"coordinates":[27.47,57.99833],"type":"Point"}
}