{
  "type": "Feature",
  "properties": {
    "gn:admin1_code":"21.0",
    "gn:admin2_code":"732.0",
    "gn:admin3_code":"2512.0",
    "gn:asciiname":"Kahkva",
    "gn:cc2":"EE",
    "gn:country_code":"EE",
    "gn:dem":40,
    "gn:feature_class":"P",
    "gn:feature_code":"PPL",
    "gn:name":"Kahkva",
    "gn:population":0,
    "gn:timezone":"Europe/Tallinn",
    "iso:country":"EE",
    "name:und_x_variant":[
        "Myza Kyakhkva",
        "Kahkva Asundus",
        "Kahkva"
    ],
    "wof:name":"Kahkva",
    "wof:placetype":"locality"
},
  "geometry": {"coordinates":[27.47,57.99833],"type":"Point"}
}