{
  "type": "Feature",
  "properties": {
    "gn:admin1_code":"7.0",
    "gn:admin2_code":"441.0",
    "gn:admin3_code":"3135.0",
    "gn:asciiname":"Kuundra",
    "gn:country_code":"EE",
    "gn:dem":21,
    "gn:feature_class":"P",
    "gn:feature_code":"PPL",
    "gn:name":"Kuundra",
    "gn:population":0,
    "gn:timezone":"Europe/Tallinn",
    "iso:country":"EE",
    "name:und_x_variant":[
        "Kundra",
        "Kuundra"
    ],
    "wof:name":"Kuundra",
    "wof:placetype":"locality"
},
  "geometry": {"coordinates":[23.78417,58.91222],"type":"Point"}
}