{
  "type": "Feature",
  "properties": {
    "gn:admin1_code":"21.0",
    "gn:admin2_code":"698.0",
    "gn:admin3_code":"3250.0",
    "gn:asciiname":"Arukuelae",
    "gn:country_code":"EE",
    "gn:dem":74,
    "gn:feature_class":"P",
    "gn:feature_code":"PPL",
    "gn:name":"Aruk\u00fcl\u00e4",
    "gn:population":0,
    "gn:timezone":"Europe/Tallinn",
    "iso:country":"EE",
    "name:und_x_variant":[
        "Aruk\u00fcl\u00e4",
        "Aruk\u00fcla"
    ],
    "wof:name":"Arukuelae",
    "wof:placetype":"locality"
},
  "geometry": {"coordinates":[26.48417,57.65583],"type":"Point"}
}