{
  "type": "Feature",
  "properties": {
    "gn:admin1_code":"21.0",
    "gn:admin2_code":"142.0",
    "gn:admin3_code":"3069.0",
    "gn:asciiname":"Lalli",
    "gn:country_code":"EE",
    "gn:dem":103,
    "gn:feature_class":"P",
    "gn:feature_code":"PPL",
    "gn:name":"Lalli",
    "gn:population":0,
    "gn:timezone":"Europe/Tallinn",
    "iso:country":"EE",
    "wof:name":"Lalli",
    "wof:placetype":"locality"
},
  "geometry": {"coordinates":[26.67111,57.72778],"type":"Point"}
}