{
  "type": "Feature",
  "properties": {
    "gn:admin1_code":"21.0",
    "gn:admin2_code":"142.0",
    "gn:admin3_code":"3069.0",
    "gn:asciiname":"Lalli",
    "gn:country_code":"EE",
    "gn:dem":103,
    "gn:feature_class":"P",
    "gn:feature_code":"PPL",
    "gn:name":"Lalli",
    "gn:population":0,
    "gn:timezone":"Europe/Tallinn",
    "iso:country":"EE",
    "name:ara_x_preferred":[
        "\u0644\u0627\u0644\u064a"
    ],
    "name:bel_x_preferred":[
        "\u041b\u0430\u043b\u0456"
    ],
    "name:deu_x_preferred":[
        "Lalli"
    ],
    "name:est_x_preferred":[
        "Lalli"
    ],
    "name:fin_x_preferred":[
        "Lalli"
    ],
    "name:fra_x_preferred":[
        "Lalli"
    ],
    "name:ita_x_preferred":[
        "Lalli"
    ],
    "name:rus_x_preferred":[
        "\u041b\u0430\u043b\u043b\u0438"
    ],
    "name:sco_x_preferred":[
        "Lalli"
    ],
    "name:spa_x_preferred":[
        "Lalli"
    ],
    "wof:name":"Lalli",
    "wof:placetype":"locality"
},
  "geometry": {"coordinates":[26.67111,57.72778],"type":"Point"}
}