{
  "type": "Feature",
  "properties": {
    "gn:admin1_code":"2.0",
    "gn:admin2_code":"205.0",
    "gn:admin3_code":"9826.0",
    "gn:asciiname":"UElendi",
    "gn:country_code":"EE",
    "gn:dem":26,
    "gn:feature_class":"P",
    "gn:feature_code":"PPL",
    "gn:name":"\u00dclendi",
    "gn:population":0,
    "gn:timezone":"Europe/Tallinn",
    "iso:country":"EE",
    "name:deu_x_preferred":[
        "\u00dclendi"
    ],
    "name:est_x_preferred":[
        "\u00dclendi"
    ],
    "name:hye_x_preferred":[
        "\u0545\u0578\u0582\u056c\u0565\u0576\u0564\u056b"
    ],
    "name:pol_x_preferred":[
        "\u00dclendi"
    ],
    "name:spa_x_preferred":[
        "\u00dclendi"
    ],
    "name:und_x_variant":[
        "Uylendi"
    ],
    "name:vol_x_preferred":[
        "\u00dclendi"
    ],
    "wof:coterminous":[
        1713310751
    ],
    "wof:lang_x_official":[
        "est"
    ],
    "wof:lang_x_spoken":[
        "est"
    ],
    "wof:name":"UElendi",
    "wof:placetype":"locality"
},
  "geometry": {"coordinates":[22.21644,58.89506],"type":"Point"}
}