{
  "type": "Feature",
  "properties": {
    "gn:admin1_code":"11.0",
    "gn:admin2_code":"430.0",
    "gn:admin3_code":"1929.0",
    "gn:asciiname":"Viira",
    "gn:country_code":"EE",
    "gn:dem":4,
    "gn:feature_class":"P",
    "gn:feature_code":"PPL",
    "gn:name":"Viira",
    "gn:population":0,
    "gn:timezone":"Europe/Tallinn",
    "iso:country":"EE",
    "name:deu_x_preferred":[
        "Viira"
    ],
    "name:est_x_preferred":[
        "Viira"
    ],
    "name:fin_x_preferred":[
        "Viira"
    ],
    "name:nld_x_preferred":[
        "Viira"
    ],
    "name:ukr_x_preferred":[
        "\u0412\u0456\u0439\u0440\u0430"
    ],
    "wof:lang_x_official":[
        "est"
    ],
    "wof:lang_x_spoken":[
        "est"
    ],
    "wof:name":"Viira",
    "wof:placetype":"locality"
},
  "geometry": {"coordinates":[23.67472,58.54583],"type":"Point"}
}