{
  "type": "Feature",
  "properties": {
    "gn:admin1_code":"8.0",
    "gn:admin2_code":"272.0",
    "gn:admin3_code":"6953.0",
    "gn:asciiname":"Torma",
    "gn:country_code":"EE",
    "gn:dem":102,
    "gn:feature_class":"P",
    "gn:feature_code":"PPL",
    "gn:name":"T\u00f5rma",
    "gn:population":0,
    "gn:timezone":"Europe/Tallinn",
    "iso:country":"EE",
    "name:und_x_variant":[
        "Tyrma",
        "T\u00f5rma"
    ],
    "wof:name":"Torma",
    "wof:placetype":"locality"
},
  "geometry": {"coordinates":[25.99972,59.28417],"type":"Point"}
}