{
  "type": "Feature",
  "properties": {
    "gn:admin1_code":"8.0",
    "gn:admin2_code":"903.0",
    "gn:admin3_code":"9121.0",
    "gn:asciiname":"Vasta",
    "gn:cc2":"EE",
    "gn:country_code":"EE",
    "gn:dem":54,
    "gn:feature_class":"P",
    "gn:feature_code":"PPL",
    "gn:name":"Vasta",
    "gn:population":0,
    "gn:timezone":"Europe/Tallinn",
    "iso:country":"EE",
    "name:und_x_variant":[
        "Myza Vasta",
        "Vasta Asundus",
        "Vasta"
    ],
    "wof:name":"Vasta",
    "wof:placetype":"locality"
},
  "geometry": {"coordinates":[26.68972,59.45861],"type":"Point"}
}