{
  "type": "Feature",
  "properties": {
    "gn:country":"EE",
    "gn:fcode":"PPL",
    "gn:population":571,
    "iso:country":"EE",
    "name:ceb_x_preferred":[
        "K\u00f5rvek\u00fcla"
    ],
    "name:eng_x_preferred":[
        "K\u00f5rvek\u00fcla"
    ],
    "name:est_x_preferred":[
        "K\u00f5rvek\u00fcla"
    ],
    "name:fra_x_preferred":[
        "K\u00f5rvek\u00fcla"
    ],
    "name:hye_x_preferred":[
        "\u053f\u056b\u057c\u057e\u0565\u056f\u0575\u0578\u0582\u056c\u0561"
    ],
    "name:nld_x_preferred":[
        "K\u00f5rvek\u00fcla"
    ],
    "name:rus_x_preferred":[
        "\u041a\u044b\u0440\u0432\u0435\u043a\u044e\u043b\u0430"
    ],
    "name:spa_x_preferred":[
        "K\u00f5rvek\u00fcla"
    ],
    "name:swe_x_preferred":[
        "K\u00f5rvek\u00fcla"
    ],
    "name:ukr_x_preferred":[
        "\u041a\u0438\u0440\u0432\u0435\u043a\u044e\u043b\u0430"
    ],
    "name:vol_x_preferred":[
        "K\u00f5rvek\u00fcla"
    ],
    "name:zho_x_preferred":[
        "\u514b\u723e\u97cb\u5c48\u62c9"
    ],
    "qs_pg:aaroncc":"EE",
    "qs_pg:gn_country":"EE",
    "qs_pg:gn_fcode":"PPL",
    "qs_pg:gn_pop":571,
    "qs_pg:name":"K\u00f5rvek\u00fcla",
    "qs_pg:name_adm0":"Eesti",
    "qs_pg:name_adm1":"Tartumaa",
    "qs_pg:photos_9k":1,
    "qs_pg:photos_9r":1,
    "qs_pg:photos_all":1,
    "qs_pg:photos_sr":0,
    "qs_pg:pop_sr":2,
    "qs_pg:qs_pg_placetype":"locality",
    "qs_pg:qs_pg_placetype_gp":"Town",
    "qs_pg:woe_adm0":23424805,
    "woe:adm0_id":23424805,
    "woe:name_adm0":"Eesti",
    "woe:name_adm1":"Tartumaa",
    "woe:placetype":"Town",
    "wof:name":"K\u00f5rvek\u00fcla",
    "wof:placetype":"locality",
    "wof:population":571
},
  "geometry": {"coordinates":[26.78222,58.42417],"type":"Point"}
}