{
  "type": "Feature",
  "properties": {
    "gn:gn_country":"EE",
    "gn:gn_fcode":"PPL",
    "gn:gn_pop":417,
    "gn:population":417,
    "iso:country":"EE",
    "name:bul_x_preferred":[
        "\u041a\u0440\u043e\u0442\u0443\u0441\u0435"
    ],
    "name:deu_x_preferred":[
        "Krootuse"
    ],
    "name:eng_x_preferred":[
        "Krootuse"
    ],
    "name:est_x_preferred":[
        "Krootuse"
    ],
    "name:hye_x_preferred":[
        "\u053f\u057c\u0578\u0578\u057f\u0578\u0582\u057d\u0565"
    ],
    "name:nld_x_preferred":[
        "Krootuse"
    ],
    "name:pol_x_preferred":[
        "Krootuse"
    ],
    "name:ron_x_preferred":[
        "Krootuse"
    ],
    "name:sco_x_preferred":[
        "Krootuse"
    ],
    "name:swe_x_preferred":[
        "Krootuse"
    ],
    "name:ukr_x_preferred":[
        "\u041a\u0440\u043e\u043e\u0442\u0443\u0441\u0435"
    ],
    "name:unk_x_variant":[
        "Myza Krotuze"
    ],
    "name:vol_x_preferred":[
        "Krootuse"
    ],
    "name:vro_x_preferred":[
        "Kruutus\u00f5"
    ],
    "qs_pg:aaroncc":"EE",
    "qs_pg:gn_country":"EE",
    "qs_pg:gn_fcode":"PPL",
    "qs_pg:gn_pop":417,
    "qs_pg:name":"Krootuse",
    "qs_pg:name_adm0":"Eesti",
    "qs_pg:name_adm1":"P\u00f5lvamaa",
    "qs_pg:photos_9k":1,
    "qs_pg:photos_9r":1,
    "qs_pg:photos_all":20,
    "qs_pg:photos_sr":0,
    "qs_pg:pop_sr":2,
    "qs_pg:qs_pg_placetype":"locality",
    "qs_pg:qs_pg_placetype_gp":"Town",
    "qs_pg:woe_adm0":23424805,
    "woe:adm0_id":23424805,
    "woe:name_adm0":"Eesti",
    "woe:name_adm1":"P\u00f5lvamaa",
    "woe:placetype":"Town",
    "wof:name":"Krootuse",
    "wof:placetype":"locality",
    "wof:population":417
},
  "geometry": {"coordinates":[26.835,58.07111],"type":"Point"}
}