{
  "type": "Feature",
  "properties": {
    "gn:admin1_code":"5.0",
    "gn:admin2_code":"247.0",
    "gn:admin3_code":"3518.0",
    "gn:asciiname":"Suevalepa",
    "gn:country_code":"EE",
    "gn:dem":106,
    "gn:feature_class":"P",
    "gn:feature_code":"PPL",
    "gn:name":"S\u00fcvalepa",
    "gn:population":0,
    "gn:timezone":"Europe/Tallinn",
    "iso:country":"EE",
    "name:est_x_preferred":[
        "S\u00fcvalepa"
    ],
    "name:hye_x_preferred":[
        "\u054d\u0575\u0578\u0582\u057e\u0561\u056c\u0565\u057a\u0561"
    ],
    "name:pol_x_preferred":[
        "S\u00fcvalepa"
    ],
    "name:spa_x_preferred":[
        "S\u00fcvalepa"
    ],
    "name:und_x_variant":[
        "S\u00fcvalepa"
    ],
    "name:vol_x_preferred":[
        "S\u00fcvalepa"
    ],
    "wof:name":"Suevalepa",
    "wof:placetype":"locality"
},
  "geometry": {"coordinates":[26.67861,58.68278000000001],"type":"Point"}
}