{
  "type": "Feature",
  "properties": {
    "gn:country":"EE",
    "gn:fcode":"PPL",
    "gn:population":129,
    "iso:country":"EE",
    "name:ceb_x_preferred":[
        "Kalana"
    ],
    "name:eng_x_preferred":[
        "Kalana"
    ],
    "name:est_x_preferred":[
        "Kalana"
    ],
    "name:hye_x_preferred":[
        "\u053f\u0561\u056c\u0561\u0576\u0561"
    ],
    "name:nld_x_preferred":[
        "Kalana"
    ],
    "name:pol_x_preferred":[
        "Kalana"
    ],
    "name:spa_x_preferred":[
        "Kalana"
    ],
    "name:swe_x_preferred":[
        "Kalana"
    ],
    "name:ukr_x_preferred":[
        "\u041a\u0430\u043b\u0430\u043d\u0430"
    ],
    "name:vol_x_preferred":[
        "Kalana"
    ],
    "name:zho_x_preferred":[
        "\u5361\u62c9\u7d0d"
    ],
    "qs_pg:aaroncc":"EE",
    "qs_pg:gn_country":"EE",
    "qs_pg:gn_fcode":"PPL",
    "qs_pg:gn_pop":129,
    "qs_pg:name":"Kalana",
    "qs_pg:name_adm0":"Eesti",
    "qs_pg:name_adm1":"J\u00f5gevamaa",
    "qs_pg:photos_9r":0,
    "qs_pg:photos_sr":0,
    "qs_pg:pop_sr":1,
    "qs_pg:qs_pg_placetype":"locality",
    "qs_pg:qs_pg_placetype_gp":"Town",
    "qs_pg:woe_adm0":23424805,
    "woe:adm0_id":23424805,
    "woe:name_adm0":"Eesti",
    "woe:name_adm1":"J\u00f5gevamaa",
    "woe:placetype":"Town",
    "wof:lang_x_official":[
        "est"
    ],
    "wof:lang_x_spoken":[
        "est"
    ],
    "wof:name":"Kalana",
    "wof:placetype":"locality",
    "wof:population":129
},
  "geometry": {"coordinates":[26.03972,58.71778],"type":"Point"}
}