{
  "type": "Feature",
  "properties": {
    "gn:gn_country":"EE",
    "gn:gn_fcode":"PPL",
    "gn:gn_pop":99,
    "gn:population":99,
    "iso:country":"EE",
    "name:arm_x_preferred":[
        "\u053f\u0561\u0562\u0565\u057c\u0576\u0565\u0565\u0574\u0565"
    ],
    "name:dut_x_preferred":[
        "Kaberneeme"
    ],
    "name:eng_x_preferred":[
        "Kaberneeme"
    ],
    "name:est_x_preferred":[
        "Kaberneeme"
    ],
    "name:fre_x_preferred":[
        "Kaberneeme"
    ],
    "name:pol_x_preferred":[
        "Kaberneeme"
    ],
    "name:rus_x_preferred":[
        "\u041a\u0430\u0431\u0435\u0440\u043d\u0435\u044d\u043c\u0435"
    ],
    "name:unk_x_variant":[
        "Kaberneyeme"
    ],
    "name:vol_x_preferred":[
        "Kaberneeme"
    ],
    "qs_pg:aaroncc":"EE",
    "qs_pg:gn_country":"EE",
    "qs_pg:gn_fcode":"PPL",
    "qs_pg:gn_pop":99,
    "qs_pg:name":"Kaberneeme",
    "qs_pg:name_adm0":"Eesti",
    "qs_pg:name_adm1":"Harjumaa",
    "qs_pg:photos":94,
    "qs_pg:photos_1k":19,
    "qs_pg:photos_9k":1,
    "qs_pg:photos_9r":3,
    "qs_pg:photos_all":94,
    "qs_pg:photos_sr":3,
    "qs_pg:pop_sr":1,
    "qs_pg:qs_pg_placetype":"locality",
    "qs_pg:qs_pg_placetype_gp":"Town",
    "qs_pg:woe_adm0":23424805,
    "woe:adm0_id":23424805,
    "woe:name_adm0":"Eesti",
    "woe:name_adm1":"Harjumaa",
    "woe:placetype":"Town",
    "wof:name":"Kaberneeme",
    "wof:placetype":"locality",
    "wof:population":99
},
  "geometry": {"coordinates":[25.26417,59.5125],"type":"Point"}
}