{
  "type": "Feature",
  "properties": {
    "gn:admin1_code":"8.0",
    "gn:admin2_code":"792.0",
    "gn:admin3_code":"4474.0",
    "gn:asciiname":"Lokuta",
    "gn:country_code":"EE",
    "gn:dem":96,
    "gn:feature_class":"P",
    "gn:feature_code":"PPL",
    "gn:name":"Lokuta",
    "gn:population":0,
    "gn:timezone":"Europe/Tallinn",
    "iso:country":"EE",
    "wof:name":"Lokuta",
    "wof:placetype":"locality"
},
  "geometry": {"coordinates":[26.05028,59.25028],"type":"Point"}
}