{
  "type": "Feature",
  "properties": {
    "gn:admin1_code":"8.0",
    "gn:admin2_code":"792.0",
    "gn:admin3_code":"4474.0",
    "gn:asciiname":"Lokuta",
    "gn:country_code":"EE",
    "gn:dem":96,
    "gn:feature_class":"P",
    "gn:feature_code":"PPL",
    "gn:name":"Lokuta",
    "gn:population":0,
    "gn:timezone":"Europe/Tallinn",
    "iso:country":"EE",
    "name:ceb_x_preferred":[
        "Lokuta"
    ],
    "name:est_x_preferred":[
        "Lokuta"
    ],
    "name:fra_x_preferred":[
        "Lokuta"
    ],
    "name:hye_x_preferred":[
        "\u053c\u0578\u056f\u0578\u0582\u057f\u0561"
    ],
    "name:pol_x_preferred":[
        "Lokuta"
    ],
    "name:sco_x_preferred":[
        "Lokuta"
    ],
    "name:swe_x_preferred":[
        "Lokuta"
    ],
    "name:ukr_x_preferred":[
        "\u041b\u043e\u043a\u0443\u0442\u0430"
    ],
    "name:vol_x_preferred":[
        "Lokuta"
    ],
    "wof:coterminous":[
        1713313767
    ],
    "wof:lang_x_official":[
        "est"
    ],
    "wof:lang_x_spoken":[
        "est"
    ],
    "wof:name":"Lokuta",
    "wof:placetype":"locality"
},
  "geometry": {"coordinates":[26.05028,59.25028],"type":"Point"}
}