{
  "type": "Feature",
  "properties": {
    "gn:admin1_code":"21.0",
    "gn:admin2_code":"917.0",
    "gn:admin3_code":"6430.0",
    "gn:asciiname":"Pulli",
    "gn:country_code":"EE",
    "gn:dem":100,
    "gn:feature_class":"P",
    "gn:feature_code":"PPL",
    "gn:name":"Pulli",
    "gn:population":0,
    "gn:timezone":"Europe/Tallinn",
    "iso:country":"EE",
    "wof:name":"Pulli",
    "wof:placetype":"locality"
},
  "geometry": {"coordinates":[26.73917,57.90056],"type":"Point"}
}