{
  "type": "Feature",
  "properties": {
    "gn:country":"EE",
    "gn:fcode":"PPL",
    "gn:population":64,
    "iso:country":"EE",
    "name:ara_x_preferred":[
        "\u0631\u0648\u0647\u0646\u0648"
    ],
    "name:aze_x_preferred":[
        "Ruhnu adas\u0131"
    ],
    "name:bel_x_preferred":[
        "\u0412\u043e\u0441\u0442\u0440\u0430\u045e \u0420\u0443\u0445\u043d\u0443"
    ],
    "name:bel_x_variant":[
        "\u0420\u0443\u0445\u043d\u0443"
    ],
    "name:ceb_x_preferred":[
        "Ruhnu Saar"
    ],
    "name:ces_x_preferred":[
        "Ruhnu"
    ],
    "name:dan_x_preferred":[
        "Run\u00f8"
    ],
    "name:deu_x_preferred":[
        "Ruhnu"
    ],
    "name:epo_x_preferred":[
        "Ruhnu"
    ],
    "name:est_x_preferred":[
        "Ruhnu"
    ],
    "name:fas_x_preferred":[
        "\u0631\u0648\u0647\u0646\u0648"
    ],
    "name:fin_x_preferred":[
        "Ruhnu"
    ],
    "name:fra_x_preferred":[
        "Ruhnu"
    ],
    "name:fry_x_preferred":[
        "Ruhnu"
    ],
    "name:heb_x_preferred":[
        "\u05e8\u05d5\u05db\u05e0\u05d5"
    ],
    "name:hrv_x_preferred":[
        "Ruhnu"
    ],
    "name:hye_x_preferred":[
        "\u054c\u0578\u0582\u0570\u0576\u0578\u0582"
    ],
    "name:ita_x_preferred":[
        "Ruhnu"
    ],
    "name:jpn_x_preferred":[
        "\u30eb\u30d5\u30cc\u5cf6"
    ],
    "name:kat_x_preferred":[
        "\u10e0\u10e3\u10f0\u10dc\u10e3"
    ],
    "name:lav_x_preferred":[
        "Ro\u0146u sala"
    ],
    "name:lit_x_preferred":[
        "Ruhnu"
    ],
    "name:mal_x_preferred":[
        "\u0d30\u0d41\u0d39\u0d4d\u0d28\u0d41"
    ],
    "name:nld_x_preferred":[
        "Ruhnu"
    ],
    "name:nno_x_preferred":[
        "Ruhnu"
    ],
    "name:nor_x_preferred":[
        "Ruhnu"
    ],
    "name:pol_x_preferred":[
        "Ruhnu"
    ],
    "name:por_x_preferred":[
        "Ruhnu"
    ],
    "name:ron_x_preferred":[
        "Ruhnu"
    ],
    "name:rus_x_preferred":[
        "\u0420\u0443\u0445\u043d\u0443"
    ],
    "name:spa_x_preferred":[
        "Ruhnu"
    ],
    "name:srp_x_preferred":[
        "\u0420\u0443\u0445\u043d\u0443"
    ],
    "name:swe_x_preferred":[
        "Run\u00f6"
    ],
    "name:ukr_x_preferred":[
        "\u0420\u0443\u0445\u043d\u0443"
    ],
    "name:und_x_variant":[
        "Rukhnu"
    ],
    "name:vie_x_preferred":[
        "Ruhnu"
    ],
    "qs_pg:aaroncc":"EE",
    "qs_pg:gn_country":"EE",
    "qs_pg:gn_fcode":"PPL",
    "qs_pg:gn_pop":64,
    "qs_pg:name":"Ruhnu",
    "qs_pg:name_adm0":"Eesti",
    "qs_pg:name_adm1":"Saaremaa",
    "qs_pg:photos_9k":1,
    "qs_pg:photos_9r":1,
    "qs_pg:photos_all":1,
    "qs_pg:photos_sr":0,
    "qs_pg:pop_sr":1,
    "qs_pg:qs_pg_placetype":"locality",
    "qs_pg:qs_pg_placetype_gp":"Town",
    "qs_pg:woe_adm0":23424805,
    "woe:adm0_id":23424805,
    "woe:name_adm0":"Eesti",
    "woe:name_adm1":"Saaremaa",
    "woe:placetype":"Town",
    "wof:coterminous":[
        1713306221
    ],
    "wof:lang_x_official":[
        "est"
    ],
    "wof:lang_x_spoken":[
        "est"
    ],
    "wof:name":"Ruhnu",
    "wof:placetype":"locality",
    "wof:population":64
},
  "geometry": {"coordinates":[23.24833,57.80028],"type":"Point"}
}