{
  "type": "Feature",
  "properties": {
    "gn:admin1_code":"14.0",
    "gn:admin2_code":"714.0",
    "gn:admin3_code":"8227.0",
    "gn:asciiname":"Uuskuela",
    "gn:country_code":"EE",
    "gn:dem":19,
    "gn:feature_class":"P",
    "gn:feature_code":"PPL",
    "gn:name":"Uusk\u00fcla",
    "gn:population":0,
    "gn:timezone":"Europe/Tallinn",
    "iso:country":"EE",
    "name:und_x_variant":[
        "Uusk\u00fcla",
        "Kristuse S\u00fcndimiseirik"
    ],
    "wof:lang_x_official":[
        "est"
    ],
    "wof:lang_x_spoken":[
        "est"
    ],
    "wof:name":"Uuskuela",
    "wof:placetype":"locality"
},
  "geometry": {"coordinates":[22.19306,58.18083],"type":"Point"}
}