{
  "type": "Feature",
  "properties": {
    "gn:admin1_code":"20.0",
    "gn:admin2_code":"899.0",
    "gn:admin3_code":"1461.0",
    "gn:asciiname":"Auksi",
    "gn:country_code":"EE",
    "gn:dem":101,
    "gn:feature_class":"P",
    "gn:feature_code":"PPL",
    "gn:name":"Auksi",
    "gn:population":0,
    "gn:timezone":"Europe/Tallinn",
    "iso:country":"EE",
    "name:eng_x_preferred":[
        "Auksi"
    ],
    "name:rus_x_preferred":[
        "\u0410\u0443\u043a\u0441\u0438"
    ],
    "wof:name":"Auksi",
    "wof:placetype":"locality"
},
  "geometry": {"coordinates":[25.58889,58.45944],"type":"Point"}
}