{
  "type": "Feature",
  "properties": {
    "gn:admin1_code":"18.0",
    "gn:admin2_code":"291.0",
    "gn:admin3_code":"8211.0",
    "gn:asciiname":"Kaegari",
    "gn:country_code":"EE",
    "gn:dem":52,
    "gn:feature_class":"P",
    "gn:feature_code":"PPL",
    "gn:name":"K\u00e4gari",
    "gn:population":0,
    "gn:timezone":"Europe/Tallinn",
    "iso:country":"EE",
    "wof:name":"Kaegari",
    "wof:placetype":"locality"
},
  "geometry": {"coordinates":[27.01028,58.35028000000001],"type":"Point"}
}