{
  "type": "Feature",
  "properties": {
    "gn:admin1_code":"20.0",
    "gn:admin2_code":"480.0",
    "gn:admin3_code":"9167.0",
    "gn:asciiname":"Veere",
    "gn:country_code":"EE",
    "gn:dem":81,
    "gn:feature_class":"P",
    "gn:feature_code":"PPL",
    "gn:name":"Veere",
    "gn:population":0,
    "gn:timezone":"Europe/Tallinn",
    "iso:country":"EE",
    "name:ara_x_preferred":[
        "\u0641\u064a\u0631\u0627\u0647"
    ],
    "name:bre_x_preferred":[
        "Veere"
    ],
    "name:cat_x_preferred":[
        "Veere"
    ],
    "name:ceb_x_preferred":[
        "Gemeente Veere"
    ],
    "name:dan_x_preferred":[
        "Veere"
    ],
    "name:deu_x_preferred":[
        "Veere"
    ],
    "name:eus_x_preferred":[
        "Veere"
    ],
    "name:fas_x_preferred":[
        "\u0641\u06cc\u0631\u0647"
    ],
    "name:fra_x_preferred":[
        "Veere"
    ],
    "name:fry_x_preferred":[
        "Feare"
    ],
    "name:gle_x_preferred":[
        "Veere"
    ],
    "name:glg_x_preferred":[
        "Veere"
    ],
    "name:hye_x_preferred":[
        "\u054e\u0565\u0575\u0580\u0565"
    ],
    "name:ind_x_preferred":[
        "Veere"
    ],
    "name:ita_x_preferred":[
        "Veere"
    ],
    "name:lim_x_preferred":[
        "Veere"
    ],
    "name:ltz_x_preferred":[
        "Veere"
    ],
    "name:msa_x_preferred":[
        "Veere"
    ],
    "name:nld_x_preferred":[
        "Veere"
    ],
    "name:nor_x_preferred":[
        "Veere"
    ],
    "name:pol_x_preferred":[
        "Veere"
    ],
    "name:ron_x_preferred":[
        "Veere"
    ],
    "name:spa_x_preferred":[
        "Veere"
    ],
    "name:sqi_x_preferred":[
        "Veere"
    ],
    "name:stq_x_preferred":[
        "Veere"
    ],
    "name:swe_x_preferred":[
        "Veere"
    ],
    "name:tur_x_preferred":[
        "Veere"
    ],
    "name:vls_x_preferred":[
        "Veere"
    ],
    "name:vol_x_preferred":[
        "Veere"
    ],
    "name:war_x_preferred":[
        "Veere"
    ],
    "name:zea_x_preferred":[
        "Ter Veere"
    ],
    "name:zho_x_preferred":[
        "\u8d39\u52d2"
    ],
    "wof:name":"Veere",
    "wof:placetype":"locality"
},
  "geometry": {"coordinates":[25.25667,58.09806],"type":"Point"}
}