{
  "type": "Feature",
  "properties": {
    "gn:admin1_code":"2.0",
    "gn:admin2_code":"205.0",
    "gn:admin3_code":"5479.0",
    "gn:asciiname":"Nurste",
    "gn:country_code":"EE",
    "gn:dem":12,
    "gn:feature_class":"P",
    "gn:feature_code":"PPL",
    "gn:name":"Nurste",
    "gn:population":0,
    "gn:timezone":"Europe/Tallinn",
    "iso:country":"EE",
    "name:deu_x_preferred":[
        "Nurste"
    ],
    "name:est_x_preferred":[
        "Nurste"
    ],
    "name:fra_x_preferred":[
        "Nurste"
    ],
    "name:hye_x_preferred":[
        "\u0546\u0578\u0582\u057c\u057d\u057f\u0565"
    ],
    "name:pol_x_preferred":[
        "Nurste"
    ],
    "name:spa_x_preferred":[
        "Nurste"
    ],
    "name:vol_x_preferred":[
        "Nurste"
    ],
    "wof:name":"Nurste",
    "wof:placetype":"locality"
},
  "geometry": {"coordinates":[22.49301,58.78587],"type":"Point"}
}