{
  "type": "Feature",
  "properties": {
    "gn:admin1_code":"13.0",
    "gn:admin2_code":"668.0",
    "gn:admin3_code":"7840.0",
    "gn:asciiname":"Pollika",
    "gn:cc2":"EE",
    "gn:country_code":"EE",
    "gn:dem":83,
    "gn:feature_class":"P",
    "gn:feature_code":"PPL",
    "gn:name":"P\u00f5llika",
    "gn:population":0,
    "gn:timezone":"Europe/Tallinn",
    "iso:country":"EE",
    "name:und_x_variant":[
        "Pyllika",
        "P\u00f5llika"
    ],
    "wof:name":"Pollika",
    "wof:placetype":"locality"
},
  "geometry": {"coordinates":[25.26667,58.98333],"type":"Point"}
}