{
  "type": "Feature",
  "properties": {
    "gn:admin1_code":"13.0",
    "gn:admin2_code":"668.0",
    "gn:admin3_code":"3283.0",
    "gn:asciiname":"Koigi",
    "gn:cc2":"EE",
    "gn:country_code":"EE",
    "gn:dem":71,
    "gn:feature_class":"P",
    "gn:feature_code":"PPL",
    "gn:name":"Koigi",
    "gn:population":0,
    "gn:timezone":"Europe/Tallinn",
    "iso:country":"EE",
    "name:ceb_x_preferred":[
        "Koigi"
    ],
    "name:est_x_preferred":[
        "Koigi"
    ],
    "name:hye_x_preferred":[
        "\u053f\u0578\u056b\u0563\u056b"
    ],
    "name:nld_x_preferred":[
        "Koigi"
    ],
    "name:ron_x_preferred":[
        "Koigi"
    ],
    "name:sco_x_preferred":[
        "Koigi"
    ],
    "name:swe_x_preferred":[
        "Koigi"
    ],
    "name:ukr_x_preferred":[
        "\u041a\u043e\u0439\u0491\u0456"
    ],
    "name:und_x_variant":[
        "Koygi",
        "Koigi"
    ],
    "name:vol_x_preferred":[
        "Koigi"
    ],
    "wof:name":"Koigi",
    "wof:placetype":"locality"
},
  "geometry": {"coordinates":[24.75639,59.07278],"type":"Point"}
}