{
  "type": "Feature",
  "properties": {
    "gn:admin1_code":"13.0",
    "gn:admin2_code":"668.0",
    "gn:admin3_code":"3283.0",
    "gn:asciiname":"Koigi",
    "gn:cc2":"EE",
    "gn:country_code":"EE",
    "gn:dem":71,
    "gn:feature_class":"P",
    "gn:feature_code":"PPL",
    "gn:name":"Koigi",
    "gn:population":0,
    "gn:timezone":"Europe/Tallinn",
    "iso:country":"EE",
    "name:und_x_variant":[
        "Koygi",
        "Koigi"
    ],
    "wof:name":"Koigi",
    "wof:placetype":"locality"
},
  "geometry": {"coordinates":[24.75639,59.07278],"type":"Point"}
}