{
  "type": "Feature",
  "properties": {
    "gn:admin1_code":"18.0",
    "gn:admin2_code":"291.0",
    "gn:admin3_code":"8211.0",
    "gn:asciiname":"Tigase",
    "gn:country_code":"EE",
    "gn:dem":46,
    "gn:feature_class":"P",
    "gn:feature_code":"PPL",
    "gn:name":"Tigase",
    "gn:population":0,
    "gn:timezone":"Europe/Tallinn",
    "iso:country":"EE",
    "name:fra_x_preferred":[
        "Tigase"
    ],
    "name:nld_x_preferred":[
        "Tigase"
    ],
    "wof:name":"Tigase",
    "wof:placetype":"locality"
},
  "geometry": {"coordinates":[26.97611,58.35583000000001],"type":"Point"}
}