{
  "type": "Feature",
  "properties": {
    "gn:admin1_code":"1.0",
    "gn:admin2_code":"726.0",
    "gn:admin3_code":"5093.0",
    "gn:asciiname":"Metskuela",
    "gn:country_code":"EE",
    "gn:dem":60,
    "gn:feature_class":"P",
    "gn:feature_code":"PPL",
    "gn:name":"Metsk\u00fcla",
    "gn:population":0,
    "gn:timezone":"Europe/Tallinn",
    "iso:country":"EE",
    "name:und_x_variant":[
        "Metsk\u00fcla",
        "\u0441\u0435\u043b. \u041c\u0435\u0442\u0441\u043a\u044e\u043b\u0430"
    ],
    "wof:name":"Metskuela",
    "wof:placetype":"locality"
},
  "geometry": {"coordinates":[24.35444,59.09667],"type":"Point"}
}