{
  "type": "Feature",
  "properties": {
    "gn:country":"EE",
    "gn:fcode":"PPL",
    "gn:population":99,
    "iso:country":"EE",
    "name:eng_x_preferred":[
        "K\u00f5nnu"
    ],
    "name:est_x_preferred":[
        "K\u00f5nnu"
    ],
    "name:fra_x_preferred":[
        "K\u00f5nnu"
    ],
    "name:hye_x_preferred":[
        "\u053f\u056b\u0576\u0576\u0578\u0582"
    ],
    "name:nld_x_preferred":[
        "K\u00f5nnu"
    ],
    "name:pol_x_preferred":[
        "K\u00f5nnu"
    ],
    "name:rus_x_preferred":[
        "\u041a\u044b\u043d\u043d\u0443"
    ],
    "name:spa_x_preferred":[
        "K\u00f5nnu"
    ],
    "name:und_x_variant":[
        "Kynnu"
    ],
    "name:vol_x_preferred":[
        "K\u00f5nnu"
    ],
    "qs_pg:aaroncc":"EE",
    "qs_pg:gn_country":"EE",
    "qs_pg:gn_fcode":"PPL",
    "qs_pg:gn_pop":99,
    "qs_pg:name":"K\u00f5nnu",
    "qs_pg:name_adm0":"Eesti",
    "qs_pg:name_adm1":"Harjumaa",
    "qs_pg:photos_9k":1,
    "qs_pg:photos_9r":1,
    "qs_pg:photos_all":2,
    "qs_pg:photos_sr":0,
    "qs_pg:pop_sr":1,
    "qs_pg:qs_pg_placetype":"locality",
    "qs_pg:qs_pg_placetype_gp":"Town",
    "qs_pg:woe_adm0":23424805,
    "woe:adm0_id":23424805,
    "woe:name_adm0":"Eesti",
    "woe:name_adm1":"Harjumaa",
    "woe:placetype":"Town",
    "wof:coterminous":[
        1713305981
    ],
    "wof:lang_x_official":[
        "est"
    ],
    "wof:lang_x_spoken":[
        "est"
    ],
    "wof:name":"K\u00f5nnu",
    "wof:placetype":"locality",
    "wof:population":99
},
  "geometry": {"coordinates":[25.71861,59.48167],"type":"Point"}
}