{
  "type": "Feature",
  "properties": {
    "gn:country":"EE",
    "gn:fcode":"PPL",
    "gn:population":105,
    "iso:country":"EE",
    "name:bul_x_preferred":[
        "\u041a\u0430\u0441\u0435\u043f\u0435\u0440\u0435"
    ],
    "name:ceb_x_preferred":[
        "Kasepere"
    ],
    "name:eng_x_preferred":[
        "Kasepere"
    ],
    "name:est_x_preferred":[
        "Kasepere"
    ],
    "name:fra_x_preferred":[
        "Kasepere"
    ],
    "name:hye_x_preferred":[
        "\u053f\u0561\u057d\u0565\u057a\u0565\u057c\u0565"
    ],
    "name:nld_x_preferred":[
        "Kasepere"
    ],
    "name:pol_x_preferred":[
        "Kasepere"
    ],
    "name:spa_x_preferred":[
        "Kasepere"
    ],
    "name:swe_x_preferred":[
        "Kasepere"
    ],
    "name:ukr_x_preferred":[
        "\u041a\u0430\u0437\u0435\u043f\u0435\u0440\u0435"
    ],
    "name:vol_x_preferred":[
        "Kasepere"
    ],
    "qs_pg:aaroncc":"EE",
    "qs_pg:gn_country":"EE",
    "qs_pg:gn_fcode":"PPL",
    "qs_pg:gn_pop":105,
    "qs_pg:name":"Kasepere",
    "qs_pg:name_adm0":"Eesti",
    "qs_pg:name_adm1":"Harjumaa",
    "qs_pg:photos_9k":1,
    "qs_pg:photos_9r":4,
    "qs_pg:photos_all":225,
    "qs_pg:photos_sr":0,
    "qs_pg:pop_sr":1,
    "qs_pg:qs_pg_placetype":"locality",
    "qs_pg:qs_pg_placetype_gp":"Town",
    "qs_pg:woe_adm0":23424805,
    "woe:adm0_id":23424805,
    "woe:name_adm0":"Eesti",
    "woe:name_adm1":"Harjumaa",
    "woe:placetype":"Town",
    "wof:name":"Kasepere",
    "wof:placetype":"locality",
    "wof:population":105
},
  "geometry": {"coordinates":[24.16222,59.21306],"type":"Point"}
}