{
  "type": "Feature",
  "properties": {
    "gn:admin1_code":"5.0",
    "gn:admin2_code":"618.0",
    "gn:admin3_code":"6262.0",
    "gn:asciiname":"Viruvere",
    "gn:country_code":"EE",
    "gn:dem":67,
    "gn:feature_class":"P",
    "gn:feature_code":"PPL",
    "gn:name":"Viruvere",
    "gn:population":0,
    "gn:timezone":"Europe/Tallinn",
    "iso:country":"EE",
    "name:est_x_preferred":[
        "Viruvere"
    ],
    "name:fra_x_preferred":[
        "Viruvere"
    ],
    "name:hye_x_preferred":[
        "\u054e\u056b\u057c\u0578\u0582\u057e\u0565\u057c\u0565"
    ],
    "name:spa_x_preferred":[
        "Viruvere"
    ],
    "name:ukr_x_preferred":[
        "\u0412\u0456\u0440\u0443\u0432\u0435\u0440\u0435"
    ],
    "name:vol_x_preferred":[
        "Viruvere"
    ],
    "wof:lang_x_official":[
        "est"
    ],
    "wof:lang_x_spoken":[
        "est"
    ],
    "wof:name":"Viruvere",
    "wof:placetype":"locality"
},
  "geometry": {"coordinates":[25.85472,58.69833],"type":"Point"}
}