{
  "type": "Feature",
  "properties": {
    "gn:admin1_code":"12.0",
    "gn:admin2_code":"708.0",
    "gn:admin3_code":"9527.0",
    "gn:asciiname":"Voika",
    "gn:country_code":"EE",
    "gn:dem":49,
    "gn:feature_class":"P",
    "gn:feature_code":"PPL",
    "gn:name":"V\u00f5ika",
    "gn:population":0,
    "gn:timezone":"Europe/Tallinn",
    "iso:country":"EE",
    "name:est_x_preferred":[
        "V\u00f5ika"
    ],
    "name:hye_x_preferred":[
        "\u054e\u056b\u056b\u056f\u0561"
    ],
    "name:pol_x_preferred":[
        "V\u00f5ika"
    ],
    "name:spa_x_preferred":[
        "V\u00f5ika"
    ],
    "name:ukr_x_preferred":[
        "\u0412\u0438\u0439\u043a\u0430"
    ],
    "name:vol_x_preferred":[
        "V\u00f5ika"
    ],
    "wof:coterminous":[
        1713310935
    ],
    "wof:lang_x_official":[
        "est"
    ],
    "wof:lang_x_spoken":[
        "est"
    ],
    "wof:name":"Voika",
    "wof:placetype":"locality"
},
  "geometry": {"coordinates":[27.36972,58.04056],"type":"Point"}
}