{
  "type": "Feature",
  "properties": {
    "gn:admin1_code":"4.0",
    "gn:admin2_code":"834.0",
    "gn:admin3_code":"6995.0",
    "gn:asciiname":"Rikassaare",
    "gn:country_code":"EE",
    "gn:dem":62,
    "gn:feature_class":"P",
    "gn:feature_code":"PPL",
    "gn:name":"Rikassaare",
    "gn:population":0,
    "gn:timezone":"Europe/Tallinn",
    "iso:country":"EE",
    "name:est_x_preferred":[
        "Rikassaare"
    ],
    "name:fra_x_preferred":[
        "Rikassaare"
    ],
    "name:hye_x_preferred":[
        "\u054c\u056b\u056f\u0561\u057d\u0561\u0561\u057c\u0565"
    ],
    "name:pol_x_preferred":[
        "Rikassaare"
    ],
    "name:spa_x_preferred":[
        "Rikassaare"
    ],
    "name:ukr_x_preferred":[
        "\u0420\u0456\u043a\u0430\u0441\u0441\u0430\u0430\u0440\u0435"
    ],
    "name:und_x_variant":[
        "Rikasaare"
    ],
    "name:vol_x_preferred":[
        "Rikassaare"
    ],
    "wof:name":"Rikassaare",
    "wof:placetype":"locality"
},
  "geometry": {"coordinates":[25.54194,58.80639],"type":"Point"}
}