{
  "type": "Feature",
  "properties": {
    "gn:admin1_code":"14.0",
    "gn:admin2_code":"478.0",
    "gn:admin3_code":"5931.0",
    "gn:asciiname":"Pallasmaa",
    "gn:cc2":"EE",
    "gn:country_code":"EE",
    "gn:dem":17,
    "gn:feature_class":"P",
    "gn:feature_code":"PPL",
    "gn:name":"Pallasmaa",
    "gn:population":0,
    "gn:timezone":"Europe/Tallinn",
    "iso:country":"EE",
    "name:und_x_variant":[
        "Pallasma",
        "Pallasmaa"
    ],
    "wof:name":"Pallasmaa",
    "wof:placetype":"locality"
},
  "geometry": {"coordinates":[23.1775,58.67111],"type":"Point"}
}