{
  "type": "Feature",
  "properties": {
    "gn:admin1_code":"21.0",
    "gn:admin2_code":"142.0",
    "gn:admin3_code":"2535.0",
    "gn:asciiname":"Kaika",
    "gn:country_code":"EE",
    "gn:dem":88,
    "gn:feature_class":"P",
    "gn:feature_code":"PPL",
    "gn:name":"Kaika",
    "gn:population":0,
    "gn:timezone":"Europe/Tallinn",
    "iso:country":"EE",
    "name:eng_x_preferred":[
        "Kaika"
    ],
    "name:rus_x_preferred":[
        "\u041a\u0430\u0439\u043a\u0430"
    ],
    "wof:name":"Kaika",
    "wof:placetype":"locality"
},
  "geometry": {"coordinates":[26.53028,57.75389000000001],"type":"Point"}
}