{
  "type": "Feature",
  "properties": {
    "gn:admin1_code":"11.0",
    "gn:admin2_code":"712.0",
    "gn:admin3_code":"7463.0",
    "gn:asciiname":"Saunametsa",
    "gn:country_code":"EE",
    "gn:dem":34,
    "gn:feature_class":"P",
    "gn:feature_code":"PPL",
    "gn:name":"Saunametsa",
    "gn:population":0,
    "gn:timezone":"Europe/Tallinn",
    "iso:country":"EE",
    "name:est_x_preferred":[
        "Saunametsa"
    ],
    "name:hye_x_preferred":[
        "\u054d\u0561\u0578\u0582\u0576\u0561\u0574\u0565\u0581\u0561"
    ],
    "name:pol_x_preferred":[
        "Saunametsa"
    ],
    "name:spa_x_preferred":[
        "Saunametsa"
    ],
    "name:vol_x_preferred":[
        "Saunametsa"
    ],
    "wof:lang_x_official":[
        "est"
    ],
    "wof:lang_x_spoken":[
        "est"
    ],
    "wof:name":"Saunametsa",
    "wof:placetype":"locality"
},
  "geometry": {"coordinates":[24.87417,58.26472],"type":"Point"}
}