{
  "type": "Feature",
  "properties": {
    "gn:admin1_code":"11.0",
    "gn:admin2_code":"214.0",
    "gn:admin3_code":"8724.0",
    "gn:asciiname":"Myaekyula",
    "gn:country_code":"EE",
    "gn:dem":65,
    "gn:feature_class":"P",
    "gn:feature_code":"PPL",
    "gn:name":"Myaekyula",
    "gn:population":0,
    "gn:timezone":"Europe/Tallinn",
    "iso:country":"EE",
    "name:und_x_variant":[
        "Aruk\u00fcla",
        "M\u00e4earu",
        "Myaekyula",
        "M\u00e4ek\u00fcla"
    ],
    "wof:lang_x_official":[
        "est"
    ],
    "wof:lang_x_spoken":[
        "est"
    ],
    "wof:name":"Myaekyula",
    "wof:placetype":"locality"
},
  "geometry": {"coordinates":[24.64944,58.04111],"type":"Point"}
}