{
  "type": "Feature",
  "properties": {
    "gn:admin1_code":"1.0",
    "gn:admin2_code":"353.0",
    "gn:admin3_code":"3474.0",
    "gn:asciiname":"Kosu",
    "gn:cc2":"EE",
    "gn:country_code":"EE",
    "gn:dem":60,
    "gn:feature_class":"P",
    "gn:feature_code":"PPL",
    "gn:name":"Kosu",
    "gn:population":0,
    "gn:timezone":"Europe/Tallinn",
    "iso:country":"EE",
    "name:und_x_variant":[
        "Kozu",
        "Kosu"
    ],
    "wof:name":"Kosu",
    "wof:placetype":"locality"
},
  "geometry": {"coordinates":[25.47056,59.405],"type":"Point"}
}