{
  "type": "Feature",
  "properties": {
    "gn:admin1_code":"12.0",
    "gn:admin2_code":"622.0",
    "gn:admin3_code":"1980.0",
    "gn:asciiname":"Vanamoisa",
    "gn:country_code":"EE",
    "gn:dem":47,
    "gn:feature_class":"P",
    "gn:feature_code":"PPL",
    "gn:name":"Vanam\u00f5isa",
    "gn:population":0,
    "gn:timezone":"Europe/Tallinn",
    "iso:country":"EE",
    "name:und_x_variant":[
        "Vanam\u00f5isa"
    ],
    "wof:name":"Vanamoisa",
    "wof:placetype":"locality"
},
  "geometry": {"coordinates":[27.10194000000001,58.22417],"type":"Point"}
}