{
  "type": "Feature",
  "properties": {
    "gn:admin1_code":"12.0",
    "gn:admin2_code":"622.0",
    "gn:admin3_code":"1980.0",
    "gn:asciiname":"Vanamoisa",
    "gn:country_code":"EE",
    "gn:dem":47,
    "gn:feature_class":"P",
    "gn:feature_code":"PPL",
    "gn:name":"Vanam\u00f5isa",
    "gn:population":0,
    "gn:timezone":"Europe/Tallinn",
    "iso:country":"EE",
    "name:ara_x_preferred":[
        "\u0641\u0627\u0646\u0627\u0645\u0648\u064a\u0633\u0627"
    ],
    "name:deu_x_preferred":[
        "Vanam\u00f5isa"
    ],
    "name:est_x_preferred":[
        "Vanam\u00f5isa"
    ],
    "name:fas_x_preferred":[
        "\u0648\u0646\u0645\u06cc\u0633\u0627"
    ],
    "name:hye_x_preferred":[
        "\u054e\u0561\u0576\u0561\u0574\u056b\u056b\u057d\u0561"
    ],
    "name:pol_x_preferred":[
        "Vanam\u00f5isa"
    ],
    "name:spa_x_preferred":[
        "Vanam\u00f5isa"
    ],
    "name:ukr_x_preferred":[
        "\u0412\u0430\u043d\u0430\u043c\u0438\u0439\u0437\u0430"
    ],
    "name:und_x_variant":[
        "Vanam\u00f5isa"
    ],
    "name:vol_x_preferred":[
        "Vanam\u00f5isa"
    ],
    "wof:name":"Vanamoisa",
    "wof:placetype":"locality"
},
  "geometry": {"coordinates":[27.10194000000001,58.22417],"type":"Point"}
}