{
  "type": "Feature",
  "properties": {
    "gn:admin1_code":"5.0",
    "gn:admin2_code":"486.0",
    "gn:admin3_code":"6174.0",
    "gn:asciiname":"Linnanomme",
    "gn:country_code":"EE",
    "gn:dem":51,
    "gn:feature_class":"P",
    "gn:feature_code":"PPL",
    "gn:name":"Linnan\u00f5mme",
    "gn:population":0,
    "gn:timezone":"Europe/Tallinn",
    "iso:country":"EE",
    "name:und_x_variant":[
        "Linnanymme",
        "Linnan\u00f5mme"
    ],
    "wof:lang_x_official":[
        "est"
    ],
    "wof:lang_x_spoken":[
        "est"
    ],
    "wof:name":"Linnanomme",
    "wof:placetype":"locality"
},
  "geometry": {"coordinates":[26.87778,58.89306],"type":"Point"}
}