{
  "type": "Feature",
  "properties": {
    "gn:gn_country":"EE",
    "gn:gn_fcode":"PPL",
    "gn:gn_pop":276,
    "gn:population":276,
    "iso:country":"EE",
    "name:ceb_x_preferred":[
        "Taagepera"
    ],
    "name:deu_x_preferred":[
        "Taagepera"
    ],
    "name:eng_x_preferred":[
        "Ala"
    ],
    "name:eng_x_variant":[
        "Taagepera"
    ],
    "name:est_x_preferred":[
        "Taagepera"
    ],
    "name:fra_x_preferred":[
        "Taagepera"
    ],
    "name:hye_x_preferred":[
        "\u054f\u0561\u0561\u0563\u0565\u057a\u0565\u057c\u0561"
    ],
    "name:nld_x_preferred":[
        "Taagepera"
    ],
    "name:pol_x_preferred":[
        "Taagepera"
    ],
    "name:rus_x_preferred":[
        "\u0410\u043b\u0430"
    ],
    "name:rus_x_variant":[
        "\u0422\u0430\u0430\u0433\u0435\u043f\u0435\u0440\u0430"
    ],
    "name:spa_x_preferred":[
        "Taagepera"
    ],
    "name:swe_x_preferred":[
        "Taagepera"
    ],
    "name:ukr_x_preferred":[
        "\u0422\u0430\u0430\u0491\u0435\u043f\u0435\u0440\u0430"
    ],
    "name:unk_x_variant":[
        "Svyatogo"
    ],
    "name:vol_x_preferred":[
        "Taagepera"
    ],
    "qs_pg:aaroncc":"EE",
    "qs_pg:gn_country":"EE",
    "qs_pg:gn_fcode":"PPL",
    "qs_pg:gn_pop":276,
    "qs_pg:name":"Ala",
    "qs_pg:name_adm0":"Eesti",
    "qs_pg:name_adm1":"Valgamaa",
    "qs_pg:photos_9r":0,
    "qs_pg:photos_sr":0,
    "qs_pg:pop_sr":2,
    "qs_pg:qs_pg_placetype":"locality",
    "qs_pg:qs_pg_placetype_gp":"Town",
    "qs_pg:woe_adm0":23424805,
    "woe:adm0_id":23424805,
    "woe:name_adm0":"Eesti",
    "woe:name_adm1":"Valgamaa",
    "woe:placetype":"Town",
    "wof:name":"Ala",
    "wof:placetype":"locality",
    "wof:population":276
},
  "geometry": {"coordinates":[25.69,58.01611],"type":"Point"}
}