{
  "type": "Feature",
  "properties": {
    "gn:admin1_code":"11.0",
    "gn:admin2_code":"430.0",
    "gn:admin3_code":"5776.0",
    "gn:asciiname":"Sookalda",
    "gn:country_code":"EE",
    "gn:dem":18,
    "gn:feature_class":"P",
    "gn:feature_code":"PPL",
    "gn:name":"Sookalda",
    "gn:population":0,
    "gn:timezone":"Europe/Tallinn",
    "iso:country":"EE",
    "name:est_x_preferred":[
        "Sookalda"
    ],
    "name:hye_x_preferred":[
        "\u054d\u0578\u0578\u056f\u0561\u056c\u0564\u0561"
    ],
    "name:pol_x_preferred":[
        "Sookalda"
    ],
    "name:spa_x_preferred":[
        "Sookalda"
    ],
    "name:vol_x_preferred":[
        "Sookalda"
    ],
    "wof:name":"Sookalda",
    "wof:placetype":"locality"
},
  "geometry": {"coordinates":[23.82528,58.53944],"type":"Point"}
}