{
  "type": "Feature",
  "properties": {
    "gn:admin1_code":"7.0",
    "gn:admin2_code":"184.0",
    "gn:admin3_code":"1824.0",
    "gn:asciiname":"Kadaka",
    "gn:country_code":"EE",
    "gn:dem":7,
    "gn:feature_class":"P",
    "gn:feature_code":"PPL",
    "gn:name":"Kadaka",
    "gn:population":0,
    "gn:timezone":"Europe/Tallinn",
    "iso:country":"EE",
    "name:deu_x_preferred":[
        "Kadaka"
    ],
    "name:est_x_preferred":[
        "Kadaka"
    ],
    "name:hye_x_preferred":[
        "\u053f\u0561\u0564\u0561\u056f\u0561"
    ],
    "name:pol_x_preferred":[
        "Kadaka"
    ],
    "name:ukr_x_preferred":[
        "\u041a\u0430\u0434\u0430\u043a\u0430"
    ],
    "name:vol_x_preferred":[
        "Kadaka"
    ],
    "wof:name":"Kadaka",
    "wof:placetype":"locality"
},
  "geometry": {"coordinates":[23.62028,58.94971999999999],"type":"Point"}
}