{
  "type": "Feature",
  "properties": {
    "gn:admin1_code":"18.0",
    "gn:admin2_code":"432.0",
    "gn:admin3_code":"7189.0",
    "gn:asciiname":"Roomu",
    "gn:cc2":"EE",
    "gn:country_code":"EE",
    "gn:dem":67,
    "gn:feature_class":"P",
    "gn:feature_code":"PPL",
    "gn:name":"R\u00f5\u00f5mu",
    "gn:population":0,
    "gn:timezone":"Europe/Tallinn",
    "iso:country":"EE",
    "name:est_x_preferred":[
        "R\u00f5\u00f5mu"
    ],
    "name:fra_x_preferred":[
        "R\u00f5\u00f5mu"
    ],
    "name:hye_x_preferred":[
        "\u054c\u056b\u056b\u0574\u0578\u0582"
    ],
    "name:nld_x_preferred":[
        "R\u00f5\u00f5mu"
    ],
    "name:pol_x_preferred":[
        "R\u00f5\u00f5mu"
    ],
    "name:spa_x_preferred":[
        "R\u00f5\u00f5mu"
    ],
    "name:ukr_x_preferred":[
        "\u0420\u0438\u0438\u043c\u0443"
    ],
    "name:und_x_variant":[
        "Rymu"
    ],
    "name:vol_x_preferred":[
        "R\u00f5\u00f5mu"
    ],
    "wof:name":"Roomu",
    "wof:placetype":"locality"
},
  "geometry": {"coordinates":[26.80444,58.3875],"type":"Point"}
}