{
  "type": "Feature",
  "properties": {
    "gn:admin1_code":"5.0",
    "gn:admin2_code":"486.0",
    "gn:admin3_code":"3842.0",
    "gn:asciiname":"Koveriku",
    "gn:cc2":"EE",
    "gn:country_code":"EE",
    "gn:dem":66,
    "gn:feature_class":"P",
    "gn:feature_code":"PPL",
    "gn:name":"K\u00f5veriku",
    "gn:population":0,
    "gn:timezone":"Europe/Tallinn",
    "iso:country":"EE",
    "name:und_x_variant":[
        "Kyrve",
        "K\u00f5rve",
        "K\u00f5veriku"
    ],
    "wof:name":"Koveriku",
    "wof:placetype":"locality"
},
  "geometry": {"coordinates":[26.81833,58.97694],"type":"Point"}
}