{
  "type": "Feature",
  "properties": {
    "gn:admin1_code":"5.0",
    "gn:admin2_code":"486.0",
    "gn:admin3_code":"3842.0",
    "gn:asciiname":"Koveriku",
    "gn:cc2":"EE",
    "gn:country_code":"EE",
    "gn:dem":66,
    "gn:feature_class":"P",
    "gn:feature_code":"PPL",
    "gn:name":"K\u00f5veriku",
    "gn:population":0,
    "gn:timezone":"Europe/Tallinn",
    "iso:country":"EE",
    "name:deu_x_preferred":[
        "K\u00f5veriku"
    ],
    "name:est_x_preferred":[
        "K\u00f5veriku"
    ],
    "name:fra_x_preferred":[
        "K\u00f5veriku"
    ],
    "name:hye_x_preferred":[
        "\u053f\u056b\u057e\u0565\u057c\u056b\u056f\u0578\u0582"
    ],
    "name:nld_x_preferred":[
        "K\u00f5veriku"
    ],
    "name:pol_x_preferred":[
        "K\u00f5veriku"
    ],
    "name:spa_x_preferred":[
        "K\u00f5veriku"
    ],
    "name:und_x_variant":[
        "Kyrve",
        "K\u00f5rve"
    ],
    "name:vol_x_preferred":[
        "K\u00f5veriku"
    ],
    "wof:coterminous":[
        1713312029
    ],
    "wof:lang_x_official":[
        "est"
    ],
    "wof:lang_x_spoken":[
        "est"
    ],
    "wof:name":"Koveriku",
    "wof:placetype":"locality"
},
  "geometry": {"coordinates":[26.81833,58.97694],"type":"Point"}
}