{
  "type": "Feature",
  "properties": {
    "gn:admin1_code":"21.0",
    "gn:admin2_code":"732.0",
    "gn:admin3_code":"3609.0",
    "gn:asciiname":"Saabolda",
    "gn:cc2":"EE",
    "gn:country_code":"EE",
    "gn:dem":54,
    "gn:feature_class":"P",
    "gn:feature_code":"PPL",
    "gn:name":"Saabolda",
    "gn:population":0,
    "gn:timezone":"Europe/Tallinn",
    "iso:country":"EE",
    "name:eng_x_preferred":[
        "Saabolda"
    ],
    "name:est_x_preferred":[
        "Saabolda"
    ],
    "name:hye_x_preferred":[
        "\u054d\u0561\u0561\u0562\u0578\u056c\u0564\u0561"
    ],
    "name:pol_x_preferred":[
        "Saabolda"
    ],
    "name:rus_x_preferred":[
        "\u0421\u0430\u043e\u0431\u043e\u043b\u0434\u0430"
    ],
    "name:sco_x_preferred":[
        "Saabolda"
    ],
    "name:spa_x_preferred":[
        "Saabolda"
    ],
    "name:ukr_x_preferred":[
        "\u0421\u0430\u0430\u0431\u043e\u043b\u0434\u0430"
    ],
    "name:und_x_variant":[
        "Zabolda",
        "Sabolda"
    ],
    "name:urd_x_preferred":[
        "\u0633\u0627\u0628\u0648\u0644\u0688\u0627"
    ],
    "name:vol_x_preferred":[
        "Saabolda"
    ],
    "wof:lang_x_official":[
        "est"
    ],
    "wof:lang_x_spoken":[
        "est"
    ],
    "wof:name":"Saabolda",
    "wof:placetype":"locality"
},
  "geometry": {"coordinates":[27.75528,57.87722],"type":"Point"}
}