{
  "type": "Feature",
  "properties": {
    "gn:admin1_code":"21.0",
    "gn:admin2_code":"732.0",
    "gn:admin3_code":"3609.0",
    "gn:asciiname":"Saabolda",
    "gn:cc2":"EE",
    "gn:country_code":"EE",
    "gn:dem":54,
    "gn:feature_class":"P",
    "gn:feature_code":"PPL",
    "gn:name":"Saabolda",
    "gn:population":0,
    "gn:timezone":"Europe/Tallinn",
    "iso:country":"EE",
    "name:eng_x_preferred":[
        "Saabolda"
    ],
    "name:rus_x_preferred":[
        "\u0421\u0430\u043e\u0431\u043e\u043b\u0434\u0430"
    ],
    "name:und_x_variant":[
        "Zabolda",
        "Sabolda",
        "Saabolda"
    ],
    "wof:name":"Saabolda",
    "wof:placetype":"locality"
},
  "geometry": {"coordinates":[27.75528,57.87722],"type":"Point"}
}