{
  "type": "Feature",
  "properties": {
    "gn:admin1_code":"2.0",
    "gn:admin2_code":"205.0",
    "gn:admin3_code":"4995.0",
    "gn:asciiname":"Ogandi",
    "gn:country_code":"EE",
    "gn:dem":10,
    "gn:feature_class":"P",
    "gn:feature_code":"PPL",
    "gn:name":"Ogandi",
    "gn:population":0,
    "gn:timezone":"Europe/Tallinn",
    "iso:country":"EE",
    "name:und_x_variant":[
        "Oandi",
        "Ogandi"
    ],
    "wof:name":"Ogandi",
    "wof:placetype":"locality"
},
  "geometry": {"coordinates":[22.55579,59.01598000000001],"type":"Point"}
}