{
  "type": "Feature",
  "properties": {
    "gn:admin1_code":"2.0",
    "gn:admin2_code":"205.0",
    "gn:admin3_code":"4465.0",
    "gn:asciiname":"Loja",
    "gn:country_code":"EE",
    "gn:dem":20,
    "gn:feature_class":"P",
    "gn:feature_code":"PPL",
    "gn:name":"Loja",
    "gn:population":0,
    "gn:timezone":"Europe/Tallinn",
    "iso:country":"EE",
    "name:deu_x_preferred":[
        "Loja"
    ],
    "name:est_x_preferred":[
        "Loja"
    ],
    "name:pol_x_preferred":[
        "Loja"
    ],
    "name:spa_x_preferred":[
        "Loja"
    ],
    "name:und_x_variant":[
        "Myza Loya",
        "Loja"
    ],
    "name:vol_x_preferred":[
        "Loja"
    ],
    "wof:name":"Loja",
    "wof:placetype":"locality"
},
  "geometry": {"coordinates":[22.82943,58.93254],"type":"Point"}
}