{
  "type": "Feature",
  "properties": {
    "gn:admin1_code":"11.0",
    "gn:admin2_code":"624.0",
    "gn:admin3_code":"3891.0",
    "gn:asciiname":"Kaerbu",
    "gn:country_code":"EE",
    "gn:dem":22,
    "gn:feature_class":"P",
    "gn:feature_code":"PPL",
    "gn:name":"K\u00e4rbu",
    "gn:population":0,
    "gn:timezone":"Europe/Tallinn",
    "iso:country":"EE",
    "name:und_x_variant":[
        "Kyarbu",
        "K\u00e4rbu"
    ],
    "wof:name":"Kaerbu",
    "wof:placetype":"locality"
},
  "geometry": {"coordinates":[24.235,58.43083000000001],"type":"Point"}
}