{
  "type": "Feature",
  "properties": {
    "gn:admin1_code":"1.0",
    "gn:admin2_code":"653.0",
    "gn:admin3_code":"3687.0",
    "gn:asciiname":"Kurna",
    "gn:country_code":"EE",
    "gn:dem":49,
    "gn:feature_class":"P",
    "gn:feature_code":"PPL",
    "gn:name":"Kurna",
    "gn:population":0,
    "gn:timezone":"Europe/Tallinn",
    "iso:country":"EE",
    "name:eng_x_preferred":[
        "Kurna"
    ],
    "name:rus_x_preferred":[
        "\u041a\u0443\u0440\u043d\u0430"
    ],
    "name:und_x_variant":[
        "Myza Kurna",
        "Kurna Asundus",
        "Kurna"
    ],
    "wof:name":"Kurna",
    "wof:placetype":"locality"
},
  "geometry": {"coordinates":[24.8389,59.33945],"type":"Point"}
}