{
  "type": "Feature",
  "properties": {
    "gn:admin1_code":"3.0",
    "gn:admin2_code":"442.0",
    "gn:admin3_code":"1368.0",
    "gn:asciiname":"Arukuela",
    "gn:country_code":"EE",
    "gn:dem":48,
    "gn:feature_class":"P",
    "gn:feature_code":"PPL",
    "gn:name":"Aruk\u00fcla",
    "gn:population":0,
    "gn:timezone":"Europe/Tallinn",
    "iso:country":"EE",
    "name:und_x_variant":[
        "Aruk\u00fcla",
        "Aru"
    ],
    "wof:name":"Arukuela",
    "wof:placetype":"locality"
},
  "geometry": {"coordinates":[27.02917,59.29556],"type":"Point"}
}