{
  "type": "Feature",
  "properties": {
    "gn:gn_country":"EE",
    "gn:gn_fcode":"PPLX",
    "gn:gn_pop":112,
    "gn:population":112,
    "iso:country":"EE",
    "name:eng_x_preferred":[
        "K\u00e4smu"
    ],
    "name:rus_x_preferred":[
        "\u041a\u044f\u0441\u043c\u0443"
    ],
    "name:unk_x_variant":[
        "Kyasmu"
    ],
    "qs_pg:aaroncc":"EE",
    "qs_pg:gn_country":"EE",
    "qs_pg:gn_fcode":"PPLX",
    "qs_pg:gn_pop":112,
    "qs_pg:name":"K\u00e4smu",
    "qs_pg:photos_9r":0,
    "qs_pg:photos_sr":0,
    "qs_pg:pop_sr":1,
    "qs_pg:qs_pg_placetype":"neighbourhood",
    "wof:name":"K\u00e4smu",
    "wof:placetype":"neighbourhood",
    "wof:population":112
},
  "geometry": {"coordinates":[25.91639,59.60306],"type":"Point"}
}