{
  "type": "Feature",
  "properties": {
    "gn:gn_country":"EE",
    "gn:gn_fcode":"PPLX",
    "gn:gn_pop":277,
    "gn:population":277,
    "iso:country":"EE",
    "name:ceb_x_preferred":[
        "Iru"
    ],
    "name:ces_x_preferred":[
        "Iru"
    ],
    "name:hye_x_preferred":[
        "\u053b\u057c\u0578\u0582"
    ],
    "name:nld_x_preferred":[
        "Iru"
    ],
    "name:spa_x_preferred":[
        "Iru"
    ],
    "name:swe_x_preferred":[
        "Iru"
    ],
    "name:unk_x_variant":[
        "Tallin"
    ],
    "qs_pg:aaroncc":"EE",
    "qs_pg:gn_country":"EE",
    "qs_pg:gn_fcode":"PPLX",
    "qs_pg:gn_pop":277,
    "qs_pg:name":"Iru",
    "qs_pg:photos_9r":0,
    "qs_pg:photos_sr":0,
    "qs_pg:pop_sr":2,
    "qs_pg:qs_pg_placetype":"neighbourhood",
    "wof:name":"Iru",
    "wof:placetype":"neighbourhood",
    "wof:population":277
},
  "geometry": {"coordinates":[24.90778,59.45944],"type":"Point"}
}