{
  "type": "Feature",
  "properties": {
    "gn:admin1_code":"1.0",
    "gn:admin2_code":"726.0",
    "gn:admin3_code":"2427.0",
    "gn:asciiname":"Kaasiku",
    "gn:country_code":"EE",
    "gn:dem":44,
    "gn:feature_class":"P",
    "gn:feature_code":"PPL",
    "gn:name":"Kaasiku",
    "gn:population":0,
    "gn:timezone":"Europe/Tallinn",
    "iso:country":"EE",
    "name:est_x_preferred":[
        "Kaasiku"
    ],
    "name:fra_x_preferred":[
        "Kaasiku"
    ],
    "name:hye_x_preferred":[
        "\u053f\u0561\u0561\u057d\u056b\u056f\u0578\u0582"
    ],
    "name:nld_x_preferred":[
        "Kaasiku"
    ],
    "name:pol_x_preferred":[
        "Kaasiku"
    ],
    "name:sco_x_preferred":[
        "Kaasiku"
    ],
    "name:spa_x_preferred":[
        "Kaasiku"
    ],
    "name:ukr_x_preferred":[
        "\u041a\u0430\u0430\u0437\u0456\u043a\u0443"
    ],
    "name:vol_x_preferred":[
        "Kaasiku"
    ],
    "wof:lang_x_official":[
        "est"
    ],
    "wof:lang_x_spoken":[
        "est"
    ],
    "wof:name":"Kaasiku",
    "wof:placetype":"locality"
},
  "geometry": {"coordinates":[24.31917,59.20306],"type":"Point"}
}