{
  "type": "Feature",
  "properties": {
    "gn:admin1_code":"1.0",
    "gn:admin2_code":"726.0",
    "gn:admin3_code":"2427.0",
    "gn:asciiname":"Kaasiku",
    "gn:country_code":"EE",
    "gn:dem":44,
    "gn:feature_class":"P",
    "gn:feature_code":"PPL",
    "gn:name":"Kaasiku",
    "gn:population":0,
    "gn:timezone":"Europe/Tallinn",
    "iso:country":"EE",
    "wof:name":"Kaasiku",
    "wof:placetype":"locality"
},
  "geometry": {"coordinates":[24.31917,59.20306],"type":"Point"}
}