{
  "type": "Feature",
  "properties": {
    "gn:admin1_code":"14.0",
    "gn:admin2_code":"714.0",
    "gn:admin3_code":"5154.0",
    "gn:asciiname":"Monnuste",
    "gn:cc2":"EE",
    "gn:country_code":"EE",
    "gn:dem":7,
    "gn:feature_class":"P",
    "gn:feature_code":"PPL",
    "gn:name":"M\u00f5nnuste",
    "gn:population":0,
    "gn:timezone":"Europe/Tallinn",
    "iso:country":"EE",
    "name:deu_x_preferred":[
        "M\u00f5nnuste"
    ],
    "name:est_x_preferred":[
        "M\u00f5nnuste"
    ],
    "name:fra_x_preferred":[
        "M\u00f5nnuste"
    ],
    "name:hye_x_preferred":[
        "\u0544\u056b\u0576\u0576\u0578\u0582\u057d\u057f\u0565"
    ],
    "name:nld_x_preferred":[
        "M\u00f5nnuste"
    ],
    "name:pol_x_preferred":[
        "M\u00f5nnuste"
    ],
    "name:spa_x_preferred":[
        "M\u00f5nnuste"
    ],
    "name:ukr_x_preferred":[
        "\u041c\u0438\u043d\u043d\u0443\u0441\u0442\u0435"
    ],
    "name:und_x_variant":[
        "M\u00f5nuste",
        "Mynuste"
    ],
    "name:vol_x_preferred":[
        "M\u00f5nnuste"
    ],
    "wof:lang_x_official":[
        "est"
    ],
    "wof:lang_x_spoken":[
        "est"
    ],
    "wof:name":"Monnuste",
    "wof:placetype":"locality"
},
  "geometry": {"coordinates":[22.28778,58.31306],"type":"Point"}
}