{
  "type": "Feature",
  "properties": {
    "gn:admin1_code":"14.0",
    "gn:admin2_code":"714.0",
    "gn:admin3_code":"5154.0",
    "gn:asciiname":"Monnuste",
    "gn:cc2":"EE",
    "gn:country_code":"EE",
    "gn:dem":7,
    "gn:feature_class":"P",
    "gn:feature_code":"PPL",
    "gn:name":"M\u00f5nnuste",
    "gn:population":0,
    "gn:timezone":"Europe/Tallinn",
    "iso:country":"EE",
    "name:und_x_variant":[
        "M\u00f5nuste",
        "M\u00f5nnuste",
        "Mynuste"
    ],
    "wof:name":"Monnuste",
    "wof:placetype":"locality"
},
  "geometry": {"coordinates":[22.28778,58.31306],"type":"Point"}
}