{
  "type": "Feature",
  "properties": {
    "gn:admin1_code":"18.0",
    "gn:admin2_code":"291.0",
    "gn:admin3_code":"9234.0",
    "gn:asciiname":"Veskimaee",
    "gn:country_code":"EE",
    "gn:dem":41,
    "gn:feature_class":"P",
    "gn:feature_code":"PPL",
    "gn:name":"Veskim\u00e4e",
    "gn:population":0,
    "gn:timezone":"Europe/Tallinn",
    "iso:country":"EE",
    "name:und_x_variant":[
        "Veskim\u00e4e"
    ],
    "wof:name":"Veskimaee",
    "wof:placetype":"locality"
},
  "geometry": {"coordinates":[26.99889000000001,58.37556],"type":"Point"}
}