{
  "type": "Feature",
  "properties": {
    "gn:admin1_code":"18.0",
    "gn:admin2_code":"291.0",
    "gn:admin3_code":"9234.0",
    "gn:asciiname":"Veskimaee",
    "gn:country_code":"EE",
    "gn:dem":41,
    "gn:feature_class":"P",
    "gn:feature_code":"PPL",
    "gn:name":"Veskim\u00e4e",
    "gn:population":0,
    "gn:timezone":"Europe/Tallinn",
    "iso:country":"EE",
    "name:est_x_preferred":[
        "Veskim\u00e4e"
    ],
    "name:hye_x_preferred":[
        "\u054e\u0565\u057d\u056f\u056b\u0574\u0575\u0561\u0565"
    ],
    "name:pol_x_preferred":[
        "Veskim\u00e4e"
    ],
    "name:spa_x_preferred":[
        "Veskim\u00e4e"
    ],
    "name:ukr_x_preferred":[
        "\u0412\u0435\u0441\u043a\u0456\u043c\u044f\u0435"
    ],
    "name:vol_x_preferred":[
        "Veskim\u00e4e"
    ],
    "wof:coterminous":[
        1713313699
    ],
    "wof:lang_x_official":[
        "est"
    ],
    "wof:lang_x_spoken":[
        "est"
    ],
    "wof:name":"Veskimaee",
    "wof:placetype":"locality"
},
  "geometry": {"coordinates":[26.99889,58.37556],"type":"Point"}
}