{
  "type": "Feature",
  "properties": {
    "gn:admin1_code":"18.0",
    "gn:admin2_code":"796.0",
    "gn:admin3_code":"3777.0",
    "gn:asciiname":"Konnujoe",
    "gn:cc2":"EE",
    "gn:country_code":"EE",
    "gn:dem":43,
    "gn:feature_class":"P",
    "gn:feature_code":"PPL",
    "gn:name":"K\u00f5nnuj\u00f5e",
    "gn:population":0,
    "gn:timezone":"Europe/Tallinn",
    "iso:country":"EE",
    "name:und_x_variant":[
        "Konnuj\u00f5e",
        "K\u00f5nnuj\u00f5e"
    ],
    "wof:name":"Konnujoe",
    "wof:placetype":"locality"
},
  "geometry": {"coordinates":[26.46889,58.54194],"type":"Point"}
}