{
  "type": "Feature",
  "properties": {
    "gn:admin1_code":"11.0",
    "gn:admin2_code":"624.0",
    "gn:admin3_code":"6325.0",
    "gn:asciiname":"Moisa",
    "gn:cc2":"EE",
    "gn:country_code":"EE",
    "gn:dem":13,
    "gn:feature_class":"P",
    "gn:feature_code":"PPL",
    "gn:name":"M\u00f5isa",
    "gn:population":0,
    "gn:timezone":"Europe/Tallinn",
    "iso:country":"EE",
    "name:und_x_variant":[
        "Myyza",
        "M\u00f5isa"
    ],
    "wof:name":"Moisa",
    "wof:placetype":"locality"
},
  "geometry": {"coordinates":[24.11667000000001,58.26667],"type":"Point"}
}