{
  "type": "Feature",
  "properties": {
    "gn:admin1_code":"11.0",
    "gn:admin2_code":"809.0",
    "gn:admin3_code":"1576.0",
    "gn:asciiname":"Elbu",
    "gn:cc2":"EE",
    "gn:country_code":"EE",
    "gn:dem":13,
    "gn:feature_class":"P",
    "gn:feature_code":"PPL",
    "gn:name":"Elbu",
    "gn:population":0,
    "gn:timezone":"Europe/Tallinn",
    "iso:country":"EE",
    "name:und_x_variant":[
        "Yelbu",
        "Elbu"
    ],
    "wof:name":"Elbu",
    "wof:placetype":"locality"
},
  "geometry": {"coordinates":[24.52722,58.51333],"type":"Point"}
}