{
  "type": "Feature",
  "properties": {
    "gn:admin1_code":"1.0",
    "gn:admin2_code":"353.0",
    "gn:admin3_code":"1363.0",
    "gn:asciiname":"Aru",
    "gn:country_code":"EE",
    "gn:dem":64,
    "gn:feature_class":"P",
    "gn:feature_code":"PPL",
    "gn:name":"Aru",
    "gn:population":0,
    "gn:timezone":"Europe/Tallinn",
    "iso:country":"EE",
    "name:est_x_preferred":[
        "Aru"
    ],
    "name:fra_x_preferred":[
        "Aru"
    ],
    "name:hye_x_preferred":[
        "\u0531\u057c\u0578\u0582"
    ],
    "name:nld_x_preferred":[
        "Aru"
    ],
    "name:pol_x_preferred":[
        "Aru"
    ],
    "name:rus_x_preferred":[
        "\u0410\u0440\u0443"
    ],
    "name:spa_x_preferred":[
        "Aru"
    ],
    "name:und_x_variant":[
        "Aru k\u00fcla",
        "Aru"
    ],
    "name:vol_x_preferred":[
        "Aru"
    ],
    "wof:name":"Aru",
    "wof:placetype":"locality"
},
  "geometry": {"coordinates":[25.49,59.424],"type":"Point"}
}