{
  "type": "Feature",
  "properties": {
    "gn:gn_country":"EE",
    "gn:gn_fcode":"PPLX",
    "gn:gn_pop":362,
    "gn:population":362,
    "iso:country":"EE",
    "name:ceb_x_preferred":[
        "Halliste"
    ],
    "name:est_x_preferred":[
        "Halliste"
    ],
    "name:fra_x_preferred":[
        "Halliste"
    ],
    "name:hye_x_preferred":[
        "\u0540\u0561\u056c\u056b\u057d\u057f\u0565"
    ],
    "name:pol_x_preferred":[
        "Halliste"
    ],
    "name:spa_x_preferred":[
        "Halliste"
    ],
    "name:swe_x_preferred":[
        "Halliste"
    ],
    "name:ukr_x_preferred":[
        "\u0413\u0430\u043b\u043b\u0456\u0441\u0442\u0435"
    ],
    "name:unk_x_variant":[
        "Khalliste"
    ],
    "name:vol_x_preferred":[
        "Halliste"
    ],
    "name:zho_x_preferred":[
        "\u54c8\u5229\u65af\u6cf0"
    ],
    "qs_pg:aaroncc":"EE",
    "qs_pg:gn_country":"EE",
    "qs_pg:gn_fcode":"PPLX",
    "qs_pg:gn_pop":362,
    "qs_pg:name":"Halliste",
    "qs_pg:photos_9r":0,
    "qs_pg:photos_sr":0,
    "qs_pg:pop_sr":2,
    "qs_pg:qs_pg_placetype":"neighbourhood",
    "wof:name":"Halliste",
    "wof:placetype":"neighbourhood",
    "wof:population":362
},
  "geometry": {"coordinates":[25.09833,58.33667],"type":"Point"}
}