{
  "type": "Feature",
  "properties": {
    "gn:admin1_code":"21.0",
    "gn:admin2_code":"917.0",
    "gn:admin3_code":"2514.0",
    "gn:asciiname":"Paeka",
    "gn:country_code":"EE",
    "gn:dem":47,
    "gn:feature_class":"P",
    "gn:feature_code":"PPL",
    "gn:name":"P\u00e4ka",
    "gn:population":0,
    "gn:timezone":"Europe/Tallinn",
    "iso:country":"EE",
    "name:und_x_variant":[
        "P\u00e4ka"
    ],
    "wof:name":"Paeka",
    "wof:placetype":"locality"
},
  "geometry": {"coordinates":[27.47778,57.94389],"type":"Point"}
}