{
  "type": "Feature",
  "properties": {
    "gn:admin1_code":"12.0",
    "gn:admin2_code":"622.0",
    "gn:admin3_code":"9470.0",
    "gn:asciiname":"Voorekuela",
    "gn:country_code":"EE",
    "gn:dem":91,
    "gn:feature_class":"P",
    "gn:feature_code":"PPL",
    "gn:name":"Voorek\u00fcla",
    "gn:population":0,
    "gn:timezone":"Europe/Tallinn",
    "iso:country":"EE",
    "name:und_x_variant":[
        "Voorek\u00fcla"
    ],
    "wof:name":"Voorekuela",
    "wof:placetype":"locality"
},
  "geometry": {"coordinates":[26.83694,58.18056],"type":"Point"}
}