{
  "type": "Feature",
  "properties": {
    "gn:admin1_code":"12.0",
    "gn:admin2_code":"622.0",
    "gn:admin3_code":"9470.0",
    "gn:asciiname":"Voorekuela",
    "gn:country_code":"EE",
    "gn:dem":91,
    "gn:feature_class":"P",
    "gn:feature_code":"PPL",
    "gn:name":"Voorek\u00fcla",
    "gn:population":0,
    "gn:timezone":"Europe/Tallinn",
    "iso:country":"EE",
    "name:est_x_preferred":[
        "Voorek\u00fcla"
    ],
    "name:hye_x_preferred":[
        "\u054e\u0578\u0578\u057c\u0565\u056f\u0575\u0578\u0582\u056c\u0561"
    ],
    "name:spa_x_preferred":[
        "Voorek\u00fcla"
    ],
    "name:ukr_x_preferred":[
        "\u0412\u043e\u043e\u0440\u0435\u043a\u044e\u043b\u0430"
    ],
    "name:vol_x_preferred":[
        "Voorek\u00fcla"
    ],
    "wof:name":"Voorekuela",
    "wof:placetype":"locality"
},
  "geometry": {"coordinates":[26.83694,58.18056],"type":"Point"}
}