{
  "type": "Feature",
  "properties": {
    "gn:admin1_code":"4.0",
    "gn:admin2_code":"834.0",
    "gn:admin3_code":"8325.0",
    "gn:asciiname":"Naesuvere",
    "gn:country_code":"EE",
    "gn:dem":65,
    "gn:feature_class":"P",
    "gn:feature_code":"PPL",
    "gn:name":"N\u00e4suvere",
    "gn:population":0,
    "gn:timezone":"Europe/Tallinn",
    "iso:country":"EE",
    "name:est_x_preferred":[
        "N\u00e4suvere"
    ],
    "name:fra_x_preferred":[
        "N\u00e4suvere"
    ],
    "name:hye_x_preferred":[
        "\u0546\u0565\u057d\u0578\u0582\u057e\u0565\u057c\u0565"
    ],
    "name:pol_x_preferred":[
        "N\u00e4suvere"
    ],
    "name:spa_x_preferred":[
        "N\u00e4suvere"
    ],
    "name:ukr_x_preferred":[
        "\u041d\u044f\u0441\u0443\u0432\u0435\u0440\u0435"
    ],
    "name:und_x_variant":[
        "Nyasuvere"
    ],
    "name:vol_x_preferred":[
        "N\u00e4suvere"
    ],
    "wof:name":"Naesuvere",
    "wof:placetype":"locality"
},
  "geometry": {"coordinates":[25.47556,58.80528],"type":"Point"}
}