{
  "type": "Feature",
  "properties": {
    "gn:gn_country":"EE",
    "gn:gn_fcode":"PPL",
    "gn:gn_pop":100,
    "gn:population":100,
    "iso:country":"EE",
    "name:eng_x_preferred":[
        "Kasispea"
    ],
    "name:est_x_preferred":[
        "Kasispea"
    ],
    "name:fra_x_preferred":[
        "Kasispea"
    ],
    "name:hye_x_preferred":[
        "\u053f\u0561\u057d\u056b\u057d\u057a\u0565\u0561"
    ],
    "name:nld_x_preferred":[
        "Kasispea"
    ],
    "name:pol_x_preferred":[
        "Kasispea"
    ],
    "name:rus_x_preferred":[
        "\u041a\u0430\u0437\u0438\u0441\u043f\u0435\u0430"
    ],
    "name:unk_x_variant":[
        "Kasisp\u00e4a"
    ],
    "name:vol_x_preferred":[
        "Kasispea"
    ],
    "qs_pg:aaroncc":"EE",
    "qs_pg:gn_country":"EE",
    "qs_pg:gn_fcode":"PPL",
    "qs_pg:gn_pop":100,
    "qs_pg:name":"Kasispea",
    "qs_pg:name_adm0":"Eesti",
    "qs_pg:name_adm1":"Harjumaa",
    "qs_pg:photos_9k":1,
    "qs_pg:photos_9r":1,
    "qs_pg:photos_all":6,
    "qs_pg:photos_sr":0,
    "qs_pg:pop_sr":1,
    "qs_pg:qs_pg_placetype":"locality",
    "qs_pg:qs_pg_placetype_gp":"Town",
    "qs_pg:woe_adm0":23424805,
    "woe:adm0_id":23424805,
    "woe:name_adm0":"Eesti",
    "woe:name_adm1":"Harjumaa",
    "woe:placetype":"Town",
    "wof:name":"Kasispea",
    "wof:placetype":"locality",
    "wof:population":100
},
  "geometry": {"coordinates":[25.77306,59.59778],"type":"Point"}
}