{
  "type": "Feature",
  "properties": {
    "gn:gn_country":"EE",
    "gn:gn_fcode":"PPLX",
    "gn:gn_pop":0,
    "iso:country":"EE",
    "qs_pg:aaroncc":"EE",
    "qs_pg:gn_country":"EE",
    "qs_pg:gn_fcode":"PPLX",
    "qs_pg:gn_pop":0,
    "qs_pg:name":"Lasnam\u00e4e",
    "qs_pg:name_adm0":"Eesti",
    "qs_pg:name_adm1":"Harjumaa",
    "qs_pg:photos":370,
    "qs_pg:photos_1k":75,
    "qs_pg:photos_9k":2,
    "qs_pg:photos_9r":5,
    "qs_pg:photos_all":370,
    "qs_pg:photos_sr":6,
    "qs_pg:pop_sr":0,
    "qs_pg:qs_pg_placetype":"neighbourhood",
    "qs_pg:qs_pg_placetype_gp":"Suburb",
    "qs_pg:woe_adm0":23424805,
    "woe:adm0_id":23424805,
    "woe:name_adm0":"Eesti",
    "woe:name_adm1":"Harjumaa",
    "woe:placetype":"Suburb",
    "wof:name":"Lasnam\u00e4e",
    "wof:placetype":"neighbourhood"
},
  "geometry": {"coordinates":[24.86017,59.4336],"type":"Point"}
}