{
  "type": "Feature",
  "properties": {
    "gn:country":"EE",
    "gn:fcode":"PPLX",
    "gn:population":0,
    "iso:country":"EE",
    "name:ces_x_preferred":[
        "Lasnam\u00e4e"
    ],
    "name:deu_x_preferred":[
        "Lasnam\u00e4e"
    ],
    "name:est_x_preferred":[
        "Lasnam\u00e4e linnaosa"
    ],
    "name:fas_x_preferred":[
        "\u0644\u0627\u0633\u0646\u0627\u0645\u0647"
    ],
    "name:fin_x_preferred":[
        "Lasnam\u00e4e"
    ],
    "name:jpn_x_preferred":[
        "\u30e9\u30b9\u30ca\u30de\u30a8"
    ],
    "name:lav_x_preferred":[
        "Lasnam\u0113"
    ],
    "name:nld_x_preferred":[
        "Lasnam\u00e4e"
    ],
    "name:pol_x_preferred":[
        "Lasnam\u00e4e"
    ],
    "name:rus_x_preferred":[
        "\u041b\u0430\u0441\u043d\u0430\u043c\u044f\u044d"
    ],
    "name:spa_x_preferred":[
        "Lasnam\u00e4e"
    ],
    "name:swe_x_preferred":[
        "Lasnam\u00e4e"
    ],
    "name:udm_x_preferred":[
        "\u041b\u0430\u0441\u043d\u0430\u043c\u044f\u044d"
    ],
    "name:ukr_x_preferred":[
        "\u041b\u0430\u0441\u043d\u0430\u043c\u044f\u0454"
    ],
    "name:urd_x_preferred":[
        "\u0644\u0627\u0633\u0646\u0627\u0645\u0627\u06cc"
    ],
    "name:vie_x_preferred":[
        "Lasnam\u00e4e"
    ],
    "name:zho_x_preferred":[
        "\u62c9\u65af\u7d0d\u9ea5\u57c3\u5340"
    ],
    "qs_pg:aaroncc":"EE",
    "qs_pg:gn_country":"EE",
    "qs_pg:gn_fcode":"PPLX",
    "qs_pg:gn_pop":0,
    "qs_pg:name":"Lasnam\u00e4e",
    "qs_pg:name_adm0":"Eesti",
    "qs_pg:name_adm1":"Harjumaa",
    "qs_pg:photos":370,
    "qs_pg:photos_1k":75,
    "qs_pg:photos_9k":2,
    "qs_pg:photos_9r":5,
    "qs_pg:photos_all":370,
    "qs_pg:photos_sr":6,
    "qs_pg:pop_sr":0,
    "qs_pg:qs_pg_placetype":"neighbourhood",
    "qs_pg:qs_pg_placetype_gp":"Suburb",
    "qs_pg:woe_adm0":23424805,
    "woe:adm0_id":23424805,
    "woe:name_adm0":"Eesti",
    "woe:name_adm1":"Harjumaa",
    "woe:placetype":"Suburb",
    "wof:name":"Lasnam\u00e4e",
    "wof:placetype":"neighbourhood"
},
  "geometry": {"coordinates":[24.86017,59.4336],"type":"Point"}
}