{
  "type": "Feature",
  "properties": {
    "gn:admin1_code":"21.0",
    "gn:admin2_code":"698.0",
    "gn:admin3_code":"4694.0",
    "gn:asciiname":"Lueuetsepa",
    "gn:country_code":"EE",
    "gn:dem":96,
    "gn:feature_class":"P",
    "gn:feature_code":"PPL",
    "gn:name":"L\u00fc\u00fctsepa",
    "gn:population":0,
    "gn:timezone":"Europe/Tallinn",
    "iso:country":"EE",
    "name:und_x_variant":[
        "L\u00fc\u00fctsepa"
    ],
    "wof:name":"Lueuetsepa",
    "wof:placetype":"locality"
},
  "geometry": {"coordinates":[26.72417,57.60861],"type":"Point"}
}