{
  "type": "Feature",
  "properties": {
    "gn:admin1_code":"21.0",
    "gn:admin2_code":"698.0",
    "gn:admin3_code":"4694.0",
    "gn:asciiname":"Lueuetsepa",
    "gn:country_code":"EE",
    "gn:dem":96,
    "gn:feature_class":"P",
    "gn:feature_code":"PPL",
    "gn:name":"L\u00fc\u00fctsepa",
    "gn:population":0,
    "gn:timezone":"Europe/Tallinn",
    "iso:country":"EE",
    "name:est_x_preferred":[
        "L\u00fc\u00fctsepa"
    ],
    "name:hye_x_preferred":[
        "\u053c\u0575\u0578\u0582\u0578\u0582\u0581\u0565\u057a\u0561"
    ],
    "name:pol_x_preferred":[
        "L\u00fc\u00fctsepa"
    ],
    "name:spa_x_preferred":[
        "L\u00fc\u00fctsepa"
    ],
    "name:ukr_x_preferred":[
        "\u041b\u044e\u044e\u0442\u0441\u0435\u043f\u0430"
    ],
    "name:vol_x_preferred":[
        "L\u00fc\u00fctsepa"
    ],
    "wof:coterminous":[
        1713315245
    ],
    "wof:lang_x_official":[
        "est"
    ],
    "wof:lang_x_spoken":[
        "est"
    ],
    "wof:name":"Lueuetsepa",
    "wof:placetype":"locality"
},
  "geometry": {"coordinates":[26.72417,57.60861],"type":"Point"}
}