{
  "type": "Feature",
  "properties": {
    "gn:gn_country":"EE",
    "gn:gn_fcode":"PPL",
    "gn:gn_pop":124,
    "gn:population":124,
    "iso:country":"EE",
    "qs_pg:aaroncc":"EE",
    "qs_pg:gn_country":"EE",
    "qs_pg:gn_fcode":"PPL",
    "qs_pg:gn_pop":124,
    "qs_pg:name":"Pataste",
    "qs_pg:name_adm0":"Eesti",
    "qs_pg:name_adm1":"J\u00f5gevamaa",
    "qs_pg:photos_9k":1,
    "qs_pg:photos_9r":1,
    "qs_pg:photos_all":1,
    "qs_pg:photos_sr":0,
    "qs_pg:pop_sr":1,
    "qs_pg:qs_pg_placetype":"locality",
    "qs_pg:qs_pg_placetype_gp":"Town",
    "qs_pg:woe_adm0":23424805,
    "woe:adm0_id":23424805,
    "woe:name_adm0":"Eesti",
    "woe:name_adm1":"J\u00f5gevamaa",
    "woe:placetype":"Town",
    "wof:name":"Pataste",
    "wof:placetype":"locality",
    "wof:population":124
},
  "geometry": {"coordinates":[26.75806,58.57944],"type":"Point"}
}