{
  "type": "Feature",
  "properties": {
    "gn:admin1_code":"18.0",
    "gn:admin2_code":"586.0",
    "gn:admin3_code":"1166.0",
    "gn:asciiname":"Udriku",
    "gn:cc2":"EE",
    "gn:country_code":"EE",
    "gn:dem":61,
    "gn:feature_class":"P",
    "gn:feature_code":"PPL",
    "gn:name":"Udriku",
    "gn:population":0,
    "gn:timezone":"Europe/Tallinn",
    "iso:country":"EE",
    "name:deu_x_preferred":[
        "Udriku"
    ],
    "name:est_x_preferred":[
        "Udriku"
    ],
    "name:fra_x_preferred":[
        "Udriku"
    ],
    "name:hye_x_preferred":[
        "\u0548\u0582\u0564\u057c\u056b\u056f\u0578\u0582"
    ],
    "name:pol_x_preferred":[
        "Udriku"
    ],
    "name:und_x_variant":[
        "Udrike",
        "Udriku"
    ],
    "name:vol_x_preferred":[
        "Udriku"
    ],
    "wof:name":"Udriku",
    "wof:placetype":"locality"
},
  "geometry": {"coordinates":[26.93333,58.51667],"type":"Point"}
}