{
  "type": "Feature",
  "properties": {
    "gn:admin1_code":"1.0",
    "gn:admin2_code":"198.0",
    "gn:admin3_code":"9683.0",
    "gn:asciiname":"Vaila",
    "gn:cc2":"EE",
    "gn:country_code":"EE",
    "gn:dem":29,
    "gn:feature_class":"P",
    "gn:feature_code":"PPL",
    "gn:name":"Vaila",
    "gn:population":0,
    "gn:timezone":"Europe/Tallinn",
    "iso:country":"EE",
    "name:und_x_variant":[
        "Vayla",
        "Vaila"
    ],
    "wof:name":"Vaila",
    "wof:placetype":"locality"
},
  "geometry": {"coordinates":[24.36667000000001,59.39639],"type":"Point"}
}