{
  "type": "Feature",
  "properties": {
    "gn:admin1_code":"4.0",
    "gn:admin2_code":"255.0",
    "gn:admin3_code":"7081.0",
    "gn:asciiname":"Tammiku",
    "gn:country_code":"EE",
    "gn:dem":112,
    "gn:feature_class":"P",
    "gn:feature_code":"PPL",
    "gn:name":"Tammiku",
    "gn:population":0,
    "gn:timezone":"Europe/Tallinn",
    "iso:country":"EE",
    "wof:name":"Tammiku",
    "wof:placetype":"locality"
},
  "geometry": {"coordinates":[25.92,59.13139],"type":"Point"}
}