{
  "type": "Feature",
  "properties": {
    "gn:admin1_code":"13.0",
    "gn:admin2_code":"668.0",
    "gn:admin3_code":"5717.0",
    "gn:asciiname":"Orguse",
    "gn:country_code":"EE",
    "gn:dem":82,
    "gn:feature_class":"P",
    "gn:feature_code":"PPL",
    "gn:name":"Orguse",
    "gn:population":0,
    "gn:timezone":"Europe/Tallinn",
    "iso:country":"EE",
    "wof:name":"Orguse",
    "wof:placetype":"locality"
},
  "geometry": {"coordinates":[24.95167,59.04444],"type":"Point"}
}