{
  "type": "Feature",
  "properties": {
    "gn:gn_country":"EE",
    "gn:gn_fcode":"PPLX",
    "gn:gn_pop":130,
    "gn:population":130,
    "iso:country":"EE",
    "name:deu_x_preferred":[
        "Neeme"
    ],
    "name:est_x_preferred":[
        "Neeme"
    ],
    "name:nld_x_preferred":[
        "Neeme"
    ],
    "name:pol_x_preferred":[
        "Neeme"
    ],
    "name:unk_x_variant":[
        "Neme"
    ],
    "name:vol_x_preferred":[
        "Neeme"
    ],
    "qs_pg:aaroncc":"EE",
    "qs_pg:gn_country":"EE",
    "qs_pg:gn_fcode":"PPLX",
    "qs_pg:gn_pop":130,
    "qs_pg:name":"Neeme",
    "qs_pg:photos_9r":0,
    "qs_pg:photos_sr":0,
    "qs_pg:pop_sr":1,
    "qs_pg:qs_pg_placetype":"neighbourhood",
    "wof:name":"Neeme",
    "wof:placetype":"neighbourhood",
    "wof:population":130
},
  "geometry": {"coordinates":[25.15056,59.52306],"type":"Point"}
}