{
  "type": "Feature",
  "properties": {
    "gn:admin1_code":"18.0",
    "gn:admin2_code":"432.0",
    "gn:admin3_code":"6249.0",
    "gn:asciiname":"Savikoja",
    "gn:country_code":"EE",
    "gn:dem":56,
    "gn:feature_class":"P",
    "gn:feature_code":"PPL",
    "gn:name":"Savikoja",
    "gn:population":0,
    "gn:timezone":"Europe/Tallinn",
    "iso:country":"EE",
    "name:est_x_preferred":[
        "Savikoja"
    ],
    "name:fra_x_preferred":[
        "Savikoja"
    ],
    "name:hye_x_preferred":[
        "\u054d\u0561\u057e\u056b\u056f\u0578\u0575\u0561"
    ],
    "name:nld_x_preferred":[
        "Savikoja"
    ],
    "name:pol_x_preferred":[
        "Savikoja"
    ],
    "name:spa_x_preferred":[
        "Savikoja"
    ],
    "name:ukr_x_preferred":[
        "\u0421\u0430\u0432\u0456\u043a\u043e\u044f"
    ],
    "name:vol_x_preferred":[
        "Savikoja"
    ],
    "wof:name":"Savikoja",
    "wof:placetype":"locality"
},
  "geometry": {"coordinates":[26.87472,58.40333],"type":"Point"}
}