{
  "type": "Feature",
  "properties": {
    "gn:admin1_code":"20.0",
    "gn:admin2_code":"899.0",
    "gn:admin3_code":"2996.0",
    "gn:asciiname":"Kibekuela",
    "gn:country_code":"EE",
    "gn:dem":69,
    "gn:feature_class":"P",
    "gn:feature_code":"PPL",
    "gn:name":"Kibek\u00fcla",
    "gn:population":0,
    "gn:timezone":"Europe/Tallinn",
    "iso:country":"EE",
    "name:und_x_variant":[
        "Kibek\u00fcla"
    ],
    "wof:name":"Kibekuela",
    "wof:placetype":"locality"
},
  "geometry": {"coordinates":[25.71694,58.32556],"type":"Point"}
}