{
  "type": "Feature",
  "properties": {
    "gn:admin1_code":"18.0",
    "gn:admin2_code":"171.0",
    "gn:admin3_code":"4895.0",
    "gn:asciiname":"Verevi",
    "gn:country_code":"EE",
    "gn:dem":72,
    "gn:feature_class":"P",
    "gn:feature_code":"PPL",
    "gn:name":"Verevi",
    "gn:population":0,
    "gn:timezone":"Europe/Tallinn",
    "iso:country":"EE",
    "name:und_x_variant":[
        "\u0412\u0435\u0440\u0435\u0432\u0435\u0440\u0435"
    ],
    "wof:name":"Verevi",
    "wof:placetype":"locality"
},
  "geometry": {"coordinates":[26.39944,58.24306],"type":"Point"}
}