{
  "type": "Feature",
  "properties": {
    "gn:admin1_code":"1.0",
    "gn:admin2_code":"353.0",
    "gn:admin3_code":"7809.0",
    "gn:asciiname":"Suru",
    "gn:cc2":"EE",
    "gn:country_code":"EE",
    "gn:dem":79,
    "gn:feature_class":"P",
    "gn:feature_code":"PPL",
    "gn:name":"Suru",
    "gn:population":0,
    "gn:timezone":"Europe/Tallinn",
    "iso:country":"EE",
    "name:est_x_preferred":[
        "Suru"
    ],
    "name:fra_x_preferred":[
        "Suru"
    ],
    "name:hye_x_preferred":[
        "\u054d\u0578\u0582\u057c\u0578\u0582"
    ],
    "name:pol_x_preferred":[
        "Suru"
    ],
    "name:rus_x_preferred":[
        "\u0421\u0443\u0440\u0443"
    ],
    "name:spa_x_preferred":[
        "Suru"
    ],
    "name:und_x_variant":[
        "Surru",
        "Suru"
    ],
    "name:vol_x_preferred":[
        "Suru"
    ],
    "wof:name":"Suru",
    "wof:placetype":"locality"
},
  "geometry": {"coordinates":[25.79472,59.42306],"type":"Point"}
}