{
  "type": "Feature",
  "properties": {
    "gn:admin1_code":"21.0",
    "gn:admin2_code":"732.0",
    "gn:admin3_code":"3494.0",
    "gn:asciiname":"Kremessova",
    "gn:country_code":"EE",
    "gn:dem":35,
    "gn:feature_class":"P",
    "gn:feature_code":"PPL",
    "gn:name":"Kremessova",
    "gn:population":0,
    "gn:timezone":"Europe/Tallinn",
    "iso:country":"EE",
    "wof:name":"Kremessova",
    "wof:placetype":"locality"
},
  "geometry": {"coordinates":[27.64139,57.98972],"type":"Point"}
}