{
  "type": "Feature",
  "properties": {
    "gn:admin1_code":"14.0",
    "gn:admin2_code":"714.0",
    "gn:admin3_code":"2231.0",
    "gn:asciiname":"Lyne",
    "gn:country_code":"EE",
    "gn:dem":15,
    "gn:feature_class":"P",
    "gn:feature_code":"PPL",
    "gn:name":"Lyne",
    "gn:population":0,
    "gn:timezone":"Europe/Tallinn",
    "iso:country":"EE",
    "name:deu_x_preferred":[
        "L\u00f6\u00f6ne"
    ],
    "name:est_x_preferred":[
        "L\u00f6\u00f6ne"
    ],
    "name:hye_x_preferred":[
        "\u053c\u0578\u0578\u0576\u0565"
    ],
    "name:pol_x_preferred":[
        "L\u00f6\u00f6ne"
    ],
    "name:spa_x_preferred":[
        "L\u00f6\u00f6ne"
    ],
    "name:vol_x_preferred":[
        "L\u00f6\u00f6ne"
    ],
    "wof:lang_x_official":[
        "est"
    ],
    "wof:lang_x_spoken":[
        "est"
    ],
    "wof:name":"Lyne",
    "wof:placetype":"locality"
},
  "geometry": {"coordinates":[22.75417,58.41583],"type":"Point"}
}