{
  "type": "Feature",
  "properties": {
    "gn:admin1_code":"1.0",
    "gn:admin2_code":"198.0",
    "gn:admin3_code":"8599.0",
    "gn:asciiname":"Lookuela",
    "gn:country_code":"EE",
    "gn:dem":32,
    "gn:feature_class":"P",
    "gn:feature_code":"PPL",
    "gn:name":"Look\u00fcla",
    "gn:population":0,
    "gn:timezone":"Europe/Tallinn",
    "iso:country":"EE",
    "name:und_x_variant":[
        "Look\u00fcla",
        "Loo"
    ],
    "wof:name":"Lookuela",
    "wof:placetype":"locality"
},
  "geometry": {"coordinates":[24.32472000000001,59.38869],"type":"Point"}
}