{
  "type": "Feature",
  "properties": {
    "gn:admin1_code":"1.0",
    "gn:admin2_code":"431.0",
    "gn:admin3_code":"4722.0",
    "gn:asciiname":"Rannakuela",
    "gn:country_code":"EE",
    "gn:dem":8,
    "gn:feature_class":"P",
    "gn:feature_code":"PPL",
    "gn:name":"Rannak\u00fcla",
    "gn:population":0,
    "gn:timezone":"Europe/Tallinn",
    "iso:country":"EE",
    "name:und_x_variant":[
        "Rannakyula",
        "Ranna",
        "Rannak\u00fcla"
    ],
    "wof:name":"Rannakuela",
    "wof:placetype":"locality"
},
  "geometry": {"coordinates":[24.10222000000001,59.27721999999999],"type":"Point"}
}