{
  "type": "Feature",
  "properties": {
    "gn:admin1_code":"18.0",
    "gn:admin2_code":"528.0",
    "gn:admin3_code":"1223.0",
    "gn:asciiname":"Altmaee",
    "gn:country_code":"EE",
    "gn:dem":82,
    "gn:feature_class":"P",
    "gn:feature_code":"PPL",
    "gn:name":"Altm\u00e4e",
    "gn:population":0,
    "gn:timezone":"Europe/Tallinn",
    "iso:country":"EE",
    "name:est_x_preferred":[
        "Altm\u00e4e"
    ],
    "name:fas_x_preferred":[
        "\u0627\u0644\u062a\u0645\u0627\u06cc"
    ],
    "name:hye_x_preferred":[
        "\u0531\u056c\u057f\u0574\u0575\u0561\u0565"
    ],
    "name:pol_x_preferred":[
        "Altm\u00e4e"
    ],
    "name:spa_x_preferred":[
        "Altm\u00e4e"
    ],
    "name:ukr_x_preferred":[
        "\u0410\u043b\u0442\u043c\u044f\u0435"
    ],
    "name:vol_x_preferred":[
        "Altm\u00e4e"
    ],
    "wof:lang_x_official":[
        "est"
    ],
    "wof:lang_x_spoken":[
        "est"
    ],
    "wof:name":"Altmaee",
    "wof:placetype":"locality"
},
  "geometry": {"coordinates":[26.46806,58.22111],"type":"Point"}
}