{
  "type": "Feature",
  "properties": {
    "gn:admin1_code":"7.0",
    "gn:admin2_code":"907.0",
    "gn:admin3_code":"1670.0",
    "gn:asciiname":"Foerby",
    "gn:country_code":"EE",
    "gn:dem":7,
    "gn:feature_class":"P",
    "gn:feature_code":"PPL",
    "gn:name":"F\u00f6rby",
    "gn:population":0,
    "gn:timezone":"Europe/Tallinn",
    "iso:country":"EE",
    "name:deu_x_preferred":[
        "F\u00f6rby"
    ],
    "name:est_x_preferred":[
        "F\u00f6rby"
    ],
    "name:hye_x_preferred":[
        "\u0556\u0578\u0578\u057c\u0562\u056b"
    ],
    "name:pol_x_preferred":[
        "F\u00f6rby"
    ],
    "name:spa_x_preferred":[
        "F\u00f6rby"
    ],
    "name:swe_x_preferred":[
        "F\u00f6rby"
    ],
    "name:ukr_x_preferred":[
        "\u0424\u0435\u0440\u0431\u044e"
    ],
    "name:und_x_variant":[
        "Verby",
        "F\u00f6rby",
        "Pherby",
        "Forbyu",
        "Vorby",
        "F\u00f6rbi"
    ],
    "name:vol_x_preferred":[
        "F\u00f6rby"
    ],
    "wof:name":"Foerby",
    "wof:placetype":"locality"
},
  "geometry": {"coordinates":[23.14531,59.00082],"type":"Point"}
}