{
  "type": "Feature",
  "properties": {
    "gn:admin1_code":"8.0",
    "gn:admin2_code":"661.0",
    "gn:admin3_code":"6850.0",
    "gn:asciiname":"Raudlepa",
    "gn:country_code":"EE",
    "gn:dem":83,
    "gn:feature_class":"P",
    "gn:feature_code":"PPL",
    "gn:name":"Raudlepa",
    "gn:population":0,
    "gn:timezone":"Europe/Tallinn",
    "iso:country":"EE",
    "name:est_x_preferred":[
        "Raudlepa"
    ],
    "name:hye_x_preferred":[
        "\u054c\u0561\u0578\u0582\u0564\u056c\u0565\u057a\u0561"
    ],
    "name:pol_x_preferred":[
        "Raudlepa"
    ],
    "name:vol_x_preferred":[
        "Raudlepa"
    ],
    "wof:name":"Raudlepa",
    "wof:placetype":"locality"
},
  "geometry": {"coordinates":[26.5025,59.36139],"type":"Point"}
}