{
  "type": "Feature",
  "properties": {
    "gn:admin1_code":"1.0",
    "gn:admin2_code":"651.0",
    "gn:admin3_code":"6228.0",
    "gn:asciiname":"Soona A48",
    "gn:country_code":"EE",
    "gn:dem":48,
    "gn:feature_class":"P",
    "gn:feature_code":"PPL",
    "gn:name":"Soona A48",
    "gn:population":0,
    "gn:timezone":"Europe/Tallinn",
    "iso:country":"EE",
    "wof:name":"Soona A48",
    "wof:placetype":"locality"
},
  "geometry": {"coordinates":[25.1225,59.28389],"type":"Point"}
}