{
  "type": "Feature",
  "properties": {
    "gn:admin1_code":"8.0",
    "gn:admin2_code":"272.0",
    "gn:admin3_code":"5741.0",
    "gn:asciiname":"Orutaguse",
    "gn:country_code":"EE",
    "gn:dem":95,
    "gn:feature_class":"P",
    "gn:feature_code":"PPL",
    "gn:name":"Orutaguse",
    "gn:population":0,
    "gn:timezone":"Europe/Tallinn",
    "iso:country":"EE",
    "name:est_x_preferred":[
        "Orutaguse"
    ],
    "name:hye_x_preferred":[
        "\u0555\u057c\u0578\u0582\u057f\u0561\u0563\u0578\u0582\u057d\u0565"
    ],
    "name:und_x_variant":[
        "Kasearu"
    ],
    "wof:name":"Orutaguse",
    "wof:placetype":"locality"
},
  "geometry": {"coordinates":[26.21028,59.32972],"type":"Point"}
}