{
  "type": "Feature",
  "properties": {
    "gn:admin1_code":"1.0",
    "gn:admin2_code":"726.0",
    "gn:admin3_code":"4717.0",
    "gn:asciiname":"Madila",
    "gn:country_code":"EE",
    "gn:dem":57,
    "gn:feature_class":"P",
    "gn:feature_code":"PPL",
    "gn:name":"Madila",
    "gn:population":0,
    "gn:timezone":"Europe/Tallinn",
    "iso:country":"EE",
    "wof:name":"Madila",
    "wof:placetype":"locality"
},
  "geometry": {"coordinates":[24.32278,59.09778000000001],"type":"Point"}
}