{
  "type": "Feature",
  "properties": {
    "gn:admin1_code":"1.0",
    "gn:admin2_code":"726.0",
    "gn:admin3_code":"4717.0",
    "gn:asciiname":"Madila",
    "gn:country_code":"EE",
    "gn:dem":57,
    "gn:feature_class":"P",
    "gn:feature_code":"PPL",
    "gn:name":"Madila",
    "gn:population":0,
    "gn:timezone":"Europe/Tallinn",
    "iso:country":"EE",
    "name:est_x_preferred":[
        "Madila"
    ],
    "name:fra_x_preferred":[
        "Madila"
    ],
    "name:hye_x_preferred":[
        "\u0544\u0561\u0564\u056b\u056c\u0561"
    ],
    "name:pol_x_preferred":[
        "Madila"
    ],
    "name:spa_x_preferred":[
        "Madila"
    ],
    "name:ukr_x_preferred":[
        "\u041c\u0430\u0434\u0456\u043b\u0430"
    ],
    "name:urd_x_preferred":[
        "\u0645\u06cc\u0688\u06cc\u0644\u0627"
    ],
    "name:vol_x_preferred":[
        "Madila"
    ],
    "wof:coterminous":[
        1713307857
    ],
    "wof:lang_x_official":[
        "est"
    ],
    "wof:lang_x_spoken":[
        "est"
    ],
    "wof:name":"Madila",
    "wof:placetype":"locality"
},
  "geometry": {"coordinates":[24.32278,59.09778],"type":"Point"}
}