{
  "type": "Feature",
  "properties": {
    "gn:admin1_code":"11.0",
    "gn:admin2_code":"430.0",
    "gn:admin3_code":"2316.0",
    "gn:asciiname":"Jaenistvere",
    "gn:country_code":"EE",
    "gn:dem":22,
    "gn:feature_class":"P",
    "gn:feature_code":"PPL",
    "gn:name":"J\u00e4nistvere",
    "gn:population":0,
    "gn:timezone":"Europe/Tallinn",
    "iso:country":"EE",
    "name:est_x_preferred":[
        "J\u00e4nistvere"
    ],
    "name:hye_x_preferred":[
        "\u0535\u0576\u056b\u057d\u057f\u057e\u0565\u057c\u0565"
    ],
    "name:pol_x_preferred":[
        "J\u00e4nistvere"
    ],
    "name:spa_x_preferred":[
        "J\u00e4nistvere"
    ],
    "name:und_x_variant":[
        "Yanistvere",
        "J\u00e4nistvere"
    ],
    "name:urd_x_preferred":[
        "\u062c\u0627\u0646\u0633\u0679\u0648\u0631\u06d2"
    ],
    "name:vol_x_preferred":[
        "J\u00e4nistvere"
    ],
    "wof:name":"Jaenistvere",
    "wof:placetype":"locality"
},
  "geometry": {"coordinates":[24.13528,58.54944],"type":"Point"}
}