{
  "type": "Feature",
  "properties": {
    "gn:admin1_code":"11.0",
    "gn:admin2_code":"430.0",
    "gn:admin3_code":"2316.0",
    "gn:asciiname":"Jaenistvere",
    "gn:country_code":"EE",
    "gn:dem":22,
    "gn:feature_class":"P",
    "gn:feature_code":"PPL",
    "gn:name":"J\u00e4nistvere",
    "gn:population":0,
    "gn:timezone":"Europe/Tallinn",
    "iso:country":"EE",
    "name:und_x_variant":[
        "Yanistvere",
        "J\u00e4nistvere"
    ],
    "wof:name":"Jaenistvere",
    "wof:placetype":"locality"
},
  "geometry": {"coordinates":[24.13528,58.54944],"type":"Point"}
}