{
  "type": "Feature",
  "properties": {
    "gn:admin1_code":"14.0",
    "gn:admin2_code":"714.0",
    "gn:admin3_code":"2412.0",
    "gn:asciiname":"Loona",
    "gn:cc2":"EE",
    "gn:country_code":"EE",
    "gn:dem":27,
    "gn:feature_class":"P",
    "gn:feature_code":"PPL",
    "gn:name":"Loona",
    "gn:population":0,
    "gn:timezone":"Europe/Tallinn",
    "iso:country":"EE",
    "name:und_x_variant":[
        "Myza Lona",
        "Loona"
    ],
    "wof:name":"Loona",
    "wof:placetype":"locality"
},
  "geometry": {"coordinates":[22.51028,58.36361],"type":"Point"}
}