{
  "type": "Feature",
  "properties": {
    "gn:country":"EE",
    "gn:fcode":"PPL",
    "gn:population":137,
    "iso:country":"EE",
    "name:ceb_x_preferred":[
        "Ridak\u00fcla"
    ],
    "name:eng_x_preferred":[
        "Ridak\u00fcla"
    ],
    "name:est_x_preferred":[
        "Ridak\u00fcla"
    ],
    "name:fra_x_preferred":[
        "Ridak\u00fcla"
    ],
    "name:hye_x_preferred":[
        "\u054c\u056b\u0564\u0561\u056f\u0575\u0578\u0582\u056c\u0561"
    ],
    "name:nld_x_preferred":[
        "Ridak\u00fcla"
    ],
    "name:pol_x_preferred":[
        "Ridak\u00fcla"
    ],
    "name:swe_x_preferred":[
        "Ridak\u00fcla"
    ],
    "name:vol_x_preferred":[
        "Ridak\u00fcla"
    ],
    "qs_pg:aaroncc":"EE",
    "qs_pg:gn_country":"EE",
    "qs_pg:gn_fcode":"PPL",
    "qs_pg:gn_pop":137,
    "qs_pg:name":"Ridak\u00fcla",
    "qs_pg:name_adm0":"Eesti",
    "qs_pg:name_adm1":"L\u00e4\u00e4ne-Virumaa",
    "qs_pg:photos_9r":0,
    "qs_pg:photos_sr":0,
    "qs_pg:pop_sr":1,
    "qs_pg:qs_pg_placetype":"locality",
    "qs_pg:qs_pg_placetype_gp":"Town",
    "qs_pg:woe_adm0":23424805,
    "woe:adm0_id":23424805,
    "woe:name_adm0":"Eesti",
    "woe:name_adm1":"L\u00e4\u00e4ne-Virumaa",
    "woe:placetype":"Town",
    "wof:lang_x_official":[
        "est"
    ],
    "wof:lang_x_spoken":[
        "est"
    ],
    "wof:name":"Ridak\u00fcla",
    "wof:placetype":"locality",
    "wof:population":137
},
  "geometry": {"coordinates":[25.99611,59.30667],"type":"Point"}
}