{
  "type": "Feature",
  "properties": {
    "gn:gn_country":"EE",
    "gn:gn_fcode":"PPL",
    "gn:gn_pop":303,
    "gn:population":303,
    "iso:country":"EE",
    "name:bul_x_preferred":[
        "\u041a\u043e\u043d\u0433\u0430"
    ],
    "name:ceb_x_preferred":[
        "Koonga"
    ],
    "name:eng_x_preferred":[
        "Koonga"
    ],
    "name:est_x_preferred":[
        "Koonga"
    ],
    "name:hye_x_preferred":[
        "\u053f\u0578\u0578\u0576\u0563\u0561"
    ],
    "name:nld_x_preferred":[
        "Koonga"
    ],
    "name:pol_x_preferred":[
        "Koonga"
    ],
    "name:spa_x_preferred":[
        "Koonga"
    ],
    "name:swe_x_preferred":[
        "Koonga"
    ],
    "name:unk_x_variant":[
        "Konga"
    ],
    "name:vol_x_preferred":[
        "Koonga"
    ],
    "name:zho_x_preferred":[
        "\u79d1\u7fc1\u52a0"
    ],
    "qs_pg:aaroncc":"EE",
    "qs_pg:gn_country":"EE",
    "qs_pg:gn_fcode":"PPL",
    "qs_pg:gn_pop":303,
    "qs_pg:name":"Koonga",
    "qs_pg:name_adm0":"Eesti",
    "qs_pg:name_adm1":"P\u00e4rnumaa",
    "qs_pg:photos_9k":1,
    "qs_pg:photos_9r":1,
    "qs_pg:photos_all":1,
    "qs_pg:photos_sr":0,
    "qs_pg:pop_sr":2,
    "qs_pg:qs_pg_placetype":"locality",
    "qs_pg:qs_pg_placetype_gp":"Town",
    "qs_pg:woe_adm0":23424805,
    "woe:adm0_id":23424805,
    "woe:name_adm0":"Eesti",
    "woe:name_adm1":"P\u00e4rnumaa",
    "woe:placetype":"Town",
    "wof:name":"Koonga",
    "wof:placetype":"locality",
    "wof:population":303
},
  "geometry": {"coordinates":[24.15417,58.5825],"type":"Point"}
}