{
  "type": "Feature",
  "properties": {
    "gn:admin1_code":"5.0",
    "gn:admin2_code":"486.0",
    "gn:admin3_code":"3884.0",
    "gn:asciiname":"Joemetsa",
    "gn:cc2":"EE",
    "gn:country_code":"EE",
    "gn:dem":42,
    "gn:feature_class":"P",
    "gn:feature_code":"PPL",
    "gn:name":"J\u00f5emetsa",
    "gn:population":0,
    "gn:timezone":"Europe/Tallinn",
    "iso:country":"EE",
    "name:deu_x_preferred":[
        "J\u00f5emetsa"
    ],
    "name:est_x_preferred":[
        "J\u00f5emetsa"
    ],
    "name:hye_x_preferred":[
        "\u0545\u056b\u0565\u0574\u0565\u0581\u0561"
    ],
    "name:pol_x_preferred":[
        "J\u00f5emetsa"
    ],
    "name:spa_x_preferred":[
        "J\u00f5emetsa"
    ],
    "name:und_x_variant":[
        "Iyyemetsa"
    ],
    "name:vol_x_preferred":[
        "J\u00f5emetsa"
    ],
    "wof:name":"Joemetsa",
    "wof:placetype":"locality"
},
  "geometry": {"coordinates":[26.92806,58.94111],"type":"Point"}
}