{
  "type": "Feature",
  "properties": {
    "gn:admin1_code":"3.0",
    "gn:admin2_code":"130.0",
    "gn:admin3_code":"8393.0",
    "gn:asciiname":"Ryasa",
    "gn:country_code":"EE",
    "gn:dem":46,
    "gn:feature_class":"P",
    "gn:feature_code":"PPL",
    "gn:name":"Ryasa",
    "gn:population":0,
    "gn:timezone":"Europe/Tallinn",
    "iso:country":"EE",
    "name:und_x_variant":[
        "R\u00e4\u00e4sa"
    ],
    "wof:name":"Ryasa",
    "wof:placetype":"locality"
},
  "geometry": {"coordinates":[27.08333,59.03333000000001],"type":"Point"}
}