{
  "type": "Feature",
  "properties": {
    "gn:admin1_code":"8.0",
    "gn:admin2_code":"901.0",
    "gn:admin3_code":"9204.0",
    "gn:asciiname":"Savilope",
    "gn:country_code":"EE",
    "gn:dem":80,
    "gn:feature_class":"P",
    "gn:feature_code":"PPL",
    "gn:name":"Savil\u00f5pe",
    "gn:population":0,
    "gn:timezone":"Europe/Tallinn",
    "iso:country":"EE",
    "name:und_x_variant":[
        "Savilepa",
        "Savil\u00f5pe"
    ],
    "wof:name":"Savilope",
    "wof:placetype":"locality"
},
  "geometry": {"coordinates":[26.68361,59.00194000000001],"type":"Point"}
}