{
  "type": "Feature",
  "properties": {
    "gn:admin1_code":"12.0",
    "gn:admin2_code":"622.0",
    "gn:admin3_code":"3050.0",
    "gn:asciiname":"Kiisa",
    "gn:country_code":"EE",
    "gn:dem":57,
    "gn:feature_class":"P",
    "gn:feature_code":"PPL",
    "gn:name":"Kiisa",
    "gn:population":0,
    "gn:timezone":"Europe/Tallinn",
    "iso:country":"EE",
    "wof:name":"Kiisa",
    "wof:placetype":"locality"
},
  "geometry": {"coordinates":[27.19944000000001,58.0625],"type":"Point"}
}