{
  "type": "Feature",
  "properties": {
    "gn:admin1_code":"20.0",
    "gn:admin2_code":"899.0",
    "gn:admin3_code":"9221.0",
    "gn:asciiname":"Vennijaagu",
    "gn:country_code":"EE",
    "gn:dem":78,
    "gn:feature_class":"P",
    "gn:feature_code":"PPL",
    "gn:name":"Vennijaagu",
    "gn:population":0,
    "gn:timezone":"Europe/Tallinn",
    "iso:country":"EE",
    "name:und_x_variant":[
        "Venek\u00fcl\u00e4"
    ],
    "wof:name":"Vennijaagu",
    "wof:placetype":"locality"
},
  "geometry": {"coordinates":[25.68417,58.36639],"type":"Point"}
}