{
  "type": "Feature",
  "properties": {
    "gn:admin1_code":"11.0",
    "gn:admin2_code":"624.0",
    "gn:admin3_code":"1513.0",
    "gn:asciiname":"Eassalu",
    "gn:country_code":"EE",
    "gn:dem":35,
    "gn:feature_class":"P",
    "gn:feature_code":"PPL",
    "gn:name":"Eassalu",
    "gn:population":0,
    "gn:timezone":"Europe/Tallinn",
    "iso:country":"EE",
    "wof:name":"Eassalu",
    "wof:placetype":"locality"
},
  "geometry": {"coordinates":[24.18667,58.39444],"type":"Point"}
}