{
  "type": "Feature",
  "properties": {
    "gn:gn_country":"EE",
    "gn:gn_fcode":"PPL",
    "gn:gn_pop":126,
    "gn:population":126,
    "iso:country":"EE",
    "name:arm_x_preferred":[
        "\u054d\u0561\u056f\u0561"
    ],
    "name:dut_x_preferred":[
        "Saka"
    ],
    "name:eng_x_preferred":[
        "Saka"
    ],
    "name:est_x_preferred":[
        "Saka"
    ],
    "name:fre_x_preferred":[
        "Saka"
    ],
    "name:ger_x_preferred":[
        "Saka"
    ],
    "name:pol_x_preferred":[
        "Saka"
    ],
    "name:rus_x_preferred":[
        "\u0421\u0430\u043a\u0430"
    ],
    "name:vol_x_preferred":[
        "Saka"
    ],
    "qs_pg:aaroncc":"EE",
    "qs_pg:gn_country":"EE",
    "qs_pg:gn_fcode":"PPL",
    "qs_pg:gn_pop":126,
    "qs_pg:name":"Saka",
    "qs_pg:name_adm0":"Eesti",
    "qs_pg:name_adm1":"Ida-Virumaa",
    "qs_pg:photos_9k":1,
    "qs_pg:photos_9r":3,
    "qs_pg:photos_all":99,
    "qs_pg:photos_sr":0,
    "qs_pg:pop_sr":1,
    "qs_pg:qs_pg_placetype":"locality",
    "qs_pg:qs_pg_placetype_gp":"Town",
    "qs_pg:woe_adm0":23424805,
    "woe:adm0_id":23424805,
    "woe:name_adm0":"Eesti",
    "woe:name_adm1":"Ida-Virumaa",
    "woe:placetype":"Town",
    "wof:name":"Saka",
    "wof:placetype":"locality",
    "wof:population":126
},
  "geometry": {"coordinates":[27.21556,59.42639],"type":"Point"}
}