{
  "type": "Feature",
  "properties": {
    "gn:gn_country":"EE",
    "gn:gn_fcode":"PPL",
    "gn:gn_pop":295,
    "gn:population":295,
    "iso:country":"EE",
    "name:ceb_x_preferred":[
        "K\u00e4ravete"
    ],
    "name:ces_x_preferred":[
        "K\u00e4ravete"
    ],
    "name:deu_x_preferred":[
        "K\u00e4ravete"
    ],
    "name:eng_x_preferred":[
        "K\u00e4ravete"
    ],
    "name:est_x_preferred":[
        "K\u00e4ravete"
    ],
    "name:fra_x_preferred":[
        "K\u00e4ravete"
    ],
    "name:hye_x_preferred":[
        "\u053f\u0565\u057c\u0561\u057e\u0565\u057f\u0565"
    ],
    "name:nld_x_preferred":[
        "K\u00e4ravete"
    ],
    "name:spa_x_preferred":[
        "K\u00e4ravete"
    ],
    "name:swe_x_preferred":[
        "K\u00e4ravete"
    ],
    "name:ukr_x_preferred":[
        "\u041a\u044f\u0440\u0430\u0432\u0435\u0442\u0435"
    ],
    "name:unk_x_variant":[
        "Myza Kyaravete"
    ],
    "name:vol_x_preferred":[
        "K\u00e4ravete"
    ],
    "qs_pg:aaroncc":"EE",
    "qs_pg:gn_country":"EE",
    "qs_pg:gn_fcode":"PPL",
    "qs_pg:gn_pop":295,
    "qs_pg:name":"K\u00e4ravete",
    "qs_pg:name_adm0":"Eesti",
    "qs_pg:name_adm1":"J\u00e4rvamaa",
    "qs_pg:photos_9k":1,
    "qs_pg:photos_9r":1,
    "qs_pg:photos_all":3,
    "qs_pg:photos_sr":0,
    "qs_pg:pop_sr":2,
    "qs_pg:qs_pg_placetype":"locality",
    "qs_pg:qs_pg_placetype_gp":"Town",
    "qs_pg:woe_adm0":23424805,
    "woe:adm0_id":23424805,
    "woe:name_adm0":"Eesti",
    "woe:name_adm1":"J\u00e4rvamaa",
    "woe:placetype":"Town",
    "wof:name":"K\u00e4ravete",
    "wof:placetype":"locality",
    "wof:population":295
},
  "geometry": {"coordinates":[25.75417,59.19111],"type":"Point"}
}