{
  "type": "Feature",
  "properties": {
    "gn:admin1_code":"11.0",
    "gn:admin2_code":"638.0",
    "gn:admin3_code":"5185.0",
    "gn:asciiname":"Maedara",
    "gn:country_code":"EE",
    "gn:dem":42,
    "gn:feature_class":"P",
    "gn:feature_code":"PPL",
    "gn:name":"M\u00e4dara",
    "gn:population":0,
    "gn:timezone":"Europe/Tallinn",
    "iso:country":"EE",
    "name:est_x_preferred":[
        "M\u00e4dara"
    ],
    "name:hye_x_preferred":[
        "\u0544\u0565\u0564\u0561\u057c\u0561"
    ],
    "name:pol_x_preferred":[
        "M\u00e4dara"
    ],
    "name:spa_x_preferred":[
        "M\u00e4dara"
    ],
    "name:und_x_variant":[
        "Myadara"
    ],
    "name:urd_x_preferred":[
        "\u0645\u06cc\u0688\u0627\u0631\u0627"
    ],
    "name:vol_x_preferred":[
        "M\u00e4dara"
    ],
    "wof:coterminous":[
        1713313471
    ],
    "wof:lang_x_official":[
        "est"
    ],
    "wof:lang_x_spoken":[
        "est"
    ],
    "wof:name":"Maedara",
    "wof:placetype":"locality"
},
  "geometry": {"coordinates":[25.19361,58.6725],"type":"Point"}
}