{
  "type": "Feature",
  "properties": {
    "gn:admin1_code":"21.0",
    "gn:admin2_code":"732.0",
    "gn:admin3_code":"3502.0",
    "gn:asciiname":"Kriiva",
    "gn:country_code":"EE",
    "gn:dem":187,
    "gn:feature_class":"P",
    "gn:feature_code":"PPL",
    "gn:name":"Kriiva",
    "gn:population":0,
    "gn:timezone":"Europe/Tallinn",
    "iso:country":"EE",
    "name:est_x_preferred":[
        "Kriiva"
    ],
    "name:hye_x_preferred":[
        "\u053f\u057c\u056b\u056b\u057e\u0561"
    ],
    "name:pol_x_preferred":[
        "Kriiva"
    ],
    "name:spa_x_preferred":[
        "Kriiva"
    ],
    "name:ukr_x_preferred":[
        "\u041a\u0440\u0456\u0457\u0432\u0430"
    ],
    "name:vol_x_preferred":[
        "Kriiva"
    ],
    "wof:name":"Kriiva",
    "wof:placetype":"locality"
},
  "geometry": {"coordinates":[27.34056,57.61111],"type":"Point"}
}