{
  "type": "Feature",
  "properties": {
    "gn:admin1_code":"21.0",
    "gn:admin2_code":"732.0",
    "gn:admin3_code":"3502.0",
    "gn:asciiname":"Kriiva",
    "gn:country_code":"EE",
    "gn:dem":187,
    "gn:feature_class":"P",
    "gn:feature_code":"PPL",
    "gn:name":"Kriiva",
    "gn:population":0,
    "gn:timezone":"Europe/Tallinn",
    "iso:country":"EE",
    "wof:name":"Kriiva",
    "wof:placetype":"locality"
},
  "geometry": {"coordinates":[27.34056,57.61111],"type":"Point"}
}