{
  "type": "Feature",
  "properties": {
    "gn:admin1_code":"1.0",
    "gn:admin2_code":"431.0",
    "gn:admin3_code":"9265.0",
    "gn:asciiname":"Vihterpalu",
    "gn:cc2":"EE",
    "gn:country_code":"EE",
    "gn:dem":18,
    "gn:feature_class":"P",
    "gn:feature_code":"PPL",
    "gn:name":"Vihterpalu",
    "gn:population":0,
    "gn:timezone":"Europe/Tallinn",
    "iso:country":"EE",
    "name:est_x_preferred":[
        "Vihterpalu"
    ],
    "name:fin_x_preferred":[
        "Vihterpalun kartano"
    ],
    "name:fra_x_preferred":[
        "Vihterpalu"
    ],
    "name:hye_x_preferred":[
        "\u054e\u056b\u0570\u057f\u0565\u057c\u057a\u0561\u056c\u0578\u0582"
    ],
    "name:pol_x_preferred":[
        "Vihterpalu"
    ],
    "name:rus_x_preferred":[
        "\u0412\u0438\u0445\u0442\u0435\u0440\u043f\u0430\u043b\u0443"
    ],
    "name:spa_x_preferred":[
        "Vihterpalu"
    ],
    "name:swe_x_preferred":[
        "Vippal"
    ],
    "name:ukr_x_preferred":[
        "\u0412\u0456\u0433\u0442\u0435\u0440\u043f\u0430\u043b\u0443"
    ],
    "name:und_x_variant":[
        "Myza Vikhterpalu",
        "Vikhterpalu",
        "Vihterpalu"
    ],
    "name:vol_x_preferred":[
        "Vihterpalu"
    ],
    "wof:name":"Vihterpalu",
    "wof:placetype":"locality"
},
  "geometry": {"coordinates":[23.87694,59.25167],"type":"Point"}
}