{
  "type": "Feature",
  "properties": {
    "gn:admin1_code":"1.0",
    "gn:admin2_code":"431.0",
    "gn:admin3_code":"9265.0",
    "gn:asciiname":"Vihterpalu",
    "gn:cc2":"EE",
    "gn:country_code":"EE",
    "gn:dem":18,
    "gn:feature_class":"P",
    "gn:feature_code":"PPL",
    "gn:name":"Vihterpalu",
    "gn:population":0,
    "gn:timezone":"Europe/Tallinn",
    "iso:country":"EE",
    "name:und_x_variant":[
        "Myza Vikhterpalu",
        "Vikhterpalu",
        "Vihterpalu"
    ],
    "wof:name":"Vihterpalu",
    "wof:placetype":"locality"
},
  "geometry": {"coordinates":[23.87694,59.25167],"type":"Point"}
}