{
  "type": "Feature",
  "properties": {
    "gn:admin1_code":"14.0",
    "gn:admin2_code":"714.0",
    "gn:admin3_code":"4041.0",
    "gn:asciiname":"Rannakuela",
    "gn:country_code":"EE",
    "gn:dem":9,
    "gn:feature_class":"P",
    "gn:feature_code":"PPL",
    "gn:name":"Rannak\u00fcla",
    "gn:population":0,
    "gn:timezone":"Europe/Tallinn",
    "iso:country":"EE",
    "name:und_x_variant":[
        "Rannak\u00fcla",
        "Ranna"
    ],
    "wof:name":"Rannakuela",
    "wof:placetype":"locality"
},
  "geometry": {"coordinates":[22.93611,58.38139],"type":"Point"}
}