{
  "type": "Feature",
  "properties": {
    "gn:admin1_code":"14.0",
    "gn:admin2_code":"714.0",
    "gn:admin3_code":"1731.0",
    "gn:asciiname":"Aula-Vintri",
    "gn:country_code":"EE",
    "gn:dem":30,
    "gn:feature_class":"P",
    "gn:feature_code":"PPL",
    "gn:name":"Aula-Vintri",
    "gn:population":0,
    "gn:timezone":"Europe/Tallinn",
    "iso:country":"EE",
    "wof:name":"Aula-Vintri",
    "wof:placetype":"locality"
},
  "geometry": {"coordinates":[22.43222,58.3875],"type":"Point"}
}