{
  "type": "Feature",
  "properties": {
    "gn:gn_country":"EE",
    "gn:gn_fcode":"PPL",
    "gn:gn_pop":354,
    "gn:population":354,
    "iso:country":"EE",
    "name:arm_x_preferred":[
        "\u054f\u0561\u0574\u056b\u057d\u057f\u0565"
    ],
    "name:dut_x_preferred":[
        "Tammiste"
    ],
    "name:eng_x_preferred":[
        "Tammiste"
    ],
    "name:est_x_preferred":[
        "Tammiste"
    ],
    "name:fre_x_preferred":[
        "Tammiste"
    ],
    "name:pol_x_preferred":[
        "Tammiste"
    ],
    "name:vol_x_preferred":[
        "Tammiste"
    ],
    "qs_pg:aaroncc":"EE",
    "qs_pg:gn_country":"EE",
    "qs_pg:gn_fcode":"PPL",
    "qs_pg:gn_pop":354,
    "qs_pg:name":"Tammiste",
    "qs_pg:name_adm0":"Eesti",
    "qs_pg:name_adm1":"P\u00e4rnumaa",
    "qs_pg:photos_9k":1,
    "qs_pg:photos_9r":1,
    "qs_pg:photos_all":1,
    "qs_pg:photos_sr":0,
    "qs_pg:pop_sr":2,
    "qs_pg:qs_pg_placetype":"locality",
    "qs_pg:qs_pg_placetype_gp":"Town",
    "qs_pg:woe_adm0":23424805,
    "woe:adm0_id":23424805,
    "woe:name_adm0":"Eesti",
    "woe:name_adm1":"P\u00e4rnumaa",
    "woe:placetype":"Town",
    "wof:name":"Tammiste",
    "wof:placetype":"locality",
    "wof:population":354
},
  "geometry": {"coordinates":[24.58194,58.38861],"type":"Point"}
}