{
  "type": "Feature",
  "properties": {
    "gn:admin1_code":"4.0",
    "gn:admin2_code":"255.0",
    "gn:admin3_code":"2702.0",
    "gn:asciiname":"Kapu",
    "gn:country_code":"EE",
    "gn:dem":113,
    "gn:feature_class":"P",
    "gn:feature_code":"PPL",
    "gn:name":"Kapu",
    "gn:population":0,
    "gn:timezone":"Europe/Tallinn",
    "iso:country":"EE",
    "name:ara_x_preferred":[
        "\u0643\u0627\u0628\u0648"
    ],
    "name:deu_x_preferred":[
        "Tapu"
    ],
    "name:eus_x_preferred":[
        "Kapu"
    ],
    "name:ind_x_preferred":[
        "Kapu"
    ],
    "name:nld_x_preferred":[
        "Kapu"
    ],
    "name:spa_x_preferred":[
        "Kapu"
    ],
    "name:swe_x_preferred":[
        "Kapu"
    ],
    "wof:name":"Kapu",
    "wof:placetype":"locality"
},
  "geometry": {"coordinates":[26.0275,58.97806],"type":"Point"}
}