{
  "type": "Feature",
  "properties": {
    "gn:admin1_code":"8.0",
    "gn:admin2_code":"792.0",
    "gn:admin3_code":"9429.0",
    "gn:asciiname":"Vistla",
    "gn:country_code":"EE",
    "gn:dem":128,
    "gn:feature_class":"P",
    "gn:feature_code":"PPL",
    "gn:name":"Vistla",
    "gn:population":0,
    "gn:timezone":"Europe/Tallinn",
    "iso:country":"EE",
    "wof:name":"Vistla",
    "wof:placetype":"locality"
},
  "geometry": {"coordinates":[26.16333,59.18306],"type":"Point"}
}