{
  "type": "Feature",
  "properties": {
    "gn:admin1_code":"8.0",
    "gn:admin2_code":"792.0",
    "gn:admin3_code":"2762.0",
    "gn:asciiname":"Nommkuela",
    "gn:country_code":"EE",
    "gn:dem":132,
    "gn:feature_class":"P",
    "gn:feature_code":"PPL",
    "gn:name":"N\u00f5mmk\u00fcla",
    "gn:population":0,
    "gn:timezone":"Europe/Tallinn",
    "iso:country":"EE",
    "name:und_x_variant":[
        "Nymmkyula",
        "Nymkyula",
        "N\u00f5mmk\u00fcla"
    ],
    "wof:name":"Nommkuela",
    "wof:placetype":"locality"
},
  "geometry": {"coordinates":[26.01833,59.20583000000001],"type":"Point"}
}