{
  "type": "Feature",
  "properties": {
    "gn:admin1_code":"13.0",
    "gn:admin2_code":"503.0",
    "gn:admin3_code":"7792.0",
    "gn:asciiname":"Sulu",
    "gn:country_code":"EE",
    "gn:dem":37,
    "gn:feature_class":"P",
    "gn:feature_code":"PPL",
    "gn:name":"Sulu",
    "gn:population":0,
    "gn:timezone":"Europe/Tallinn",
    "iso:country":"EE",
    "name:est_x_preferred":[
        "Sulu"
    ],
    "name:fra_x_preferred":[
        "Sulu"
    ],
    "name:hye_x_preferred":[
        "\u054d\u0578\u0582\u056c\u0578\u0582"
    ],
    "name:pol_x_preferred":[
        "Sulu"
    ],
    "name:sco_x_preferred":[
        "Sulu"
    ],
    "name:vol_x_preferred":[
        "Sulu"
    ],
    "wof:name":"Sulu",
    "wof:placetype":"locality"
},
  "geometry": {"coordinates":[24.48139,58.82333000000001],"type":"Point"}
}