{
  "type": "Feature",
  "properties": {
    "gn:gn_country":"EE",
    "gn:gn_fcode":"PPL",
    "gn:gn_pop":213,
    "gn:population":213,
    "iso:country":"EE",
    "name:bul_x_preferred":[
        "\u0425\u043e\u043b\u0441\u0442\u0440\u0435"
    ],
    "name:ceb_x_preferred":[
        "Holstre"
    ],
    "name:ell_x_preferred":[
        "\u03a7\u03cc\u03bb\u03c3\u03c4\u03c1\u03b5"
    ],
    "name:eng_x_preferred":[
        "Holstre"
    ],
    "name:est_x_preferred":[
        "Holstre"
    ],
    "name:fra_x_preferred":[
        "Holstre"
    ],
    "name:hye_x_preferred":[
        "\u0540\u0578\u056c\u057d\u057f\u057c\u0565"
    ],
    "name:nld_x_preferred":[
        "Holstre"
    ],
    "name:pol_x_preferred":[
        "Holstre"
    ],
    "name:spa_x_preferred":[
        "Holstre"
    ],
    "name:swe_x_preferred":[
        "Holstre"
    ],
    "name:ukr_x_preferred":[
        "\u0413\u043e\u043b\u0441\u0442\u0440\u0435"
    ],
    "name:unk_x_variant":[
        "Myza Kholstre"
    ],
    "name:vol_x_preferred":[
        "Holstre"
    ],
    "qs_pg:aaroncc":"EE",
    "qs_pg:gn_country":"EE",
    "qs_pg:gn_fcode":"PPL",
    "qs_pg:gn_pop":213,
    "qs_pg:name":"Holstre",
    "qs_pg:name_adm0":"Eesti",
    "qs_pg:name_adm1":"Viljandimaa",
    "qs_pg:photos_9r":0,
    "qs_pg:photos_sr":0,
    "qs_pg:pop_sr":2,
    "qs_pg:qs_pg_placetype":"locality",
    "qs_pg:qs_pg_placetype_gp":"Town",
    "qs_pg:woe_adm0":23424805,
    "woe:adm0_id":23424805,
    "woe:name_adm0":"Eesti",
    "woe:name_adm1":"Viljandimaa",
    "woe:placetype":"Town",
    "wof:name":"Holstre",
    "wof:placetype":"locality",
    "wof:population":213
},
  "geometry": {"coordinates":[25.70361,58.27333],"type":"Point"}
}