{
  "type": "Feature",
  "properties": {
    "gn:gn_country":"EE",
    "gn:gn_fcode":"PPLX",
    "gn:gn_pop":101,
    "gn:population":101,
    "iso:country":"EE",
    "name:unk_x_variant":[
        "Kolgaabla"
    ],
    "qs_pg:aaroncc":"EE",
    "qs_pg:gn_country":"EE",
    "qs_pg:gn_fcode":"PPLX",
    "qs_pg:gn_pop":101,
    "qs_pg:name":"Kolga-Aabla",
    "qs_pg:photos_9r":0,
    "qs_pg:photos_sr":0,
    "qs_pg:pop_sr":1,
    "qs_pg:qs_pg_placetype":"neighbourhood",
    "wof:name":"Kolga-Aabla",
    "wof:placetype":"neighbourhood",
    "wof:population":101
},
  "geometry": {"coordinates":[25.53556,59.56028],"type":"Point"}
}