{
  "type": "Feature",
  "properties": {
    "gn:admin1_code":"14.0",
    "gn:asciiname":"Orinomme",
    "gn:cc2":"EE",
    "gn:country_code":"EE",
    "gn:dem":1,
    "gn:feature_class":"P",
    "gn:feature_code":"PPL",
    "gn:name":"Orin\u00f5mme",
    "gn:population":0,
    "gn:timezone":"Europe/Tallinn",
    "iso:country":"EE",
    "name:und_x_variant":[
        "Orinymme",
        "Orin\u00f5mme"
    ],
    "wof:name":"Orinomme",
    "wof:placetype":"locality"
},
  "geometry": {"coordinates":[23.03639,58.57666999999999],"type":"Point"}
}