{
  "type": "Feature",
  "properties": {
    "gn:admin1_code":"4.0",
    "gn:admin2_code":"567.0",
    "gn:admin3_code":"3131.0",
    "gn:asciiname":"Kirila",
    "gn:country_code":"EE",
    "gn:dem":70,
    "gn:feature_class":"P",
    "gn:feature_code":"PPL",
    "gn:name":"Kirila",
    "gn:population":0,
    "gn:timezone":"Europe/Tallinn",
    "iso:country":"EE",
    "name:est_x_preferred":[
        "Kirila"
    ],
    "name:hye_x_preferred":[
        "\u053f\u056b\u057c\u056b\u056c\u0561"
    ],
    "name:pol_x_preferred":[
        "Kirila"
    ],
    "name:ukr_x_preferred":[
        "\u041a\u0456\u0440\u0456\u043b\u0430"
    ],
    "name:vol_x_preferred":[
        "Kirila"
    ],
    "wof:name":"Kirila",
    "wof:placetype":"locality"
},
  "geometry": {"coordinates":[25.555,58.84972],"type":"Point"}
}