{
  "type": "Feature",
  "properties": {
    "gn:admin1_code":"4.0",
    "gn:admin2_code":"567.0",
    "gn:admin3_code":"3131.0",
    "gn:asciiname":"Kirila",
    "gn:country_code":"EE",
    "gn:dem":70,
    "gn:feature_class":"P",
    "gn:feature_code":"PPL",
    "gn:name":"Kirila",
    "gn:population":0,
    "gn:timezone":"Europe/Tallinn",
    "iso:country":"EE",
    "wof:name":"Kirila",
    "wof:placetype":"locality"
},
  "geometry": {"coordinates":[25.555,58.84972],"type":"Point"}
}