{
  "type": "Feature",
  "properties": {
    "gn:admin1_code":"1.0",
    "gn:admin2_code":"653.0",
    "gn:admin3_code":"9832.0",
    "gn:asciiname":"Ile-Joe",
    "gn:country_code":"EE",
    "gn:dem":42,
    "gn:feature_class":"P",
    "gn:feature_code":"PPL",
    "gn:name":"Ile-Joe",
    "gn:population":0,
    "gn:timezone":"Europe/Tallinn",
    "iso:country":"EE",
    "name:und_x_variant":[
        "\u00dclej\u00f5e",
        "Ile-Joe"
    ],
    "wof:name":"Ile-Joe",
    "wof:placetype":"locality"
},
  "geometry": {"coordinates":[24.93926,59.41063000000001],"type":"Point"}
}