{
  "type": "Feature",
  "properties": {
    "gn:gn_country":"EE",
    "gn:gn_fcode":"PPL",
    "gn:gn_pop":127,
    "gn:population":127,
    "iso:country":"EE",
    "name:arm_x_preferred":[
        "\u053c\u0561\u056b\u0574\u0575\u0561\u056c\u0561"
    ],
    "name:cze_x_preferred":[
        "Laimjala"
    ],
    "name:dut_x_preferred":[
        "Laimjala"
    ],
    "name:eng_x_preferred":[
        "Laimjala"
    ],
    "name:est_x_preferred":[
        "Laimjala"
    ],
    "name:ger_x_preferred":[
        "Laimjala"
    ],
    "name:pol_x_preferred":[
        "Laimjala"
    ],
    "name:srp_x_preferred":[
        "\u041b\u0430\u0458\u043c\u0458\u0430\u043b\u0430"
    ],
    "name:unk_x_variant":[
        "Myza Laim\u2019yala"
    ],
    "name:urd_x_preferred":[
        "\u0644\u0627\u0626\u0645\u062c\u0627\u0644\u0627"
    ],
    "name:vol_x_preferred":[
        "Laimjala"
    ],
    "qs_pg:aaroncc":"EE",
    "qs_pg:gn_country":"EE",
    "qs_pg:gn_fcode":"PPL",
    "qs_pg:gn_pop":127,
    "qs_pg:name":"Laimjala",
    "qs_pg:name_adm0":"Eesti",
    "qs_pg:name_adm1":"Saaremaa",
    "qs_pg:photos_9k":1,
    "qs_pg:photos_9r":1,
    "qs_pg:photos_all":2,
    "qs_pg:photos_sr":0,
    "qs_pg:pop_sr":1,
    "qs_pg:qs_pg_placetype":"locality",
    "qs_pg:qs_pg_placetype_gp":"Town",
    "qs_pg:woe_adm0":23424805,
    "woe:adm0_id":23424805,
    "woe:name_adm0":"Eesti",
    "woe:name_adm1":"Saaremaa",
    "woe:placetype":"Town",
    "wof:name":"Laimjala",
    "wof:placetype":"locality",
    "wof:population":127
},
  "geometry": {"coordinates":[23.01556,58.42056],"type":"Point"}
}