{
  "type": "Feature",
  "properties": {
    "gn:admin1_code":"18.0",
    "gn:admin2_code":"171.0",
    "gn:admin3_code":"3973.0",
    "gn:asciiname":"Kuelaaseme",
    "gn:country_code":"EE",
    "gn:dem":72,
    "gn:feature_class":"P",
    "gn:feature_code":"PPL",
    "gn:name":"K\u00fclaaseme",
    "gn:population":0,
    "gn:timezone":"Europe/Tallinn",
    "iso:country":"EE",
    "name:est_x_preferred":[
        "K\u00fclaaseme"
    ],
    "name:fra_x_preferred":[
        "K\u00fclaaseme"
    ],
    "name:hye_x_preferred":[
        "\u053f\u0575\u0578\u0582\u056c\u0561\u0561\u057d\u0565\u0574\u0565"
    ],
    "name:pol_x_preferred":[
        "K\u00fclaaseme"
    ],
    "name:spa_x_preferred":[
        "K\u00fclaaseme"
    ],
    "name:ukr_x_preferred":[
        "\u041a\u044e\u043b\u0430\u0430\u0437\u0435\u043c\u0435"
    ],
    "name:und_x_variant":[
        "K\u00fclaaseme"
    ],
    "name:vol_x_preferred":[
        "K\u00fclaaseme"
    ],
    "wof:name":"Kuelaaseme",
    "wof:placetype":"locality"
},
  "geometry": {"coordinates":[26.39306,58.28778000000001],"type":"Point"}
}