{
  "type": "Feature",
  "properties": {
    "gn:admin1_code":"14.0",
    "gn:admin2_code":"714.0",
    "gn:admin3_code":"2823.0",
    "gn:asciiname":"Kasti",
    "gn:cc2":"EE",
    "gn:country_code":"EE",
    "gn:dem":10,
    "gn:feature_class":"P",
    "gn:feature_code":"PPL",
    "gn:name":"Kasti",
    "gn:population":0,
    "gn:timezone":"Europe/Tallinn",
    "iso:country":"EE",
    "name:deu_x_preferred":[
        "Kasti"
    ],
    "name:est_x_preferred":[
        "Kasti"
    ],
    "name:fra_x_preferred":[
        "Kasti"
    ],
    "name:hye_x_preferred":[
        "\u053f\u0561\u057d\u057f\u056b"
    ],
    "name:nld_x_preferred":[
        "Kasti"
    ],
    "name:pol_x_preferred":[
        "Kasti"
    ],
    "name:spa_x_preferred":[
        "Kasti"
    ],
    "name:ukr_x_preferred":[
        "\u041a\u0430\u0441\u0442\u0456"
    ],
    "name:und_x_variant":[
        "Myza Kasti",
        "Kasti Asundus",
        "Kasti"
    ],
    "name:vol_x_preferred":[
        "Kasti"
    ],
    "wof:name":"Kasti",
    "wof:placetype":"locality"
},
  "geometry": {"coordinates":[22.63944,58.26139000000001],"type":"Point"}
}