{
  "type": "Feature",
  "properties": {
    "gn:gn_country":"EE",
    "gn:gn_fcode":"PPLX",
    "gn:gn_pop":138,
    "gn:population":138,
    "iso:country":"EE",
    "name:cat_x_preferred":[
        "Ira"
    ],
    "name:ceb_x_preferred":[
        "Ira"
    ],
    "name:dan_x_preferred":[
        "IRA"
    ],
    "name:deu_x_preferred":[
        "Ira"
    ],
    "name:fas_x_preferred":[
        "\u0627\u06cc\u0631\u0627"
    ],
    "name:fra_x_preferred":[
        "Ira"
    ],
    "name:fry_x_preferred":[
        "Ira"
    ],
    "name:hun_x_preferred":[
        "IRA"
    ],
    "name:pol_x_preferred":[
        "Ira"
    ],
    "name:por_x_preferred":[
        "Ira"
    ],
    "name:rus_x_preferred":[
        "\u0418\u0440\u0430"
    ],
    "name:slv_x_preferred":[
        "Ira"
    ],
    "name:spa_x_preferred":[
        "Ira"
    ],
    "name:swe_x_preferred":[
        "Ira"
    ],
    "name:unk_x_variant":[
        "Iru"
    ],
    "name:vol_x_preferred":[
        "Ira"
    ],
    "qs_pg:aaroncc":"EE",
    "qs_pg:gn_country":"EE",
    "qs_pg:gn_fcode":"PPLX",
    "qs_pg:gn_pop":138,
    "qs_pg:name":"Ira",
    "qs_pg:photos_9r":0,
    "qs_pg:photos_sr":0,
    "qs_pg:pop_sr":1,
    "qs_pg:qs_pg_placetype":"neighbourhood",
    "wof:name":"Ira",
    "wof:placetype":"neighbourhood",
    "wof:population":138
},
  "geometry": {"coordinates":[24.71917,58.98722],"type":"Point"}
}