{
  "type": "Feature",
  "properties": {
    "gn:gn_country":"EE",
    "gn:gn_fcode":"PPLX",
    "gn:gn_pop":138,
    "gn:population":138,
    "iso:country":"EE",
    "name:unk_x_variant":[
        "Iru"
    ],
    "qs_pg:aaroncc":"EE",
    "qs_pg:gn_country":"EE",
    "qs_pg:gn_fcode":"PPLX",
    "qs_pg:gn_pop":138,
    "qs_pg:name":"Ira",
    "qs_pg:photos_9r":0,
    "qs_pg:photos_sr":0,
    "qs_pg:pop_sr":1,
    "qs_pg:qs_pg_placetype":"neighbourhood",
    "wof:name":"Ira",
    "wof:placetype":"neighbourhood",
    "wof:population":138
},
  "geometry": {"coordinates":[24.71917,58.98722],"type":"Point"}
}