{
  "type": "Feature",
  "properties": {
    "gn:admin1_code":"7.0",
    "gn:admin2_code":"441.0",
    "gn:admin3_code":"8607.0",
    "gn:asciiname":"Ubasalu",
    "gn:country_code":"EE",
    "gn:dem":20,
    "gn:feature_class":"P",
    "gn:feature_code":"PPL",
    "gn:name":"Ubasalu",
    "gn:population":0,
    "gn:timezone":"Europe/Tallinn",
    "iso:country":"EE",
    "name:deu_x_preferred":[
        "Ubasalu"
    ],
    "name:est_x_preferred":[
        "Ubasalu"
    ],
    "name:fas_x_preferred":[
        "\u06cc\u0648\u0628\u0627\u0633\u0627\u0644\u0648"
    ],
    "name:hye_x_preferred":[
        "\u0548\u0582\u0562\u0561\u057d\u0561\u056c\u0578\u0582"
    ],
    "name:nld_x_preferred":[
        "Ubasalu"
    ],
    "name:pol_x_preferred":[
        "Ubasalu"
    ],
    "name:spa_x_preferred":[
        "Ubasalu"
    ],
    "name:ukr_x_preferred":[
        "\u0423\u0431\u0430\u0441\u0430\u043b\u0443"
    ],
    "name:urd_x_preferred":[
        "\u0627\u0628\u0627\u0633\u0627\u0644\u0648"
    ],
    "name:vol_x_preferred":[
        "Ubasalu"
    ],
    "wof:lang_x_official":[
        "est"
    ],
    "wof:lang_x_spoken":[
        "est"
    ],
    "wof:name":"Ubasalu",
    "wof:placetype":"locality"
},
  "geometry": {"coordinates":[23.98722,58.87694],"type":"Point"}
}