{
  "type": "Feature",
  "properties": {
    "gn:admin1_code":"19.0",
    "gn:admin2_code":"557.0",
    "gn:admin3_code":"2837.0",
    "gn:asciiname":"Kastolatsi",
    "gn:country_code":"EE",
    "gn:dem":116,
    "gn:feature_class":"P",
    "gn:feature_code":"PPL",
    "gn:name":"Kastolatsi",
    "gn:population":0,
    "gn:timezone":"Europe/Tallinn",
    "iso:country":"EE",
    "wof:name":"Kastolatsi",
    "wof:placetype":"locality"
},
  "geometry": {"coordinates":[26.475,58.08917],"type":"Point"}
}