{
  "type": "Feature",
  "properties": {
    "gn:admin1_code":"19.0",
    "gn:admin2_code":"557.0",
    "gn:admin3_code":"2837.0",
    "gn:asciiname":"Kastolatsi",
    "gn:country_code":"EE",
    "gn:dem":116,
    "gn:feature_class":"P",
    "gn:feature_code":"PPL",
    "gn:name":"Kastolatsi",
    "gn:population":0,
    "gn:timezone":"Europe/Tallinn",
    "iso:country":"EE",
    "name:est_x_preferred":[
        "Kastolatsi"
    ],
    "name:hye_x_preferred":[
        "\u053f\u0561\u057d\u057f\u0578\u056c\u0561\u0581\u056b"
    ],
    "name:pol_x_preferred":[
        "Kastolatsi"
    ],
    "name:spa_x_preferred":[
        "Kastolatsi"
    ],
    "name:ukr_x_preferred":[
        "\u041a\u0430\u0441\u0442\u043e\u043b\u0430\u0442\u0441\u0456"
    ],
    "name:vol_x_preferred":[
        "Kastolatsi"
    ],
    "wof:coterminous":[
        1713314111
    ],
    "wof:lang_x_official":[
        "est"
    ],
    "wof:lang_x_spoken":[
        "est"
    ],
    "wof:name":"Kastolatsi",
    "wof:placetype":"locality"
},
  "geometry": {"coordinates":[26.475,58.08917],"type":"Point"}
}