{
  "type": "Feature",
  "properties": {
    "gn:admin1_code":"8.0",
    "gn:admin2_code":"272.0",
    "gn:admin3_code":"2614.0",
    "gn:asciiname":"Kallukse",
    "gn:country_code":"EE",
    "gn:dem":86,
    "gn:feature_class":"P",
    "gn:feature_code":"PPL",
    "gn:name":"Kallukse",
    "gn:population":0,
    "gn:timezone":"Europe/Tallinn",
    "iso:country":"EE",
    "name:est_x_preferred":[
        "Kallukse"
    ],
    "name:hye_x_preferred":[
        "\u053f\u0561\u056c\u056c\u0578\u0582\u056f\u057d\u0565"
    ],
    "name:pol_x_preferred":[
        "Kallukse"
    ],
    "name:vol_x_preferred":[
        "Kallukse"
    ],
    "wof:lang_x_official":[
        "est"
    ],
    "wof:lang_x_spoken":[
        "est"
    ],
    "wof:name":"Kallukse",
    "wof:placetype":"locality"
},
  "geometry": {"coordinates":[26.07056,59.36056],"type":"Point"}
}