{
  "type": "Feature",
  "properties": {
    "gn:admin1_code":"14.0",
    "gn:admin2_code":"714.0",
    "gn:admin3_code":"8517.0",
    "gn:asciiname":"Torise",
    "gn:cc2":"EE",
    "gn:country_code":"EE",
    "gn:dem":30,
    "gn:feature_class":"P",
    "gn:feature_code":"PPL",
    "gn:name":"T\u00f5rise",
    "gn:population":0,
    "gn:timezone":"Europe/Tallinn",
    "iso:country":"EE",
    "name:und_x_variant":[
        "Tyrise",
        "T\u00f5rise"
    ],
    "wof:name":"Torise",
    "wof:placetype":"locality"
},
  "geometry": {"coordinates":[22.48806,58.45333],"type":"Point"}
}