{
  "type": "Feature",
  "properties": {
    "gn:admin1_code":"14.0",
    "gn:admin2_code":"714.0",
    "gn:admin3_code":"8517.0",
    "gn:asciiname":"Torise",
    "gn:cc2":"EE",
    "gn:country_code":"EE",
    "gn:dem":30,
    "gn:feature_class":"P",
    "gn:feature_code":"PPL",
    "gn:name":"T\u00f5rise",
    "gn:population":0,
    "gn:timezone":"Europe/Tallinn",
    "iso:country":"EE",
    "name:deu_x_preferred":[
        "T\u00f5rise"
    ],
    "name:est_x_preferred":[
        "T\u00f5rise"
    ],
    "name:fas_x_preferred":[
        "\u062a\u0648\u0631\u06cc\u0633"
    ],
    "name:fra_x_preferred":[
        "T\u00f5rise"
    ],
    "name:hye_x_preferred":[
        "\u054f\u056b\u057c\u056b\u057d\u0565"
    ],
    "name:nld_x_preferred":[
        "T\u00f5rise"
    ],
    "name:pol_x_preferred":[
        "T\u00f5rise"
    ],
    "name:spa_x_preferred":[
        "T\u00f5rise"
    ],
    "name:ukr_x_preferred":[
        "\u0422\u0438\u0440\u0456\u0437\u0435"
    ],
    "name:und_x_variant":[
        "Tyrise"
    ],
    "name:vol_x_preferred":[
        "T\u00f5rise"
    ],
    "wof:coterminous":[
        1713308363
    ],
    "wof:lang_x_official":[
        "est"
    ],
    "wof:lang_x_spoken":[
        "est"
    ],
    "wof:name":"Torise",
    "wof:placetype":"locality"
},
  "geometry": {"coordinates":[22.48806,58.45333],"type":"Point"}
}