{
  "type": "Feature",
  "properties": {
    "gn:admin1_code":"18.0",
    "gn:admin2_code":"796.0",
    "gn:admin3_code":"3777.0",
    "gn:asciiname":"Suuresoeoedi",
    "gn:country_code":"EE",
    "gn:dem":44,
    "gn:feature_class":"P",
    "gn:feature_code":"PPL",
    "gn:name":"Suures\u00f6\u00f6di",
    "gn:population":0,
    "gn:timezone":"Europe/Tallinn",
    "iso:country":"EE",
    "name:und_x_variant":[
        "Suures\u00f6\u00f6di",
        "K\u00f5nnu-Suures\u00f6\u00f6di"
    ],
    "wof:name":"Suuresoeoedi",
    "wof:placetype":"locality"
},
  "geometry": {"coordinates":[26.44444,58.53889],"type":"Point"}
}