{
  "type": "Feature",
  "properties": {
    "gn:admin1_code":"12.0",
    "gn:admin2_code":"622.0",
    "gn:admin3_code":"3923.0",
    "gn:asciiname":"Maekipaeaelne",
    "gn:country_code":"EE",
    "gn:dem":47,
    "gn:feature_class":"P",
    "gn:feature_code":"PPL",
    "gn:name":"M\u00e4kip\u00e4\u00e4lne",
    "gn:population":0,
    "gn:timezone":"Europe/Tallinn",
    "iso:country":"EE",
    "wof:name":"Maekipaeaelne",
    "wof:placetype":"locality"
},
  "geometry": {"coordinates":[27.09222,58.18083000000001],"type":"Point"}
}