{
  "type": "Feature",
  "properties": {
    "gn:admin1_code":"1.0",
    "gn:admin2_code":"141.0",
    "gn:admin3_code":"1961.0",
    "gn:asciiname":"Haermakosu",
    "gn:country_code":"EE",
    "gn:dem":71,
    "gn:feature_class":"P",
    "gn:feature_code":"PPL",
    "gn:name":"H\u00e4rmakosu",
    "gn:population":0,
    "gn:timezone":"Europe/Tallinn",
    "iso:country":"EE",
    "name:und_x_variant":[
        "Yermakozu",
        "Khyarmakosu",
        "H\u00e4rmakosu"
    ],
    "wof:name":"Haermakosu",
    "wof:placetype":"locality"
},
  "geometry": {"coordinates":[25.47,59.39611],"type":"Point"}
}