{
  "type": "Feature",
  "properties": {
    "gn:gn_country":"EE",
    "gn:gn_fcode":"PPL",
    "gn:gn_pop":113,
    "gn:population":113,
    "iso:country":"EE",
    "name:ceb_x_preferred":[
        "P\u00f5drangu"
    ],
    "name:eng_x_preferred":[
        "P\u00f5drangu"
    ],
    "name:est_x_preferred":[
        "P\u00f5drangu"
    ],
    "name:hye_x_preferred":[
        "\u054a\u056b\u0564\u057c\u0561\u0576\u0563\u0578\u0582"
    ],
    "name:nld_x_preferred":[
        "P\u00f5drangu"
    ],
    "name:pol_x_preferred":[
        "P\u00f5drangu"
    ],
    "name:rus_x_preferred":[
        "\u041f\u044b\u0434\u0440\u0430\u043d\u0433\u0443"
    ],
    "name:swe_x_preferred":[
        "P\u00f5drangu"
    ],
    "name:ukr_x_preferred":[
        "\u041f\u0438\u0434\u0440\u0430\u043d\u0491\u0443"
    ],
    "name:unk_x_variant":[
        "Myza Pydrangu"
    ],
    "name:vol_x_preferred":[
        "P\u00f5drangu"
    ],
    "qs_pg:aaroncc":"EE",
    "qs_pg:gn_country":"EE",
    "qs_pg:gn_fcode":"PPL",
    "qs_pg:gn_pop":113,
    "qs_pg:name":"P\u00f5drangu",
    "qs_pg:name_adm0":"Eesti",
    "qs_pg:name_adm1":"L\u00e4\u00e4ne-Virumaa",
    "qs_pg:photos_9r":0,
    "qs_pg:photos_sr":0,
    "qs_pg:pop_sr":1,
    "qs_pg:qs_pg_placetype":"locality",
    "qs_pg:qs_pg_placetype_gp":"Town",
    "qs_pg:woe_adm0":23424805,
    "woe:adm0_id":23424805,
    "woe:name_adm0":"Eesti",
    "woe:name_adm1":"L\u00e4\u00e4ne-Virumaa",
    "woe:placetype":"Town",
    "wof:name":"P\u00f5drangu",
    "wof:placetype":"locality",
    "wof:population":113
},
  "geometry": {"coordinates":[26.13889,59.13306],"type":"Point"}
}