{
  "type": "Feature",
  "properties": {
    "gn:admin1_code":"20.0",
    "gn:admin2_code":"480.0",
    "gn:admin3_code":"7433.0",
    "gn:asciiname":"Sambla",
    "gn:country_code":"EE",
    "gn:dem":73,
    "gn:feature_class":"P",
    "gn:feature_code":"PPL",
    "gn:name":"Sambla",
    "gn:population":0,
    "gn:timezone":"Europe/Tallinn",
    "iso:country":"EE",
    "wof:lang_x_official":[
        "est"
    ],
    "wof:lang_x_spoken":[
        "est"
    ],
    "wof:name":"Sambla",
    "wof:placetype":"locality"
},
  "geometry": {"coordinates":[25.23694,58.14028],"type":"Point"}
}