{
  "type": "Feature",
  "properties": {
    "gn:gn_country":"EE",
    "gn:gn_fcode":"PPL",
    "gn:gn_pop":216,
    "gn:population":216,
    "iso:country":"EE",
    "name:bul_x_preferred":[
        "\u0412\u0430\u0445\u0435\u043d\u0443\u0440\u043c\u0435"
    ],
    "name:ceb_x_preferred":[
        "Vahenurme"
    ],
    "name:eng_x_preferred":[
        "Vahenurme"
    ],
    "name:est_x_preferred":[
        "Vahenurme"
    ],
    "name:hye_x_preferred":[
        "\u054e\u0561\u0570\u0565\u0576\u0578\u0582\u057c\u0574\u0565"
    ],
    "name:nld_x_preferred":[
        "Vahenurme"
    ],
    "name:pol_x_preferred":[
        "Vahenurme"
    ],
    "name:rus_x_preferred":[
        "\u0412\u0430\u0445\u0435\u043d\u0443\u0440\u043c\u0435"
    ],
    "name:spa_x_preferred":[
        "Vahenurme"
    ],
    "name:swe_x_preferred":[
        "Vahenurme"
    ],
    "name:vol_x_preferred":[
        "Vahenurme"
    ],
    "qs_pg:aaroncc":"EE",
    "qs_pg:gn_country":"EE",
    "qs_pg:gn_fcode":"PPL",
    "qs_pg:gn_pop":216,
    "qs_pg:name":"Vahenurme",
    "qs_pg:name_adm0":"Eesti",
    "qs_pg:name_adm1":"P\u00e4rnumaa",
    "qs_pg:photos_9k":1,
    "qs_pg:photos_9r":1,
    "qs_pg:photos_all":1,
    "qs_pg:photos_sr":0,
    "qs_pg:pop_sr":2,
    "qs_pg:qs_pg_placetype":"locality",
    "qs_pg:qs_pg_placetype_gp":"Town",
    "qs_pg:woe_adm0":23424805,
    "woe:adm0_id":23424805,
    "woe:name_adm0":"Eesti",
    "woe:name_adm1":"P\u00e4rnumaa",
    "woe:placetype":"Town",
    "wof:name":"Vahenurme",
    "wof:placetype":"locality",
    "wof:population":216
},
  "geometry": {"coordinates":[24.39639,58.6175],"type":"Point"}
}