{
  "type": "Feature",
  "properties": {
    "gn:admin1_code":"14.0",
    "gn:admin2_code":"714.0",
    "gn:admin3_code":"5836.0",
    "gn:asciiname":"Paevere",
    "gn:country_code":"EE",
    "gn:dem":7,
    "gn:feature_class":"P",
    "gn:feature_code":"PPL",
    "gn:name":"Paevere",
    "gn:population":0,
    "gn:timezone":"Europe/Tallinn",
    "iso:country":"EE",
    "name:deu_x_preferred":[
        "Paevere"
    ],
    "name:est_x_preferred":[
        "Paevere"
    ],
    "name:fra_x_preferred":[
        "Paevere"
    ],
    "name:hye_x_preferred":[
        "\u054a\u0561\u0587\u0565\u057c\u0565"
    ],
    "name:nld_x_preferred":[
        "Paevere"
    ],
    "name:pol_x_preferred":[
        "Paevere"
    ],
    "name:spa_x_preferred":[
        "Paevere"
    ],
    "name:ukr_x_preferred":[
        "\u041f\u0430\u0435\u0432\u0435\u0440\u0435"
    ],
    "name:vol_x_preferred":[
        "Paevere"
    ],
    "wof:name":"Paevere",
    "wof:placetype":"locality"
},
  "geometry": {"coordinates":[22.30861,58.29389000000001],"type":"Point"}
}