{
  "type": "Feature",
  "properties": {
    "gn:admin1_code":"8.0",
    "gn:admin2_code":"901.0",
    "gn:admin3_code":"5465.0",
    "gn:asciiname":"Kuivajoe",
    "gn:country_code":"EE",
    "gn:dem":90,
    "gn:feature_class":"P",
    "gn:feature_code":"PPL",
    "gn:name":"Kuivaj\u00f5e",
    "gn:population":0,
    "gn:timezone":"Europe/Tallinn",
    "iso:country":"EE",
    "wof:name":"Kuivajoe",
    "wof:placetype":"locality"
},
  "geometry": {"coordinates":[26.58417,59.29056],"type":"Point"}
}