{
  "type": "Feature",
  "properties": {
    "gn:admin1_code":"14.0",
    "gn:admin2_code":"714.0",
    "gn:admin3_code":"3967.0",
    "gn:asciiname":"Kuedema",
    "gn:country_code":"EE",
    "gn:dem":12,
    "gn:feature_class":"P",
    "gn:feature_code":"PPL",
    "gn:name":"K\u00fcdema",
    "gn:population":0,
    "gn:timezone":"Europe/Tallinn",
    "iso:country":"EE",
    "name:deu_x_preferred":[
        "K\u00fcdema"
    ],
    "name:est_x_preferred":[
        "K\u00fcdema"
    ],
    "name:hye_x_preferred":[
        "\u053f\u0575\u0578\u0582\u0564\u0565\u0574\u0561"
    ],
    "name:pol_x_preferred":[
        "K\u00fcdema"
    ],
    "name:spa_x_preferred":[
        "K\u00fcdema"
    ],
    "name:und_x_variant":[
        "Myza Kyudema",
        "K\u00fcdema Asundus",
        "Kugalepa",
        "K\u00fcdema"
    ],
    "name:vol_x_preferred":[
        "K\u00fcdema"
    ],
    "wof:name":"Kuedema",
    "wof:placetype":"locality"
},
  "geometry": {"coordinates":[22.30028,58.47528000000001],"type":"Point"}
}