{
  "type": "Feature",
  "properties": {
    "gn:admin1_code":"1.0",
    "gn:admin2_code":"726.0",
    "gn:admin3_code":"3439.0",
    "gn:asciiname":"Voore",
    "gn:country_code":"EE",
    "gn:dem":47,
    "gn:feature_class":"P",
    "gn:feature_code":"PPL",
    "gn:name":"Voore",
    "gn:population":0,
    "gn:timezone":"Europe/Tallinn",
    "iso:country":"EE",
    "name:und_x_variant":[
        "Myza Vore",
        "Voore Asundus",
        "Voore"
    ],
    "wof:name":"Voore",
    "wof:placetype":"locality"
},
  "geometry": {"coordinates":[24.58138,59.25745],"type":"Point"}
}