{
  "type": "Feature",
  "properties": {
    "gn:admin1_code":"13.0",
    "gn:admin2_code":"668.0",
    "gn:admin3_code":"2161.0",
    "gn:asciiname":"Jalase",
    "gn:cc2":"EE",
    "gn:country_code":"EE",
    "gn:dem":56,
    "gn:feature_class":"P",
    "gn:feature_code":"PPL",
    "gn:name":"Jalase",
    "gn:population":0,
    "gn:timezone":"Europe/Tallinn",
    "iso:country":"EE",
    "name:und_x_variant":[
        "Yalase",
        "Jalase"
    ],
    "wof:name":"Jalase",
    "wof:placetype":"locality"
},
  "geometry": {"coordinates":[24.62333,58.97056],"type":"Point"}
}