{
  "type": "Feature",
  "properties": {
    "gn:admin1_code":"13.0",
    "gn:admin2_code":"668.0",
    "gn:admin3_code":"2161.0",
    "gn:asciiname":"Jalase",
    "gn:cc2":"EE",
    "gn:country_code":"EE",
    "gn:dem":56,
    "gn:feature_class":"P",
    "gn:feature_code":"PPL",
    "gn:name":"Jalase",
    "gn:population":0,
    "gn:timezone":"Europe/Tallinn",
    "iso:country":"EE",
    "name:est_x_preferred":[
        "Jalase"
    ],
    "name:hye_x_preferred":[
        "\u0545\u0561\u056c\u0561\u057d\u0565"
    ],
    "name:pol_x_preferred":[
        "Jalase"
    ],
    "name:rus_x_preferred":[
        "\u042f\u043b\u0430\u0441\u0435"
    ],
    "name:sco_x_preferred":[
        "Jalase"
    ],
    "name:spa_x_preferred":[
        "Jalase"
    ],
    "name:und_x_variant":[
        "Yalase"
    ],
    "name:urd_x_preferred":[
        "\u062c\u0644\u0633\u06d2"
    ],
    "name:vol_x_preferred":[
        "Jalase"
    ],
    "wof:coterminous":[
        1713314553
    ],
    "wof:lang_x_official":[
        "est"
    ],
    "wof:lang_x_spoken":[
        "est"
    ],
    "wof:name":"Jalase",
    "wof:placetype":"locality"
},
  "geometry": {"coordinates":[24.62333,58.97056],"type":"Point"}
}