{
  "type": "Feature",
  "properties": {
    "gn:admin1_code":"8.0",
    "gn:admin2_code":"901.0",
    "gn:admin3_code":"8390.0",
    "gn:asciiname":"Allika",
    "gn:country_code":"EE",
    "gn:dem":81,
    "gn:feature_class":"P",
    "gn:feature_code":"PPL",
    "gn:name":"Allika",
    "gn:population":0,
    "gn:timezone":"Europe/Tallinn",
    "iso:country":"EE",
    "name:deu_x_preferred":[
        "Allika"
    ],
    "name:est_x_preferred":[
        "Allika"
    ],
    "name:hye_x_preferred":[
        "\u0531\u056c\u056c\u056b\u056f\u0561"
    ],
    "name:nld_x_preferred":[
        "Allika"
    ],
    "name:pol_x_preferred":[
        "Allika"
    ],
    "name:sco_x_preferred":[
        "Allika"
    ],
    "name:ukr_x_preferred":[
        "\u0410\u043b\u043b\u0456\u043a\u0430"
    ],
    "name:vol_x_preferred":[
        "Allika"
    ],
    "wof:name":"Allika",
    "wof:placetype":"locality"
},
  "geometry": {"coordinates":[26.83333,59.18333000000001],"type":"Point"}
}