{
  "type": "Feature",
  "properties": {
    "gn:admin1_code":"7.0",
    "gn:admin2_code":"441.0",
    "gn:admin3_code":"2266.0",
    "gn:asciiname":"Oomkuela",
    "gn:country_code":"EE",
    "gn:dem":22,
    "gn:feature_class":"P",
    "gn:feature_code":"PPL",
    "gn:name":"Oomk\u00fcla",
    "gn:population":0,
    "gn:timezone":"Europe/Tallinn",
    "iso:country":"EE",
    "name:und_x_variant":[
        "Omkyula",
        "Oomk\u00fcla"
    ],
    "wof:name":"Oomkuela",
    "wof:placetype":"locality"
},
  "geometry": {"coordinates":[24.01917000000001,58.85139],"type":"Point"}
}