{
  "type": "Feature",
  "properties": {
    "gn:admin1_code":"14.0",
    "gn:admin2_code":"714.0",
    "gn:admin3_code":"9197.0",
    "gn:asciiname":"Vendise",
    "gn:country_code":"EE",
    "gn:dem":37,
    "gn:feature_class":"P",
    "gn:feature_code":"PPL",
    "gn:name":"Vendise",
    "gn:population":0,
    "gn:timezone":"Europe/Tallinn",
    "iso:country":"EE",
    "name:deu_x_preferred":[
        "Vendise"
    ],
    "name:est_x_preferred":[
        "Vendise"
    ],
    "name:fas_x_preferred":[
        "\u0648\u0646\u062f\u06cc\u0633"
    ],
    "name:fra_x_preferred":[
        "Vendise"
    ],
    "name:hye_x_preferred":[
        "\u054e\u0565\u0576\u0564\u056b\u057d\u0565"
    ],
    "name:pol_x_preferred":[
        "Vendise"
    ],
    "name:spa_x_preferred":[
        "Vendise"
    ],
    "name:ukr_x_preferred":[
        "\u0412\u0435\u043d\u0434\u0456\u0437\u0435"
    ],
    "name:und_x_variant":[
        "Kiriku"
    ],
    "name:vol_x_preferred":[
        "Vendise"
    ],
    "wof:name":"Vendise",
    "wof:placetype":"locality"
},
  "geometry": {"coordinates":[22.34278,58.38556],"type":"Point"}
}