{
  "type": "Feature",
  "properties": {
    "gn:admin1_code":"14.0",
    "gn:admin2_code":"714.0",
    "gn:admin3_code":"9197.0",
    "gn:asciiname":"Vendise",
    "gn:country_code":"EE",
    "gn:dem":37,
    "gn:feature_class":"P",
    "gn:feature_code":"PPL",
    "gn:name":"Vendise",
    "gn:population":0,
    "gn:timezone":"Europe/Tallinn",
    "iso:country":"EE",
    "name:und_x_variant":[
        "Kiriku"
    ],
    "wof:name":"Vendise",
    "wof:placetype":"locality"
},
  "geometry": {"coordinates":[22.34278,58.38556],"type":"Point"}
}