{
  "type": "Feature",
  "properties": {
    "gn:admin1_code":"2.0",
    "gn:admin2_code":"205.0",
    "gn:admin3_code":"4898.0",
    "gn:asciiname":"Metsalauka",
    "gn:country_code":"EE",
    "gn:dem":12,
    "gn:feature_class":"P",
    "gn:feature_code":"PPL",
    "gn:name":"Metsalauka",
    "gn:population":0,
    "gn:timezone":"Europe/Tallinn",
    "iso:country":"EE",
    "name:deu_x_preferred":[
        "Metsalauka"
    ],
    "name:est_x_preferred":[
        "Metsalauka"
    ],
    "name:fra_x_preferred":[
        "Metsalauka"
    ],
    "name:hye_x_preferred":[
        "\u0544\u0565\u0581\u0561\u056c\u0561\u0578\u0582\u056f\u0561"
    ],
    "name:pol_x_preferred":[
        "Metsalauka"
    ],
    "name:spa_x_preferred":[
        "Metsalauka"
    ],
    "name:vol_x_preferred":[
        "Metsalauka"
    ],
    "wof:coterminous":[
        1713310793
    ],
    "wof:lang_x_official":[
        "est"
    ],
    "wof:lang_x_spoken":[
        "est"
    ],
    "wof:name":"Metsalauka",
    "wof:placetype":"locality"
},
  "geometry": {"coordinates":[22.577,58.71521],"type":"Point"}
}