{
  "type": "Feature",
  "properties": {
    "gn:admin1_code":"2.0",
    "gn:admin2_code":"205.0",
    "gn:admin3_code":"4898.0",
    "gn:asciiname":"Metsalauka",
    "gn:country_code":"EE",
    "gn:dem":12,
    "gn:feature_class":"P",
    "gn:feature_code":"PPL",
    "gn:name":"Metsalauka",
    "gn:population":0,
    "gn:timezone":"Europe/Tallinn",
    "iso:country":"EE",
    "wof:name":"Metsalauka",
    "wof:placetype":"locality"
},
  "geometry": {"coordinates":[22.577,58.71521],"type":"Point"}
}