{
  "type": "Feature",
  "properties": {
    "gn:admin1_code":"20.0",
    "gn:admin2_code":"899.0",
    "gn:admin3_code":"5763.0",
    "gn:asciiname":"Otikuela",
    "gn:country_code":"EE",
    "gn:dem":43,
    "gn:feature_class":"P",
    "gn:feature_code":"PPL",
    "gn:name":"Otik\u00fcla",
    "gn:population":0,
    "gn:timezone":"Europe/Tallinn",
    "iso:country":"EE",
    "name:und_x_variant":[
        "Oti",
        "Otik\u00fcla"
    ],
    "wof:name":"Otikuela",
    "wof:placetype":"locality"
},
  "geometry": {"coordinates":[25.95694,58.44611],"type":"Point"}
}