{
  "type": "Feature",
  "properties": {
    "gn:admin1_code":"14.0",
    "gn:admin2_code":"714.0",
    "gn:admin3_code":"3719.0",
    "gn:asciiname":"Kuusiku",
    "gn:cc2":"EE",
    "gn:country_code":"EE",
    "gn:dem":16,
    "gn:feature_class":"P",
    "gn:feature_code":"PPL",
    "gn:name":"Kuusiku",
    "gn:population":0,
    "gn:timezone":"Europe/Tallinn",
    "iso:country":"EE",
    "name:und_x_variant":[
        "Kusiku-Il\u2019pla",
        "Kuusiku"
    ],
    "wof:name":"Kuusiku",
    "wof:placetype":"locality"
},
  "geometry": {"coordinates":[22.67583,58.29639],"type":"Point"}
}