{
  "type": "Feature",
  "properties": {
    "gn:admin1_code":"18.0",
    "gn:admin2_code":"796.0",
    "gn:admin3_code":"7542.0",
    "gn:asciiname":"Sepa",
    "gn:country_code":"EE",
    "gn:dem":62,
    "gn:feature_class":"P",
    "gn:feature_code":"PPL",
    "gn:name":"Sepa",
    "gn:population":0,
    "gn:timezone":"Europe/Tallinn",
    "iso:country":"EE",
    "wof:name":"Sepa",
    "wof:placetype":"locality"
},
  "geometry": {"coordinates":[26.50083,58.58472],"type":"Point"}
}