{
  "type": "Feature",
  "properties": {
    "gn:admin1_code":"5.0",
    "gn:admin2_code":"486.0",
    "gn:admin3_code":"4308.0",
    "gn:asciiname":"Soo-otsa",
    "gn:country_code":"EE",
    "gn:dem":57,
    "gn:feature_class":"P",
    "gn:feature_code":"PPL",
    "gn:name":"Soo-otsa",
    "gn:population":0,
    "gn:timezone":"Europe/Tallinn",
    "iso:country":"EE",
    "name:und_x_variant":[
        "Sootsa"
    ],
    "wof:name":"Soo-otsa",
    "wof:placetype":"locality"
},
  "geometry": {"coordinates":[26.80167,58.69917],"type":"Point"}
}