{
  "type": "Feature",
  "properties": {
    "gn:admin1_code":"5.0",
    "gn:admin2_code":"486.0",
    "gn:admin3_code":"9029.0",
    "gn:asciiname":"Vanassaare",
    "gn:country_code":"EE",
    "gn:dem":47,
    "gn:feature_class":"P",
    "gn:feature_code":"PPL",
    "gn:name":"Vanassaare",
    "gn:population":0,
    "gn:timezone":"Europe/Tallinn",
    "iso:country":"EE",
    "wof:name":"Vanassaare",
    "wof:placetype":"locality"
},
  "geometry": {"coordinates":[26.79889,58.66667],"type":"Point"}
}