{
  "type": "Feature",
  "properties": {
    "gn:admin1_code":"5.0",
    "gn:admin2_code":"486.0",
    "gn:admin3_code":"9029.0",
    "gn:asciiname":"Vanassaare",
    "gn:country_code":"EE",
    "gn:dem":47,
    "gn:feature_class":"P",
    "gn:feature_code":"PPL",
    "gn:name":"Vanassaare",
    "gn:population":0,
    "gn:timezone":"Europe/Tallinn",
    "iso:country":"EE",
    "name:ara_x_preferred":[
        "\u0641\u0627\u0646\u0627\u0633\u0627\u0631"
    ],
    "name:est_x_preferred":[
        "Vanassaare"
    ],
    "name:fas_x_preferred":[
        "\u0648\u0646\u0633\u0627\u0631"
    ],
    "name:hye_x_preferred":[
        "\u054e\u0561\u0576\u0561\u057d\u0561\u0561\u057c\u0565"
    ],
    "name:pol_x_preferred":[
        "Vanassaare"
    ],
    "name:spa_x_preferred":[
        "Vanassaare"
    ],
    "name:ukr_x_preferred":[
        "\u0412\u0430\u043d\u0430\u0441\u0441\u0430\u0430\u0440\u0435"
    ],
    "name:vol_x_preferred":[
        "Vanassaare"
    ],
    "wof:lang_x_official":[
        "est"
    ],
    "wof:lang_x_spoken":[
        "est"
    ],
    "wof:name":"Vanassaare",
    "wof:placetype":"locality"
},
  "geometry": {"coordinates":[26.79889,58.66667],"type":"Point"}
}