{
  "type": "Feature",
  "properties": {
    "gn:admin1_code":"3.0",
    "gn:admin2_code":"514.0",
    "gn:admin3_code":"1908.0",
    "gn:asciiname":"Hundinurga",
    "gn:country_code":"EE",
    "gn:dem":41,
    "gn:feature_class":"P",
    "gn:feature_code":"PPL",
    "gn:name":"Hundinurga",
    "gn:population":0,
    "gn:timezone":"Europe/Tallinn",
    "iso:country":"EE",
    "name:deu_x_preferred":[
        "Hundinurga"
    ],
    "name:est_x_preferred":[
        "Hundinurga"
    ],
    "name:hye_x_preferred":[
        "\u0540\u0578\u0582\u0576\u0564\u056b\u0576\u0578\u0582\u057c\u0563\u0561"
    ],
    "name:ukr_x_preferred":[
        "\u0413\u0443\u043d\u0434\u0456\u043d\u0443\u0440\u0491\u0430"
    ],
    "name:vol_x_preferred":[
        "Hundinurga"
    ],
    "wof:coterminous":[
        1713307695
    ],
    "wof:lang_x_official":[
        "est"
    ],
    "wof:lang_x_spoken":[
        "est"
    ],
    "wof:name":"Hundinurga",
    "wof:placetype":"locality"
},
  "geometry": {"coordinates":[27.892,59.3637],"type":"Point"}
}