{
  "type": "Feature",
  "properties": {
    "gn:admin1_code":"3.0",
    "gn:admin2_code":"514.0",
    "gn:admin3_code":"1908.0",
    "gn:asciiname":"Hundinurga",
    "gn:country_code":"EE",
    "gn:dem":41,
    "gn:feature_class":"P",
    "gn:feature_code":"PPL",
    "gn:name":"Hundinurga",
    "gn:population":0,
    "gn:timezone":"Europe/Tallinn",
    "iso:country":"EE",
    "wof:name":"Hundinurga",
    "wof:placetype":"locality"
},
  "geometry": {"coordinates":[27.892,59.3637],"type":"Point"}
}