{
  "type": "Feature",
  "properties": {
    "gn:admin1_code":"13.0",
    "gn:admin2_code":"503.0",
    "gn:admin3_code":"5921.0",
    "gn:asciiname":"Uhja",
    "gn:country_code":"EE",
    "gn:dem":36,
    "gn:feature_class":"P",
    "gn:feature_code":"PPL",
    "gn:name":"Uhja",
    "gn:population":0,
    "gn:timezone":"Europe/Tallinn",
    "iso:country":"EE",
    "name:und_x_variant":[
        "Ukh\u2019ya",
        "Uhja"
    ],
    "wof:lang_x_official":[
        "est"
    ],
    "wof:lang_x_spoken":[
        "est"
    ],
    "wof:name":"Uhja",
    "wof:placetype":"locality"
},
  "geometry": {"coordinates":[24.4825,58.73639],"type":"Point"}
}