{
  "type": "Feature",
  "properties": {
    "gn:admin1_code":"11.0",
    "gn:admin2_code":"430.0",
    "gn:admin3_code":"8091.0",
    "gn:asciiname":"Koima",
    "gn:country_code":"EE",
    "gn:dem":19,
    "gn:feature_class":"P",
    "gn:feature_code":"PPL",
    "gn:name":"K\u00f5ima",
    "gn:population":0,
    "gn:timezone":"Europe/Tallinn",
    "iso:country":"EE",
    "name:und_x_variant":[
        "K\u00f5ima"
    ],
    "wof:coterminous":[
        1713308989
    ],
    "wof:lang_x_official":[
        "est"
    ],
    "wof:lang_x_spoken":[
        "est"
    ],
    "wof:name":"Koima",
    "wof:placetype":"locality"
},
  "geometry": {"coordinates":[24.20889,58.61417],"type":"Point"}
}