{
  "type": "Feature",
  "properties": {
    "gn:admin1_code":"14.0",
    "gn:admin2_code":"714.0",
    "gn:admin3_code":"2200.0",
    "gn:asciiname":"Saia",
    "gn:cc2":"EE",
    "gn:country_code":"EE",
    "gn:dem":14,
    "gn:feature_class":"P",
    "gn:feature_code":"PPL",
    "gn:name":"Saia",
    "gn:population":0,
    "gn:timezone":"Europe/Tallinn",
    "iso:country":"EE",
    "name:deu_x_preferred":[
        "Saia"
    ],
    "name:est_x_preferred":[
        "Saia"
    ],
    "name:fra_x_preferred":[
        "Saia"
    ],
    "name:hye_x_preferred":[
        "\u054d\u0561\u056b\u0561"
    ],
    "name:nld_x_preferred":[
        "Saia"
    ],
    "name:pol_x_preferred":[
        "Saia"
    ],
    "name:spa_x_preferred":[
        "Saia"
    ],
    "name:ukr_x_preferred":[
        "\u0421\u0430\u0439\u0430"
    ],
    "name:und_x_variant":[
        "Saya",
        "Saia"
    ],
    "name:urd_x_preferred":[
        "\u0633\u06cc\u0627"
    ],
    "name:vol_x_preferred":[
        "Saia"
    ],
    "wof:name":"Saia",
    "wof:placetype":"locality"
},
  "geometry": {"coordinates":[22.47,58.32972],"type":"Point"}
}