{
  "type": "Feature",
  "properties": {
    "gn:gn_country":"EE",
    "gn:gn_fcode":"PPL",
    "gn:gn_pop":106,
    "gn:population":106,
    "iso:country":"EE",
    "name:ceb_x_preferred":[
        "Visusti"
    ],
    "name:deu_x_preferred":[
        "Visusti"
    ],
    "name:est_x_preferred":[
        "Visusti"
    ],
    "name:hye_x_preferred":[
        "\u054e\u056b\u057d\u0578\u0582\u057d\u057f\u056b"
    ],
    "name:pol_x_preferred":[
        "Visusti"
    ],
    "name:spa_x_preferred":[
        "Visusti"
    ],
    "name:swe_x_preferred":[
        "Visusti"
    ],
    "name:vol_x_preferred":[
        "Visusti"
    ],
    "qs_pg:aaroncc":"EE",
    "qs_pg:gn_country":"EE",
    "qs_pg:gn_fcode":"PPL",
    "qs_pg:gn_pop":106,
    "qs_pg:name":"Visusti",
    "qs_pg:name_adm0":"Eesti",
    "qs_pg:name_adm1":"J\u00e4rvamaa",
    "qs_pg:photos_9r":0,
    "qs_pg:photos_sr":0,
    "qs_pg:pop_sr":1,
    "qs_pg:qs_pg_placetype":"locality",
    "qs_pg:qs_pg_placetype_gp":"Town",
    "qs_pg:woe_adm0":23424805,
    "woe:adm0_id":23424805,
    "woe:name_adm0":"Eesti",
    "woe:name_adm1":"J\u00e4rvamaa",
    "woe:placetype":"Town",
    "wof:name":"Visusti",
    "wof:placetype":"locality",
    "wof:population":106
},
  "geometry": {"coordinates":[26.50472,58.62361],"type":"Point"}
}