{
  "type": "Feature",
  "properties": {
    "gn:admin1_code":"11.0",
    "gn:admin2_code":"624.0",
    "gn:admin3_code":"3746.0",
    "gn:asciiname":"Karuga",
    "gn:country_code":"EE",
    "gn:dem":39,
    "gn:feature_class":"P",
    "gn:feature_code":"PPL",
    "gn:name":"Karuga",
    "gn:population":0,
    "gn:timezone":"Europe/Tallinn",
    "iso:country":"EE",
    "wof:name":"Karuga",
    "wof:placetype":"locality"
},
  "geometry": {"coordinates":[24.14417000000001,58.34721999999999],"type":"Point"}
}