{
  "type": "Feature",
  "properties": {
    "gn:admin1_code":"18.0",
    "gn:admin2_code":"291.0",
    "gn:admin3_code":"1752.0",
    "gn:asciiname":"Hammaste",
    "gn:cc2":"EE",
    "gn:country_code":"EE",
    "gn:dem":50,
    "gn:feature_class":"P",
    "gn:feature_code":"PPL",
    "gn:name":"Hammaste",
    "gn:population":0,
    "gn:timezone":"Europe/Tallinn",
    "iso:country":"EE",
    "name:und_x_variant":[
        "Khammaste",
        "Hammaste"
    ],
    "wof:name":"Hammaste",
    "wof:placetype":"locality"
},
  "geometry": {"coordinates":[27.00639,58.28471999999999],"type":"Point"}
}