{
  "type": "Feature",
  "properties": {
    "gn:admin1_code":"14.0",
    "gn:admin2_code":"714.0",
    "gn:admin3_code":"5967.0",
    "gn:asciiname":"Pammana",
    "gn:country_code":"EE",
    "gn:dem":17,
    "gn:feature_class":"P",
    "gn:feature_code":"PPL",
    "gn:name":"Pammana",
    "gn:population":0,
    "gn:timezone":"Europe/Tallinn",
    "iso:country":"EE",
    "name:deu_x_preferred":[
        "Pammana"
    ],
    "name:est_x_preferred":[
        "Pammana"
    ],
    "name:hye_x_preferred":[
        "\u054a\u0561\u0574\u0574\u0561\u0576\u0561"
    ],
    "name:nld_x_preferred":[
        "Pammana"
    ],
    "name:pol_x_preferred":[
        "Pammana"
    ],
    "name:spa_x_preferred":[
        "Pammana"
    ],
    "name:vol_x_preferred":[
        "Pammana"
    ],
    "wof:name":"Pammana",
    "wof:placetype":"locality"
},
  "geometry": {"coordinates":[22.56583,58.62111],"type":"Point"}
}