{
  "type": "Feature",
  "properties": {
    "gn:admin1_code":"8.0",
    "gn:admin2_code":"792.0",
    "gn:admin3_code":"8549.0",
    "gn:asciiname":"Pruuna",
    "gn:country_code":"EE",
    "gn:dem":92,
    "gn:feature_class":"P",
    "gn:feature_code":"PPL",
    "gn:name":"Pruuna",
    "gn:population":0,
    "gn:timezone":"Europe/Tallinn",
    "iso:country":"EE",
    "name:und_x_variant":[
        "Myza Pruna",
        "Pruuna Asundus",
        "Pruuna"
    ],
    "wof:name":"Pruuna",
    "wof:placetype":"locality"
},
  "geometry": {"coordinates":[25.85278,59.26221999999999],"type":"Point"}
}