{
  "type": "Feature",
  "properties": {
    "gn:admin1_code":"8.0",
    "gn:admin2_code":"792.0",
    "gn:admin3_code":"8549.0",
    "gn:asciiname":"Pruuna",
    "gn:country_code":"EE",
    "gn:dem":92,
    "gn:feature_class":"P",
    "gn:feature_code":"PPL",
    "gn:name":"Pruuna",
    "gn:population":0,
    "gn:timezone":"Europe/Tallinn",
    "iso:country":"EE",
    "name:est_x_preferred":[
        "Pruuna"
    ],
    "name:fra_x_preferred":[
        "Pruuna"
    ],
    "name:hye_x_preferred":[
        "\u054a\u057c\u0578\u0582\u0578\u0582\u0576\u0561"
    ],
    "name:ukr_x_preferred":[
        "\u041f\u0440\u0443\u0443\u043d\u0430"
    ],
    "name:und_x_variant":[
        "Myza Pruna",
        "Pruuna Asundus"
    ],
    "name:vol_x_preferred":[
        "Pruuna"
    ],
    "wof:name":"Pruuna",
    "wof:placetype":"locality"
},
  "geometry": {"coordinates":[25.85278,59.26221999999999],"type":"Point"}
}