{
  "type": "Feature",
  "properties": {
    "gn:admin1_code":"20.0",
    "gn:admin2_code":"899.0",
    "gn:admin3_code":"7076.0",
    "gn:asciiname":"Kuebeme",
    "gn:country_code":"EE",
    "gn:dem":69,
    "gn:feature_class":"P",
    "gn:feature_code":"PPL",
    "gn:name":"K\u00fcbeme",
    "gn:population":0,
    "gn:timezone":"Europe/Tallinn",
    "iso:country":"EE",
    "name:und_x_variant":[
        "Kyubeme",
        "K\u00fcbeme"
    ],
    "wof:lang_x_official":[
        "est"
    ],
    "wof:lang_x_spoken":[
        "est"
    ],
    "wof:name":"Kuebeme",
    "wof:placetype":"locality"
},
  "geometry": {"coordinates":[25.91667,58.16667],"type":"Point"}
}