{
  "type": "Feature",
  "properties": {
    "gn:admin1_code":"8.0",
    "gn:admin2_code":"901.0",
    "gn:admin3_code":"1043.0",
    "gn:asciiname":"Aasuvaelja",
    "gn:country_code":"EE",
    "gn:dem":76,
    "gn:feature_class":"P",
    "gn:feature_code":"PPL",
    "gn:name":"Aasuv\u00e4lja",
    "gn:population":0,
    "gn:timezone":"Europe/Tallinn",
    "iso:country":"EE",
    "name:ces_x_preferred":[
        "Aasuv\u00e4lja"
    ],
    "name:est_x_preferred":[
        "Aasuv\u00e4lja"
    ],
    "name:fas_x_preferred":[
        "\u0622\u0633\u0648\u0648\u0627\u0644\u062c\u0627"
    ],
    "name:hye_x_preferred":[
        "\u0531\u0561\u057d\u0578\u0582\u057e\u0565\u056c\u0575\u0561"
    ],
    "name:pol_x_preferred":[
        "Aasuv\u00e4lja"
    ],
    "name:urd_x_preferred":[
        "\u0622\u0633\u0648\u0648\u0627\u0644\u062c\u0627"
    ],
    "name:vol_x_preferred":[
        "Aasuv\u00e4lja"
    ],
    "wof:lang_x_official":[
        "est"
    ],
    "wof:lang_x_spoken":[
        "est"
    ],
    "wof:name":"Aasuvaelja",
    "wof:placetype":"locality"
},
  "geometry": {"coordinates":[26.59722,59.32556],"type":"Point"}
}