{
  "type": "Feature",
  "properties": {
    "gn:admin1_code":"4.0",
    "gn:admin2_code":"567.0",
    "gn:admin3_code":"5317.0",
    "gn:asciiname":"Kriilevaelja",
    "gn:country_code":"EE",
    "gn:dem":70,
    "gn:feature_class":"P",
    "gn:feature_code":"PPL",
    "gn:name":"Kriilev\u00e4lja",
    "gn:population":0,
    "gn:timezone":"Europe/Tallinn",
    "iso:country":"EE",
    "name:est_x_preferred":[
        "Kriilev\u00e4lja"
    ],
    "name:hye_x_preferred":[
        "\u053f\u057c\u056b\u056b\u056c\u0587\u0565\u056c\u0575\u0561"
    ],
    "name:pol_x_preferred":[
        "Kriilev\u00e4lja"
    ],
    "name:ukr_x_preferred":[
        "\u041a\u0440\u0456\u0439\u043b\u0435\u0432\u044f\u043b\u044c\u044f"
    ],
    "name:und_x_variant":[
        "Kriilev\u00e4lja"
    ],
    "name:vol_x_preferred":[
        "Kriilev\u00e4lja"
    ],
    "wof:name":"Kriilevaelja",
    "wof:placetype":"locality"
},
  "geometry": {"coordinates":[25.60278,58.87778],"type":"Point"}
}