{
  "type": "Feature",
  "properties": {
    "gn:admin1_code":"8.0",
    "gn:admin2_code":"928.0",
    "gn:admin3_code":"6836.0",
    "gn:asciiname":"Rastla",
    "gn:country_code":"EE",
    "gn:dem":107,
    "gn:feature_class":"P",
    "gn:feature_code":"PPL",
    "gn:name":"Rastla",
    "gn:population":0,
    "gn:timezone":"Europe/Tallinn",
    "iso:country":"EE",
    "wof:name":"Rastla",
    "wof:placetype":"locality"
},
  "geometry": {"coordinates":[26.30278,59.08917],"type":"Point"}
}