{
  "type": "Feature",
  "properties": {
    "gn:admin1_code":"11.0",
    "gn:admin2_code":"430.0",
    "gn:admin3_code":"7379.0",
    "gn:asciiname":"Salevere",
    "gn:cc2":"EE",
    "gn:country_code":"EE",
    "gn:dem":11,
    "gn:feature_class":"P",
    "gn:feature_code":"PPL",
    "gn:name":"Salevere",
    "gn:population":0,
    "gn:timezone":"Europe/Tallinn",
    "iso:country":"EE",
    "name:und_x_variant":[
        "Polumyza Salevere",
        "Salevere"
    ],
    "wof:name":"Salevere",
    "wof:placetype":"locality"
},
  "geometry": {"coordinates":[23.59806,58.69],"type":"Point"}
}