{
  "type": "Feature",
  "properties": {
    "gn:admin1_code":"11.0",
    "gn:admin2_code":"430.0",
    "gn:admin3_code":"7379.0",
    "gn:asciiname":"Salevere",
    "gn:cc2":"EE",
    "gn:country_code":"EE",
    "gn:dem":11,
    "gn:feature_class":"P",
    "gn:feature_code":"PPL",
    "gn:name":"Salevere",
    "gn:population":0,
    "gn:timezone":"Europe/Tallinn",
    "iso:country":"EE",
    "name:deu_x_preferred":[
        "Salevere"
    ],
    "name:est_x_preferred":[
        "Salevere"
    ],
    "name:hye_x_preferred":[
        "\u054d\u0561\u056c\u0587\u0565\u057c\u0565"
    ],
    "name:nld_x_preferred":[
        "Salevere"
    ],
    "name:pol_x_preferred":[
        "Salevere"
    ],
    "name:ukr_x_preferred":[
        "\u0421\u0430\u043b\u0435\u0432\u0435\u0440\u0435"
    ],
    "name:und_x_variant":[
        "Polumyza Salevere"
    ],
    "name:vol_x_preferred":[
        "Salevere"
    ],
    "wof:coterminous":[
        1713309343
    ],
    "wof:lang_x_official":[
        "est"
    ],
    "wof:lang_x_spoken":[
        "est"
    ],
    "wof:name":"Salevere",
    "wof:placetype":"locality"
},
  "geometry": {"coordinates":[23.59806,58.69],"type":"Point"}
}