{
  "type": "Feature",
  "properties": {
    "gn:admin1_code":"21.0",
    "gn:admin2_code":"917.0",
    "gn:admin3_code":"3981.0",
    "gn:asciiname":"Roodsi",
    "gn:country_code":"EE",
    "gn:dem":161,
    "gn:feature_class":"P",
    "gn:feature_code":"PPL",
    "gn:name":"Roodsi",
    "gn:population":0,
    "gn:timezone":"Europe/Tallinn",
    "iso:country":"EE",
    "name:und_x_variant":[
        "Rootsi"
    ],
    "wof:name":"Roodsi",
    "wof:placetype":"locality"
},
  "geometry": {"coordinates":[27.285,57.75389000000001],"type":"Point"}
}