{
  "type": "Feature",
  "properties": {
    "gn:admin1_code":"13.0",
    "gn:admin2_code":"317.0",
    "gn:admin3_code":"5854.0",
    "gn:asciiname":"Tamsalu",
    "gn:country_code":"EE",
    "gn:dem":68,
    "gn:feature_class":"P",
    "gn:feature_code":"PPL",
    "gn:name":"Tamsalu",
    "gn:population":0,
    "gn:timezone":"Europe/Tallinn",
    "iso:country":"EE",
    "name:und_x_variant":[
        "Tukam\u00e4e"
    ],
    "wof:name":"Tamsalu",
    "wof:placetype":"locality"
},
  "geometry": {"coordinates":[24.89167,59.17361],"type":"Point"}
}