{
  "type": "Feature",
  "properties": {
    "gn:admin1_code":"1.0",
    "gn:admin2_code":"726.0",
    "gn:admin3_code":"7571.0",
    "gn:asciiname":"Selgkuela",
    "gn:country_code":"EE",
    "gn:dem":45,
    "gn:feature_class":"P",
    "gn:feature_code":"PPL",
    "gn:name":"Selgk\u00fcla",
    "gn:population":0,
    "gn:timezone":"Europe/Tallinn",
    "iso:country":"EE",
    "name:und_x_variant":[
        "Sel\u2019gkyula",
        "Selgk\u00fcla"
    ],
    "wof:name":"Selgkuela",
    "wof:placetype":"locality"
},
  "geometry": {"coordinates":[24.15694,59.11611],"type":"Point"}
}