{
  "type": "Feature",
  "properties": {
    "gn:admin1_code":"18.0",
    "gn:admin2_code":"291.0",
    "gn:admin3_code":"3772.0",
    "gn:asciiname":"Liispollu",
    "gn:cc2":"EE",
    "gn:country_code":"EE",
    "gn:dem":38,
    "gn:feature_class":"P",
    "gn:feature_code":"PPL",
    "gn:name":"Liisp\u00f5llu",
    "gn:population":0,
    "gn:timezone":"Europe/Tallinn",
    "iso:country":"EE",
    "name:und_x_variant":[
        "Liispyllu",
        "Lispyllu",
        "Liisp\u00f5llu"
    ],
    "wof:name":"Liispollu",
    "wof:placetype":"locality"
},
  "geometry": {"coordinates":[27.23333,58.27639],"type":"Point"}
}