{
  "type": "Feature",
  "properties": {
    "gn:admin1_code":"18.0",
    "gn:admin2_code":"291.0",
    "gn:admin3_code":"3772.0",
    "gn:asciiname":"Liispollu",
    "gn:cc2":"EE",
    "gn:country_code":"EE",
    "gn:dem":38,
    "gn:feature_class":"P",
    "gn:feature_code":"PPL",
    "gn:name":"Liisp\u00f5llu",
    "gn:population":0,
    "gn:timezone":"Europe/Tallinn",
    "iso:country":"EE",
    "name:est_x_preferred":[
        "Liisp\u00f5llu"
    ],
    "name:fra_x_preferred":[
        "Liisp\u00f5llu"
    ],
    "name:hye_x_preferred":[
        "\u053c\u056b\u056b\u057d\u057a\u056b\u056c\u056c\u0578\u0582"
    ],
    "name:pol_x_preferred":[
        "Liisp\u00f5llu"
    ],
    "name:spa_x_preferred":[
        "Liisp\u00f5llu"
    ],
    "name:ukr_x_preferred":[
        "\u041b\u0456\u0439\u0441\u043f\u0438\u043b\u043b\u0443"
    ],
    "name:und_x_variant":[
        "Liispyllu",
        "Lispyllu"
    ],
    "name:vol_x_preferred":[
        "Liisp\u00f5llu"
    ],
    "wof:coterminous":[
        1713313517
    ],
    "wof:lang_x_official":[
        "est"
    ],
    "wof:lang_x_spoken":[
        "est"
    ],
    "wof:name":"Liispollu",
    "wof:placetype":"locality"
},
  "geometry": {"coordinates":[27.23333,58.27639],"type":"Point"}
}