{
  "type": "Feature",
  "properties": {
    "gn:admin1_code":"8.0",
    "gn:admin2_code":"903.0",
    "gn:admin3_code":"5456.0",
    "gn:asciiname":"Nugeri",
    "gn:country_code":"EE",
    "gn:dem":54,
    "gn:feature_class":"P",
    "gn:feature_code":"PPL",
    "gn:name":"Nugeri",
    "gn:population":0,
    "gn:timezone":"Europe/Tallinn",
    "iso:country":"EE",
    "wof:name":"Nugeri",
    "wof:placetype":"locality"
},
  "geometry": {"coordinates":[26.64861,59.45056],"type":"Point"}
}