{
  "type": "Feature",
  "properties": {
    "gn:admin1_code":"13.0",
    "gn:admin2_code":"293.0",
    "gn:admin3_code":"5334.0",
    "gn:asciiname":"Roue",
    "gn:country_code":"EE",
    "gn:dem":65,
    "gn:feature_class":"P",
    "gn:feature_code":"PPL",
    "gn:name":"R\u00f5ue",
    "gn:population":0,
    "gn:timezone":"Europe/Tallinn",
    "iso:country":"EE",
    "name:est_x_preferred":[
        "R\u00f5ue"
    ],
    "name:hye_x_preferred":[
        "\u054c\u056b\u0578\u0582\u0565"
    ],
    "name:pol_x_preferred":[
        "R\u00f5ue"
    ],
    "name:sco_x_preferred":[
        "R\u00f5ue"
    ],
    "name:spa_x_preferred":[
        "R\u00f5ue"
    ],
    "name:und_x_variant":[
        "Ryue",
        "R\u00f5ude"
    ],
    "name:vol_x_preferred":[
        "R\u00f5ue"
    ],
    "wof:coterminous":[
        1713311167
    ],
    "wof:lang_x_official":[
        "est"
    ],
    "wof:lang_x_spoken":[
        "est"
    ],
    "wof:name":"Roue",
    "wof:placetype":"locality"
},
  "geometry": {"coordinates":[24.89833,58.90417],"type":"Point"}
}