{
  "type": "Feature",
  "properties": {
    "gn:admin1_code":"8.0",
    "gn:admin2_code":"903.0",
    "gn:admin3_code":"4305.0",
    "gn:asciiname":"Letipea",
    "gn:country_code":"EE",
    "gn:dem":21,
    "gn:feature_class":"P",
    "gn:feature_code":"PPL",
    "gn:name":"Letipea",
    "gn:population":0,
    "gn:timezone":"Europe/Tallinn",
    "iso:country":"EE",
    "name:eng_x_preferred":[
        "Letipea"
    ],
    "name:est_x_preferred":[
        "Letipea"
    ],
    "name:hye_x_preferred":[
        "\u053c\u0565\u057f\u056b\u057a\u0565\u0561"
    ],
    "name:pol_x_preferred":[
        "Letipea"
    ],
    "name:rus_x_preferred":[
        "\u041b\u0435\u0442\u0438\u043f\u0435\u0430"
    ],
    "name:vol_x_preferred":[
        "Letipea"
    ],
    "wof:coterminous":[
        1713307651
    ],
    "wof:lang_x_official":[
        "est"
    ],
    "wof:lang_x_spoken":[
        "est"
    ],
    "wof:name":"Letipea",
    "wof:placetype":"locality"
},
  "geometry": {"coordinates":[26.60167,59.54056],"type":"Point"}
}