{
  "type": "Feature",
  "properties": {
    "gn:admin1_code":"8.0",
    "gn:admin2_code":"191.0",
    "gn:admin3_code":"1562.0",
    "gn:asciiname":"Eisma",
    "gn:country_code":"EE",
    "gn:dem":23,
    "gn:feature_class":"P",
    "gn:feature_code":"PPL",
    "gn:name":"Eisma",
    "gn:population":0,
    "gn:timezone":"Europe/Tallinn",
    "iso:country":"EE",
    "name:deu_x_preferred":[
        "Eisma"
    ],
    "name:est_x_preferred":[
        "Eisma"
    ],
    "name:fra_x_preferred":[
        "Eisma"
    ],
    "name:hye_x_preferred":[
        "\u0537\u056b\u057d\u0574\u0561"
    ],
    "name:swe_x_preferred":[
        "Eisma"
    ],
    "name:vol_x_preferred":[
        "Eisma"
    ],
    "wof:name":"Eisma",
    "wof:placetype":"locality"
},
  "geometry": {"coordinates":[26.30472,59.56028000000001],"type":"Point"}
}