{
  "type": "Feature",
  "properties": {
    "gn:admin1_code":"8.0",
    "gn:admin2_code":"272.0",
    "gn:admin3_code":"9490.0",
    "gn:asciiname":"Voduvere",
    "gn:country_code":"EE",
    "gn:dem":86,
    "gn:feature_class":"P",
    "gn:feature_code":"PPL",
    "gn:name":"V\u00f5duvere",
    "gn:population":0,
    "gn:timezone":"Europe/Tallinn",
    "iso:country":"EE",
    "name:und_x_variant":[
        "V\u00f5duvere"
    ],
    "wof:name":"Voduvere",
    "wof:placetype":"locality"
},
  "geometry": {"coordinates":[26.10694,59.32471999999999],"type":"Point"}
}