{
  "type": "Feature",
  "properties": {
    "gn:admin1_code":"11.0",
    "gn:admin2_code":"214.0",
    "gn:admin3_code":"4746.0",
    "gn:asciiname":"Majaka",
    "gn:country_code":"EE",
    "gn:dem":17,
    "gn:feature_class":"P",
    "gn:feature_code":"PPL",
    "gn:name":"Majaka",
    "gn:population":0,
    "gn:timezone":"Europe/Tallinn",
    "iso:country":"EE",
    "name:eng_x_preferred":[
        "Majaka"
    ],
    "name:est_x_preferred":[
        "Majaka"
    ],
    "name:hye_x_preferred":[
        "\u0544\u0561\u0575\u0561\u056f\u0561"
    ],
    "name:pol_x_preferred":[
        "Majaka"
    ],
    "name:rus_x_preferred":[
        "\u041c\u0430\u044f\u043a\u0430"
    ],
    "name:spa_x_preferred":[
        "Majaka"
    ],
    "name:ukr_x_preferred":[
        "\u041c\u0430\u044f\u043a\u0430"
    ],
    "name:vol_x_preferred":[
        "Majaka"
    ],
    "wof:name":"Majaka",
    "wof:placetype":"locality"
},
  "geometry": {"coordinates":[24.41167,57.97556],"type":"Point"}
}