{
  "type": "Feature",
  "properties": {
    "gn:admin1_code":"13.0",
    "gn:admin2_code":"503.0",
    "gn:admin3_code":"6624.0",
    "gn:asciiname":"Myza Pyadeva",
    "gn:country_code":"EE",
    "gn:dem":41,
    "gn:feature_class":"P",
    "gn:feature_code":"PPL",
    "gn:name":"Myza Pyadeva",
    "gn:population":0,
    "gn:timezone":"Europe/Tallinn",
    "iso:country":"EE",
    "name:deu_x_preferred":[
        "P\u00e4\u00e4deva"
    ],
    "name:est_x_preferred":[
        "P\u00e4\u00e4deva"
    ],
    "name:fra_x_preferred":[
        "P\u00e4\u00e4deva"
    ],
    "name:hye_x_preferred":[
        "\u054a\u0565\u0565\u0564\u0587\u0561"
    ],
    "name:pol_x_preferred":[
        "P\u00e4\u00e4deva"
    ],
    "name:sco_x_preferred":[
        "P\u00e4\u00e4deva"
    ],
    "name:spa_x_preferred":[
        "P\u00e4\u00e4deva"
    ],
    "name:und_x_variant":[
        "P\u00e4\u00e4deva Asundus",
        "Myza Pyadeva"
    ],
    "name:vol_x_preferred":[
        "P\u00e4\u00e4deva"
    ],
    "wof:lang_x_official":[
        "est"
    ],
    "wof:lang_x_spoken":[
        "est"
    ],
    "wof:name":"Myza Pyadeva",
    "wof:placetype":"locality"
},
  "geometry": {"coordinates":[24.43528,58.9375],"type":"Point"}
}