{
  "type": "Feature",
  "properties": {
    "gn:admin1_code":"13.0",
    "gn:admin2_code":"503.0",
    "gn:admin3_code":"6624.0",
    "gn:asciiname":"Myza Pyadeva",
    "gn:country_code":"EE",
    "gn:dem":41,
    "gn:feature_class":"P",
    "gn:feature_code":"PPL",
    "gn:name":"Myza Pyadeva",
    "gn:population":0,
    "gn:timezone":"Europe/Tallinn",
    "iso:country":"EE",
    "name:und_x_variant":[
        "P\u00e4\u00e4deva Asundus",
        "Myza Pyadeva",
        "P\u00e4\u00e4deva"
    ],
    "wof:name":"Myza Pyadeva",
    "wof:placetype":"locality"
},
  "geometry": {"coordinates":[24.43528,58.9375],"type":"Point"}
}