{
  "type": "Feature",
  "properties": {
    "gn:gn_country":"EE",
    "gn:gn_fcode":"PPL",
    "gn:gn_pop":106,
    "gn:population":106,
    "iso:country":"EE",
    "name:eng_x_preferred":[
        "V\u00f5tikvere"
    ],
    "name:est_x_preferred":[
        "V\u00f5tikvere"
    ],
    "name:fra_x_preferred":[
        "V\u00f5tikvere"
    ],
    "name:hye_x_preferred":[
        "\u054e\u056b\u057f\u056b\u056f\u057e\u0565\u057c\u0565"
    ],
    "name:pol_x_preferred":[
        "V\u00f5tikvere"
    ],
    "name:unk_x_variant":[
        "Vytikvere"
    ],
    "name:vol_x_preferred":[
        "V\u00f5tikvere"
    ],
    "qs_pg:aaroncc":"EE",
    "qs_pg:gn_country":"EE",
    "qs_pg:gn_fcode":"PPL",
    "qs_pg:gn_pop":106,
    "qs_pg:name":"V\u00f5tikvere",
    "qs_pg:photos_9r":0,
    "qs_pg:photos_sr":0,
    "qs_pg:pop_sr":1,
    "qs_pg:qs_pg_placetype":"locality",
    "wof:name":"V\u00f5tikvere",
    "wof:placetype":"locality",
    "wof:population":106
},
  "geometry": {"coordinates":[26.84944,58.86639],"type":"Point"}
}