{
  "type": "Feature",
  "properties": {
    "gn:admin1_code":"20.0",
    "gn:admin2_code":"615.0",
    "gn:admin3_code":"3142.0",
    "gn:asciiname":"Palu",
    "gn:cc2":"EE",
    "gn:country_code":"EE",
    "gn:dem":56,
    "gn:feature_class":"P",
    "gn:feature_code":"PPL",
    "gn:name":"Palu",
    "gn:population":0,
    "gn:timezone":"Europe/Tallinn",
    "iso:country":"EE",
    "name:und_x_variant":[
        "Paluk\u00fcla",
        "Palu"
    ],
    "wof:name":"Palu",
    "wof:placetype":"locality"
},
  "geometry": {"coordinates":[25.75,58.65],"type":"Point"}
}