{
  "type": "Feature",
  "properties": {
    "gn:admin1_code":"8.0",
    "gn:admin2_code":"191.0",
    "gn:admin3_code":"3401.0",
    "gn:asciiname":"Koolimaee",
    "gn:country_code":"EE",
    "gn:dem":16,
    "gn:feature_class":"P",
    "gn:feature_code":"PPL",
    "gn:name":"Koolim\u00e4e",
    "gn:population":0,
    "gn:timezone":"Europe/Tallinn",
    "iso:country":"EE",
    "name:est_x_preferred":[
        "Koolim\u00e4e"
    ],
    "name:fra_x_preferred":[
        "Koolim\u00e4e"
    ],
    "name:hye_x_preferred":[
        "\u053f\u0578\u0578\u056c\u056b\u0574\u0575\u0561\u0565"
    ],
    "name:und_x_variant":[
        "Koolim\u00e4e"
    ],
    "name:vol_x_preferred":[
        "Koolim\u00e4e"
    ],
    "wof:name":"Koolimaee",
    "wof:placetype":"locality"
},
  "geometry": {"coordinates":[26.02056,59.61028],"type":"Point"}
}