{
  "type": "Feature",
  "properties": {
    "gn:country":"EE",
    "gn:fcode":"PPL",
    "gn:population":332,
    "iso:country":"EE",
    "name:ceb_x_preferred":[
        "Kullamaa"
    ],
    "name:ces_x_preferred":[
        "Kullamaa"
    ],
    "name:deu_x_preferred":[
        "Kullamaa"
    ],
    "name:eng_x_preferred":[
        "Kullamaa"
    ],
    "name:est_x_preferred":[
        "Kullamaa"
    ],
    "name:hye_x_preferred":[
        "\u053f\u0578\u0582\u056c\u056c\u0561\u0574\u0561\u0561"
    ],
    "name:pol_x_preferred":[
        "Kullamaa"
    ],
    "name:rus_x_preferred":[
        "\u041a\u0443\u043b\u043b\u0430\u043c\u0430\u0430"
    ],
    "name:srp_x_preferred":[
        "\u041a\u0443\u043b\u0430\u043c\u0430"
    ],
    "name:swe_x_preferred":[
        "Kullamaa"
    ],
    "name:ukr_x_preferred":[
        "\u041a\u0443\u043b\u043b\u0430\u043c\u0430\u0430"
    ],
    "name:und_x_variant":[
        "Gol\u2019denbek"
    ],
    "name:vol_x_preferred":[
        "Kullamaa"
    ],
    "name:zho_x_preferred":[
        "\u5eab\u62c9\u99ac"
    ],
    "qs_pg:aaroncc":"EE",
    "qs_pg:gn_country":"EE",
    "qs_pg:gn_fcode":"PPL",
    "qs_pg:gn_pop":332,
    "qs_pg:name":"Kullamaa",
    "qs_pg:name_adm0":"Eesti",
    "qs_pg:name_adm1":"L\u00e4\u00e4nemaa",
    "qs_pg:photos_9k":1,
    "qs_pg:photos_9r":1,
    "qs_pg:photos_all":1,
    "qs_pg:photos_sr":0,
    "qs_pg:pop_sr":2,
    "qs_pg:qs_pg_placetype":"locality",
    "qs_pg:qs_pg_placetype_gp":"Town",
    "qs_pg:woe_adm0":23424805,
    "woe:adm0_id":23424805,
    "woe:name_adm0":"Eesti",
    "woe:name_adm1":"L\u00e4\u00e4nemaa",
    "woe:placetype":"Town",
    "wof:name":"Kullamaa",
    "wof:placetype":"locality",
    "wof:population":332
},
  "geometry": {"coordinates":[24.08167,58.87889],"type":"Point"}
}