{
  "type": "Feature",
  "properties": {
    "gn:gn_country":"EE",
    "gn:gn_fcode":"PPL",
    "gn:gn_pop":94,
    "gn:population":94,
    "iso:country":"EE",
    "name:eng_x_preferred":[
        "P\u00f6\u00f6ritsa"
    ],
    "name:est_x_preferred":[
        "P\u00f6\u00f6ritsa"
    ],
    "name:fra_x_preferred":[
        "P\u00f6\u00f6ritsa"
    ],
    "name:hye_x_preferred":[
        "\u054a\u0578\u0578\u057c\u056b\u0581\u0561"
    ],
    "name:nld_x_preferred":[
        "P\u00f6\u00f6ritsa"
    ],
    "name:pol_x_preferred":[
        "P\u00f6\u00f6ritsa"
    ],
    "name:spa_x_preferred":[
        "P\u00f6\u00f6ritsa"
    ],
    "name:ukr_x_preferred":[
        "\u041f\u0454\u0435\u0440\u0456\u0442\u0441\u0430"
    ],
    "name:vol_x_preferred":[
        "P\u00f6\u00f6ritsa"
    ],
    "qs_pg:aaroncc":"EE",
    "qs_pg:gn_country":"EE",
    "qs_pg:gn_fcode":"PPL",
    "qs_pg:gn_pop":94,
    "qs_pg:name":"P\u00f6\u00f6ritsa",
    "qs_pg:name_adm0":"Eesti",
    "qs_pg:name_adm1":"Tartumaa",
    "qs_pg:photos_9k":1,
    "qs_pg:photos_9r":1,
    "qs_pg:photos_all":1,
    "qs_pg:photos_sr":0,
    "qs_pg:pop_sr":1,
    "qs_pg:qs_pg_placetype":"locality",
    "qs_pg:qs_pg_placetype_gp":"Town",
    "qs_pg:woe_adm0":23424805,
    "woe:adm0_id":23424805,
    "woe:name_adm0":"Eesti",
    "woe:name_adm1":"Tartumaa",
    "woe:placetype":"Town",
    "wof:name":"P\u00f6\u00f6ritsa",
    "wof:placetype":"locality",
    "wof:population":94
},
  "geometry": {"coordinates":[26.29778,58.24222],"type":"Point"}
}