{
  "type": "Feature",
  "properties": {
    "gn:admin1_code":"21.0",
    "gn:admin2_code":"698.0",
    "gn:admin3_code":"4358.0",
    "gn:asciiname":"Liivakupalu",
    "gn:country_code":"EE",
    "gn:dem":161,
    "gn:feature_class":"P",
    "gn:feature_code":"PPL",
    "gn:name":"Liivakupalu",
    "gn:population":0,
    "gn:timezone":"Europe/Tallinn",
    "iso:country":"EE",
    "name:und_x_variant":[
        "Linnam\u00e4e"
    ],
    "wof:name":"Liivakupalu",
    "wof:placetype":"locality"
},
  "geometry": {"coordinates":[26.96611,57.76167],"type":"Point"}
}