{
  "type": "Feature",
  "properties": {
    "gn:admin1_code":"20.0",
    "gn:admin2_code":"480.0",
    "gn:admin3_code":"6572.0",
    "gn:asciiname":"Paeidre",
    "gn:country_code":"EE",
    "gn:dem":80,
    "gn:feature_class":"P",
    "gn:feature_code":"PPL",
    "gn:name":"P\u00e4idre",
    "gn:population":0,
    "gn:timezone":"Europe/Tallinn",
    "iso:country":"EE",
    "name:und_x_variant":[
        "Pyaydre",
        "P\u00e4idre"
    ],
    "wof:name":"Paeidre",
    "wof:placetype":"locality"
},
  "geometry": {"coordinates":[25.535,58.25556],"type":"Point"}
}