{
  "type": "Feature",
  "properties": {
    "gn:admin1_code":"1.0",
    "gn:admin2_code":"245.0",
    "gn:admin3_code":"5997.0",
    "gn:asciiname":"Parasmaee",
    "gn:country_code":"EE",
    "gn:dem":46,
    "gn:feature_class":"P",
    "gn:feature_code":"PPL",
    "gn:name":"Parasm\u00e4e",
    "gn:population":0,
    "gn:timezone":"Europe/Tallinn",
    "iso:country":"EE",
    "name:und_x_variant":[
        "Parasmyae",
        "Parasmya",
        "Parasm\u00e4e"
    ],
    "wof:name":"Parasmaee",
    "wof:placetype":"locality"
},
  "geometry": {"coordinates":[25.12368,59.41308000000001],"type":"Point"}
}