{
  "type": "Feature",
  "properties": {
    "gn:admin1_code":"1.0",
    "gn:admin2_code":"245.0",
    "gn:admin3_code":"5997.0",
    "gn:asciiname":"Parasmaee",
    "gn:country_code":"EE",
    "gn:dem":46,
    "gn:feature_class":"P",
    "gn:feature_code":"PPL",
    "gn:name":"Parasm\u00e4e",
    "gn:population":0,
    "gn:timezone":"Europe/Tallinn",
    "iso:country":"EE",
    "name:est_x_preferred":[
        "Parasm\u00e4e"
    ],
    "name:fra_x_preferred":[
        "Parasm\u00e4e"
    ],
    "name:hye_x_preferred":[
        "\u054a\u0561\u057c\u0561\u057d\u0574\u0575\u0561\u0565"
    ],
    "name:nld_x_preferred":[
        "Parasm\u00e4e"
    ],
    "name:pol_x_preferred":[
        "Parasm\u00e4e"
    ],
    "name:spa_x_preferred":[
        "Parasm\u00e4e"
    ],
    "name:und_x_variant":[
        "Parasmyae",
        "Parasmya"
    ],
    "name:vol_x_preferred":[
        "Parasm\u00e4e"
    ],
    "wof:name":"Parasmaee",
    "wof:placetype":"locality"
},
  "geometry": {"coordinates":[25.12368,59.41308000000001],"type":"Point"}
}