{
  "type": "Feature",
  "properties": {
    "gn:admin1_code":"21.0",
    "gn:admin2_code":"698.0",
    "gn:admin3_code":"1968.0",
    "gn:asciiname":"Huerova",
    "gn:country_code":"EE",
    "gn:dem":75,
    "gn:feature_class":"P",
    "gn:feature_code":"PPL",
    "gn:name":"H\u00fcrova",
    "gn:population":0,
    "gn:timezone":"Europe/Tallinn",
    "iso:country":"EE",
    "name:und_x_variant":[
        "H\u00fcrova"
    ],
    "wof:name":"Huerova",
    "wof:placetype":"locality"
},
  "geometry": {"coordinates":[26.59389,57.62389],"type":"Point"}
}