{
  "type": "Feature",
  "properties": {
    "gn:admin1_code":"21.0",
    "gn:admin2_code":"698.0",
    "gn:admin3_code":"1968.0",
    "gn:asciiname":"Huerova",
    "gn:country_code":"EE",
    "gn:dem":75,
    "gn:feature_class":"P",
    "gn:feature_code":"PPL",
    "gn:name":"H\u00fcrova",
    "gn:population":0,
    "gn:timezone":"Europe/Tallinn",
    "iso:country":"EE",
    "name:est_x_preferred":[
        "H\u00fcrova"
    ],
    "name:hye_x_preferred":[
        "\u0540\u0575\u0578\u0582\u057c\u0578\u057e\u0561"
    ],
    "name:pol_x_preferred":[
        "H\u00fcrova"
    ],
    "name:spa_x_preferred":[
        "H\u00fcrova"
    ],
    "name:ukr_x_preferred":[
        "\u0425\u044e\u0440\u043e\u0432\u0430"
    ],
    "name:vol_x_preferred":[
        "H\u00fcrova"
    ],
    "wof:lang_x_official":[
        "est"
    ],
    "wof:lang_x_spoken":[
        "est"
    ],
    "wof:name":"Huerova",
    "wof:placetype":"locality"
},
  "geometry": {"coordinates":[26.59389,57.62389],"type":"Point"}
}