{
  "type": "Feature",
  "properties": {
    "gn:admin1_code":"4.0",
    "gn:admin2_code":"255.0",
    "gn:admin3_code":"1100.0",
    "gn:asciiname":"Ageri",
    "gn:country_code":"EE",
    "gn:dem":90,
    "gn:feature_class":"P",
    "gn:feature_code":"PPL",
    "gn:name":"Ageri",
    "gn:population":0,
    "gn:timezone":"Europe/Tallinn",
    "iso:country":"EE",
    "wof:name":"Ageri",
    "wof:placetype":"locality"
},
  "geometry": {"coordinates":[25.7625,59.08778],"type":"Point"}
}