{
  "type": "Feature",
  "properties": {
    "gn:admin1_code":"4.0",
    "gn:admin2_code":"255.0",
    "gn:admin3_code":"1100.0",
    "gn:asciiname":"Ageri",
    "gn:country_code":"EE",
    "gn:dem":90,
    "gn:feature_class":"P",
    "gn:feature_code":"PPL",
    "gn:name":"Ageri",
    "gn:population":0,
    "gn:timezone":"Europe/Tallinn",
    "iso:country":"EE",
    "name:est_x_preferred":[
        "Ageri"
    ],
    "name:fas_x_preferred":[
        "\u0627\u06cc\u062c\u0631\u06cc"
    ],
    "name:fra_x_preferred":[
        "Ageri"
    ],
    "name:hye_x_preferred":[
        "\u0531\u0563\u0565\u057c\u056b"
    ],
    "name:pol_x_preferred":[
        "Ageri"
    ],
    "name:spa_x_preferred":[
        "Ageri"
    ],
    "name:ukr_x_preferred":[
        "\u0410\u0491\u0435\u0440\u0456"
    ],
    "name:urd_x_preferred":[
        "\u0627\u06cc\u062c\u0631\u06cc"
    ],
    "name:vol_x_preferred":[
        "Ageri"
    ],
    "wof:name":"Ageri",
    "wof:placetype":"locality"
},
  "geometry": {"coordinates":[25.7625,59.08778],"type":"Point"}
}