{
  "type": "Feature",
  "properties": {
    "gn:admin1_code":"21.0",
    "gn:admin2_code":"698.0",
    "gn:admin3_code":"6128.0",
    "gn:asciiname":"Jaervepalu",
    "gn:country_code":"EE",
    "gn:dem":108,
    "gn:feature_class":"P",
    "gn:feature_code":"PPL",
    "gn:name":"J\u00e4rvepalu",
    "gn:population":0,
    "gn:timezone":"Europe/Tallinn",
    "iso:country":"EE",
    "name:und_x_variant":[
        "J\u00e4rvepalu"
    ],
    "wof:name":"Jaervepalu",
    "wof:placetype":"locality"
},
  "geometry": {"coordinates":[26.79583,57.75],"type":"Point"}
}