{
  "type": "Feature",
  "properties": {
    "gn:admin1_code":"21.0",
    "gn:admin2_code":"698.0",
    "gn:admin3_code":"6128.0",
    "gn:asciiname":"Jaervepalu",
    "gn:country_code":"EE",
    "gn:dem":108,
    "gn:feature_class":"P",
    "gn:feature_code":"PPL",
    "gn:name":"J\u00e4rvepalu",
    "gn:population":0,
    "gn:timezone":"Europe/Tallinn",
    "iso:country":"EE",
    "name:est_x_preferred":[
        "J\u00e4rvepalu"
    ],
    "name:hye_x_preferred":[
        "\u0535\u057c\u057e\u0565\u057a\u0561\u056c\u0578\u0582"
    ],
    "name:myv_x_preferred":[
        "\u042f\u0440\u0432\u0435\u043f\u0430\u043b\u0443"
    ],
    "name:pol_x_preferred":[
        "J\u00e4rvepalu"
    ],
    "name:spa_x_preferred":[
        "J\u00e4rvepalu"
    ],
    "name:ukr_x_preferred":[
        "\u042f\u0440\u0432\u0435\u043f\u0430\u043b\u0443"
    ],
    "name:urd_x_preferred":[
        "\u062c\u0627\u0631\u0648\u067e\u0627\u0644\u0648"
    ],
    "name:vol_x_preferred":[
        "J\u00e4rvepalu"
    ],
    "wof:name":"Jaervepalu",
    "wof:placetype":"locality"
},
  "geometry": {"coordinates":[26.79583,57.75],"type":"Point"}
}