{
  "type": "Feature",
  "properties": {
    "gn:country":"EE",
    "gn:fcode":"PPL",
    "gn:population":448,
    "iso:country":"EE",
    "name:ceb_x_preferred":[
        "J\u00f5\u00f5pre"
    ],
    "name:ces_x_preferred":[
        "J\u00f5\u00f5pre"
    ],
    "name:eng_x_preferred":[
        "J\u00f5\u00f5pre"
    ],
    "name:est_x_preferred":[
        "J\u00f5\u00f5pre"
    ],
    "name:hye_x_preferred":[
        "\u0545\u056b\u056b\u057a\u057c\u0565"
    ],
    "name:nld_x_preferred":[
        "J\u00f5\u00f5pre"
    ],
    "name:pol_x_preferred":[
        "J\u00f5\u00f5pre"
    ],
    "name:swe_x_preferred":[
        "J\u00f5\u00f5pre"
    ],
    "name:vol_x_preferred":[
        "J\u00f5\u00f5pre"
    ],
    "qs_pg:aaroncc":"EE",
    "qs_pg:gn_country":"EE",
    "qs_pg:gn_fcode":"PPL",
    "qs_pg:gn_pop":448,
    "qs_pg:name":"J\u00f5\u00f5pre",
    "qs_pg:name_adm0":"Eesti",
    "qs_pg:name_adm1":"P\u00e4rnumaa",
    "qs_pg:photos_9k":1,
    "qs_pg:photos_9r":1,
    "qs_pg:photos_all":4,
    "qs_pg:photos_sr":0,
    "qs_pg:pop_sr":2,
    "qs_pg:qs_pg_placetype":"locality",
    "qs_pg:qs_pg_placetype_gp":"Town",
    "qs_pg:woe_adm0":23424805,
    "woe:adm0_id":23424805,
    "woe:name_adm0":"Eesti",
    "woe:name_adm1":"P\u00e4rnumaa",
    "woe:placetype":"Town",
    "wof:name":"J\u00f5\u00f5pre",
    "wof:placetype":"locality",
    "wof:population":448
},
  "geometry": {"coordinates":[24.32417,58.47333],"type":"Point"}
}