{
  "type": "Feature",
  "properties": {
    "gn:admin1_code":"2.0",
    "gn:admin2_code":"205.0",
    "gn:admin3_code":"6609.0",
    "gn:asciiname":"Soru",
    "gn:country_code":"EE",
    "gn:dem":8,
    "gn:feature_class":"P",
    "gn:feature_code":"PPL",
    "gn:name":"S\u00f5ru",
    "gn:population":10,
    "gn:timezone":"Europe/Tallinn",
    "iso:country":"EE",
    "name:ces_x_preferred":[
        "S\u00f5ru"
    ],
    "name:deu_x_preferred":[
        "Serr\u00f6"
    ],
    "name:deu_x_variant":[
        "S\u00f5ru"
    ],
    "name:est_x_preferred":[
        "S\u00f5ru"
    ],
    "name:fra_x_preferred":[
        "S\u00f5ru"
    ],
    "name:hye_x_preferred":[
        "\u054d\u056b\u057c\u0578\u0582"
    ],
    "name:pol_x_preferred":[
        "S\u00f5ru"
    ],
    "name:rus_x_preferred":[
        "\u0421\u044b\u0440\u0443"
    ],
    "name:spa_x_preferred":[
        "S\u00f5ru"
    ],
    "name:swe_x_preferred":[
        "S\u00f5ru"
    ],
    "name:und_x_variant":[
        "S\u00f5ru"
    ],
    "name:vol_x_preferred":[
        "S\u00f5ru"
    ],
    "wof:name":"Soru",
    "wof:placetype":"locality",
    "wof:population":10
},
  "geometry": {"coordinates":[22.52233,58.69665],"type":"Point"}
}