{
  "type": "Feature",
  "properties": {
    "gn:gn_country":"EE",
    "gn:gn_fcode":"PPL",
    "gn:gn_pop":928,
    "gn:population":928,
    "iso:country":"EE",
    "name:ceb_x_preferred":[
        "Mustla"
    ],
    "name:ces_x_preferred":[
        "Mustla"
    ],
    "name:est_x_preferred":[
        "Mustla"
    ],
    "name:fra_x_preferred":[
        "Mustla"
    ],
    "name:hye_x_preferred":[
        "\u0544\u0578\u0582\u057d\u057f\u056c\u0561"
    ],
    "name:lit_x_preferred":[
        "Mustla"
    ],
    "name:rus_x_preferred":[
        "\u041c\u0443\u0441\u0442\u043b\u0430"
    ],
    "name:spa_x_preferred":[
        "Mustla"
    ],
    "name:swe_x_preferred":[
        "Mustla"
    ],
    "name:ukr_x_preferred":[
        "\u041c\u0443\u0441\u0442\u043b\u0430"
    ],
    "name:unk_x_variant":[
        "Mustlakyula"
    ],
    "name:vol_x_preferred":[
        "Mustla"
    ],
    "name:zho_x_preferred":[
        "\u7a46\u65af\u7279\u62c9"
    ],
    "qs_pg:aaroncc":"EE",
    "qs_pg:gn_country":"EE",
    "qs_pg:gn_fcode":"PPL",
    "qs_pg:gn_pop":928,
    "qs_pg:name":"Mustla",
    "qs_pg:name_adm0":"Eesti",
    "qs_pg:name_adm1":"P\u00e4rnumaa",
    "qs_pg:photos_9k":1,
    "qs_pg:photos_9r":1,
    "qs_pg:photos_all":2,
    "qs_pg:photos_sr":0,
    "qs_pg:pop_sr":2,
    "qs_pg:qs_pg_placetype":"locality",
    "qs_pg:qs_pg_placetype_gp":"Town",
    "qs_pg:woe_adm0":23424805,
    "woe:adm0_id":23424805,
    "woe:name_adm0":"Eesti",
    "woe:name_adm1":"P\u00e4rnumaa",
    "woe:placetype":"Town",
    "wof:name":"Mustla",
    "wof:placetype":"locality",
    "wof:population":928
},
  "geometry": {"coordinates":[25.10028,58.13417],"type":"Point"}
}