{
  "type": "Feature",
  "properties": {
    "gn:admin1_code":"1.0",
    "gn:admin2_code":"198.0",
    "gn:admin3_code":"3997.0",
    "gn:asciiname":"Metsakuela",
    "gn:country_code":"EE",
    "gn:dem":36,
    "gn:feature_class":"P",
    "gn:feature_code":"PPL",
    "gn:name":"Metsak\u00fcla",
    "gn:population":0,
    "gn:timezone":"Europe/Tallinn",
    "iso:country":"EE",
    "name:und_x_variant":[
        "Metsak\u00fcla",
        "Metsa"
    ],
    "wof:name":"Metsakuela",
    "wof:placetype":"locality"
},
  "geometry": {"coordinates":[24.45278,59.34361],"type":"Point"}
}