{
  "type": "Feature",
  "properties": {
    "gn:gn_country":"EE",
    "gn:gn_fcode":"PPL",
    "gn:gn_pop":294,
    "gn:population":294,
    "iso:country":"EE",
    "name:bul_x_preferred":[
        "\u041a\u0435\u0430\u0432\u0430"
    ],
    "name:eng_x_preferred":[
        "Keava"
    ],
    "name:est_x_preferred":[
        "Keava"
    ],
    "name:fra_x_preferred":[
        "Keava"
    ],
    "name:hye_x_preferred":[
        "\u053f\u0565\u0561\u057e\u0561"
    ],
    "name:pol_x_preferred":[
        "Keava"
    ],
    "name:sco_x_preferred":[
        "Keava"
    ],
    "name:swe_x_preferred":[
        "Keava"
    ],
    "name:unk_x_variant":[
        "Kedenp\u00fch"
    ],
    "name:vol_x_preferred":[
        "Keava"
    ],
    "qs_pg:aaroncc":"EE",
    "qs_pg:gn_country":"EE",
    "qs_pg:gn_fcode":"PPL",
    "qs_pg:gn_pop":294,
    "qs_pg:name":"Keava",
    "qs_pg:name_adm0":"Eesti",
    "qs_pg:name_adm1":"Raplamaa",
    "qs_pg:photos_9r":0,
    "qs_pg:photos_sr":0,
    "qs_pg:pop_sr":2,
    "qs_pg:qs_pg_placetype":"locality",
    "qs_pg:qs_pg_placetype_gp":"Town",
    "qs_pg:woe_adm0":23424805,
    "woe:adm0_id":23424805,
    "woe:name_adm0":"Eesti",
    "woe:name_adm1":"Raplamaa",
    "woe:placetype":"Town",
    "wof:name":"Keava",
    "wof:placetype":"locality",
    "wof:population":294
},
  "geometry": {"coordinates":[24.90333,58.94639],"type":"Point"}
}