{
  "type": "Feature",
  "properties": {
    "gn:admin1_code":"21.0",
    "gn:admin2_code":"698.0",
    "gn:admin3_code":"7712.0",
    "gn:asciiname":"Soolaette",
    "gn:country_code":"EE",
    "gn:dem":143,
    "gn:feature_class":"P",
    "gn:feature_code":"PPL",
    "gn:name":"Sool\u00e4tte",
    "gn:population":0,
    "gn:timezone":"Europe/Tallinn",
    "iso:country":"EE",
    "name:est_x_preferred":[
        "Sool\u00e4tte"
    ],
    "name:hye_x_preferred":[
        "\u054d\u0578\u0578\u056c\u0565\u057f\u057f\u0565"
    ],
    "name:pol_x_preferred":[
        "Sool\u00e4tte"
    ],
    "name:spa_x_preferred":[
        "Sool\u00e4tte"
    ],
    "name:ukr_x_preferred":[
        "\u0421\u043e\u043e\u043b\u044f\u0442\u0442\u0435"
    ],
    "name:und_x_variant":[
        "Sool\u00e4tte"
    ],
    "name:vol_x_preferred":[
        "Sool\u00e4tte"
    ],
    "wof:name":"Soolaette",
    "wof:placetype":"locality"
},
  "geometry": {"coordinates":[26.84333,57.62806],"type":"Point"}
}