{
  "type": "Feature",
  "properties": {
    "gn:admin1_code":"14.0",
    "gn:admin2_code":"714.0",
    "gn:admin3_code":"8693.0",
    "gn:asciiname":"Unguma",
    "gn:country_code":"EE",
    "gn:dem":10,
    "gn:feature_class":"P",
    "gn:feature_code":"PPL",
    "gn:name":"Unguma",
    "gn:population":0,
    "gn:timezone":"Europe/Tallinn",
    "iso:country":"EE",
    "name:und_x_variant":[
        "Ungema",
        "Ungumaa",
        "Unguma"
    ],
    "wof:name":"Unguma",
    "wof:placetype":"locality"
},
  "geometry": {"coordinates":[23.13528,58.46806],"type":"Point"}
}