{
  "type": "Feature",
  "properties": {
    "gn:admin1_code":"11.0",
    "gn:admin2_code":"430.0",
    "gn:admin3_code":"6054.0",
    "gn:asciiname":"Vaeaenja",
    "gn:country_code":"EE",
    "gn:dem":34,
    "gn:feature_class":"P",
    "gn:feature_code":"PPL",
    "gn:name":"V\u00e4\u00e4nja",
    "gn:population":0,
    "gn:timezone":"Europe/Tallinn",
    "iso:country":"EE",
    "name:und_x_variant":[
        "Vyan\u2019ya",
        "Myza Vyan\u2019ya",
        "V\u00e4\u00e4nja"
    ],
    "wof:name":"Vaeaenja",
    "wof:placetype":"locality"
},
  "geometry": {"coordinates":[23.92417,58.54361],"type":"Point"}
}