{
  "type": "Feature",
  "properties": {
    "gn:admin1_code":"13.0",
    "gn:admin2_code":"317.0",
    "gn:admin3_code":"6140.0",
    "gn:asciiname":"Adila-Krimmi",
    "gn:country_code":"EE",
    "gn:dem":64,
    "gn:feature_class":"P",
    "gn:feature_code":"PPL",
    "gn:name":"Adila-Krimmi",
    "gn:population":0,
    "gn:timezone":"Europe/Tallinn",
    "iso:country":"EE",
    "wof:name":"Adila-Krimmi",
    "wof:placetype":"locality"
},
  "geometry": {"coordinates":[24.61333,59.11944],"type":"Point"}
}