{
  "type": "Feature",
  "properties": {
    "gn:gn_country":"EE",
    "gn:gn_fcode":"PPL",
    "gn:gn_pop":102,
    "gn:population":102,
    "iso:country":"EE",
    "name:arm_x_preferred":[
        "\u054a\u0578\u0578\u057c\u0561"
    ],
    "name:dut_x_preferred":[
        "P\u00f6\u00f6ra"
    ],
    "name:eng_x_preferred":[
        "P\u00f6\u00f6ra"
    ],
    "name:est_x_preferred":[
        "P\u00f6\u00f6ra"
    ],
    "name:pol_x_preferred":[
        "P\u00f6\u00f6ra"
    ],
    "name:swe_x_preferred":[
        "P\u00f6\u00f6ra"
    ],
    "name:ukr_x_preferred":[
        "\u041f\u0454\u0435\u0440\u0430"
    ],
    "name:vol_x_preferred":[
        "P\u00f6\u00f6ra"
    ],
    "qs_pg:aaroncc":"EE",
    "qs_pg:gn_country":"EE",
    "qs_pg:gn_fcode":"PPL",
    "qs_pg:gn_pop":102,
    "qs_pg:name":"P\u00f6\u00f6ra",
    "qs_pg:name_adm0":"Eesti",
    "qs_pg:name_adm1":"J\u00f5gevamaa",
    "qs_pg:photos_9r":0,
    "qs_pg:photos_sr":0,
    "qs_pg:pop_sr":1,
    "qs_pg:qs_pg_placetype":"locality",
    "qs_pg:qs_pg_placetype_gp":"Town",
    "qs_pg:woe_adm0":23424805,
    "woe:adm0_id":23424805,
    "woe:name_adm0":"Eesti",
    "woe:name_adm1":"J\u00f5gevamaa",
    "woe:placetype":"Town",
    "wof:name":"P\u00f6\u00f6ra",
    "wof:placetype":"locality",
    "wof:population":102
},
  "geometry": {"coordinates":[26.26,58.65333],"type":"Point"}
}