{
  "type": "Feature",
  "properties": {
    "gn:country":"EE",
    "gn:fcode":"PPL",
    "gn:population":517,
    "iso:country":"EE",
    "name:ara_x_preferred":[
        "\u0641\u0627\u0646\u0627 \u0641\u0648\u064a\u062f\u0648"
    ],
    "name:ceb_x_preferred":[
        "Vana-V\u00f5idu"
    ],
    "name:eng_x_preferred":[
        "Vana-V\u00f5idu"
    ],
    "name:est_x_preferred":[
        "Vana-V\u00f5idu"
    ],
    "name:fas_x_preferred":[
        "\u0648\u0627\u0646\u0627 \u0648\u06cc\u062f\u0648"
    ],
    "name:fra_x_preferred":[
        "Vana-V\u00f5idu"
    ],
    "name:hye_x_preferred":[
        "\u054e\u0561\u0576\u0561-\u054e\u056b\u056b\u0564\u0578\u0582"
    ],
    "name:nld_x_preferred":[
        "Vana-V\u00f5idu"
    ],
    "name:pol_x_preferred":[
        "Vana-V\u00f5idu"
    ],
    "name:spa_x_preferred":[
        "Vana-V\u00f5idu"
    ],
    "name:swe_x_preferred":[
        "Vana-V\u00f5idu"
    ],
    "name:ukr_x_preferred":[
        "\u0412\u0430\u043d\u0430-\u0412\u0438\u0439\u0434\u0443"
    ],
    "name:vol_x_preferred":[
        "Vana-V\u00f5idu"
    ],
    "qs_pg:aaroncc":"EE",
    "qs_pg:gn_country":"EE",
    "qs_pg:gn_fcode":"PPL",
    "qs_pg:gn_pop":517,
    "qs_pg:name":"Vana-V\u00f5idu",
    "qs_pg:name_adm0":"Eesti",
    "qs_pg:name_adm1":"Viljandimaa",
    "qs_pg:photos_9r":0,
    "qs_pg:photos_sr":0,
    "qs_pg:pop_sr":2,
    "qs_pg:qs_pg_placetype":"locality",
    "qs_pg:qs_pg_placetype_gp":"Town",
    "qs_pg:woe_adm0":23424805,
    "woe:adm0_id":23424805,
    "woe:name_adm0":"Eesti",
    "woe:name_adm1":"Viljandimaa",
    "woe:placetype":"Town",
    "wof:name":"Vana-V\u00f5idu",
    "wof:placetype":"locality",
    "wof:population":517
},
  "geometry": {"coordinates":[25.65417,58.39056],"type":"Point"}
}