{
  "type": "Feature",
  "properties": {
    "gn:admin1_code":"21.0",
    "gn:admin2_code":"732.0",
    "gn:admin3_code":"8416.0",
    "gn:asciiname":"Tuplova",
    "gn:country_code":"EE",
    "gn:dem":86,
    "gn:feature_class":"P",
    "gn:feature_code":"PPL",
    "gn:name":"Tuplova",
    "gn:population":0,
    "gn:timezone":"Europe/Tallinn",
    "iso:country":"EE",
    "name:und_x_variant":[
        "Tupl\u2019uva"
    ],
    "wof:name":"Tuplova",
    "wof:placetype":"locality"
},
  "geometry": {"coordinates":[27.50167,57.82278],"type":"Point"}
}