{
  "type": "Feature",
  "properties": {
    "gn:admin1_code":"7.0",
    "gn:admin2_code":"907.0",
    "gn:admin3_code":"7875.0",
    "gn:asciiname":"Sviby",
    "gn:country_code":"EE",
    "gn:dem":8,
    "gn:feature_class":"P",
    "gn:feature_code":"PPL",
    "gn:name":"Sviby",
    "gn:population":0,
    "gn:timezone":"Europe/Tallinn",
    "iso:country":"EE",
    "name:deu_x_preferred":[
        "Sviby"
    ],
    "name:est_x_preferred":[
        "Sviby"
    ],
    "name:hye_x_preferred":[
        "\u054d\u057e\u056b\u0562\u056b"
    ],
    "name:pol_x_preferred":[
        "Sviby"
    ],
    "name:ron_x_preferred":[
        "Sviby"
    ],
    "name:spa_x_preferred":[
        "Sviby"
    ],
    "name:swe_x_preferred":[
        "Sviby"
    ],
    "name:ukr_x_preferred":[
        "\u0421\u0432\u0456\u0431\u044e"
    ],
    "name:und_x_variant":[
        "Svibi",
        "Sviybi",
        "Sviby",
        "Sviibi"
    ],
    "name:vol_x_preferred":[
        "Sviby"
    ],
    "wof:name":"Sviby",
    "wof:placetype":"locality"
},
  "geometry": {"coordinates":[23.30194,58.98521],"type":"Point"}
}