{
  "type": "Feature",
  "properties": {
    "gn:admin1_code":"1.0",
    "gn:admin2_code":"338.0",
    "gn:admin3_code":"6875.0",
    "gn:asciiname":"Volle",
    "gn:cc2":"EE",
    "gn:country_code":"EE",
    "gn:dem":70,
    "gn:feature_class":"P",
    "gn:feature_code":"PPL",
    "gn:name":"V\u00f5lle",
    "gn:population":0,
    "gn:timezone":"Europe/Tallinn",
    "iso:country":"EE",
    "name:und_x_variant":[
        "Vylle",
        "V\u00f5lle"
    ],
    "wof:name":"Volle",
    "wof:placetype":"locality"
},
  "geometry": {"coordinates":[25.22389,59.18556],"type":"Point"}
}