{
  "type": "Feature",
  "properties": {
    "gn:admin1_code":"2.0",
    "gn:admin2_code":"205.0",
    "gn:admin3_code":"7438.0",
    "gn:asciiname":"Sarve",
    "gn:country_code":"EE",
    "gn:dem":4,
    "gn:feature_class":"P",
    "gn:feature_code":"PPL",
    "gn:name":"Sarve",
    "gn:population":0,
    "gn:timezone":"Europe/Tallinn",
    "iso:country":"EE",
    "name:deu_x_preferred":[
        "Sarve"
    ],
    "name:est_x_preferred":[
        "Sarve"
    ],
    "name:hye_x_preferred":[
        "\u054d\u0561\u057c\u057e\u0565"
    ],
    "name:pol_x_preferred":[
        "Sarve"
    ],
    "name:spa_x_preferred":[
        "Sarve"
    ],
    "name:vol_x_preferred":[
        "Sarve"
    ],
    "wof:coterminous":[
        1713310653
    ],
    "wof:lang_x_official":[
        "est"
    ],
    "wof:lang_x_spoken":[
        "est"
    ],
    "wof:name":"Sarve",
    "wof:placetype":"locality"
},
  "geometry": {"coordinates":[23.0567,58.83646],"type":"Point"}
}