{
  "type": "Feature",
  "properties": {
    "gn:admin1_code":"18.0",
    "gn:admin2_code":"283.0",
    "gn:admin3_code":"9419.0",
    "gn:asciiname":"Visnapuu",
    "gn:country_code":"EE",
    "gn:dem":129,
    "gn:feature_class":"P",
    "gn:feature_code":"PPL",
    "gn:name":"Visnapuu",
    "gn:population":0,
    "gn:timezone":"Europe/Tallinn",
    "iso:country":"EE",
    "name:est_x_preferred":[
        "Visnapuu"
    ],
    "name:fra_x_preferred":[
        "Visnapuu"
    ],
    "name:hye_x_preferred":[
        "\u054e\u056b\u057d\u0576\u0561\u057a\u0578\u0582\u0578\u0582"
    ],
    "name:pol_x_preferred":[
        "Visnapuu"
    ],
    "name:spa_x_preferred":[
        "Visnapuu"
    ],
    "name:ukr_x_preferred":[
        "\u0412\u0456\u0441\u043d\u0430\u043f\u0443\u0443"
    ],
    "name:vol_x_preferred":[
        "Visnapuu"
    ],
    "wof:name":"Visnapuu",
    "wof:placetype":"locality"
},
  "geometry": {"coordinates":[26.59861,58.22139],"type":"Point"}
}